Workbook

Sheet Summary
A2: NEXT WP008 sourcing scenarios
A4: Scenario: | B4: =Assumptions!C5 -> Balanced | D4: Price period: | E4: =Assumptions!C6 -> H1 2026 | G4: Data basis: | H4: =Assumptions!C7 -> Reported
A6: Illustrative shifts from China using FY2025 trade-mass weights. Candidate origin, capability and sourcing clearance remain pending. No allocation is released.
A8: Product | B8: China baseline | C8: Requested shift | D8: Feasible limit | E8: Applied shift | F8: Cost index | G8: Cost change | H8: HHI change (pts) | I8: Release
A9: Cotton T-shirts | B9: =Cost_Model!D8 -> 0.032221227 | C9: =Assumptions!C12 -> 0.1 | D9: =Cost_Model!D51 -> 0.032221227 | E9: =Cost_Model!E51 -> 0.032221227 | F9: =100*Cost_Model!F51/Cost_Model!B51 -> 99.915376 | G9: =F9/100-1 -> -0.00084624275 | H9: =(Cost_Model!J51-Cost_Model!G51)*10000 -> 39.567478 | I9: =Cost_Model!O51 -> Hold
A10: MMF knitwear | B10: =Cost_Model!D18 -> 0.36613275 | C10: =Assumptions!C12 -> 0.1 | D10: =Cost_Model!D52 -> 0.014153298 | E10: =Cost_Model!E52 -> 0.014153298 | F10: =100*Cost_Model!F52/Cost_Model!B52 -> 99.5373 | G10: =F10/100-1 -> -0.0046270035 | H10: =(Cost_Model!J52-Cost_Model!G52)*10000 -> -88.19323 | I10: =Cost_Model!O52 -> Hold
A11: Synthetic dresses | B11: =Cost_Model!D28 -> 0.47952185 | C11: =Assumptions!C12 -> 0.1 | D11: =Cost_Model!D53 -> 0.2 | E11: =Cost_Model!E53 -> 0.1 | F11: =100*Cost_Model!F53/Cost_Model!B53 -> 99.509124 | G11: =F11/100-1 -> -0.0049087561 | H11: =(Cost_Model!J53-Cost_Model!G53)*10000 -> -635.80165 | I11: =Cost_Model!O53 -> Hold
A12: Cotton shirts | B12: =Cost_Model!D38 -> 0.069159901 | C12: =Assumptions!C12 -> 0.1 | D12: =Cost_Model!D54 -> 0.069159901 | E12: =Cost_Model!E54 -> 0.069159901 | F12: =100*Cost_Model!F54/Cost_Model!B54 -> 101.34489 | G12: =F12/100-1 -> 0.013448904 | H12: =(Cost_Model!J54-Cost_Model!G54)*10000 -> 117.77114 | I12: =Cost_Model!O54 -> Hold
A14: Index 100 = unchanged country mix under the same prices and tariff treatment. Negative HHI change means lower concentration within the product’s ten-country benchmark.
A15: =IF(AND(H10<0,H11<0,H9>0,H12>0),"The synthetic pair de-concentrates; both cotton codes concentrate further. Bangladesh remains dominant in the cotton baseline. These results support a category-specific investigation, not a blanket reduction in China.","Concentration effects differ by category and receiver mix. Read each HHI change separately; reducing China alone does not guarantee diversification.") -> The synthetic pair de-concentrates; both cotton codes concentrate further. Bangladesh remains dominant in the cotton baseline. These results support a category-specific investigation, not a blanket reduction in China.
A16: Scenario | B16: Requested shift | C16: Eligible index | D16: MFN index | E16: Active index | F16: Cost change | G16: Smallest shift | H16: Largest shift | I16: Release
A17: Cautious | B17: =Assumptions!B17 -> 0.05 | C17: =100*(1+SUMPRODUCT(Assumptions!$C$38:$C$41,Cost_Model!F60:F63)) -> 100.04489 | D17: =100*(1+SUMPRODUCT(Assumptions!$C$38:$C$41,Cost_Model!G60:G63)) -> 100.54108 | E17: =IF(Assumptions!C9="Eligible preference",C17,D17) -> 100.04489 | F17: =E17/100-1 -> 0.00044885644 | G17: =MIN(Cost_Model!E60:E63) -> 0.014153298 | H17: =MAX(Cost_Model!E60:E63) -> 0.05 | I17: =IF(COUNTIF(Cost_Model!N60:N63,"Hold")=0,"Evidence recorded","Hold") -> Hold
A18: Balanced | B18: =Assumptions!B18 -> 0.1 | C18: =100*(1+SUMPRODUCT(Assumptions!$C$38:$C$41,Cost_Model!F64:F67)) -> 100.07667 | D18: =100*(1+SUMPRODUCT(Assumptions!$C$38:$C$41,Cost_Model!G64:G67)) -> 100.78714 | E18: =IF(Assumptions!C9="Eligible preference",C18,D18) -> 100.07667 | F18: =E18/100-1 -> 0.0007667253 | G18: =MIN(Cost_Model!E64:E67) -> 0.014153298 | H18: =MAX(Cost_Model!E64:E67) -> 0.1 | I18: =IF(COUNTIF(Cost_Model!N64:N67,"Hold")=0,"Evidence recorded","Hold") -> Hold
A19: Accelerated | B19: =Assumptions!B19 -> 0.15 | C19: =100*(1+SUMPRODUCT(Assumptions!$C$38:$C$41,Cost_Model!F68:F71)) -> 100.01531 | D19: =100*(1+SUMPRODUCT(Assumptions!$C$38:$C$41,Cost_Model!G68:G71)) -> 100.87774 | E19: =IF(Assumptions!C9="Eligible preference",C19,D19) -> 100.01531 | F19: =E19/100-1 -> 0.00015313079 | G19: =MIN(Cost_Model!E68:E71) -> 0.014153298 | H19: =MAX(Cost_Model!E68:E71) -> 0.15 | I19: =IF(COUNTIF(Cost_Model!N68:N71,"Hold")=0,"Evidence recorded","Hold") -> Hold
A21: Basket comparison uses equal category spend weights. Preferences and fallback each have their own unchanged-mix baseline of 100. Compare cost changes, not absolute duty costs, across these indices.
A40: The three scenarios test scale, not three different strategies. India receives 50% of each shift; Turkey and Vietnam receive 25% each. Change the receiver weights in Assumptions to test another mix.
A41: Myanmar receives no additional share. Its observed benchmark share is retained; this makes no claim about NEXT’s existing sourcing. All candidate evidence checks remain open.
A42: Reported observations are the baseline. Common-month sensitivity removes a product-month for every partner if any partner/World observation is REVIEW or unusable. It holds FY2025 allocation weights fixed.
A43: The model excludes unobserved lead-time, working-capital and transition costs. WP009 should test whether premiums and tariff fallback overturn the benchmark result before a recommendation is made.
A44: WP004: 85.61% of China’s four-code value is in the synthetic pair. China’s tariff rate is 12% on all four codes. H5 remains partly tested because comparable capability and achievable supplier economics are unverified.
A46: Product | B46: India baseline | C46: India after | D46: India multiple | E46: Vietnam baseline | F46: Vietnam after | G46: Vietnam multiple | H46: Turkey multiple | I46: Max receiver multiple
A47: =A9 -> Cotton T-shirts | B47: =Cost_Model!D9 -> 0.10252755 | C47: =Cost_Model!R9 -> 0.11863816 | D47: =Cost_Model!AE9 -> 1.1571345 | E47: =Cost_Model!D15 -> 0.015508884 | F47: =Cost_Model!R15 -> 0.023564191 | G47: =Cost_Model!AE15 -> 1.5193995 | H47: =Cost_Model!AE14 -> 1.123337 | I47: =MAX(Cost_Model!AF6:AF15) -> 1.5193995
A48: =A10 -> MMF knitwear | B48: =Cost_Model!D19 -> 0.0035383246 | C48: =Cost_Model!R19 -> 0.010614974 | D48: =Cost_Model!AE19 -> 3 | E48: =Cost_Model!D25 -> 0.0088231666 | F48: =Cost_Model!R25 -> 0.012361491 | G48: =Cost_Model!AE25 -> 1.4010266 | H48: =Cost_Model!AE24 -> 1.0216474 | I48: =MAX(Cost_Model!AF16:AF25) -> 3
A49: =A11 -> Synthetic dresses | B49: =Cost_Model!D29 -> 0.15126886 | C49: =Cost_Model!R29 -> 0.20126886 | D49: =Cost_Model!AE29 -> 1.3305373 | E49: =Cost_Model!D35 -> 0.034917395 | F49: =Cost_Model!R35 -> 0.059917395 | G49: =Cost_Model!AE35 -> 1.7159755 | H49: =Cost_Model!AE34 -> 1.7346679 | I49: =MAX(Cost_Model!AF26:AF35) -> 1.7346679
A50: =A12 -> Cotton shirts | B50: =Cost_Model!D39 -> 0.16719111 | C50: =Cost_Model!R39 -> 0.20177106 | D50: =Cost_Model!AE39 -> 1.2068289 | E50: =Cost_Model!D45 -> 0.05205513 | F50: =Cost_Model!R45 -> 0.069345105 | G50: =Cost_Model!AE45 -> 1.3321474 | H50: =Cost_Model!AE44 -> 1.425978 | I50: =MAX(Cost_Model!AF36:AF45) -> 1.425978
A52: Multiples show scenario share divided by FY2025 baseline share. With fixed product volume they also describe the implied volume multiple. They do not measure a supplier’s production capacity.
A53: =IF(Assumptions!F14="Yes","The baseline-share multiple cap is enabled. MMF knitwear can hit this limit before the requested shift is reached. Compare the share-only case and code-specific receiver mixes in WP009.","The baseline-share multiple cap is disabled. Large implied receiver expansions remain visible above and require separate feasibility testing.") -> The baseline-share multiple cap is enabled. MMF knitwear can hit this limit before the requested shift is reached. Compare the share-only case and code-specific receiver mixes in WP009.

Sheet Assumptions
A2: WP008 model assumptions
B5: Scenario | C5: Balanced
B6: Price period | C6: H1 2026
B7: Data basis | C7: Reported
B8: Tariff window | C8: From 15 Jul 2026
B9: Tariff treatment | C9: Eligible preference
B10: Recipient country share ceiling | C10: 0.35
B11: Maximum addition per recipient | C11: 0.1
B12: Active requested shift | C12: =IF(COUNTIFS(A17:A19,C5,B17:B19,"<>")=1,SUMIF(A17:A19,C5,B17:B19),"n.a.") -> 0.1
B13: Input status | C13: =IF(AND(OR(F14="Yes",F14="No"),IF(F14="Yes",AND(ISNUMBER(C14),C14>=1),TRUE),COUNT(C10:C11)=2,C10>0,C10<=1,C11>=0,C11<=1,ISNUMBER(C12),C12>=0,C12<=1,COUNT(B24:B33)=10,MIN(B24:B33)>=0,ABS(SUM(B24:B33)-1)<0.000000001,B26=0,B29=0,COUNT(C24:C33)=10,MIN(C24:C33)>=0,COUNT(C38:C41)=4,MIN(C38:C41)>=0,ABS(SUM(C38:C41)-1)<0.000000001),"Valid","Invalid inputs") -> Valid
B14: Maximum baseline-share multiple | C14: 3 | E14: Apply multiple cap | F14: Yes
A16: Scenario | B16: Requested shift
A17: Cautious | B17: 0.05
A18: Balanced | B18: 0.1
A19: Accelerated | B19: 0.15
A23: Country | B23: Receiver weight | C23: Incremental premium | D23: Basis
A24: Bangladesh | B24: 0 | C24: 0 | D24: Scenario assumption
A25: Cambodia | B25: 0 | C25: 0 | D25: Scenario assumption
A26: China | B26: 0 | C26: 0 | D26: Scenario assumption
A27: India | B27: 0.5 | C27: 0 | D27: Scenario assumption
A28: Morocco | B28: 0 | C28: 0 | D28: Scenario assumption
A29: Myanmar | B29: 0 | C29: 0 | D29: Scenario assumption
A30: Pakistan | B30: 0 | C30: 0 | D30: Scenario assumption
A31: Sri Lanka | B31: 0 | C31: 0 | D31: Scenario assumption
A32: Turkey | B32: 0.25 | C32: 0 | D32: Scenario assumption
A33: Vietnam | B33: 0.25 | C33: 0 | D33: Scenario assumption
A37: CN8 | B37: Product | C37: Basket spend weight | E37: FY2025 UK import value (£) | F37: Value weight
A38: 61091000 | B38: Cotton T-shirts | C38: 0.25 | E38: 1223299784 | F38: =E38/SUM($E$38:$E$41) -> 0.47878752
A39: 61103099 | B39: MMF knitwear | C39: 0.25 | E39: 719371758 | F39: =E39/SUM($E$38:$E$41) -> 0.28155504
A40: 62044300 | B40: Synthetic dresses | C40: 0.25 | E40: 349077816 | F40: =E40/SUM($E$38:$E$41) -> 0.13662563
A41: 62052000 | B41: Cotton shirts | C41: 0.25 | E41: 263245768 | F41: =E41/SUM($E$38:$E$41) -> 0.10303181
A43: Amber cells are editable assumptions. Receiver weights allocate each feasible shift: India 50%, Turkey 25%, Vietnam 25%. This is a test portfolio, not an optimised allocation or a capacity assessment.
A44: China is the donor. FY2025 ten-country import-mass shares remain the fixed baseline. Myanmar retains its baseline benchmark share and receives no increment. Country ceilings constrain additions only.
A45: Receiver headroom is the minimum of the 35% share ceiling, 10pp addition limit and, when enabled, (maximum multiple − 1) × baseline share. The default 3× cap is a modelling safeguard, not verified capacity. Zero-baseline receivers cannot grow while it is enabled.
A46: Equal 25% category spend weights create a synthetic cost index. They do not represent NEXT spend. Incremental premiums apply only to transferred volume; zero means the scenario excludes a premium.
A47: The tariff window is independent of the trade period: changing it holds observed prices constant for a policy comparison. It does not estimate duty actually paid during that trade period.
A48: Illustrative requested shifts are 5/10/15pp (Q5.2). Receiver mix, ceilings, zero premiums and equal category weights are explicit model assumptions. See docs/Research_Question_and_Scope.md.
A49: Set Apply multiple cap to No to reproduce the original share-only constraints. The receiver mix remains common across codes; WP009 will test code-specific mixes and alternative growth limits.
A50: Value-weight reference: WP004 Commodity_Shortlist!G2:G5 and WP006 world_trade_period_reported, FULL_YEAR 2025. These weights are queued for WP009; active basket weights remain in C38:C41. They describe the UK four-code market, not NEXT spend.

Sheet Cost_Model
A2: Cost and allocation model
A4: Scenario: | B4: =Assumptions!C5 -> Balanced | D4: Price period: | E4: =Assumptions!C6 -> H1 2026 | H4: =Assumptions!C7 -> Reported | K4: =Assumptions!C9 -> Eligible preference
A5: CN8 | B5: Country | C5: FY25 mass (kg) | D5: Baseline share | E5: Price value (£) | F5: Price mass (kg) | G5: UV (£/kg) | H5: Eligible tariff | I5: MFN tariff | J5: Eligible £/kg | K5: MFN £/kg | L5: Active £/kg | M5: Receiver weight | N5: Premium | O5: Shift direction | P5: Shift limit | Q5: Active change | R5: Scenario share | S5: Baseline cost | T5: Scenario cost | U5: Unit-shift cost | V5: Baseline HHI | W5: HHI linear term | X5: HHI square term | Y5: Evidence-ready increment | Z5: Eligible baseline | AA5: Eligible direction | AB5: MFN baseline | AC5: MFN direction | AD5: Input coverage | AE5: Share multiple | AF5: Receiver multiple | AG5: Multiple-cap excess
A6: 61091000 | B6: Bangladesh | C6: =SUMIFS(Trade_Periods!$F$6:$F$125,Trade_Periods!$B$6:$B$125,"FY2025",Trade_Periods!$C$6:$C$125,B6,Trade_Periods!$D$6:$D$125,A6) -> 44227971 | D6: =C6/SUM(C6:C15) -> 0.58622087 | E6: =IF(Assumptions!$C$7="Reported",SUMIFS(Trade_Periods!$E$6:$E$125,Trade_Periods!$B$6:$B$125,Assumptions!$C$6,Trade_Periods!$C$6:$C$125,B6,Trade_Periods!$D$6:$D$125,A6),SUMIFS(Trade_Periods!$L$6:$L$125,Trade_Periods!$B$6:$B$125,Assumptions!$C$6,Trade_Periods!$C$6:$C$125,B6,Trade_Periods!$D$6:$D$125,A6)) -> 254631302 | F6: =IF(Assumptions!$C$7="Reported",SUMIFS(Trade_Periods!$F$6:$F$125,Trade_Periods!$B$6:$B$125,Assumptions!$C$6,Trade_Periods!$C$6:$C$125,B6,Trade_Periods!$D$6:$D$125,A6),SUMIFS(Trade_Periods!$M$6:$M$125,Trade_Periods!$B$6:$B$125,Assumptions!$C$6,Trade_Periods!$C$6:$C$125,B6,Trade_Periods!$D$6:$D$125,A6)) -> 24484056 | G6: =IF(F6>0,E6/F6,"n.a.") -> 10.399882 | H6: =IF(Assumptions!$C$8="2025",SUMIFS(Tariffs!$D$6:$D$45,Tariffs!$B$6:$B$45,B6,Tariffs!$C$6:$C$45,A6),IF(Assumptions!$C$8="1 Jan to 14 Jul 2026",SUMIFS(Tariffs!$E$6:$E$45,Tariffs!$B$6:$B$45,B6,Tariffs!$C$6:$C$45,A6),SUMIFS(Tariffs!$F$6:$F$45,Tariffs!$B$6:$B$45,B6,Tariffs!$C$6:$C$45,A6))) -> 0 | I6: =SUMIFS(Tariffs!$G$6:$G$45,Tariffs!$B$6:$B$45,B6,Tariffs!$C$6:$C$45,A6) -> 0.12 | J6: =G6*(1+H6) -> 10.399882 | K6: =G6*(1+I6) -> 11.647868 | L6: =IF(Assumptions!$C$9="Eligible preference",J6,K6) -> 10.399882 | M6: =Assumptions!B24 -> 0 | N6: =Assumptions!C24 -> 0 | O6: =IF(B6="China",-1,M6) -> 0 | P6: =IF(B6="China",D6,IF(M6>0,MAX(0,MIN(Assumptions!$C$10-D6,Assumptions!$C$11,IF(Assumptions!$F$14="Yes",(Assumptions!$C$14-1)*D6,1))/M6),1)) -> 1 | Q6: =$E51*O6 -> 0 | R6: =D6+Q6 -> 0.58622087 | S6: =D6*L6 -> 6.0966281 | T6: =R6*L6+MAX(0,Q6)*L6*N6 -> 6.0966281 | U6: =O6*L6+M6*L6*N6 -> 0 | V6: =D6^2 -> 0.34365491 | W6: =2*D6*O6 -> 0 | X6: =O6^2 -> 0 | Y6: =IF(Candidate_Gates!N6="Pass",MAX(0,Q6),0) -> 0 | Z6: =D6*J6 -> 6.0966281 | AA6: =O6*J6+M6*J6*N6 -> 0 | AB6: =D6*K6 -> 6.8282234 | AC6: =O6*K6+M6*K6*N6 -> 0 | AD6: =IF(AND(C6>=0,F6>0,E6>0,ISNUMBER(G6),COUNTIFS(Trade_Periods!$B$6:$B$125,Assumptions!$C$6,Trade_Periods!$C$6:$C$125,B6,Trade_Periods!$D$6:$D$125,A6)=1,COUNTIFS(Tariffs!$B$6:$B$45,B6,Tariffs!$C$6:$C$45,A6)=1),"Ready","Missing data") -> Ready | AE6: =IF(D6>0,R6/D6,"n.a.") -> 1 | AF6: =IF(M6>0,IF(D6>0,R6/D6,IF(R6=0,0,"n.a.")),0) -> 0 | AG6: =IF(AND(Assumptions!$F$14="Yes",M6>0),MAX(0,R6-Assumptions!$C$14*D6),0) -> 0
A7: 61091000 | B7: Cambodia | C7: =SUMIFS(Trade_Periods!$F$6:$F$125,Trade_Periods!$B$6:$B$125,"FY2025",Trade_Periods!$C$6:$C$125,B7,Trade_Periods!$D$6:$D$125,A7) -> 547756 | D7: =C7/SUM(C6:C15) -> 0.0072602471 | E7: =IF(Assumptions!$C$7="Reported",SUMIFS(Trade_Periods!$E$6:$E$125,Trade_Periods!$B$6:$B$125,Assumptions!$C$6,Trade_Periods!$C$6:$C$125,B7,Trade_Periods!$D$6:$D$125,A7),SUMIFS(Trade_Periods!$L$6:$L$125,Trade_Periods!$B$6:$B$125,Assumptions!$C$6,Trade_Periods!$C$6:$C$125,B7,Trade_Periods!$D$6:$D$125,A7)) -> 5968533 | F7: =IF(Assumptions!$C$7="Reported",SUMIFS(Trade_Periods!$F$6:$F$125,Trade_Periods!$B$6:$B$125,Assumptions!$C$6,Trade_Periods!$C$6:$C$125,B7,Trade_Periods!$D$6:$D$125,A7),SUMIFS(Trade_Periods!$M$6:$M$125,Trade_Periods!$B$6:$B$125,Assumptions!$C$6,Trade_Periods!$C$6:$C$125,B7,Trade_Periods!$D$6:$D$125,A7)) -> 334694 | G7: =IF(F7>0,E7/F7,"n.a.") -> 17.832805 | H7: =IF(Assumptions!$C$8="2025",SUMIFS(Tariffs!$D$6:$D$45,Tariffs!$B$6:$B$45,B7,Tariffs!$C$6:$C$45,A7),IF(Assumptions!$C$8="1 Jan to 14 Jul 2026",SUMIFS(Tariffs!$E$6:$E$45,Tariffs!$B$6:$B$45,B7,Tariffs!$C$6:$C$45,A7),SUMIFS(Tariffs!$F$6:$F$45,Tariffs!$B$6:$B$45,B7,Tariffs!$C$6:$C$45,A7))) -> 0 | I7: =SUMIFS(Tariffs!$G$6:$G$45,Tariffs!$B$6:$B$45,B7,Tariffs!$C$6:$C$45,A7) -> 0.12 | J7: =G7*(1+H7) -> 17.832805 | K7: =G7*(1+I7) -> 19.972742 | L7: =IF(Assumptions!$C$9="Eligible preference",J7,K7) -> 17.832805 | M7: =Assumptions!B25 -> 0 | N7: =Assumptions!C25 -> 0 | O7: =IF(B7="China",-1,M7) -> 0 | P7: =IF(B7="China",D7,IF(M7>0,MAX(0,MIN(Assumptions!$C$10-D7,Assumptions!$C$11,IF(Assumptions!$F$14="Yes",(Assumptions!$C$14-1)*D7,1))/M7),1)) -> 1 | Q7: =$E51*O7 -> 0 | R7: =D7+Q7 -> 0.0072602471 | S7: =D7*L7 -> 0.12947057 | T7: =R7*L7+MAX(0,Q7)*L7*N7 -> 0.12947057 | U7: =O7*L7+M7*L7*N7 -> 0 | V7: =D7^2 -> 5.2711188e-05 | W7: =2*D7*O7 -> 0 | X7: =O7^2 -> 0 | Y7: =IF(Candidate_Gates!N7="Pass",MAX(0,Q7),0) -> 0 | Z7: =D7*J7 -> 0.12947057 | AA7: =O7*J7+M7*J7*N7 -> 0 | AB7: =D7*K7 -> 0.14500704 | AC7: =O7*K7+M7*K7*N7 -> 0 | AD7: =IF(AND(C7>=0,F7>0,E7>0,ISNUMBER(G7),COUNTIFS(Trade_Periods!$B$6:$B$125,Assumptions!$C$6,Trade_Periods!$C$6:$C$125,B7,Trade_Periods!$D$6:$D$125,A7)=1,COUNTIFS(Tariffs!$B$6:$B$45,B7,Tariffs!$C$6:$C$45,A7)=1),"Ready","Missing data") -> Ready | AE7: =IF(D7>0,R7/D7,"n.a.") -> 1 | AF7: =IF(M7>0,IF(D7>0,R7/D7,IF(R7=0,0,"n.a.")),0) -> 0 | AG7: =IF(AND(Assumptions!$F$14="Yes",M7>0),MAX(0,R7-Assumptions!$C$14*D7),0) -> 0
A8: 61091000 | B8: China | C8: =SUMIFS(Trade_Periods!$F$6:$F$125,Trade_Periods!$B$6:$B$125,"FY2025",Trade_Periods!$C$6:$C$125,B8,Trade_Periods!$D$6:$D$125,A8) -> 2430960 | D8: =C8/SUM(C6:C15) -> 0.032221227 | E8: =IF(Assumptions!$C$7="Reported",SUMIFS(Trade_Periods!$E$6:$E$125,Trade_Periods!$B$6:$B$125,Assumptions!$C$6,Trade_Periods!$C$6:$C$125,B8,Trade_Periods!$D$6:$D$125,A8),SUMIFS(Trade_Periods!$L$6:$L$125,Trade_Periods!$B$6:$B$125,Assumptions!$C$6,Trade_Periods!$C$6:$C$125,B8,Trade_Periods!$D$6:$D$125,A8)) -> 27268063 | F8: =IF(Assumptions!$C$7="Reported",SUMIFS(Trade_Periods!$F$6:$F$125,Trade_Periods!$B$6:$B$125,Assumptions!$C$6,Trade_Periods!$C$6:$C$125,B8,Trade_Periods!$D$6:$D$125,A8),SUMIFS(Trade_Periods!$M$6:$M$125,Trade_Periods!$B$6:$B$125,Assumptions!$C$6,Trade_Periods!$C$6:$C$125,B8,Trade_Periods!$D$6:$D$125,A8)) -> 1611661 | G8: =IF(F8>0,E8/F8,"n.a.") -> 16.91923 | H8: =IF(Assumptions!$C$8="2025",SUMIFS(Tariffs!$D$6:$D$45,Tariffs!$B$6:$B$45,B8,Tariffs!$C$6:$C$45,A8),IF(Assumptions!$C$8="1 Jan to 14 Jul 2026",SUMIFS(Tariffs!$E$6:$E$45,Tariffs!$B$6:$B$45,B8,Tariffs!$C$6:$C$45,A8),SUMIFS(Tariffs!$F$6:$F$45,Tariffs!$B$6:$B$45,B8,Tariffs!$C$6:$C$45,A8))) -> 0.12 | I8: =SUMIFS(Tariffs!$G$6:$G$45,Tariffs!$B$6:$B$45,B8,Tariffs!$C$6:$C$45,A8) -> 0.12 | J8: =G8*(1+H8) -> 18.949538 | K8: =G8*(1+I8) -> 18.949538 | L8: =IF(Assumptions!$C$9="Eligible preference",J8,K8) -> 18.949538 | M8: =Assumptions!B26 -> 0 | N8: =Assumptions!C26 -> 0 | O8: =IF(B8="China",-1,M8) -> -1 | P8: =IF(B8="China",D8,IF(M8>0,MAX(0,MIN(Assumptions!$C$10-D8,Assumptions!$C$11,IF(Assumptions!$F$14="Yes",(Assumptions!$C$14-1)*D8,1))/M8),1)) -> 0.032221227 | Q8: =$E51*O8 -> -0.032221227 | R8: =D8+Q8 -> 0 | S8: =D8*L8 -> 0.61057734 | T8: =R8*L8+MAX(0,Q8)*L8*N8 -> 0 | U8: =O8*L8+M8*L8*N8 -> -18.949538 | V8: =D8^2 -> 0.0010382075 | W8: =2*D8*O8 -> -0.064442454 | X8: =O8^2 -> 1 | Y8: =IF(Candidate_Gates!N8="Pass",MAX(0,Q8),0) -> 0 | Z8: =D8*J8 -> 0.61057734 | AA8: =O8*J8+M8*J8*N8 -> -18.949538 | AB8: =D8*K8 -> 0.61057734 | AC8: =O8*K8+M8*K8*N8 -> -18.949538 | AD8: =IF(AND(C8>=0,F8>0,E8>0,ISNUMBER(G8),COUNTIFS(Trade_Periods!$B$6:$B$125,Assumptions!$C$6,Trade_Periods!$C$6:$C$125,B8,Trade_Periods!$D$6:$D$125,A8)=1,COUNTIFS(Tariffs!$B$6:$B$45,B8,Tariffs!$C$6:$C$45,A8)=1),"Ready","Missing data") -> Ready | AE8: =IF(D8>0,R8/D8,"n.a.") -> 0 | AF8: =IF(M8>0,IF(D8>0,R8/D8,IF(R8=0,0,"n.a.")),0) -> 0 | AG8: =IF(AND(Assumptions!$F$14="Yes",M8>0),MAX(0,R8-Assumptions!$C$14*D8),0) -> 0
A9: 61091000 | B9: India | C9: =SUMIFS(Trade_Periods!$F$6:$F$125,Trade_Periods!$B$6:$B$125,"FY2025",Trade_Periods!$C$6:$C$125,B9,Trade_Periods!$D$6:$D$125,A9) -> 7735285 | D9: =C9/SUM(C6:C15) -> 0.10252755 | E9: =IF(Assumptions!$C$7="Reported",SUMIFS(Trade_Periods!$E$6:$E$125,Trade_Periods!$B$6:$B$125,Assumptions!$C$6,Trade_Periods!$C$6:$C$125,B9,Trade_Periods!$D$6:$D$125,A9),SUMIFS(Trade_Periods!$L$6:$L$125,Trade_Periods!$B$6:$B$125,Assumptions!$C$6,Trade_Periods!$C$6:$C$125,B9,Trade_Periods!$D$6:$D$125,A9)) -> 54416583 | F9: =IF(Assumptions!$C$7="Reported",SUMIFS(Trade_Periods!$F$6:$F$125,Trade_Periods!$B$6:$B$125,Assumptions!$C$6,Trade_Periods!$C$6:$C$125,B9,Trade_Periods!$D$6:$D$125,A9),SUMIFS(Trade_Periods!$M$6:$M$125,Trade_Periods!$B$6:$B$125,Assumptions!$C$6,Trade_Periods!$C$6:$C$125,B9,Trade_Periods!$D$6:$D$125,A9)) -> 4347817 | G9: =IF(F9>0,E9/F9,"n.a.") -> 12.51584 | H9: =IF(Assumptions!$C$8="2025",SUMIFS(Tariffs!$D$6:$D$45,Tariffs!$B$6:$B$45,B9,Tariffs!$C$6:$C$45,A9),IF(Assumptions!$C$8="1 Jan to 14 Jul 2026",SUMIFS(Tariffs!$E$6:$E$45,Tariffs!$B$6:$B$45,B9,Tariffs!$C$6:$C$45,A9),SUMIFS(Tariffs!$F$6:$F$45,Tariffs!$B$6:$B$45,B9,Tariffs!$C$6:$C$45,A9))) -> 0 | I9: =SUMIFS(Tariffs!$G$6:$G$45,Tariffs!$B$6:$B$45,B9,Tariffs!$C$6:$C$45,A9) -> 0.12 | J9: =G9*(1+H9) -> 12.51584 | K9: =G9*(1+I9) -> 14.017741 | L9: =IF(Assumptions!$C$9="Eligible preference",J9,K9) -> 12.51584 | M9: =Assumptions!B27 -> 0.5 | N9: =Assumptions!C27 -> 0 | O9: =IF(B9="China",-1,M9) -> 0.5 | P9: =IF(B9="China",D9,IF(M9>0,MAX(0,MIN(Assumptions!$C$10-D9,Assumptions!$C$11,IF(Assumptions!$F$14="Yes",(Assumptions!$C$14-1)*D9,1))/M9),1)) -> 0.2 | Q9: =$E51*O9 -> 0.016110613 | R9: =D9+Q9 -> 0.11863816 | S9: =D9*L9 -> 1.2832184 | T9: =R9*L9+MAX(0,Q9)*L9*N9 -> 1.4848563 | U9: =O9*L9+M9*L9*N9 -> 6.2579201 | V9: =D9^2 -> 0.010511898 | W9: =2*D9*O9 -> 0.10252755 | X9: =O9^2 -> 0.25 | Y9: =IF(Candidate_Gates!N9="Pass",MAX(0,Q9),0) -> 0 | Z9: =D9*J9 -> 1.2832184 | AA9: =O9*J9+M9*J9*N9 -> 6.2579201 | AB9: =D9*K9 -> 1.4372046 | AC9: =O9*K9+M9*K9*N9 -> 7.0088705 | AD9: =IF(AND(C9>=0,F9>0,E9>0,ISNUMBER(G9),COUNTIFS(Trade_Periods!$B$6:$B$125,Assumptions!$C$6,Trade_Periods!$C$6:$C$125,B9,Trade_Periods!$D$6:$D$125,A9)=1,COUNTIFS(Tariffs!$B$6:$B$45,B9,Tariffs!$C$6:$C$45,A9)=1),"Ready","Missing data") -> Ready | AE9: =IF(D9>0,R9/D9,"n.a.") -> 1.1571345 | AF9: =IF(M9>0,IF(D9>0,R9/D9,IF(R9=0,0,"n.a.")),0) -> 1.1571345 | AG9: =IF(AND(Assumptions!$F$14="Yes",M9>0),MAX(0,R9-Assumptions!$C$14*D9),0) -> 0
A10: 61091000 | B10: Morocco | C10: =SUMIFS(Trade_Periods!$F$6:$F$125,Trade_Periods!$B$6:$B$125,"FY2025",Trade_Periods!$C$6:$C$125,B10,Trade_Periods!$D$6:$D$125,A10) -> 1265062 | D10: =C10/SUM(C6:C15) -> 0.016767799 | E10: =IF(Assumptions!$C$7="Reported",SUMIFS(Trade_Periods!$E$6:$E$125,Trade_Periods!$B$6:$B$125,Assumptions!$C$6,Trade_Periods!$C$6:$C$125,B10,Trade_Periods!$D$6:$D$125,A10),SUMIFS(Trade_Periods!$L$6:$L$125,Trade_Periods!$B$6:$B$125,Assumptions!$C$6,Trade_Periods!$C$6:$C$125,B10,Trade_Periods!$D$6:$D$125,A10)) -> 4957179 | F10: =IF(Assumptions!$C$7="Reported",SUMIFS(Trade_Periods!$F$6:$F$125,Trade_Periods!$B$6:$B$125,Assumptions!$C$6,Trade_Periods!$C$6:$C$125,B10,Trade_Periods!$D$6:$D$125,A10),SUMIFS(Trade_Periods!$M$6:$M$125,Trade_Periods!$B$6:$B$125,Assumptions!$C$6,Trade_Periods!$C$6:$C$125,B10,Trade_Periods!$D$6:$D$125,A10)) -> 526732 | G10: =IF(F10>0,E10/F10,"n.a.") -> 9.4111977 | H10: =IF(Assumptions!$C$8="2025",SUMIFS(Tariffs!$D$6:$D$45,Tariffs!$B$6:$B$45,B10,Tariffs!$C$6:$C$45,A10),IF(Assumptions!$C$8="1 Jan to 14 Jul 2026",SUMIFS(Tariffs!$E$6:$E$45,Tariffs!$B$6:$B$45,B10,Tariffs!$C$6:$C$45,A10),SUMIFS(Tariffs!$F$6:$F$45,Tariffs!$B$6:$B$45,B10,Tariffs!$C$6:$C$45,A10))) -> 0 | I10: =SUMIFS(Tariffs!$G$6:$G$45,Tariffs!$B$6:$B$45,B10,Tariffs!$C$6:$C$45,A10) -> 0.12 | J10: =G10*(1+H10) -> 9.4111977 | K10: =G10*(1+I10) -> 10.540541 | L10: =IF(Assumptions!$C$9="Eligible preference",J10,K10) -> 9.4111977 | M10: =Assumptions!B28 -> 0 | N10: =Assumptions!C28 -> 0 | O10: =IF(B10="China",-1,M10) -> 0 | P10: =IF(B10="China",D10,IF(M10>0,MAX(0,MIN(Assumptions!$C$10-D10,Assumptions!$C$11,IF(Assumptions!$F$14="Yes",(Assumptions!$C$14-1)*D10,1))/M10),1)) -> 1 | Q10: =$E51*O10 -> 0 | R10: =D10+Q10 -> 0.016767799 | S10: =D10*L10 -> 0.15780508 | T10: =R10*L10+MAX(0,Q10)*L10*N10 -> 0.15780508 | U10: =O10*L10+M10*L10*N10 -> 0 | V10: =D10^2 -> 0.0002811591 | W10: =2*D10*O10 -> 0 | X10: =O10^2 -> 0 | Y10: =IF(Candidate_Gates!N10="Pass",MAX(0,Q10),0) -> 0 | Z10: =D10*J10 -> 0.15780508 | AA10: =O10*J10+M10*J10*N10 -> 0 | AB10: =D10*K10 -> 0.17674168 | AC10: =O10*K10+M10*K10*N10 -> 0 | AD10: =IF(AND(C10>=0,F10>0,E10>0,ISNUMBER(G10),COUNTIFS(Trade_Periods!$B$6:$B$125,Assumptions!$C$6,Trade_Periods!$C$6:$C$125,B10,Trade_Periods!$D$6:$D$125,A10)=1,COUNTIFS(Tariffs!$B$6:$B$45,B10,Tariffs!$C$6:$C$45,A10)=1),"Ready","Missing data") -> Ready | AE10: =IF(D10>0,R10/D10,"n.a.") -> 1 | AF10: =IF(M10>0,IF(D10>0,R10/D10,IF(R10=0,0,"n.a.")),0) -> 0 | AG10: =IF(AND(Assumptions!$F$14="Yes",M10>0),MAX(0,R10-Assumptions!$C$14*D10),0) -> 0
A11: 61091000 | B11: Myanmar | C11: =SUMIFS(Trade_Periods!$F$6:$F$125,Trade_Periods!$B$6:$B$125,"FY2025",Trade_Periods!$C$6:$C$125,B11,Trade_Periods!$D$6:$D$125,A11) -> 29326 | D11: =C11/SUM(C6:C15) -> 0.00038870228 | E11: =IF(Assumptions!$C$7="Reported",SUMIFS(Trade_Periods!$E$6:$E$125,Trade_Periods!$B$6:$B$125,Assumptions!$C$6,Trade_Periods!$C$6:$C$125,B11,Trade_Periods!$D$6:$D$125,A11),SUMIFS(Trade_Periods!$L$6:$L$125,Trade_Periods!$B$6:$B$125,Assumptions!$C$6,Trade_Periods!$C$6:$C$125,B11,Trade_Periods!$D$6:$D$125,A11)) -> 619607 | F11: =IF(Assumptions!$C$7="Reported",SUMIFS(Trade_Periods!$F$6:$F$125,Trade_Periods!$B$6:$B$125,Assumptions!$C$6,Trade_Periods!$C$6:$C$125,B11,Trade_Periods!$D$6:$D$125,A11),SUMIFS(Trade_Periods!$M$6:$M$125,Trade_Periods!$B$6:$B$125,Assumptions!$C$6,Trade_Periods!$C$6:$C$125,B11,Trade_Periods!$D$6:$D$125,A11)) -> 58361 | G11: =IF(F11>0,E11/F11,"n.a.") -> 10.616799 | H11: =IF(Assumptions!$C$8="2025",SUMIFS(Tariffs!$D$6:$D$45,Tariffs!$B$6:$B$45,B11,Tariffs!$C$6:$C$45,A11),IF(Assumptions!$C$8="1 Jan to 14 Jul 2026",SUMIFS(Tariffs!$E$6:$E$45,Tariffs!$B$6:$B$45,B11,Tariffs!$C$6:$C$45,A11),SUMIFS(Tariffs!$F$6:$F$45,Tariffs!$B$6:$B$45,B11,Tariffs!$C$6:$C$45,A11))) -> 0 | I11: =SUMIFS(Tariffs!$G$6:$G$45,Tariffs!$B$6:$B$45,B11,Tariffs!$C$6:$C$45,A11) -> 0.12 | J11: =G11*(1+H11) -> 10.616799 | K11: =G11*(1+I11) -> 11.890815 | L11: =IF(Assumptions!$C$9="Eligible preference",J11,K11) -> 10.616799 | M11: =Assumptions!B29 -> 0 | N11: =Assumptions!C29 -> 0 | O11: =IF(B11="China",-1,M11) -> 0 | P11: =IF(B11="China",D11,IF(M11>0,MAX(0,MIN(Assumptions!$C$10-D11,Assumptions!$C$11,IF(Assumptions!$F$14="Yes",(Assumptions!$C$14-1)*D11,1))/M11),1)) -> 1 | Q11: =$E51*O11 -> 0 | R11: =D11+Q11 -> 0.00038870228 | S11: =D11*L11 -> 0.0041267739 | T11: =R11*L11+MAX(0,Q11)*L11*N11 -> 0.0041267739 | U11: =O11*L11+M11*L11*N11 -> 0 | V11: =D11^2 -> 1.5108946e-07 | W11: =2*D11*O11 -> 0 | X11: =O11^2 -> 0 | Y11: =IF(Candidate_Gates!N11="Pass",MAX(0,Q11),0) -> 0 | Z11: =D11*J11 -> 0.0041267739 | AA11: =O11*J11+M11*J11*N11 -> 0 | AB11: =D11*K11 -> 0.0046219868 | AC11: =O11*K11+M11*K11*N11 -> 0 | AD11: =IF(AND(C11>=0,F11>0,E11>0,ISNUMBER(G11),COUNTIFS(Trade_Periods!$B$6:$B$125,Assumptions!$C$6,Trade_Periods!$C$6:$C$125,B11,Trade_Periods!$D$6:$D$125,A11)=1,COUNTIFS(Tariffs!$B$6:$B$45,B11,Tariffs!$C$6:$C$45,A11)=1),"Ready","Missing data") -> Ready | AE11: =IF(D11>0,R11/D11,"n.a.") -> 1 | AF11: =IF(M11>0,IF(D11>0,R11/D11,IF(R11=0,0,"n.a.")),0) -> 0 | AG11: =IF(AND(Assumptions!$F$14="Yes",M11>0),MAX(0,R11-Assumptions!$C$14*D11),0) -> 0
A12: 61091000 | B12: Pakistan | C12: =SUMIFS(Trade_Periods!$F$6:$F$125,Trade_Periods!$B$6:$B$125,"FY2025",Trade_Periods!$C$6:$C$125,B12,Trade_Periods!$D$6:$D$125,A12) -> 10896985 | D12: =C12/SUM(C6:C15) -> 0.14443439 | E12: =IF(Assumptions!$C$7="Reported",SUMIFS(Trade_Periods!$E$6:$E$125,Trade_Periods!$B$6:$B$125,Assumptions!$C$6,Trade_Periods!$C$6:$C$125,B12,Trade_Periods!$D$6:$D$125,A12),SUMIFS(Trade_Periods!$L$6:$L$125,Trade_Periods!$B$6:$B$125,Assumptions!$C$6,Trade_Periods!$C$6:$C$125,B12,Trade_Periods!$D$6:$D$125,A12)) -> 20868271 | F12: =IF(Assumptions!$C$7="Reported",SUMIFS(Trade_Periods!$F$6:$F$125,Trade_Periods!$B$6:$B$125,Assumptions!$C$6,Trade_Periods!$C$6:$C$125,B12,Trade_Periods!$D$6:$D$125,A12),SUMIFS(Trade_Periods!$M$6:$M$125,Trade_Periods!$B$6:$B$125,Assumptions!$C$6,Trade_Periods!$C$6:$C$125,B12,Trade_Periods!$D$6:$D$125,A12)) -> 1714193 | G12: =IF(F12>0,E12/F12,"n.a.") -> 12.173816 | H12: =IF(Assumptions!$C$8="2025",SUMIFS(Tariffs!$D$6:$D$45,Tariffs!$B$6:$B$45,B12,Tariffs!$C$6:$C$45,A12),IF(Assumptions!$C$8="1 Jan to 14 Jul 2026",SUMIFS(Tariffs!$E$6:$E$45,Tariffs!$B$6:$B$45,B12,Tariffs!$C$6:$C$45,A12),SUMIFS(Tariffs!$F$6:$F$45,Tariffs!$B$6:$B$45,B12,Tariffs!$C$6:$C$45,A12))) -> 0 | I12: =SUMIFS(Tariffs!$G$6:$G$45,Tariffs!$B$6:$B$45,B12,Tariffs!$C$6:$C$45,A12) -> 0.12 | J12: =G12*(1+H12) -> 12.173816 | K12: =G12*(1+I12) -> 13.634674 | L12: =IF(Assumptions!$C$9="Eligible preference",J12,K12) -> 12.173816 | M12: =Assumptions!B30 -> 0 | N12: =Assumptions!C30 -> 0 | O12: =IF(B12="China",-1,M12) -> 0 | P12: =IF(B12="China",D12,IF(M12>0,MAX(0,MIN(Assumptions!$C$10-D12,Assumptions!$C$11,IF(Assumptions!$F$14="Yes",(Assumptions!$C$14-1)*D12,1))/M12),1)) -> 1 | Q12: =$E51*O12 -> 0 | R12: =D12+Q12 -> 0.14443439 | S12: =D12*L12 -> 1.7583178 | T12: =R12*L12+MAX(0,Q12)*L12*N12 -> 1.7583178 | U12: =O12*L12+M12*L12*N12 -> 0 | V12: =D12^2 -> 0.020861293 | W12: =2*D12*O12 -> 0 | X12: =O12^2 -> 0 | Y12: =IF(Candidate_Gates!N12="Pass",MAX(0,Q12),0) -> 0 | Z12: =D12*J12 -> 1.7583178 | AA12: =O12*J12+M12*J12*N12 -> 0 | AB12: =D12*K12 -> 1.9693159 | AC12: =O12*K12+M12*K12*N12 -> 0 | AD12: =IF(AND(C12>=0,F12>0,E12>0,ISNUMBER(G12),COUNTIFS(Trade_Periods!$B$6:$B$125,Assumptions!$C$6,Trade_Periods!$C$6:$C$125,B12,Trade_Periods!$D$6:$D$125,A12)=1,COUNTIFS(Tariffs!$B$6:$B$45,B12,Tariffs!$C$6:$C$45,A12)=1),"Ready","Missing data") -> Ready | AE12: =IF(D12>0,R12/D12,"n.a.") -> 1 | AF12: =IF(M12>0,IF(D12>0,R12/D12,IF(R12=0,0,"n.a.")),0) -> 0 | AG12: =IF(AND(Assumptions!$F$14="Yes",M12>0),MAX(0,R12-Assumptions!$C$14*D12),0) -> 0
A13: 61091000 | B13: Sri Lanka | C13: =SUMIFS(Trade_Periods!$F$6:$F$125,Trade_Periods!$B$6:$B$125,"FY2025",Trade_Periods!$C$6:$C$125,B13,Trade_Periods!$D$6:$D$125,A13) -> 2215013 | D13: =C13/SUM(C6:C15) -> 0.029358951 | E13: =IF(Assumptions!$C$7="Reported",SUMIFS(Trade_Periods!$E$6:$E$125,Trade_Periods!$B$6:$B$125,Assumptions!$C$6,Trade_Periods!$C$6:$C$125,B13,Trade_Periods!$D$6:$D$125,A13),SUMIFS(Trade_Periods!$L$6:$L$125,Trade_Periods!$B$6:$B$125,Assumptions!$C$6,Trade_Periods!$C$6:$C$125,B13,Trade_Periods!$D$6:$D$125,A13)) -> 8791535 | F13: =IF(Assumptions!$C$7="Reported",SUMIFS(Trade_Periods!$F$6:$F$125,Trade_Periods!$B$6:$B$125,Assumptions!$C$6,Trade_Periods!$C$6:$C$125,B13,Trade_Periods!$D$6:$D$125,A13),SUMIFS(Trade_Periods!$M$6:$M$125,Trade_Periods!$B$6:$B$125,Assumptions!$C$6,Trade_Periods!$C$6:$C$125,B13,Trade_Periods!$D$6:$D$125,A13)) -> 729136 | G13: =IF(F13>0,E13/F13,"n.a.") -> 12.057469 | H13: =IF(Assumptions!$C$8="2025",SUMIFS(Tariffs!$D$6:$D$45,Tariffs!$B$6:$B$45,B13,Tariffs!$C$6:$C$45,A13),IF(Assumptions!$C$8="1 Jan to 14 Jul 2026",SUMIFS(Tariffs!$E$6:$E$45,Tariffs!$B$6:$B$45,B13,Tariffs!$C$6:$C$45,A13),SUMIFS(Tariffs!$F$6:$F$45,Tariffs!$B$6:$B$45,B13,Tariffs!$C$6:$C$45,A13))) -> 0 | I13: =SUMIFS(Tariffs!$G$6:$G$45,Tariffs!$B$6:$B$45,B13,Tariffs!$C$6:$C$45,A13) -> 0.12 | J13: =G13*(1+H13) -> 12.057469 | K13: =G13*(1+I13) -> 13.504366 | L13: =IF(Assumptions!$C$9="Eligible preference",J13,K13) -> 12.057469 | M13: =Assumptions!B31 -> 0 | N13: =Assumptions!C31 -> 0 | O13: =IF(B13="China",-1,M13) -> 0 | P13: =IF(B13="China",D13,IF(M13>0,MAX(0,MIN(Assumptions!$C$10-D13,Assumptions!$C$11,IF(Assumptions!$F$14="Yes",(Assumptions!$C$14-1)*D13,1))/M13),1)) -> 1 | Q13: =$E51*O13 -> 0 | R13: =D13+Q13 -> 0.029358951 | S13: =D13*L13 -> 0.35399466 | T13: =R13*L13+MAX(0,Q13)*L13*N13 -> 0.35399466 | U13: =O13*L13+M13*L13*N13 -> 0 | V13: =D13^2 -> 0.00086194802 | W13: =2*D13*O13 -> 0 | X13: =O13^2 -> 0 | Y13: =IF(Candidate_Gates!N13="Pass",MAX(0,Q13),0) -> 0 | Z13: =D13*J13 -> 0.35399466 | AA13: =O13*J13+M13*J13*N13 -> 0 | AB13: =D13*K13 -> 0.39647401 | AC13: =O13*K13+M13*K13*N13 -> 0 | AD13: =IF(AND(C13>=0,F13>0,E13>0,ISNUMBER(G13),COUNTIFS(Trade_Periods!$B$6:$B$125,Assumptions!$C$6,Trade_Periods!$C$6:$C$125,B13,Trade_Periods!$D$6:$D$125,A13)=1,COUNTIFS(Tariffs!$B$6:$B$45,B13,Tariffs!$C$6:$C$45,A13)=1),"Ready","Missing data") -> Ready | AE13: =IF(D13>0,R13/D13,"n.a.") -> 1 | AF13: =IF(M13>0,IF(D13>0,R13/D13,IF(R13=0,0,"n.a.")),0) -> 0 | AG13: =IF(AND(Assumptions!$F$14="Yes",M13>0),MAX(0,R13-Assumptions!$C$14*D13),0) -> 0
A14: 61091000 | B14: Turkey | C14: =SUMIFS(Trade_Periods!$F$6:$F$125,Trade_Periods!$B$6:$B$125,"FY2025",Trade_Periods!$C$6:$C$125,B14,Trade_Periods!$D$6:$D$125,A14) -> 4927477 | D14: =C14/SUM(C6:C15) -> 0.065311381 | E14: =IF(Assumptions!$C$7="Reported",SUMIFS(Trade_Periods!$E$6:$E$125,Trade_Periods!$B$6:$B$125,Assumptions!$C$6,Trade_Periods!$C$6:$C$125,B14,Trade_Periods!$D$6:$D$125,A14),SUMIFS(Trade_Periods!$L$6:$L$125,Trade_Periods!$B$6:$B$125,Assumptions!$C$6,Trade_Periods!$C$6:$C$125,B14,Trade_Periods!$D$6:$D$125,A14)) -> 58384062 | F14: =IF(Assumptions!$C$7="Reported",SUMIFS(Trade_Periods!$F$6:$F$125,Trade_Periods!$B$6:$B$125,Assumptions!$C$6,Trade_Periods!$C$6:$C$125,B14,Trade_Periods!$D$6:$D$125,A14),SUMIFS(Trade_Periods!$M$6:$M$125,Trade_Periods!$B$6:$B$125,Assumptions!$C$6,Trade_Periods!$C$6:$C$125,B14,Trade_Periods!$D$6:$D$125,A14)) -> 2450042 | G14: =IF(F14>0,E14/F14,"n.a.") -> 23.829821 | H14: =IF(Assumptions!$C$8="2025",SUMIFS(Tariffs!$D$6:$D$45,Tariffs!$B$6:$B$45,B14,Tariffs!$C$6:$C$45,A14),IF(Assumptions!$C$8="1 Jan to 14 Jul 2026",SUMIFS(Tariffs!$E$6:$E$45,Tariffs!$B$6:$B$45,B14,Tariffs!$C$6:$C$45,A14),SUMIFS(Tariffs!$F$6:$F$45,Tariffs!$B$6:$B$45,B14,Tariffs!$C$6:$C$45,A14))) -> 0 | I14: =SUMIFS(Tariffs!$G$6:$G$45,Tariffs!$B$6:$B$45,B14,Tariffs!$C$6:$C$45,A14) -> 0.12 | J14: =G14*(1+H14) -> 23.829821 | K14: =G14*(1+I14) -> 26.689399 | L14: =IF(Assumptions!$C$9="Eligible preference",J14,K14) -> 23.829821 | M14: =Assumptions!B32 -> 0.25 | N14: =Assumptions!C32 -> 0 | O14: =IF(B14="China",-1,M14) -> 0.25 | P14: =IF(B14="China",D14,IF(M14>0,MAX(0,MIN(Assumptions!$C$10-D14,Assumptions!$C$11,IF(Assumptions!$F$14="Yes",(Assumptions!$C$14-1)*D14,1))/M14),1)) -> 0.4 | Q14: =$E51*O14 -> 0.0080553067 | R14: =D14+Q14 -> 0.073366687 | S14: =D14*L14 -> 1.5563585 | T14: =R14*L14+MAX(0,Q14)*L14*N14 -> 1.748315 | U14: =O14*L14+M14*L14*N14 -> 5.9574552 | V14: =D14^2 -> 0.0042655764 | W14: =2*D14*O14 -> 0.03265569 | X14: =O14^2 -> 0.0625 | Y14: =IF(Candidate_Gates!N14="Pass",MAX(0,Q14),0) -> 0 | Z14: =D14*J14 -> 1.5563585 | AA14: =O14*J14+M14*J14*N14 -> 5.9574552 | AB14: =D14*K14 -> 1.7431215 | AC14: =O14*K14+M14*K14*N14 -> 6.6723498 | AD14: =IF(AND(C14>=0,F14>0,E14>0,ISNUMBER(G14),COUNTIFS(Trade_Periods!$B$6:$B$125,Assumptions!$C$6,Trade_Periods!$C$6:$C$125,B14,Trade_Periods!$D$6:$D$125,A14)=1,COUNTIFS(Tariffs!$B$6:$B$45,B14,Tariffs!$C$6:$C$45,A14)=1),"Ready","Missing data") -> Ready | AE14: =IF(D14>0,R14/D14,"n.a.") -> 1.123337 | AF14: =IF(M14>0,IF(D14>0,R14/D14,IF(R14=0,0,"n.a.")),0) -> 1.123337 | AG14: =IF(AND(Assumptions!$F$14="Yes",M14>0),MAX(0,R14-Assumptions!$C$14*D14),0) -> 0
A15: 61091000 | B15: Vietnam | C15: =SUMIFS(Trade_Periods!$F$6:$F$125,Trade_Periods!$B$6:$B$125,"FY2025",Trade_Periods!$C$6:$C$125,B15,Trade_Periods!$D$6:$D$125,A15) -> 1170082 | D15: =C15/SUM(C6:C15) -> 0.015508884 | E15: =IF(Assumptions!$C$7="Reported",SUMIFS(Trade_Periods!$E$6:$E$125,Trade_Periods!$B$6:$B$125,Assumptions!$C$6,Trade_Periods!$C$6:$C$125,B15,Trade_Periods!$D$6:$D$125,A15),SUMIFS(Trade_Periods!$L$6:$L$125,Trade_Periods!$B$6:$B$125,Assumptions!$C$6,Trade_Periods!$C$6:$C$125,B15,Trade_Periods!$D$6:$D$125,A15)) -> 13656174 | F15: =IF(Assumptions!$C$7="Reported",SUMIFS(Trade_Periods!$F$6:$F$125,Trade_Periods!$B$6:$B$125,Assumptions!$C$6,Trade_Periods!$C$6:$C$125,B15,Trade_Periods!$D$6:$D$125,A15),SUMIFS(Trade_Periods!$M$6:$M$125,Trade_Periods!$B$6:$B$125,Assumptions!$C$6,Trade_Periods!$C$6:$C$125,B15,Trade_Periods!$D$6:$D$125,A15)) -> 532624 | G15: =IF(F15>0,E15/F15,"n.a.") -> 25.639427 | H15: =IF(Assumptions!$C$8="2025",SUMIFS(Tariffs!$D$6:$D$45,Tariffs!$B$6:$B$45,B15,Tariffs!$C$6:$C$45,A15),IF(Assumptions!$C$8="1 Jan to 14 Jul 2026",SUMIFS(Tariffs!$E$6:$E$45,Tariffs!$B$6:$B$45,B15,Tariffs!$C$6:$C$45,A15),SUMIFS(Tariffs!$F$6:$F$45,Tariffs!$B$6:$B$45,B15,Tariffs!$C$6:$C$45,A15))) -> 0 | I15: =SUMIFS(Tariffs!$G$6:$G$45,Tariffs!$B$6:$B$45,B15,Tariffs!$C$6:$C$45,A15) -> 0.12 | J15: =G15*(1+H15) -> 25.639427 | K15: =G15*(1+I15) -> 28.716158 | L15: =IF(Assumptions!$C$9="Eligible preference",J15,K15) -> 25.639427 | M15: =Assumptions!B33 -> 0.25 | N15: =Assumptions!C33 -> 0 | O15: =IF(B15="China",-1,M15) -> 0.25 | P15: =IF(B15="China",D15,IF(M15>0,MAX(0,MIN(Assumptions!$C$10-D15,Assumptions!$C$11,IF(Assumptions!$F$14="Yes",(Assumptions!$C$14-1)*D15,1))/M15),1)) -> 0.12407107 | Q15: =$E51*O15 -> 0.0080553067 | R15: =D15+Q15 -> 0.023564191 | S15: =D15*L15 -> 0.3976389 | T15: =R15*L15+MAX(0,Q15)*L15*N15 -> 0.60417235 | U15: =O15*L15+M15*L15*N15 -> 6.4098567 | V15: =D15^2 -> 0.00024052549 | W15: =2*D15*O15 -> 0.0077544422 | X15: =O15^2 -> 0.0625 | Y15: =IF(Candidate_Gates!N15="Pass",MAX(0,Q15),0) -> 0 | Z15: =D15*J15 -> 0.3976389 | AA15: =O15*J15+M15*J15*N15 -> 6.4098567 | AB15: =D15*K15 -> 0.44535557 | AC15: =O15*K15+M15*K15*N15 -> 7.1790395 | AD15: =IF(AND(C15>=0,F15>0,E15>0,ISNUMBER(G15),COUNTIFS(Trade_Periods!$B$6:$B$125,Assumptions!$C$6,Trade_Periods!$C$6:$C$125,B15,Trade_Periods!$D$6:$D$125,A15)=1,COUNTIFS(Tariffs!$B$6:$B$45,B15,Tariffs!$C$6:$C$45,A15)=1),"Ready","Missing data") -> Ready | AE15: =IF(D15>0,R15/D15,"n.a.") -> 1.5193995 | AF15: =IF(M15>0,IF(D15>0,R15/D15,IF(R15=0,0,"n.a.")),0) -> 1.5193995 | AG15: =IF(AND(Assumptions!$F$14="Yes",M15>0),MAX(0,R15-Assumptions!$C$14*D15),0) -> 0
A16: 61103099 | B16: Bangladesh | C16: =SUMIFS(Trade_Periods!$F$6:$F$125,Trade_Periods!$B$6:$B$125,"FY2025",Trade_Periods!$C$6:$C$125,B16,Trade_Periods!$D$6:$D$125,A16) -> 13246692 | D16: =C16/SUM(C16:C25) -> 0.29466445 | E16: =IF(Assumptions!$C$7="Reported",SUMIFS(Trade_Periods!$E$6:$E$125,Trade_Periods!$B$6:$B$125,Assumptions!$C$6,Trade_Periods!$C$6:$C$125,B16,Trade_Periods!$D$6:$D$125,A16),SUMIFS(Trade_Periods!$L$6:$L$125,Trade_Periods!$B$6:$B$125,Assumptions!$C$6,Trade_Periods!$C$6:$C$125,B16,Trade_Periods!$D$6:$D$125,A16)) -> 41106466 | F16: =IF(Assumptions!$C$7="Reported",SUMIFS(Trade_Periods!$F$6:$F$125,Trade_Periods!$B$6:$B$125,Assumptions!$C$6,Trade_Periods!$C$6:$C$125,B16,Trade_Periods!$D$6:$D$125,A16),SUMIFS(Trade_Periods!$M$6:$M$125,Trade_Periods!$B$6:$B$125,Assumptions!$C$6,Trade_Periods!$C$6:$C$125,B16,Trade_Periods!$D$6:$D$125,A16)) -> 3340374 | G16: =IF(F16>0,E16/F16,"n.a.") -> 12.305947 | H16: =IF(Assumptions!$C$8="2025",SUMIFS(Tariffs!$D$6:$D$45,Tariffs!$B$6:$B$45,B16,Tariffs!$C$6:$C$45,A16),IF(Assumptions!$C$8="1 Jan to 14 Jul 2026",SUMIFS(Tariffs!$E$6:$E$45,Tariffs!$B$6:$B$45,B16,Tariffs!$C$6:$C$45,A16),SUMIFS(Tariffs!$F$6:$F$45,Tariffs!$B$6:$B$45,B16,Tariffs!$C$6:$C$45,A16))) -> 0 | I16: =SUMIFS(Tariffs!$G$6:$G$45,Tariffs!$B$6:$B$45,B16,Tariffs!$C$6:$C$45,A16) -> 0.12 | J16: =G16*(1+H16) -> 12.305947 | K16: =G16*(1+I16) -> 13.782661 | L16: =IF(Assumptions!$C$9="Eligible preference",J16,K16) -> 12.305947 | M16: =Assumptions!B24 -> 0 | N16: =Assumptions!C24 -> 0 | O16: =IF(B16="China",-1,M16) -> 0 | P16: =IF(B16="China",D16,IF(M16>0,MAX(0,MIN(Assumptions!$C$10-D16,Assumptions!$C$11,IF(Assumptions!$F$14="Yes",(Assumptions!$C$14-1)*D16,1))/M16),1)) -> 1 | Q16: =$E52*O16 -> 0 | R16: =D16+Q16 -> 0.29466445 | S16: =D16*L16 -> 3.6261252 | T16: =R16*L16+MAX(0,Q16)*L16*N16 -> 3.6261252 | U16: =O16*L16+M16*L16*N16 -> 0 | V16: =D16^2 -> 0.086827139 | W16: =2*D16*O16 -> 0 | X16: =O16^2 -> 0 | Y16: =IF(Candidate_Gates!N16="Pass",MAX(0,Q16),0) -> 0 | Z16: =D16*J16 -> 3.6261252 | AA16: =O16*J16+M16*J16*N16 -> 0 | AB16: =D16*K16 -> 4.0612602 | AC16: =O16*K16+M16*K16*N16 -> 0 | AD16: =IF(AND(C16>=0,F16>0,E16>0,ISNUMBER(G16),COUNTIFS(Trade_Periods!$B$6:$B$125,Assumptions!$C$6,Trade_Periods!$C$6:$C$125,B16,Trade_Periods!$D$6:$D$125,A16)=1,COUNTIFS(Tariffs!$B$6:$B$45,B16,Tariffs!$C$6:$C$45,A16)=1),"Ready","Missing data") -> Ready | AE16: =IF(D16>0,R16/D16,"n.a.") -> 1 | AF16: =IF(M16>0,IF(D16>0,R16/D16,IF(R16=0,0,"n.a.")),0) -> 0 | AG16: =IF(AND(Assumptions!$F$14="Yes",M16>0),MAX(0,R16-Assumptions!$C$14*D16),0) -> 0
A17: 61103099 | B17: Cambodia | C17: =SUMIFS(Trade_Periods!$F$6:$F$125,Trade_Periods!$B$6:$B$125,"FY2025",Trade_Periods!$C$6:$C$125,B17,Trade_Periods!$D$6:$D$125,A17) -> 6288565 | D17: =C17/SUM(C16:C25) -> 0.13988523 | E17: =IF(Assumptions!$C$7="Reported",SUMIFS(Trade_Periods!$E$6:$E$125,Trade_Periods!$B$6:$B$125,Assumptions!$C$6,Trade_Periods!$C$6:$C$125,B17,Trade_Periods!$D$6:$D$125,A17),SUMIFS(Trade_Periods!$L$6:$L$125,Trade_Periods!$B$6:$B$125,Assumptions!$C$6,Trade_Periods!$C$6:$C$125,B17,Trade_Periods!$D$6:$D$125,A17)) -> 20275618 | F17: =IF(Assumptions!$C$7="Reported",SUMIFS(Trade_Periods!$F$6:$F$125,Trade_Periods!$B$6:$B$125,Assumptions!$C$6,Trade_Periods!$C$6:$C$125,B17,Trade_Periods!$D$6:$D$125,A17),SUMIFS(Trade_Periods!$M$6:$M$125,Trade_Periods!$B$6:$B$125,Assumptions!$C$6,Trade_Periods!$C$6:$C$125,B17,Trade_Periods!$D$6:$D$125,A17)) -> 1804538 | G17: =IF(F17>0,E17/F17,"n.a.") -> 11.235905 | H17: =IF(Assumptions!$C$8="2025",SUMIFS(Tariffs!$D$6:$D$45,Tariffs!$B$6:$B$45,B17,Tariffs!$C$6:$C$45,A17),IF(Assumptions!$C$8="1 Jan to 14 Jul 2026",SUMIFS(Tariffs!$E$6:$E$45,Tariffs!$B$6:$B$45,B17,Tariffs!$C$6:$C$45,A17),SUMIFS(Tariffs!$F$6:$F$45,Tariffs!$B$6:$B$45,B17,Tariffs!$C$6:$C$45,A17))) -> 0 | I17: =SUMIFS(Tariffs!$G$6:$G$45,Tariffs!$B$6:$B$45,B17,Tariffs!$C$6:$C$45,A17) -> 0.12 | J17: =G17*(1+H17) -> 11.235905 | K17: =G17*(1+I17) -> 12.584214 | L17: =IF(Assumptions!$C$9="Eligible preference",J17,K17) -> 11.235905 | M17: =Assumptions!B25 -> 0 | N17: =Assumptions!C25 -> 0 | O17: =IF(B17="China",-1,M17) -> 0 | P17: =IF(B17="China",D17,IF(M17>0,MAX(0,MIN(Assumptions!$C$10-D17,Assumptions!$C$11,IF(Assumptions!$F$14="Yes",(Assumptions!$C$14-1)*D17,1))/M17),1)) -> 1 | Q17: =$E52*O17 -> 0 | R17: =D17+Q17 -> 0.13988523 | S17: =D17*L17 -> 1.5717372 | T17: =R17*L17+MAX(0,Q17)*L17*N17 -> 1.5717372 | U17: =O17*L17+M17*L17*N17 -> 0 | V17: =D17^2 -> 0.019567878 | W17: =2*D17*O17 -> 0 | X17: =O17^2 -> 0 | Y17: =IF(Candidate_Gates!N17="Pass",MAX(0,Q17),0) -> 0 | Z17: =D17*J17 -> 1.5717372 | AA17: =O17*J17+M17*J17*N17 -> 0 | AB17: =D17*K17 -> 1.7603457 | AC17: =O17*K17+M17*K17*N17 -> 0 | AD17: =IF(AND(C17>=0,F17>0,E17>0,ISNUMBER(G17),COUNTIFS(Trade_Periods!$B$6:$B$125,Assumptions!$C$6,Trade_Periods!$C$6:$C$125,B17,Trade_Periods!$D$6:$D$125,A17)=1,COUNTIFS(Tariffs!$B$6:$B$45,B17,Tariffs!$C$6:$C$45,A17)=1),"Ready","Missing data") -> Ready | AE17: =IF(D17>0,R17/D17,"n.a.") -> 1 | AF17: =IF(M17>0,IF(D17>0,R17/D17,IF(R17=0,0,"n.a.")),0) -> 0 | AG17: =IF(AND(Assumptions!$F$14="Yes",M17>0),MAX(0,R17-Assumptions!$C$14*D17),0) -> 0
A18: 61103099 | B18: China | C18: =SUMIFS(Trade_Periods!$F$6:$F$125,Trade_Periods!$B$6:$B$125,"FY2025",Trade_Periods!$C$6:$C$125,B18,Trade_Periods!$D$6:$D$125,A18) -> 16459562 | D18: =C18/SUM(C16:C25) -> 0.36613275 | E18: =IF(Assumptions!$C$7="Reported",SUMIFS(Trade_Periods!$E$6:$E$125,Trade_Periods!$B$6:$B$125,Assumptions!$C$6,Trade_Periods!$C$6:$C$125,B18,Trade_Periods!$D$6:$D$125,A18),SUMIFS(Trade_Periods!$L$6:$L$125,Trade_Periods!$B$6:$B$125,Assumptions!$C$6,Trade_Periods!$C$6:$C$125,B18,Trade_Periods!$D$6:$D$125,A18)) -> 44515052 | F18: =IF(Assumptions!$C$7="Reported",SUMIFS(Trade_Periods!$F$6:$F$125,Trade_Periods!$B$6:$B$125,Assumptions!$C$6,Trade_Periods!$C$6:$C$125,B18,Trade_Periods!$D$6:$D$125,A18),SUMIFS(Trade_Periods!$M$6:$M$125,Trade_Periods!$B$6:$B$125,Assumptions!$C$6,Trade_Periods!$C$6:$C$125,B18,Trade_Periods!$D$6:$D$125,A18)) -> 2608798 | G18: =IF(F18>0,E18/F18,"n.a.") -> 17.063434 | H18: =IF(Assumptions!$C$8="2025",SUMIFS(Tariffs!$D$6:$D$45,Tariffs!$B$6:$B$45,B18,Tariffs!$C$6:$C$45,A18),IF(Assumptions!$C$8="1 Jan to 14 Jul 2026",SUMIFS(Tariffs!$E$6:$E$45,Tariffs!$B$6:$B$45,B18,Tariffs!$C$6:$C$45,A18),SUMIFS(Tariffs!$F$6:$F$45,Tariffs!$B$6:$B$45,B18,Tariffs!$C$6:$C$45,A18))) -> 0.12 | I18: =SUMIFS(Tariffs!$G$6:$G$45,Tariffs!$B$6:$B$45,B18,Tariffs!$C$6:$C$45,A18) -> 0.12 | J18: =G18*(1+H18) -> 19.111046 | K18: =G18*(1+I18) -> 19.111046 | L18: =IF(Assumptions!$C$9="Eligible preference",J18,K18) -> 19.111046 | M18: =Assumptions!B26 -> 0 | N18: =Assumptions!C26 -> 0 | O18: =IF(B18="China",-1,M18) -> -1 | P18: =IF(B18="China",D18,IF(M18>0,MAX(0,MIN(Assumptions!$C$10-D18,Assumptions!$C$11,IF(Assumptions!$F$14="Yes",(Assumptions!$C$14-1)*D18,1))/M18),1)) -> 0.36613275 | Q18: =$E52*O18 -> -0.014153298 | R18: =D18+Q18 -> 0.35197946 | S18: =D18*L18 -> 6.9971798 | T18: =R18*L18+MAX(0,Q18)*L18*N18 -> 6.7266955 | U18: =O18*L18+M18*L18*N18 -> -19.111046 | V18: =D18^2 -> 0.13405319 | W18: =2*D18*O18 -> -0.73226551 | X18: =O18^2 -> 1 | Y18: =IF(Candidate_Gates!N18="Pass",MAX(0,Q18),0) -> 0 | Z18: =D18*J18 -> 6.9971798 | AA18: =O18*J18+M18*J18*N18 -> -19.111046 | AB18: =D18*K18 -> 6.9971798 | AC18: =O18*K18+M18*K18*N18 -> -19.111046 | AD18: =IF(AND(C18>=0,F18>0,E18>0,ISNUMBER(G18),COUNTIFS(Trade_Periods!$B$6:$B$125,Assumptions!$C$6,Trade_Periods!$C$6:$C$125,B18,Trade_Periods!$D$6:$D$125,A18)=1,COUNTIFS(Tariffs!$B$6:$B$45,B18,Tariffs!$C$6:$C$45,A18)=1),"Ready","Missing data") -> Ready | AE18: =IF(D18>0,R18/D18,"n.a.") -> 0.96134381 | AF18: =IF(M18>0,IF(D18>0,R18/D18,IF(R18=0,0,"n.a.")),0) -> 0 | AG18: =IF(AND(Assumptions!$F$14="Yes",M18>0),MAX(0,R18-Assumptions!$C$14*D18),0) -> 0
A19: 61103099 | B19: India | C19: =SUMIFS(Trade_Periods!$F$6:$F$125,Trade_Periods!$B$6:$B$125,"FY2025",Trade_Periods!$C$6:$C$125,B19,Trade_Periods!$D$6:$D$125,A19) -> 159066 | D19: =C19/SUM(C16:C25) -> 0.0035383246 | E19: =IF(Assumptions!$C$7="Reported",SUMIFS(Trade_Periods!$E$6:$E$125,Trade_Periods!$B$6:$B$125,Assumptions!$C$6,Trade_Periods!$C$6:$C$125,B19,Trade_Periods!$D$6:$D$125,A19),SUMIFS(Trade_Periods!$L$6:$L$125,Trade_Periods!$B$6:$B$125,Assumptions!$C$6,Trade_Periods!$C$6:$C$125,B19,Trade_Periods!$D$6:$D$125,A19)) -> 709744 | F19: =IF(Assumptions!$C$7="Reported",SUMIFS(Trade_Periods!$F$6:$F$125,Trade_Periods!$B$6:$B$125,Assumptions!$C$6,Trade_Periods!$C$6:$C$125,B19,Trade_Periods!$D$6:$D$125,A19),SUMIFS(Trade_Periods!$M$6:$M$125,Trade_Periods!$B$6:$B$125,Assumptions!$C$6,Trade_Periods!$C$6:$C$125,B19,Trade_Periods!$D$6:$D$125,A19)) -> 46899 | G19: =IF(F19>0,E19/F19,"n.a.") -> 15.133457 | H19: =IF(Assumptions!$C$8="2025",SUMIFS(Tariffs!$D$6:$D$45,Tariffs!$B$6:$B$45,B19,Tariffs!$C$6:$C$45,A19),IF(Assumptions!$C$8="1 Jan to 14 Jul 2026",SUMIFS(Tariffs!$E$6:$E$45,Tariffs!$B$6:$B$45,B19,Tariffs!$C$6:$C$45,A19),SUMIFS(Tariffs!$F$6:$F$45,Tariffs!$B$6:$B$45,B19,Tariffs!$C$6:$C$45,A19))) -> 0 | I19: =SUMIFS(Tariffs!$G$6:$G$45,Tariffs!$B$6:$B$45,B19,Tariffs!$C$6:$C$45,A19) -> 0.12 | J19: =G19*(1+H19) -> 15.133457 | K19: =G19*(1+I19) -> 16.949472 | L19: =IF(Assumptions!$C$9="Eligible preference",J19,K19) -> 15.133457 | M19: =Assumptions!B27 -> 0.5 | N19: =Assumptions!C27 -> 0 | O19: =IF(B19="China",-1,M19) -> 0.5 | P19: =IF(B19="China",D19,IF(M19>0,MAX(0,MIN(Assumptions!$C$10-D19,Assumptions!$C$11,IF(Assumptions!$F$14="Yes",(Assumptions!$C$14-1)*D19,1))/M19),1)) -> 0.014153298 | Q19: =$E52*O19 -> 0.0070766491 | R19: =D19+Q19 -> 0.010614974 | S19: =D19*L19 -> 0.053547083 | T19: =R19*L19+MAX(0,Q19)*L19*N19 -> 0.16064125 | U19: =O19*L19+M19*L19*N19 -> 7.5667285 | V19: =D19^2 -> 1.2519741e-05 | W19: =2*D19*O19 -> 0.0035383246 | X19: =O19^2 -> 0.25 | Y19: =IF(Candidate_Gates!N19="Pass",MAX(0,Q19),0) -> 0 | Z19: =D19*J19 -> 0.053547083 | AA19: =O19*J19+M19*J19*N19 -> 7.5667285 | AB19: =D19*K19 -> 0.059972733 | AC19: =O19*K19+M19*K19*N19 -> 8.4747359 | AD19: =IF(AND(C19>=0,F19>0,E19>0,ISNUMBER(G19),COUNTIFS(Trade_Periods!$B$6:$B$125,Assumptions!$C$6,Trade_Periods!$C$6:$C$125,B19,Trade_Periods!$D$6:$D$125,A19)=1,COUNTIFS(Tariffs!$B$6:$B$45,B19,Tariffs!$C$6:$C$45,A19)=1),"Ready","Missing data") -> Ready | AE19: =IF(D19>0,R19/D19,"n.a.") -> 3 | AF19: =IF(M19>0,IF(D19>0,R19/D19,IF(R19=0,0,"n.a.")),0) -> 3 | AG19: =IF(AND(Assumptions!$F$14="Yes",M19>0),MAX(0,R19-Assumptions!$C$14*D19),0) -> 0
A20: 61103099 | B20: Morocco | C20: =SUMIFS(Trade_Periods!$F$6:$F$125,Trade_Periods!$B$6:$B$125,"FY2025",Trade_Periods!$C$6:$C$125,B20,Trade_Periods!$D$6:$D$125,A20) -> 19704 | D20: =C20/SUM(C16:C25) -> 0.00043830327 | E20: =IF(Assumptions!$C$7="Reported",SUMIFS(Trade_Periods!$E$6:$E$125,Trade_Periods!$B$6:$B$125,Assumptions!$C$6,Trade_Periods!$C$6:$C$125,B20,Trade_Periods!$D$6:$D$125,A20),SUMIFS(Trade_Periods!$L$6:$L$125,Trade_Periods!$B$6:$B$125,Assumptions!$C$6,Trade_Periods!$C$6:$C$125,B20,Trade_Periods!$D$6:$D$125,A20)) -> 94543 | F20: =IF(Assumptions!$C$7="Reported",SUMIFS(Trade_Periods!$F$6:$F$125,Trade_Periods!$B$6:$B$125,Assumptions!$C$6,Trade_Periods!$C$6:$C$125,B20,Trade_Periods!$D$6:$D$125,A20),SUMIFS(Trade_Periods!$M$6:$M$125,Trade_Periods!$B$6:$B$125,Assumptions!$C$6,Trade_Periods!$C$6:$C$125,B20,Trade_Periods!$D$6:$D$125,A20)) -> 3440 | G20: =IF(F20>0,E20/F20,"n.a.") -> 27.48343 | H20: =IF(Assumptions!$C$8="2025",SUMIFS(Tariffs!$D$6:$D$45,Tariffs!$B$6:$B$45,B20,Tariffs!$C$6:$C$45,A20),IF(Assumptions!$C$8="1 Jan to 14 Jul 2026",SUMIFS(Tariffs!$E$6:$E$45,Tariffs!$B$6:$B$45,B20,Tariffs!$C$6:$C$45,A20),SUMIFS(Tariffs!$F$6:$F$45,Tariffs!$B$6:$B$45,B20,Tariffs!$C$6:$C$45,A20))) -> 0 | I20: =SUMIFS(Tariffs!$G$6:$G$45,Tariffs!$B$6:$B$45,B20,Tariffs!$C$6:$C$45,A20) -> 0.12 | J20: =G20*(1+H20) -> 27.48343 | K20: =G20*(1+I20) -> 30.781442 | L20: =IF(Assumptions!$C$9="Eligible preference",J20,K20) -> 27.48343 | M20: =Assumptions!B28 -> 0 | N20: =Assumptions!C28 -> 0 | O20: =IF(B20="China",-1,M20) -> 0 | P20: =IF(B20="China",D20,IF(M20>0,MAX(0,MIN(Assumptions!$C$10-D20,Assumptions!$C$11,IF(Assumptions!$F$14="Yes",(Assumptions!$C$14-1)*D20,1))/M20),1)) -> 1 | Q20: =$E52*O20 -> 0 | R20: =D20+Q20 -> 0.00043830327 | S20: =D20*L20 -> 0.012046077 | T20: =R20*L20+MAX(0,Q20)*L20*N20 -> 0.012046077 | U20: =O20*L20+M20*L20*N20 -> 0 | V20: =D20^2 -> 1.9210975e-07 | W20: =2*D20*O20 -> 0 | X20: =O20^2 -> 0 | Y20: =IF(Candidate_Gates!N20="Pass",MAX(0,Q20),0) -> 0 | Z20: =D20*J20 -> 0.012046077 | AA20: =O20*J20+M20*J20*N20 -> 0 | AB20: =D20*K20 -> 0.013491606 | AC20: =O20*K20+M20*K20*N20 -> 0 | AD20: =IF(AND(C20>=0,F20>0,E20>0,ISNUMBER(G20),COUNTIFS(Trade_Periods!$B$6:$B$125,Assumptions!$C$6,Trade_Periods!$C$6:$C$125,B20,Trade_Periods!$D$6:$D$125,A20)=1,COUNTIFS(Tariffs!$B$6:$B$45,B20,Tariffs!$C$6:$C$45,A20)=1),"Ready","Missing data") -> Ready | AE20: =IF(D20>0,R20/D20,"n.a.") -> 1 | AF20: =IF(M20>0,IF(D20>0,R20/D20,IF(R20=0,0,"n.a.")),0) -> 0 | AG20: =IF(AND(Assumptions!$F$14="Yes",M20>0),MAX(0,R20-Assumptions!$C$14*D20),0) -> 0
A21: 61103099 | B21: Myanmar | C21: =SUMIFS(Trade_Periods!$F$6:$F$125,Trade_Periods!$B$6:$B$125,"FY2025",Trade_Periods!$C$6:$C$125,B21,Trade_Periods!$D$6:$D$125,A21) -> 508754 | D21: =C21/SUM(C16:C25) -> 0.011316917 | E21: =IF(Assumptions!$C$7="Reported",SUMIFS(Trade_Periods!$E$6:$E$125,Trade_Periods!$B$6:$B$125,Assumptions!$C$6,Trade_Periods!$C$6:$C$125,B21,Trade_Periods!$D$6:$D$125,A21),SUMIFS(Trade_Periods!$L$6:$L$125,Trade_Periods!$B$6:$B$125,Assumptions!$C$6,Trade_Periods!$C$6:$C$125,B21,Trade_Periods!$D$6:$D$125,A21)) -> 1019595 | F21: =IF(Assumptions!$C$7="Reported",SUMIFS(Trade_Periods!$F$6:$F$125,Trade_Periods!$B$6:$B$125,Assumptions!$C$6,Trade_Periods!$C$6:$C$125,B21,Trade_Periods!$D$6:$D$125,A21),SUMIFS(Trade_Periods!$M$6:$M$125,Trade_Periods!$B$6:$B$125,Assumptions!$C$6,Trade_Periods!$C$6:$C$125,B21,Trade_Periods!$D$6:$D$125,A21)) -> 72000 | G21: =IF(F21>0,E21/F21,"n.a.") -> 14.161042 | H21: =IF(Assumptions!$C$8="2025",SUMIFS(Tariffs!$D$6:$D$45,Tariffs!$B$6:$B$45,B21,Tariffs!$C$6:$C$45,A21),IF(Assumptions!$C$8="1 Jan to 14 Jul 2026",SUMIFS(Tariffs!$E$6:$E$45,Tariffs!$B$6:$B$45,B21,Tariffs!$C$6:$C$45,A21),SUMIFS(Tariffs!$F$6:$F$45,Tariffs!$B$6:$B$45,B21,Tariffs!$C$6:$C$45,A21))) -> 0 | I21: =SUMIFS(Tariffs!$G$6:$G$45,Tariffs!$B$6:$B$45,B21,Tariffs!$C$6:$C$45,A21) -> 0.12 | J21: =G21*(1+H21) -> 14.161042 | K21: =G21*(1+I21) -> 15.860367 | L21: =IF(Assumptions!$C$9="Eligible preference",J21,K21) -> 14.161042 | M21: =Assumptions!B29 -> 0 | N21: =Assumptions!C29 -> 0 | O21: =IF(B21="China",-1,M21) -> 0 | P21: =IF(B21="China",D21,IF(M21>0,MAX(0,MIN(Assumptions!$C$10-D21,Assumptions!$C$11,IF(Assumptions!$F$14="Yes",(Assumptions!$C$14-1)*D21,1))/M21),1)) -> 1 | Q21: =$E52*O21 -> 0 | R21: =D21+Q21 -> 0.011316917 | S21: =D21*L21 -> 0.16025934 | T21: =R21*L21+MAX(0,Q21)*L21*N21 -> 0.16025934 | U21: =O21*L21+M21*L21*N21 -> 0 | V21: =D21^2 -> 0.00012807262 | W21: =2*D21*O21 -> 0 | X21: =O21^2 -> 0 | Y21: =IF(Candidate_Gates!N21="Pass",MAX(0,Q21),0) -> 0 | Z21: =D21*J21 -> 0.16025934 | AA21: =O21*J21+M21*J21*N21 -> 0 | AB21: =D21*K21 -> 0.17949046 | AC21: =O21*K21+M21*K21*N21 -> 0 | AD21: =IF(AND(C21>=0,F21>0,E21>0,ISNUMBER(G21),COUNTIFS(Trade_Periods!$B$6:$B$125,Assumptions!$C$6,Trade_Periods!$C$6:$C$125,B21,Trade_Periods!$D$6:$D$125,A21)=1,COUNTIFS(Tariffs!$B$6:$B$45,B21,Tariffs!$C$6:$C$45,A21)=1),"Ready","Missing data") -> Ready | AE21: =IF(D21>0,R21/D21,"n.a.") -> 1 | AF21: =IF(M21>0,IF(D21>0,R21/D21,IF(R21=0,0,"n.a.")),0) -> 0 | AG21: =IF(AND(Assumptions!$F$14="Yes",M21>0),MAX(0,R21-Assumptions!$C$14*D21),0) -> 0
A22: 61103099 | B22: Pakistan | C22: =SUMIFS(Trade_Periods!$F$6:$F$125,Trade_Periods!$B$6:$B$125,"FY2025",Trade_Periods!$C$6:$C$125,B22,Trade_Periods!$D$6:$D$125,A22) -> 427235 | D22: =C22/SUM(C16:C25) -> 0.0095035777 | E22: =IF(Assumptions!$C$7="Reported",SUMIFS(Trade_Periods!$E$6:$E$125,Trade_Periods!$B$6:$B$125,Assumptions!$C$6,Trade_Periods!$C$6:$C$125,B22,Trade_Periods!$D$6:$D$125,A22),SUMIFS(Trade_Periods!$L$6:$L$125,Trade_Periods!$B$6:$B$125,Assumptions!$C$6,Trade_Periods!$C$6:$C$125,B22,Trade_Periods!$D$6:$D$125,A22)) -> 2797761 | F22: =IF(Assumptions!$C$7="Reported",SUMIFS(Trade_Periods!$F$6:$F$125,Trade_Periods!$B$6:$B$125,Assumptions!$C$6,Trade_Periods!$C$6:$C$125,B22,Trade_Periods!$D$6:$D$125,A22),SUMIFS(Trade_Periods!$M$6:$M$125,Trade_Periods!$B$6:$B$125,Assumptions!$C$6,Trade_Periods!$C$6:$C$125,B22,Trade_Periods!$D$6:$D$125,A22)) -> 189105 | G22: =IF(F22>0,E22/F22,"n.a.") -> 14.794749 | H22: =IF(Assumptions!$C$8="2025",SUMIFS(Tariffs!$D$6:$D$45,Tariffs!$B$6:$B$45,B22,Tariffs!$C$6:$C$45,A22),IF(Assumptions!$C$8="1 Jan to 14 Jul 2026",SUMIFS(Tariffs!$E$6:$E$45,Tariffs!$B$6:$B$45,B22,Tariffs!$C$6:$C$45,A22),SUMIFS(Tariffs!$F$6:$F$45,Tariffs!$B$6:$B$45,B22,Tariffs!$C$6:$C$45,A22))) -> 0 | I22: =SUMIFS(Tariffs!$G$6:$G$45,Tariffs!$B$6:$B$45,B22,Tariffs!$C$6:$C$45,A22) -> 0.12 | J22: =G22*(1+H22) -> 14.794749 | K22: =G22*(1+I22) -> 16.570119 | L22: =IF(Assumptions!$C$9="Eligible preference",J22,K22) -> 14.794749 | M22: =Assumptions!B30 -> 0 | N22: =Assumptions!C30 -> 0 | O22: =IF(B22="China",-1,M22) -> 0 | P22: =IF(B22="China",D22,IF(M22>0,MAX(0,MIN(Assumptions!$C$10-D22,Assumptions!$C$11,IF(Assumptions!$F$14="Yes",(Assumptions!$C$14-1)*D22,1))/M22),1)) -> 1 | Q22: =$E52*O22 -> 0 | R22: =D22+Q22 -> 0.0095035777 | S22: =D22*L22 -> 0.14060305 | T22: =R22*L22+MAX(0,Q22)*L22*N22 -> 0.14060305 | U22: =O22*L22+M22*L22*N22 -> 0 | V22: =D22^2 -> 9.031799e-05 | W22: =2*D22*O22 -> 0 | X22: =O22^2 -> 0 | Y22: =IF(Candidate_Gates!N22="Pass",MAX(0,Q22),0) -> 0 | Z22: =D22*J22 -> 0.14060305 | AA22: =O22*J22+M22*J22*N22 -> 0 | AB22: =D22*K22 -> 0.15747541 | AC22: =O22*K22+M22*K22*N22 -> 0 | AD22: =IF(AND(C22>=0,F22>0,E22>0,ISNUMBER(G22),COUNTIFS(Trade_Periods!$B$6:$B$125,Assumptions!$C$6,Trade_Periods!$C$6:$C$125,B22,Trade_Periods!$D$6:$D$125,A22)=1,COUNTIFS(Tariffs!$B$6:$B$45,B22,Tariffs!$C$6:$C$45,A22)=1),"Ready","Missing data") -> Ready | AE22: =IF(D22>0,R22/D22,"n.a.") -> 1 | AF22: =IF(M22>0,IF(D22>0,R22/D22,IF(R22=0,0,"n.a.")),0) -> 0 | AG22: =IF(AND(Assumptions!$F$14="Yes",M22>0),MAX(0,R22-Assumptions!$C$14*D22),0) -> 0
A23: 61103099 | B23: Sri Lanka | C23: =SUMIFS(Trade_Periods!$F$6:$F$125,Trade_Periods!$B$6:$B$125,"FY2025",Trade_Periods!$C$6:$C$125,B23,Trade_Periods!$D$6:$D$125,A23) -> 100905 | D23: =C23/SUM(C16:C25) -> 0.0022445692 | E23: =IF(Assumptions!$C$7="Reported",SUMIFS(Trade_Periods!$E$6:$E$125,Trade_Periods!$B$6:$B$125,Assumptions!$C$6,Trade_Periods!$C$6:$C$125,B23,Trade_Periods!$D$6:$D$125,A23),SUMIFS(Trade_Periods!$L$6:$L$125,Trade_Periods!$B$6:$B$125,Assumptions!$C$6,Trade_Periods!$C$6:$C$125,B23,Trade_Periods!$D$6:$D$125,A23)) -> 732589 | F23: =IF(Assumptions!$C$7="Reported",SUMIFS(Trade_Periods!$F$6:$F$125,Trade_Periods!$B$6:$B$125,Assumptions!$C$6,Trade_Periods!$C$6:$C$125,B23,Trade_Periods!$D$6:$D$125,A23),SUMIFS(Trade_Periods!$M$6:$M$125,Trade_Periods!$B$6:$B$125,Assumptions!$C$6,Trade_Periods!$C$6:$C$125,B23,Trade_Periods!$D$6:$D$125,A23)) -> 34757 | G23: =IF(F23>0,E23/F23,"n.a.") -> 21.077452 | H23: =IF(Assumptions!$C$8="2025",SUMIFS(Tariffs!$D$6:$D$45,Tariffs!$B$6:$B$45,B23,Tariffs!$C$6:$C$45,A23),IF(Assumptions!$C$8="1 Jan to 14 Jul 2026",SUMIFS(Tariffs!$E$6:$E$45,Tariffs!$B$6:$B$45,B23,Tariffs!$C$6:$C$45,A23),SUMIFS(Tariffs!$F$6:$F$45,Tariffs!$B$6:$B$45,B23,Tariffs!$C$6:$C$45,A23))) -> 0 | I23: =SUMIFS(Tariffs!$G$6:$G$45,Tariffs!$B$6:$B$45,B23,Tariffs!$C$6:$C$45,A23) -> 0.12 | J23: =G23*(1+H23) -> 21.077452 | K23: =G23*(1+I23) -> 23.606746 | L23: =IF(Assumptions!$C$9="Eligible preference",J23,K23) -> 21.077452 | M23: =Assumptions!B31 -> 0 | N23: =Assumptions!C31 -> 0 | O23: =IF(B23="China",-1,M23) -> 0 | P23: =IF(B23="China",D23,IF(M23>0,MAX(0,MIN(Assumptions!$C$10-D23,Assumptions!$C$11,IF(Assumptions!$F$14="Yes",(Assumptions!$C$14-1)*D23,1))/M23),1)) -> 1 | Q23: =$E52*O23 -> 0 | R23: =D23+Q23 -> 0.0022445692 | S23: =D23*L23 -> 0.047309799 | T23: =R23*L23+MAX(0,Q23)*L23*N23 -> 0.047309799 | U23: =O23*L23+M23*L23*N23 -> 0 | V23: =D23^2 -> 5.0380908e-06 | W23: =2*D23*O23 -> 0 | X23: =O23^2 -> 0 | Y23: =IF(Candidate_Gates!N23="Pass",MAX(0,Q23),0) -> 0 | Z23: =D23*J23 -> 0.047309799 | AA23: =O23*J23+M23*J23*N23 -> 0 | AB23: =D23*K23 -> 0.052986975 | AC23: =O23*K23+M23*K23*N23 -> 0 | AD23: =IF(AND(C23>=0,F23>0,E23>0,ISNUMBER(G23),COUNTIFS(Trade_Periods!$B$6:$B$125,Assumptions!$C$6,Trade_Periods!$C$6:$C$125,B23,Trade_Periods!$D$6:$D$125,A23)=1,COUNTIFS(Tariffs!$B$6:$B$45,B23,Tariffs!$C$6:$C$45,A23)=1),"Ready","Missing data") -> Ready | AE23: =IF(D23>0,R23/D23,"n.a.") -> 1 | AF23: =IF(M23>0,IF(D23>0,R23/D23,IF(R23=0,0,"n.a.")),0) -> 0 | AG23: =IF(AND(Assumptions!$F$14="Yes",M23>0),MAX(0,R23-Assumptions!$C$14*D23),0) -> 0
A24: 61103099 | B24: Turkey | C24: =SUMIFS(Trade_Periods!$F$6:$F$125,Trade_Periods!$B$6:$B$125,"FY2025",Trade_Periods!$C$6:$C$125,B24,Trade_Periods!$D$6:$D$125,A24) -> 7348045 | D24: =C24/SUM(C16:C25) -> 0.16345271 | E24: =IF(Assumptions!$C$7="Reported",SUMIFS(Trade_Periods!$E$6:$E$125,Trade_Periods!$B$6:$B$125,Assumptions!$C$6,Trade_Periods!$C$6:$C$125,B24,Trade_Periods!$D$6:$D$125,A24),SUMIFS(Trade_Periods!$L$6:$L$125,Trade_Periods!$B$6:$B$125,Assumptions!$C$6,Trade_Periods!$C$6:$C$125,B24,Trade_Periods!$D$6:$D$125,A24)) -> 15949155 | F24: =IF(Assumptions!$C$7="Reported",SUMIFS(Trade_Periods!$F$6:$F$125,Trade_Periods!$B$6:$B$125,Assumptions!$C$6,Trade_Periods!$C$6:$C$125,B24,Trade_Periods!$D$6:$D$125,A24),SUMIFS(Trade_Periods!$M$6:$M$125,Trade_Periods!$B$6:$B$125,Assumptions!$C$6,Trade_Periods!$C$6:$C$125,B24,Trade_Periods!$D$6:$D$125,A24)) -> 2413703 | G24: =IF(F24>0,E24/F24,"n.a.") -> 6.6077537 | H24: =IF(Assumptions!$C$8="2025",SUMIFS(Tariffs!$D$6:$D$45,Tariffs!$B$6:$B$45,B24,Tariffs!$C$6:$C$45,A24),IF(Assumptions!$C$8="1 Jan to 14 Jul 2026",SUMIFS(Tariffs!$E$6:$E$45,Tariffs!$B$6:$B$45,B24,Tariffs!$C$6:$C$45,A24),SUMIFS(Tariffs!$F$6:$F$45,Tariffs!$B$6:$B$45,B24,Tariffs!$C$6:$C$45,A24))) -> 0 | I24: =SUMIFS(Tariffs!$G$6:$G$45,Tariffs!$B$6:$B$45,B24,Tariffs!$C$6:$C$45,A24) -> 0.12 | J24: =G24*(1+H24) -> 6.6077537 | K24: =G24*(1+I24) -> 7.4006842 | L24: =IF(Assumptions!$C$9="Eligible preference",J24,K24) -> 6.6077537 | M24: =Assumptions!B32 -> 0.25 | N24: =Assumptions!C32 -> 0 | O24: =IF(B24="China",-1,M24) -> 0.25 | P24: =IF(B24="China",D24,IF(M24>0,MAX(0,MIN(Assumptions!$C$10-D24,Assumptions!$C$11,IF(Assumptions!$F$14="Yes",(Assumptions!$C$14-1)*D24,1))/M24),1)) -> 0.4 | Q24: =$E52*O24 -> 0.0035383246 | R24: =D24+Q24 -> 0.16699103 | S24: =D24*L24 -> 1.0800552 | T24: =R24*L24+MAX(0,Q24)*L24*N24 -> 1.1034356 | U24: =O24*L24+M24*L24*N24 -> 1.6519384 | V24: =D24^2 -> 0.026716787 | W24: =2*D24*O24 -> 0.081726353 | X24: =O24^2 -> 0.0625 | Y24: =IF(Candidate_Gates!N24="Pass",MAX(0,Q24),0) -> 0 | Z24: =D24*J24 -> 1.0800552 | AA24: =O24*J24+M24*J24*N24 -> 1.6519384 | AB24: =D24*K24 -> 1.2096619 | AC24: =O24*K24+M24*K24*N24 -> 1.850171 | AD24: =IF(AND(C24>=0,F24>0,E24>0,ISNUMBER(G24),COUNTIFS(Trade_Periods!$B$6:$B$125,Assumptions!$C$6,Trade_Periods!$C$6:$C$125,B24,Trade_Periods!$D$6:$D$125,A24)=1,COUNTIFS(Tariffs!$B$6:$B$45,B24,Tariffs!$C$6:$C$45,A24)=1),"Ready","Missing data") -> Ready | AE24: =IF(D24>0,R24/D24,"n.a.") -> 1.0216474 | AF24: =IF(M24>0,IF(D24>0,R24/D24,IF(R24=0,0,"n.a.")),0) -> 1.0216474 | AG24: =IF(AND(Assumptions!$F$14="Yes",M24>0),MAX(0,R24-Assumptions!$C$14*D24),0) -> 0
A25: 61103099 | B25: Vietnam | C25: =SUMIFS(Trade_Periods!$F$6:$F$125,Trade_Periods!$B$6:$B$125,"FY2025",Trade_Periods!$C$6:$C$125,B25,Trade_Periods!$D$6:$D$125,A25) -> 396647 | D25: =C25/SUM(C16:C25) -> 0.0088231666 | E25: =IF(Assumptions!$C$7="Reported",SUMIFS(Trade_Periods!$E$6:$E$125,Trade_Periods!$B$6:$B$125,Assumptions!$C$6,Trade_Periods!$C$6:$C$125,B25,Trade_Periods!$D$6:$D$125,A25),SUMIFS(Trade_Periods!$L$6:$L$125,Trade_Periods!$B$6:$B$125,Assumptions!$C$6,Trade_Periods!$C$6:$C$125,B25,Trade_Periods!$D$6:$D$125,A25)) -> 6261277 | F25: =IF(Assumptions!$C$7="Reported",SUMIFS(Trade_Periods!$F$6:$F$125,Trade_Periods!$B$6:$B$125,Assumptions!$C$6,Trade_Periods!$C$6:$C$125,B25,Trade_Periods!$D$6:$D$125,A25),SUMIFS(Trade_Periods!$M$6:$M$125,Trade_Periods!$B$6:$B$125,Assumptions!$C$6,Trade_Periods!$C$6:$C$125,B25,Trade_Periods!$D$6:$D$125,A25)) -> 292287 | G25: =IF(F25>0,E25/F25,"n.a.") -> 21.421675 | H25: =IF(Assumptions!$C$8="2025",SUMIFS(Tariffs!$D$6:$D$45,Tariffs!$B$6:$B$45,B25,Tariffs!$C$6:$C$45,A25),IF(Assumptions!$C$8="1 Jan to 14 Jul 2026",SUMIFS(Tariffs!$E$6:$E$45,Tariffs!$B$6:$B$45,B25,Tariffs!$C$6:$C$45,A25),SUMIFS(Tariffs!$F$6:$F$45,Tariffs!$B$6:$B$45,B25,Tariffs!$C$6:$C$45,A25))) -> 0 | I25: =SUMIFS(Tariffs!$G$6:$G$45,Tariffs!$B$6:$B$45,B25,Tariffs!$C$6:$C$45,A25) -> 0.12 | J25: =G25*(1+H25) -> 21.421675 | K25: =G25*(1+I25) -> 23.992276 | L25: =IF(Assumptions!$C$9="Eligible preference",J25,K25) -> 21.421675 | M25: =Assumptions!B33 -> 0.25 | N25: =Assumptions!C33 -> 0 | O25: =IF(B25="China",-1,M25) -> 0.25 | P25: =IF(B25="China",D25,IF(M25>0,MAX(0,MIN(Assumptions!$C$10-D25,Assumptions!$C$11,IF(Assumptions!$F$14="Yes",(Assumptions!$C$14-1)*D25,1))/M25),1)) -> 0.070585333 | Q25: =$E52*O25 -> 0.0035383246 | R25: =D25+Q25 -> 0.012361491 | S25: =D25*L25 -> 0.189007 | T25: =R25*L25+MAX(0,Q25)*L25*N25 -> 0.26480384 | U25: =O25*L25+M25*L25*N25 -> 5.3554186 | V25: =D25^2 -> 7.7848269e-05 | W25: =2*D25*O25 -> 0.0044115833 | X25: =O25^2 -> 0.0625 | Y25: =IF(Candidate_Gates!N25="Pass",MAX(0,Q25),0) -> 0 | Z25: =D25*J25 -> 0.189007 | AA25: =O25*J25+M25*J25*N25 -> 5.3554186 | AB25: =D25*K25 -> 0.21168784 | AC25: =O25*K25+M25*K25*N25 -> 5.9980689 | AD25: =IF(AND(C25>=0,F25>0,E25>0,ISNUMBER(G25),COUNTIFS(Trade_Periods!$B$6:$B$125,Assumptions!$C$6,Trade_Periods!$C$6:$C$125,B25,Trade_Periods!$D$6:$D$125,A25)=1,COUNTIFS(Tariffs!$B$6:$B$45,B25,Tariffs!$C$6:$C$45,A25)=1),"Ready","Missing data") -> Ready | AE25: =IF(D25>0,R25/D25,"n.a.") -> 1.4010266 | AF25: =IF(M25>0,IF(D25>0,R25/D25,IF(R25=0,0,"n.a.")),0) -> 1.4010266 | AG25: =IF(AND(Assumptions!$F$14="Yes",M25>0),MAX(0,R25-Assumptions!$C$14*D25),0) -> 0
A26: 62044300 | B26: Bangladesh | C26: =SUMIFS(Trade_Periods!$F$6:$F$125,Trade_Periods!$B$6:$B$125,"FY2025",Trade_Periods!$C$6:$C$125,B26,Trade_Periods!$D$6:$D$125,A26) -> 788304 | D26: =C26/SUM(C26:C35) -> 0.10006297 | E26: =IF(Assumptions!$C$7="Reported",SUMIFS(Trade_Periods!$E$6:$E$125,Trade_Periods!$B$6:$B$125,Assumptions!$C$6,Trade_Periods!$C$6:$C$125,B26,Trade_Periods!$D$6:$D$125,A26),SUMIFS(Trade_Periods!$L$6:$L$125,Trade_Periods!$B$6:$B$125,Assumptions!$C$6,Trade_Periods!$C$6:$C$125,B26,Trade_Periods!$D$6:$D$125,A26)) -> 6924029 | F26: =IF(Assumptions!$C$7="Reported",SUMIFS(Trade_Periods!$F$6:$F$125,Trade_Periods!$B$6:$B$125,Assumptions!$C$6,Trade_Periods!$C$6:$C$125,B26,Trade_Periods!$D$6:$D$125,A26),SUMIFS(Trade_Periods!$M$6:$M$125,Trade_Periods!$B$6:$B$125,Assumptions!$C$6,Trade_Periods!$C$6:$C$125,B26,Trade_Periods!$D$6:$D$125,A26)) -> 450236 | G26: =IF(F26>0,E26/F26,"n.a.") -> 15.378666 | H26: =IF(Assumptions!$C$8="2025",SUMIFS(Tariffs!$D$6:$D$45,Tariffs!$B$6:$B$45,B26,Tariffs!$C$6:$C$45,A26),IF(Assumptions!$C$8="1 Jan to 14 Jul 2026",SUMIFS(Tariffs!$E$6:$E$45,Tariffs!$B$6:$B$45,B26,Tariffs!$C$6:$C$45,A26),SUMIFS(Tariffs!$F$6:$F$45,Tariffs!$B$6:$B$45,B26,Tariffs!$C$6:$C$45,A26))) -> 0 | I26: =SUMIFS(Tariffs!$G$6:$G$45,Tariffs!$B$6:$B$45,B26,Tariffs!$C$6:$C$45,A26) -> 0.12 | J26: =G26*(1+H26) -> 15.378666 | K26: =G26*(1+I26) -> 17.224106 | L26: =IF(Assumptions!$C$9="Eligible preference",J26,K26) -> 15.378666 | M26: =Assumptions!B24 -> 0 | N26: =Assumptions!C24 -> 0 | O26: =IF(B26="China",-1,M26) -> 0 | P26: =IF(B26="China",D26,IF(M26>0,MAX(0,MIN(Assumptions!$C$10-D26,Assumptions!$C$11,IF(Assumptions!$F$14="Yes",(Assumptions!$C$14-1)*D26,1))/M26),1)) -> 1 | Q26: =$E53*O26 -> 0 | R26: =D26+Q26 -> 0.10006297 | S26: =D26*L26 -> 1.538835 | T26: =R26*L26+MAX(0,Q26)*L26*N26 -> 1.538835 | U26: =O26*L26+M26*L26*N26 -> 0 | V26: =D26^2 -> 0.010012598 | W26: =2*D26*O26 -> 0 | X26: =O26^2 -> 0 | Y26: =IF(Candidate_Gates!N26="Pass",MAX(0,Q26),0) -> 0 | Z26: =D26*J26 -> 1.538835 | AA26: =O26*J26+M26*J26*N26 -> 0 | AB26: =D26*K26 -> 1.7234952 | AC26: =O26*K26+M26*K26*N26 -> 0 | AD26: =IF(AND(C26>=0,F26>0,E26>0,ISNUMBER(G26),COUNTIFS(Trade_Periods!$B$6:$B$125,Assumptions!$C$6,Trade_Periods!$C$6:$C$125,B26,Trade_Periods!$D$6:$D$125,A26)=1,COUNTIFS(Tariffs!$B$6:$B$45,B26,Tariffs!$C$6:$C$45,A26)=1),"Ready","Missing data") -> Ready | AE26: =IF(D26>0,R26/D26,"n.a.") -> 1 | AF26: =IF(M26>0,IF(D26>0,R26/D26,IF(R26=0,0,"n.a.")),0) -> 0 | AG26: =IF(AND(Assumptions!$F$14="Yes",M26>0),MAX(0,R26-Assumptions!$C$14*D26),0) -> 0
A27: 62044300 | B27: Cambodia | C27: =SUMIFS(Trade_Periods!$F$6:$F$125,Trade_Periods!$B$6:$B$125,"FY2025",Trade_Periods!$C$6:$C$125,B27,Trade_Periods!$D$6:$D$125,A27) -> 193821 | D27: =C27/SUM(C26:C35) -> 0.024602571 | E27: =IF(Assumptions!$C$7="Reported",SUMIFS(Trade_Periods!$E$6:$E$125,Trade_Periods!$B$6:$B$125,Assumptions!$C$6,Trade_Periods!$C$6:$C$125,B27,Trade_Periods!$D$6:$D$125,A27),SUMIFS(Trade_Periods!$L$6:$L$125,Trade_Periods!$B$6:$B$125,Assumptions!$C$6,Trade_Periods!$C$6:$C$125,B27,Trade_Periods!$D$6:$D$125,A27)) -> 2808404 | F27: =IF(Assumptions!$C$7="Reported",SUMIFS(Trade_Periods!$F$6:$F$125,Trade_Periods!$B$6:$B$125,Assumptions!$C$6,Trade_Periods!$C$6:$C$125,B27,Trade_Periods!$D$6:$D$125,A27),SUMIFS(Trade_Periods!$M$6:$M$125,Trade_Periods!$B$6:$B$125,Assumptions!$C$6,Trade_Periods!$C$6:$C$125,B27,Trade_Periods!$D$6:$D$125,A27)) -> 150870 | G27: =IF(F27>0,E27/F27,"n.a.") -> 18.614728 | H27: =IF(Assumptions!$C$8="2025",SUMIFS(Tariffs!$D$6:$D$45,Tariffs!$B$6:$B$45,B27,Tariffs!$C$6:$C$45,A27),IF(Assumptions!$C$8="1 Jan to 14 Jul 2026",SUMIFS(Tariffs!$E$6:$E$45,Tariffs!$B$6:$B$45,B27,Tariffs!$C$6:$C$45,A27),SUMIFS(Tariffs!$F$6:$F$45,Tariffs!$B$6:$B$45,B27,Tariffs!$C$6:$C$45,A27))) -> 0 | I27: =SUMIFS(Tariffs!$G$6:$G$45,Tariffs!$B$6:$B$45,B27,Tariffs!$C$6:$C$45,A27) -> 0.12 | J27: =G27*(1+H27) -> 18.614728 | K27: =G27*(1+I27) -> 20.848495 | L27: =IF(Assumptions!$C$9="Eligible preference",J27,K27) -> 18.614728 | M27: =Assumptions!B25 -> 0 | N27: =Assumptions!C25 -> 0 | O27: =IF(B27="China",-1,M27) -> 0 | P27: =IF(B27="China",D27,IF(M27>0,MAX(0,MIN(Assumptions!$C$10-D27,Assumptions!$C$11,IF(Assumptions!$F$14="Yes",(Assumptions!$C$14-1)*D27,1))/M27),1)) -> 1 | Q27: =$E53*O27 -> 0 | R27: =D27+Q27 -> 0.024602571 | S27: =D27*L27 -> 0.45797017 | T27: =R27*L27+MAX(0,Q27)*L27*N27 -> 0.45797017 | U27: =O27*L27+M27*L27*N27 -> 0 | V27: =D27^2 -> 0.00060528651 | W27: =2*D27*O27 -> 0 | X27: =O27^2 -> 0 | Y27: =IF(Candidate_Gates!N27="Pass",MAX(0,Q27),0) -> 0 | Z27: =D27*J27 -> 0.45797017 | AA27: =O27*J27+M27*J27*N27 -> 0 | AB27: =D27*K27 -> 0.51292659 | AC27: =O27*K27+M27*K27*N27 -> 0 | AD27: =IF(AND(C27>=0,F27>0,E27>0,ISNUMBER(G27),COUNTIFS(Trade_Periods!$B$6:$B$125,Assumptions!$C$6,Trade_Periods!$C$6:$C$125,B27,Trade_Periods!$D$6:$D$125,A27)=1,COUNTIFS(Tariffs!$B$6:$B$45,B27,Tariffs!$C$6:$C$45,A27)=1),"Ready","Missing data") -> Ready | AE27: =IF(D27>0,R27/D27,"n.a.") -> 1 | AF27: =IF(M27>0,IF(D27>0,R27/D27,IF(R27=0,0,"n.a.")),0) -> 0 | AG27: =IF(AND(Assumptions!$F$14="Yes",M27>0),MAX(0,R27-Assumptions!$C$14*D27),0) -> 0
A28: 62044300 | B28: China | C28: =SUMIFS(Trade_Periods!$F$6:$F$125,Trade_Periods!$B$6:$B$125,"FY2025",Trade_Periods!$C$6:$C$125,B28,Trade_Periods!$D$6:$D$125,A28) -> 3777711 | D28: =C28/SUM(C26:C35) -> 0.47952185 | E28: =IF(Assumptions!$C$7="Reported",SUMIFS(Trade_Periods!$E$6:$E$125,Trade_Periods!$B$6:$B$125,Assumptions!$C$6,Trade_Periods!$C$6:$C$125,B28,Trade_Periods!$D$6:$D$125,A28),SUMIFS(Trade_Periods!$L$6:$L$125,Trade_Periods!$B$6:$B$125,Assumptions!$C$6,Trade_Periods!$C$6:$C$125,B28,Trade_Periods!$D$6:$D$125,A28)) -> 52333750 | F28: =IF(Assumptions!$C$7="Reported",SUMIFS(Trade_Periods!$F$6:$F$125,Trade_Periods!$B$6:$B$125,Assumptions!$C$6,Trade_Periods!$C$6:$C$125,B28,Trade_Periods!$D$6:$D$125,A28),SUMIFS(Trade_Periods!$M$6:$M$125,Trade_Periods!$B$6:$B$125,Assumptions!$C$6,Trade_Periods!$C$6:$C$125,B28,Trade_Periods!$D$6:$D$125,A28)) -> 1892903 | G28: =IF(F28>0,E28/F28,"n.a.") -> 27.647349 | H28: =IF(Assumptions!$C$8="2025",SUMIFS(Tariffs!$D$6:$D$45,Tariffs!$B$6:$B$45,B28,Tariffs!$C$6:$C$45,A28),IF(Assumptions!$C$8="1 Jan to 14 Jul 2026",SUMIFS(Tariffs!$E$6:$E$45,Tariffs!$B$6:$B$45,B28,Tariffs!$C$6:$C$45,A28),SUMIFS(Tariffs!$F$6:$F$45,Tariffs!$B$6:$B$45,B28,Tariffs!$C$6:$C$45,A28))) -> 0.12 | I28: =SUMIFS(Tariffs!$G$6:$G$45,Tariffs!$B$6:$B$45,B28,Tariffs!$C$6:$C$45,A28) -> 0.12 | J28: =G28*(1+H28) -> 30.965031 | K28: =G28*(1+I28) -> 30.965031 | L28: =IF(Assumptions!$C$9="Eligible preference",J28,K28) -> 30.965031 | M28: =Assumptions!B26 -> 0 | N28: =Assumptions!C26 -> 0 | O28: =IF(B28="China",-1,M28) -> -1 | P28: =IF(B28="China",D28,IF(M28>0,MAX(0,MIN(Assumptions!$C$10-D28,Assumptions!$C$11,IF(Assumptions!$F$14="Yes",(Assumptions!$C$14-1)*D28,1))/M28),1)) -> 0.47952185 | Q28: =$E53*O28 -> -0.1 | R28: =D28+Q28 -> 0.37952185 | S28: =D28*L28 -> 14.848409 | T28: =R28*L28+MAX(0,Q28)*L28*N28 -> 11.751906 | U28: =O28*L28+M28*L28*N28 -> -30.965031 | V28: =D28^2 -> 0.2299412 | W28: =2*D28*O28 -> -0.9590437 | X28: =O28^2 -> 1 | Y28: =IF(Candidate_Gates!N28="Pass",MAX(0,Q28),0) -> 0 | Z28: =D28*J28 -> 14.848409 | AA28: =O28*J28+M28*J28*N28 -> -30.965031 | AB28: =D28*K28 -> 14.848409 | AC28: =O28*K28+M28*K28*N28 -> -30.965031 | AD28: =IF(AND(C28>=0,F28>0,E28>0,ISNUMBER(G28),COUNTIFS(Trade_Periods!$B$6:$B$125,Assumptions!$C$6,Trade_Periods!$C$6:$C$125,B28,Trade_Periods!$D$6:$D$125,A28)=1,COUNTIFS(Tariffs!$B$6:$B$45,B28,Tariffs!$C$6:$C$45,A28)=1),"Ready","Missing data") -> Ready | AE28: =IF(D28>0,R28/D28,"n.a.") -> 0.79145893 | AF28: =IF(M28>0,IF(D28>0,R28/D28,IF(R28=0,0,"n.a.")),0) -> 0 | AG28: =IF(AND(Assumptions!$F$14="Yes",M28>0),MAX(0,R28-Assumptions!$C$14*D28),0) -> 0
A29: 62044300 | B29: India | C29: =SUMIFS(Trade_Periods!$F$6:$F$125,Trade_Periods!$B$6:$B$125,"FY2025",Trade_Periods!$C$6:$C$125,B29,Trade_Periods!$D$6:$D$125,A29) -> 1191708 | D29: =C29/SUM(C26:C35) -> 0.15126886 | E29: =IF(Assumptions!$C$7="Reported",SUMIFS(Trade_Periods!$E$6:$E$125,Trade_Periods!$B$6:$B$125,Assumptions!$C$6,Trade_Periods!$C$6:$C$125,B29,Trade_Periods!$D$6:$D$125,A29),SUMIFS(Trade_Periods!$L$6:$L$125,Trade_Periods!$B$6:$B$125,Assumptions!$C$6,Trade_Periods!$C$6:$C$125,B29,Trade_Periods!$D$6:$D$125,A29)) -> 20258876 | F29: =IF(Assumptions!$C$7="Reported",SUMIFS(Trade_Periods!$F$6:$F$125,Trade_Periods!$B$6:$B$125,Assumptions!$C$6,Trade_Periods!$C$6:$C$125,B29,Trade_Periods!$D$6:$D$125,A29),SUMIFS(Trade_Periods!$M$6:$M$125,Trade_Periods!$B$6:$B$125,Assumptions!$C$6,Trade_Periods!$C$6:$C$125,B29,Trade_Periods!$D$6:$D$125,A29)) -> 721170 | G29: =IF(F29>0,E29/F29,"n.a.") -> 28.091679 | H29: =IF(Assumptions!$C$8="2025",SUMIFS(Tariffs!$D$6:$D$45,Tariffs!$B$6:$B$45,B29,Tariffs!$C$6:$C$45,A29),IF(Assumptions!$C$8="1 Jan to 14 Jul 2026",SUMIFS(Tariffs!$E$6:$E$45,Tariffs!$B$6:$B$45,B29,Tariffs!$C$6:$C$45,A29),SUMIFS(Tariffs!$F$6:$F$45,Tariffs!$B$6:$B$45,B29,Tariffs!$C$6:$C$45,A29))) -> 0 | I29: =SUMIFS(Tariffs!$G$6:$G$45,Tariffs!$B$6:$B$45,B29,Tariffs!$C$6:$C$45,A29) -> 0.12 | J29: =G29*(1+H29) -> 28.091679 | K29: =G29*(1+I29) -> 31.46268 | L29: =IF(Assumptions!$C$9="Eligible preference",J29,K29) -> 28.091679 | M29: =Assumptions!B27 -> 0.5 | N29: =Assumptions!C27 -> 0 | O29: =IF(B29="China",-1,M29) -> 0.5 | P29: =IF(B29="China",D29,IF(M29>0,MAX(0,MIN(Assumptions!$C$10-D29,Assumptions!$C$11,IF(Assumptions!$F$14="Yes",(Assumptions!$C$14-1)*D29,1))/M29),1)) -> 0.2 | Q29: =$E53*O29 -> 0.05 | R29: =D29+Q29 -> 0.20126886 | S29: =D29*L29 -> 4.2493961 | T29: =R29*L29+MAX(0,Q29)*L29*N29 -> 5.6539801 | U29: =O29*L29+M29*L29*N29 -> 14.045839 | V29: =D29^2 -> 0.022882267 | W29: =2*D29*O29 -> 0.15126886 | X29: =O29^2 -> 0.25 | Y29: =IF(Candidate_Gates!N29="Pass",MAX(0,Q29),0) -> 0 | Z29: =D29*J29 -> 4.2493961 | AA29: =O29*J29+M29*J29*N29 -> 14.045839 | AB29: =D29*K29 -> 4.7593237 | AC29: =O29*K29+M29*K29*N29 -> 15.73134 | AD29: =IF(AND(C29>=0,F29>0,E29>0,ISNUMBER(G29),COUNTIFS(Trade_Periods!$B$6:$B$125,Assumptions!$C$6,Trade_Periods!$C$6:$C$125,B29,Trade_Periods!$D$6:$D$125,A29)=1,COUNTIFS(Tariffs!$B$6:$B$45,B29,Tariffs!$C$6:$C$45,A29)=1),"Ready","Missing data") -> Ready | AE29: =IF(D29>0,R29/D29,"n.a.") -> 1.3305373 | AF29: =IF(M29>0,IF(D29>0,R29/D29,IF(R29=0,0,"n.a.")),0) -> 1.3305373 | AG29: =IF(AND(Assumptions!$F$14="Yes",M29>0),MAX(0,R29-Assumptions!$C$14*D29),0) -> 0
A30: 62044300 | B30: Morocco | C30: =SUMIFS(Trade_Periods!$F$6:$F$125,Trade_Periods!$B$6:$B$125,"FY2025",Trade_Periods!$C$6:$C$125,B30,Trade_Periods!$D$6:$D$125,A30) -> 483259 | D30: =C30/SUM(C26:C35) -> 0.061342238 | E30: =IF(Assumptions!$C$7="Reported",SUMIFS(Trade_Periods!$E$6:$E$125,Trade_Periods!$B$6:$B$125,Assumptions!$C$6,Trade_Periods!$C$6:$C$125,B30,Trade_Periods!$D$6:$D$125,A30),SUMIFS(Trade_Periods!$L$6:$L$125,Trade_Periods!$B$6:$B$125,Assumptions!$C$6,Trade_Periods!$C$6:$C$125,B30,Trade_Periods!$D$6:$D$125,A30)) -> 5511176 | F30: =IF(Assumptions!$C$7="Reported",SUMIFS(Trade_Periods!$F$6:$F$125,Trade_Periods!$B$6:$B$125,Assumptions!$C$6,Trade_Periods!$C$6:$C$125,B30,Trade_Periods!$D$6:$D$125,A30),SUMIFS(Trade_Periods!$M$6:$M$125,Trade_Periods!$B$6:$B$125,Assumptions!$C$6,Trade_Periods!$C$6:$C$125,B30,Trade_Periods!$D$6:$D$125,A30)) -> 218537 | G30: =IF(F30>0,E30/F30,"n.a.") -> 25.218503 | H30: =IF(Assumptions!$C$8="2025",SUMIFS(Tariffs!$D$6:$D$45,Tariffs!$B$6:$B$45,B30,Tariffs!$C$6:$C$45,A30),IF(Assumptions!$C$8="1 Jan to 14 Jul 2026",SUMIFS(Tariffs!$E$6:$E$45,Tariffs!$B$6:$B$45,B30,Tariffs!$C$6:$C$45,A30),SUMIFS(Tariffs!$F$6:$F$45,Tariffs!$B$6:$B$45,B30,Tariffs!$C$6:$C$45,A30))) -> 0 | I30: =SUMIFS(Tariffs!$G$6:$G$45,Tariffs!$B$6:$B$45,B30,Tariffs!$C$6:$C$45,A30) -> 0.12 | J30: =G30*(1+H30) -> 25.218503 | K30: =G30*(1+I30) -> 28.244723 | L30: =IF(Assumptions!$C$9="Eligible preference",J30,K30) -> 25.218503 | M30: =Assumptions!B28 -> 0 | N30: =Assumptions!C28 -> 0 | O30: =IF(B30="China",-1,M30) -> 0 | P30: =IF(B30="China",D30,IF(M30>0,MAX(0,MIN(Assumptions!$C$10-D30,Assumptions!$C$11,IF(Assumptions!$F$14="Yes",(Assumptions!$C$14-1)*D30,1))/M30),1)) -> 1 | Q30: =$E53*O30 -> 0 | R30: =D30+Q30 -> 0.061342238 | S30: =D30*L30 -> 1.5469594 | T30: =R30*L30+MAX(0,Q30)*L30*N30 -> 1.5469594 | U30: =O30*L30+M30*L30*N30 -> 0 | V30: =D30^2 -> 0.0037628702 | W30: =2*D30*O30 -> 0 | X30: =O30^2 -> 0 | Y30: =IF(Candidate_Gates!N30="Pass",MAX(0,Q30),0) -> 0 | Z30: =D30*J30 -> 1.5469594 | AA30: =O30*J30+M30*J30*N30 -> 0 | AB30: =D30*K30 -> 1.7325946 | AC30: =O30*K30+M30*K30*N30 -> 0 | AD30: =IF(AND(C30>=0,F30>0,E30>0,ISNUMBER(G30),COUNTIFS(Trade_Periods!$B$6:$B$125,Assumptions!$C$6,Trade_Periods!$C$6:$C$125,B30,Trade_Periods!$D$6:$D$125,A30)=1,COUNTIFS(Tariffs!$B$6:$B$45,B30,Tariffs!$C$6:$C$45,A30)=1),"Ready","Missing data") -> Ready | AE30: =IF(D30>0,R30/D30,"n.a.") -> 1 | AF30: =IF(M30>0,IF(D30>0,R30/D30,IF(R30=0,0,"n.a.")),0) -> 0 | AG30: =IF(AND(Assumptions!$F$14="Yes",M30>0),MAX(0,R30-Assumptions!$C$14*D30),0) -> 0
A31: 62044300 | B31: Myanmar | C31: =SUMIFS(Trade_Periods!$F$6:$F$125,Trade_Periods!$B$6:$B$125,"FY2025",Trade_Periods!$C$6:$C$125,B31,Trade_Periods!$D$6:$D$125,A31) -> 138284 | D31: =C31/SUM(C26:C35) -> 0.01755301 | E31: =IF(Assumptions!$C$7="Reported",SUMIFS(Trade_Periods!$E$6:$E$125,Trade_Periods!$B$6:$B$125,Assumptions!$C$6,Trade_Periods!$C$6:$C$125,B31,Trade_Periods!$D$6:$D$125,A31),SUMIFS(Trade_Periods!$L$6:$L$125,Trade_Periods!$B$6:$B$125,Assumptions!$C$6,Trade_Periods!$C$6:$C$125,B31,Trade_Periods!$D$6:$D$125,A31)) -> 2412796 | F31: =IF(Assumptions!$C$7="Reported",SUMIFS(Trade_Periods!$F$6:$F$125,Trade_Periods!$B$6:$B$125,Assumptions!$C$6,Trade_Periods!$C$6:$C$125,B31,Trade_Periods!$D$6:$D$125,A31),SUMIFS(Trade_Periods!$M$6:$M$125,Trade_Periods!$B$6:$B$125,Assumptions!$C$6,Trade_Periods!$C$6:$C$125,B31,Trade_Periods!$D$6:$D$125,A31)) -> 37986 | G31: =IF(F31>0,E31/F31,"n.a.") -> 63.518033 | H31: =IF(Assumptions!$C$8="2025",SUMIFS(Tariffs!$D$6:$D$45,Tariffs!$B$6:$B$45,B31,Tariffs!$C$6:$C$45,A31),IF(Assumptions!$C$8="1 Jan to 14 Jul 2026",SUMIFS(Tariffs!$E$6:$E$45,Tariffs!$B$6:$B$45,B31,Tariffs!$C$6:$C$45,A31),SUMIFS(Tariffs!$F$6:$F$45,Tariffs!$B$6:$B$45,B31,Tariffs!$C$6:$C$45,A31))) -> 0 | I31: =SUMIFS(Tariffs!$G$6:$G$45,Tariffs!$B$6:$B$45,B31,Tariffs!$C$6:$C$45,A31) -> 0.12 | J31: =G31*(1+H31) -> 63.518033 | K31: =G31*(1+I31) -> 71.140197 | L31: =IF(Assumptions!$C$9="Eligible preference",J31,K31) -> 63.518033 | M31: =Assumptions!B29 -> 0 | N31: =Assumptions!C29 -> 0 | O31: =IF(B31="China",-1,M31) -> 0 | P31: =IF(B31="China",D31,IF(M31>0,MAX(0,MIN(Assumptions!$C$10-D31,Assumptions!$C$11,IF(Assumptions!$F$14="Yes",(Assumptions!$C$14-1)*D31,1))/M31),1)) -> 1 | Q31: =$E53*O31 -> 0 | R31: =D31+Q31 -> 0.01755301 | S31: =D31*L31 -> 1.1149327 | T31: =R31*L31+MAX(0,Q31)*L31*N31 -> 1.1149327 | U31: =O31*L31+M31*L31*N31 -> 0 | V31: =D31^2 -> 0.00030810816 | W31: =2*D31*O31 -> 0 | X31: =O31^2 -> 0 | Y31: =IF(Candidate_Gates!N31="Pass",MAX(0,Q31),0) -> 0 | Z31: =D31*J31 -> 1.1149327 | AA31: =O31*J31+M31*J31*N31 -> 0 | AB31: =D31*K31 -> 1.2487246 | AC31: =O31*K31+M31*K31*N31 -> 0 | AD31: =IF(AND(C31>=0,F31>0,E31>0,ISNUMBER(G31),COUNTIFS(Trade_Periods!$B$6:$B$125,Assumptions!$C$6,Trade_Periods!$C$6:$C$125,B31,Trade_Periods!$D$6:$D$125,A31)=1,COUNTIFS(Tariffs!$B$6:$B$45,B31,Tariffs!$C$6:$C$45,A31)=1),"Ready","Missing data") -> Ready | AE31: =IF(D31>0,R31/D31,"n.a.") -> 1 | AF31: =IF(M31>0,IF(D31>0,R31/D31,IF(R31=0,0,"n.a.")),0) -> 0 | AG31: =IF(AND(Assumptions!$F$14="Yes",M31>0),MAX(0,R31-Assumptions!$C$14*D31),0) -> 0
A32: 62044300 | B32: Pakistan | C32: =SUMIFS(Trade_Periods!$F$6:$F$125,Trade_Periods!$B$6:$B$125,"FY2025",Trade_Periods!$C$6:$C$125,B32,Trade_Periods!$D$6:$D$125,A32) -> 78305 | D32: =C32/SUM(C26:C35) -> 0.0099396058 | E32: =IF(Assumptions!$C$7="Reported",SUMIFS(Trade_Periods!$E$6:$E$125,Trade_Periods!$B$6:$B$125,Assumptions!$C$6,Trade_Periods!$C$6:$C$125,B32,Trade_Periods!$D$6:$D$125,A32),SUMIFS(Trade_Periods!$L$6:$L$125,Trade_Periods!$B$6:$B$125,Assumptions!$C$6,Trade_Periods!$C$6:$C$125,B32,Trade_Periods!$D$6:$D$125,A32)) -> 496523 | F32: =IF(Assumptions!$C$7="Reported",SUMIFS(Trade_Periods!$F$6:$F$125,Trade_Periods!$B$6:$B$125,Assumptions!$C$6,Trade_Periods!$C$6:$C$125,B32,Trade_Periods!$D$6:$D$125,A32),SUMIFS(Trade_Periods!$M$6:$M$125,Trade_Periods!$B$6:$B$125,Assumptions!$C$6,Trade_Periods!$C$6:$C$125,B32,Trade_Periods!$D$6:$D$125,A32)) -> 26975 | G32: =IF(F32>0,E32/F32,"n.a.") -> 18.406784 | H32: =IF(Assumptions!$C$8="2025",SUMIFS(Tariffs!$D$6:$D$45,Tariffs!$B$6:$B$45,B32,Tariffs!$C$6:$C$45,A32),IF(Assumptions!$C$8="1 Jan to 14 Jul 2026",SUMIFS(Tariffs!$E$6:$E$45,Tariffs!$B$6:$B$45,B32,Tariffs!$C$6:$C$45,A32),SUMIFS(Tariffs!$F$6:$F$45,Tariffs!$B$6:$B$45,B32,Tariffs!$C$6:$C$45,A32))) -> 0 | I32: =SUMIFS(Tariffs!$G$6:$G$45,Tariffs!$B$6:$B$45,B32,Tariffs!$C$6:$C$45,A32) -> 0.12 | J32: =G32*(1+H32) -> 18.406784 | K32: =G32*(1+I32) -> 20.615598 | L32: =IF(Assumptions!$C$9="Eligible preference",J32,K32) -> 18.406784 | M32: =Assumptions!B30 -> 0 | N32: =Assumptions!C30 -> 0 | O32: =IF(B32="China",-1,M32) -> 0 | P32: =IF(B32="China",D32,IF(M32>0,MAX(0,MIN(Assumptions!$C$10-D32,Assumptions!$C$11,IF(Assumptions!$F$14="Yes",(Assumptions!$C$14-1)*D32,1))/M32),1)) -> 1 | Q32: =$E53*O32 -> 0 | R32: =D32+Q32 -> 0.0099396058 | S32: =D32*L32 -> 0.18295618 | T32: =R32*L32+MAX(0,Q32)*L32*N32 -> 0.18295618 | U32: =O32*L32+M32*L32*N32 -> 0 | V32: =D32^2 -> 9.8795764e-05 | W32: =2*D32*O32 -> 0 | X32: =O32^2 -> 0 | Y32: =IF(Candidate_Gates!N32="Pass",MAX(0,Q32),0) -> 0 | Z32: =D32*J32 -> 0.18295618 | AA32: =O32*J32+M32*J32*N32 -> 0 | AB32: =D32*K32 -> 0.20491092 | AC32: =O32*K32+M32*K32*N32 -> 0 | AD32: =IF(AND(C32>=0,F32>0,E32>0,ISNUMBER(G32),COUNTIFS(Trade_Periods!$B$6:$B$125,Assumptions!$C$6,Trade_Periods!$C$6:$C$125,B32,Trade_Periods!$D$6:$D$125,A32)=1,COUNTIFS(Tariffs!$B$6:$B$45,B32,Tariffs!$C$6:$C$45,A32)=1),"Ready","Missing data") -> Ready | AE32: =IF(D32>0,R32/D32,"n.a.") -> 1 | AF32: =IF(M32>0,IF(D32>0,R32/D32,IF(R32=0,0,"n.a.")),0) -> 0 | AG32: =IF(AND(Assumptions!$F$14="Yes",M32>0),MAX(0,R32-Assumptions!$C$14*D32),0) -> 0
A33: 62044300 | B33: Sri Lanka | C33: =SUMIFS(Trade_Periods!$F$6:$F$125,Trade_Periods!$B$6:$B$125,"FY2025",Trade_Periods!$C$6:$C$125,B33,Trade_Periods!$D$6:$D$125,A33) -> 683522 | D33: =C33/SUM(C26:C35) -> 0.086762522 | E33: =IF(Assumptions!$C$7="Reported",SUMIFS(Trade_Periods!$E$6:$E$125,Trade_Periods!$B$6:$B$125,Assumptions!$C$6,Trade_Periods!$C$6:$C$125,B33,Trade_Periods!$D$6:$D$125,A33),SUMIFS(Trade_Periods!$L$6:$L$125,Trade_Periods!$B$6:$B$125,Assumptions!$C$6,Trade_Periods!$C$6:$C$125,B33,Trade_Periods!$D$6:$D$125,A33)) -> 7697741 | F33: =IF(Assumptions!$C$7="Reported",SUMIFS(Trade_Periods!$F$6:$F$125,Trade_Periods!$B$6:$B$125,Assumptions!$C$6,Trade_Periods!$C$6:$C$125,B33,Trade_Periods!$D$6:$D$125,A33),SUMIFS(Trade_Periods!$M$6:$M$125,Trade_Periods!$B$6:$B$125,Assumptions!$C$6,Trade_Periods!$C$6:$C$125,B33,Trade_Periods!$D$6:$D$125,A33)) -> 462849 | G33: =IF(F33>0,E33/F33,"n.a.") -> 16.631214 | H33: =IF(Assumptions!$C$8="2025",SUMIFS(Tariffs!$D$6:$D$45,Tariffs!$B$6:$B$45,B33,Tariffs!$C$6:$C$45,A33),IF(Assumptions!$C$8="1 Jan to 14 Jul 2026",SUMIFS(Tariffs!$E$6:$E$45,Tariffs!$B$6:$B$45,B33,Tariffs!$C$6:$C$45,A33),SUMIFS(Tariffs!$F$6:$F$45,Tariffs!$B$6:$B$45,B33,Tariffs!$C$6:$C$45,A33))) -> 0 | I33: =SUMIFS(Tariffs!$G$6:$G$45,Tariffs!$B$6:$B$45,B33,Tariffs!$C$6:$C$45,A33) -> 0.12 | J33: =G33*(1+H33) -> 16.631214 | K33: =G33*(1+I33) -> 18.62696 | L33: =IF(Assumptions!$C$9="Eligible preference",J33,K33) -> 16.631214 | M33: =Assumptions!B31 -> 0 | N33: =Assumptions!C31 -> 0 | O33: =IF(B33="China",-1,M33) -> 0 | P33: =IF(B33="China",D33,IF(M33>0,MAX(0,MIN(Assumptions!$C$10-D33,Assumptions!$C$11,IF(Assumptions!$F$14="Yes",(Assumptions!$C$14-1)*D33,1))/M33),1)) -> 1 | Q33: =$E53*O33 -> 0 | R33: =D33+Q33 -> 0.086762522 | S33: =D33*L33 -> 1.4429661 | T33: =R33*L33+MAX(0,Q33)*L33*N33 -> 1.4429661 | U33: =O33*L33+M33*L33*N33 -> 0 | V33: =D33^2 -> 0.0075277352 | W33: =2*D33*O33 -> 0 | X33: =O33^2 -> 0 | Y33: =IF(Candidate_Gates!N33="Pass",MAX(0,Q33),0) -> 0 | Z33: =D33*J33 -> 1.4429661 | AA33: =O33*J33+M33*J33*N33 -> 0 | AB33: =D33*K33 -> 1.616122 | AC33: =O33*K33+M33*K33*N33 -> 0 | AD33: =IF(AND(C33>=0,F33>0,E33>0,ISNUMBER(G33),COUNTIFS(Trade_Periods!$B$6:$B$125,Assumptions!$C$6,Trade_Periods!$C$6:$C$125,B33,Trade_Periods!$D$6:$D$125,A33)=1,COUNTIFS(Tariffs!$B$6:$B$45,B33,Tariffs!$C$6:$C$45,A33)=1),"Ready","Missing data") -> Ready | AE33: =IF(D33>0,R33/D33,"n.a.") -> 1 | AF33: =IF(M33>0,IF(D33>0,R33/D33,IF(R33=0,0,"n.a.")),0) -> 0 | AG33: =IF(AND(Assumptions!$F$14="Yes",M33>0),MAX(0,R33-Assumptions!$C$14*D33),0) -> 0
A34: 62044300 | B34: Turkey | C34: =SUMIFS(Trade_Periods!$F$6:$F$125,Trade_Periods!$B$6:$B$125,"FY2025",Trade_Periods!$C$6:$C$125,B34,Trade_Periods!$D$6:$D$125,A34) -> 268083 | D34: =C34/SUM(C26:C35) -> 0.034028981 | E34: =IF(Assumptions!$C$7="Reported",SUMIFS(Trade_Periods!$E$6:$E$125,Trade_Periods!$B$6:$B$125,Assumptions!$C$6,Trade_Periods!$C$6:$C$125,B34,Trade_Periods!$D$6:$D$125,A34),SUMIFS(Trade_Periods!$L$6:$L$125,Trade_Periods!$B$6:$B$125,Assumptions!$C$6,Trade_Periods!$C$6:$C$125,B34,Trade_Periods!$D$6:$D$125,A34)) -> 2652697 | F34: =IF(Assumptions!$C$7="Reported",SUMIFS(Trade_Periods!$F$6:$F$125,Trade_Periods!$B$6:$B$125,Assumptions!$C$6,Trade_Periods!$C$6:$C$125,B34,Trade_Periods!$D$6:$D$125,A34),SUMIFS(Trade_Periods!$M$6:$M$125,Trade_Periods!$B$6:$B$125,Assumptions!$C$6,Trade_Periods!$C$6:$C$125,B34,Trade_Periods!$D$6:$D$125,A34)) -> 68957 | G34: =IF(F34>0,E34/F34,"n.a.") -> 38.468857 | H34: =IF(Assumptions!$C$8="2025",SUMIFS(Tariffs!$D$6:$D$45,Tariffs!$B$6:$B$45,B34,Tariffs!$C$6:$C$45,A34),IF(Assumptions!$C$8="1 Jan to 14 Jul 2026",SUMIFS(Tariffs!$E$6:$E$45,Tariffs!$B$6:$B$45,B34,Tariffs!$C$6:$C$45,A34),SUMIFS(Tariffs!$F$6:$F$45,Tariffs!$B$6:$B$45,B34,Tariffs!$C$6:$C$45,A34))) -> 0 | I34: =SUMIFS(Tariffs!$G$6:$G$45,Tariffs!$B$6:$B$45,B34,Tariffs!$C$6:$C$45,A34) -> 0.12 | J34: =G34*(1+H34) -> 38.468857 | K34: =G34*(1+I34) -> 43.08512 | L34: =IF(Assumptions!$C$9="Eligible preference",J34,K34) -> 38.468857 | M34: =Assumptions!B32 -> 0.25 | N34: =Assumptions!C32 -> 0 | O34: =IF(B34="China",-1,M34) -> 0.25 | P34: =IF(B34="China",D34,IF(M34>0,MAX(0,MIN(Assumptions!$C$10-D34,Assumptions!$C$11,IF(Assumptions!$F$14="Yes",(Assumptions!$C$14-1)*D34,1))/M34),1)) -> 0.27223185 | Q34: =$E53*O34 -> 0.025 | R34: =D34+Q34 -> 0.059028981 | S34: =D34*L34 -> 1.309056 | T34: =R34*L34+MAX(0,Q34)*L34*N34 -> 2.2707774 | U34: =O34*L34+M34*L34*N34 -> 9.6172144 | V34: =D34^2 -> 0.0011579715 | W34: =2*D34*O34 -> 0.01701449 | X34: =O34^2 -> 0.0625 | Y34: =IF(Candidate_Gates!N34="Pass",MAX(0,Q34),0) -> 0 | Z34: =D34*J34 -> 1.309056 | AA34: =O34*J34+M34*J34*N34 -> 9.6172144 | AB34: =D34*K34 -> 1.4661427 | AC34: =O34*K34+M34*K34*N34 -> 10.77128 | AD34: =IF(AND(C34>=0,F34>0,E34>0,ISNUMBER(G34),COUNTIFS(Trade_Periods!$B$6:$B$125,Assumptions!$C$6,Trade_Periods!$C$6:$C$125,B34,Trade_Periods!$D$6:$D$125,A34)=1,COUNTIFS(Tariffs!$B$6:$B$45,B34,Tariffs!$C$6:$C$45,A34)=1),"Ready","Missing data") -> Ready | AE34: =IF(D34>0,R34/D34,"n.a.") -> 1.7346679 | AF34: =IF(M34>0,IF(D34>0,R34/D34,IF(R34=0,0,"n.a.")),0) -> 1.7346679 | AG34: =IF(AND(Assumptions!$F$14="Yes",M34>0),MAX(0,R34-Assumptions!$C$14*D34),0) -> 0
A35: 62044300 | B35: Vietnam | C35: =SUMIFS(Trade_Periods!$F$6:$F$125,Trade_Periods!$B$6:$B$125,"FY2025",Trade_Periods!$C$6:$C$125,B35,Trade_Periods!$D$6:$D$125,A35) -> 275082 | D35: =C35/SUM(C26:C35) -> 0.034917395 | E35: =IF(Assumptions!$C$7="Reported",SUMIFS(Trade_Periods!$E$6:$E$125,Trade_Periods!$B$6:$B$125,Assumptions!$C$6,Trade_Periods!$C$6:$C$125,B35,Trade_Periods!$D$6:$D$125,A35),SUMIFS(Trade_Periods!$L$6:$L$125,Trade_Periods!$B$6:$B$125,Assumptions!$C$6,Trade_Periods!$C$6:$C$125,B35,Trade_Periods!$D$6:$D$125,A35)) -> 4252865 | F35: =IF(Assumptions!$C$7="Reported",SUMIFS(Trade_Periods!$F$6:$F$125,Trade_Periods!$B$6:$B$125,Assumptions!$C$6,Trade_Periods!$C$6:$C$125,B35,Trade_Periods!$D$6:$D$125,A35),SUMIFS(Trade_Periods!$M$6:$M$125,Trade_Periods!$B$6:$B$125,Assumptions!$C$6,Trade_Periods!$C$6:$C$125,B35,Trade_Periods!$D$6:$D$125,A35)) -> 181343 | G35: =IF(F35>0,E35/F35,"n.a.") -> 23.452049 | H35: =IF(Assumptions!$C$8="2025",SUMIFS(Tariffs!$D$6:$D$45,Tariffs!$B$6:$B$45,B35,Tariffs!$C$6:$C$45,A35),IF(Assumptions!$C$8="1 Jan to 14 Jul 2026",SUMIFS(Tariffs!$E$6:$E$45,Tariffs!$B$6:$B$45,B35,Tariffs!$C$6:$C$45,A35),SUMIFS(Tariffs!$F$6:$F$45,Tariffs!$B$6:$B$45,B35,Tariffs!$C$6:$C$45,A35))) -> 0.015 | I35: =SUMIFS(Tariffs!$G$6:$G$45,Tariffs!$B$6:$B$45,B35,Tariffs!$C$6:$C$45,A35) -> 0.12 | J35: =G35*(1+H35) -> 23.80383 | K35: =G35*(1+I35) -> 26.266295 | L35: =IF(Assumptions!$C$9="Eligible preference",J35,K35) -> 23.80383 | M35: =Assumptions!B33 -> 0.25 | N35: =Assumptions!C33 -> 0 | O35: =IF(B35="China",-1,M35) -> 0.25 | P35: =IF(B35="China",D35,IF(M35>0,MAX(0,MIN(Assumptions!$C$10-D35,Assumptions!$C$11,IF(Assumptions!$F$14="Yes",(Assumptions!$C$14-1)*D35,1))/M35),1)) -> 0.27933916 | Q35: =$E53*O35 -> 0.025 | R35: =D35+Q35 -> 0.059917395 | S35: =D35*L35 -> 0.83116775 | T35: =R35*L35+MAX(0,Q35)*L35*N35 -> 1.4262635 | U35: =O35*L35+M35*L35*N35 -> 5.9509575 | V35: =D35^2 -> 0.0012192245 | W35: =2*D35*O35 -> 0.017458698 | X35: =O35^2 -> 0.0625 | Y35: =IF(Candidate_Gates!N35="Pass",MAX(0,Q35),0) -> 0 | Z35: =D35*J35 -> 0.83116775 | AA35: =O35*J35+M35*J35*N35 -> 5.9509575 | AB35: =D35*K35 -> 0.91715062 | AC35: =O35*K35+M35*K35*N35 -> 6.5665738 | AD35: =IF(AND(C35>=0,F35>0,E35>0,ISNUMBER(G35),COUNTIFS(Trade_Periods!$B$6:$B$125,Assumptions!$C$6,Trade_Periods!$C$6:$C$125,B35,Trade_Periods!$D$6:$D$125,A35)=1,COUNTIFS(Tariffs!$B$6:$B$45,B35,Tariffs!$C$6:$C$45,A35)=1),"Ready","Missing data") -> Ready | AE35: =IF(D35>0,R35/D35,"n.a.") -> 1.7159755 | AF35: =IF(M35>0,IF(D35>0,R35/D35,IF(R35=0,0,"n.a.")),0) -> 1.7159755 | AG35: =IF(AND(Assumptions!$F$14="Yes",M35>0),MAX(0,R35-Assumptions!$C$14*D35),0) -> 0
A36: 62052000 | B36: Bangladesh | C36: =SUMIFS(Trade_Periods!$F$6:$F$125,Trade_Periods!$B$6:$B$125,"FY2025",Trade_Periods!$C$6:$C$125,B36,Trade_Periods!$D$6:$D$125,A36) -> 4630717 | D36: =C36/SUM(C36:C45) -> 0.54748094 | E36: =IF(Assumptions!$C$7="Reported",SUMIFS(Trade_Periods!$E$6:$E$125,Trade_Periods!$B$6:$B$125,Assumptions!$C$6,Trade_Periods!$C$6:$C$125,B36,Trade_Periods!$D$6:$D$125,A36),SUMIFS(Trade_Periods!$L$6:$L$125,Trade_Periods!$B$6:$B$125,Assumptions!$C$6,Trade_Periods!$C$6:$C$125,B36,Trade_Periods!$D$6:$D$125,A36)) -> 36256449 | F36: =IF(Assumptions!$C$7="Reported",SUMIFS(Trade_Periods!$F$6:$F$125,Trade_Periods!$B$6:$B$125,Assumptions!$C$6,Trade_Periods!$C$6:$C$125,B36,Trade_Periods!$D$6:$D$125,A36),SUMIFS(Trade_Periods!$M$6:$M$125,Trade_Periods!$B$6:$B$125,Assumptions!$C$6,Trade_Periods!$C$6:$C$125,B36,Trade_Periods!$D$6:$D$125,A36)) -> 2116872 | G36: =IF(F36>0,E36/F36,"n.a.") -> 17.12737 | H36: =IF(Assumptions!$C$8="2025",SUMIFS(Tariffs!$D$6:$D$45,Tariffs!$B$6:$B$45,B36,Tariffs!$C$6:$C$45,A36),IF(Assumptions!$C$8="1 Jan to 14 Jul 2026",SUMIFS(Tariffs!$E$6:$E$45,Tariffs!$B$6:$B$45,B36,Tariffs!$C$6:$C$45,A36),SUMIFS(Tariffs!$F$6:$F$45,Tariffs!$B$6:$B$45,B36,Tariffs!$C$6:$C$45,A36))) -> 0 | I36: =SUMIFS(Tariffs!$G$6:$G$45,Tariffs!$B$6:$B$45,B36,Tariffs!$C$6:$C$45,A36) -> 0.12 | J36: =G36*(1+H36) -> 17.12737 | K36: =G36*(1+I36) -> 19.182654 | L36: =IF(Assumptions!$C$9="Eligible preference",J36,K36) -> 17.12737 | M36: =Assumptions!B24 -> 0 | N36: =Assumptions!C24 -> 0 | O36: =IF(B36="China",-1,M36) -> 0 | P36: =IF(B36="China",D36,IF(M36>0,MAX(0,MIN(Assumptions!$C$10-D36,Assumptions!$C$11,IF(Assumptions!$F$14="Yes",(Assumptions!$C$14-1)*D36,1))/M36),1)) -> 1 | Q36: =$E54*O36 -> 0 | R36: =D36+Q36 -> 0.54748094 | S36: =D36*L36 -> 9.3769084 | T36: =R36*L36+MAX(0,Q36)*L36*N36 -> 9.3769084 | U36: =O36*L36+M36*L36*N36 -> 0 | V36: =D36^2 -> 0.29973538 | W36: =2*D36*O36 -> 0 | X36: =O36^2 -> 0 | Y36: =IF(Candidate_Gates!N36="Pass",MAX(0,Q36),0) -> 0 | Z36: =D36*J36 -> 9.3769084 | AA36: =O36*J36+M36*J36*N36 -> 0 | AB36: =D36*K36 -> 10.502137 | AC36: =O36*K36+M36*K36*N36 -> 0 | AD36: =IF(AND(C36>=0,F36>0,E36>0,ISNUMBER(G36),COUNTIFS(Trade_Periods!$B$6:$B$125,Assumptions!$C$6,Trade_Periods!$C$6:$C$125,B36,Trade_Periods!$D$6:$D$125,A36)=1,COUNTIFS(Tariffs!$B$6:$B$45,B36,Tariffs!$C$6:$C$45,A36)=1),"Ready","Missing data") -> Ready | AE36: =IF(D36>0,R36/D36,"n.a.") -> 1 | AF36: =IF(M36>0,IF(D36>0,R36/D36,IF(R36=0,0,"n.a.")),0) -> 0 | AG36: =IF(AND(Assumptions!$F$14="Yes",M36>0),MAX(0,R36-Assumptions!$C$14*D36),0) -> 0
A37: 62052000 | B37: Cambodia | C37: =SUMIFS(Trade_Periods!$F$6:$F$125,Trade_Periods!$B$6:$B$125,"FY2025",Trade_Periods!$C$6:$C$125,B37,Trade_Periods!$D$6:$D$125,A37) -> 674204 | D37: =C37/SUM(C36:C45) -> 0.079709868 | E37: =IF(Assumptions!$C$7="Reported",SUMIFS(Trade_Periods!$E$6:$E$125,Trade_Periods!$B$6:$B$125,Assumptions!$C$6,Trade_Periods!$C$6:$C$125,B37,Trade_Periods!$D$6:$D$125,A37),SUMIFS(Trade_Periods!$L$6:$L$125,Trade_Periods!$B$6:$B$125,Assumptions!$C$6,Trade_Periods!$C$6:$C$125,B37,Trade_Periods!$D$6:$D$125,A37)) -> 6216726 | F37: =IF(Assumptions!$C$7="Reported",SUMIFS(Trade_Periods!$F$6:$F$125,Trade_Periods!$B$6:$B$125,Assumptions!$C$6,Trade_Periods!$C$6:$C$125,B37,Trade_Periods!$D$6:$D$125,A37),SUMIFS(Trade_Periods!$M$6:$M$125,Trade_Periods!$B$6:$B$125,Assumptions!$C$6,Trade_Periods!$C$6:$C$125,B37,Trade_Periods!$D$6:$D$125,A37)) -> 285166 | G37: =IF(F37>0,E37/F37,"n.a.") -> 21.800376 | H37: =IF(Assumptions!$C$8="2025",SUMIFS(Tariffs!$D$6:$D$45,Tariffs!$B$6:$B$45,B37,Tariffs!$C$6:$C$45,A37),IF(Assumptions!$C$8="1 Jan to 14 Jul 2026",SUMIFS(Tariffs!$E$6:$E$45,Tariffs!$B$6:$B$45,B37,Tariffs!$C$6:$C$45,A37),SUMIFS(Tariffs!$F$6:$F$45,Tariffs!$B$6:$B$45,B37,Tariffs!$C$6:$C$45,A37))) -> 0 | I37: =SUMIFS(Tariffs!$G$6:$G$45,Tariffs!$B$6:$B$45,B37,Tariffs!$C$6:$C$45,A37) -> 0.12 | J37: =G37*(1+H37) -> 21.800376 | K37: =G37*(1+I37) -> 24.416421 | L37: =IF(Assumptions!$C$9="Eligible preference",J37,K37) -> 21.800376 | M37: =Assumptions!B25 -> 0 | N37: =Assumptions!C25 -> 0 | O37: =IF(B37="China",-1,M37) -> 0 | P37: =IF(B37="China",D37,IF(M37>0,MAX(0,MIN(Assumptions!$C$10-D37,Assumptions!$C$11,IF(Assumptions!$F$14="Yes",(Assumptions!$C$14-1)*D37,1))/M37),1)) -> 1 | Q37: =$E54*O37 -> 0 | R37: =D37+Q37 -> 0.079709868 | S37: =D37*L37 -> 1.7377051 | T37: =R37*L37+MAX(0,Q37)*L37*N37 -> 1.7377051 | U37: =O37*L37+M37*L37*N37 -> 0 | V37: =D37^2 -> 0.0063536631 | W37: =2*D37*O37 -> 0 | X37: =O37^2 -> 0 | Y37: =IF(Candidate_Gates!N37="Pass",MAX(0,Q37),0) -> 0 | Z37: =D37*J37 -> 1.7377051 | AA37: =O37*J37+M37*J37*N37 -> 0 | AB37: =D37*K37 -> 1.9462297 | AC37: =O37*K37+M37*K37*N37 -> 0 | AD37: =IF(AND(C37>=0,F37>0,E37>0,ISNUMBER(G37),COUNTIFS(Trade_Periods!$B$6:$B$125,Assumptions!$C$6,Trade_Periods!$C$6:$C$125,B37,Trade_Periods!$D$6:$D$125,A37)=1,COUNTIFS(Tariffs!$B$6:$B$45,B37,Tariffs!$C$6:$C$45,A37)=1),"Ready","Missing data") -> Ready | AE37: =IF(D37>0,R37/D37,"n.a.") -> 1 | AF37: =IF(M37>0,IF(D37>0,R37/D37,IF(R37=0,0,"n.a.")),0) -> 0 | AG37: =IF(AND(Assumptions!$F$14="Yes",M37>0),MAX(0,R37-Assumptions!$C$14*D37),0) -> 0
A38: 62052000 | B38: China | C38: =SUMIFS(Trade_Periods!$F$6:$F$125,Trade_Periods!$B$6:$B$125,"FY2025",Trade_Periods!$C$6:$C$125,B38,Trade_Periods!$D$6:$D$125,A38) -> 584970 | D38: =C38/SUM(C36:C45) -> 0.069159901 | E38: =IF(Assumptions!$C$7="Reported",SUMIFS(Trade_Periods!$E$6:$E$125,Trade_Periods!$B$6:$B$125,Assumptions!$C$6,Trade_Periods!$C$6:$C$125,B38,Trade_Periods!$D$6:$D$125,A38),SUMIFS(Trade_Periods!$L$6:$L$125,Trade_Periods!$B$6:$B$125,Assumptions!$C$6,Trade_Periods!$C$6:$C$125,B38,Trade_Periods!$D$6:$D$125,A38)) -> 5317772 | F38: =IF(Assumptions!$C$7="Reported",SUMIFS(Trade_Periods!$F$6:$F$125,Trade_Periods!$B$6:$B$125,Assumptions!$C$6,Trade_Periods!$C$6:$C$125,B38,Trade_Periods!$D$6:$D$125,A38),SUMIFS(Trade_Periods!$M$6:$M$125,Trade_Periods!$B$6:$B$125,Assumptions!$C$6,Trade_Periods!$C$6:$C$125,B38,Trade_Periods!$D$6:$D$125,A38)) -> 245226 | G38: =IF(F38>0,E38/F38,"n.a.") -> 21.685188 | H38: =IF(Assumptions!$C$8="2025",SUMIFS(Tariffs!$D$6:$D$45,Tariffs!$B$6:$B$45,B38,Tariffs!$C$6:$C$45,A38),IF(Assumptions!$C$8="1 Jan to 14 Jul 2026",SUMIFS(Tariffs!$E$6:$E$45,Tariffs!$B$6:$B$45,B38,Tariffs!$C$6:$C$45,A38),SUMIFS(Tariffs!$F$6:$F$45,Tariffs!$B$6:$B$45,B38,Tariffs!$C$6:$C$45,A38))) -> 0.12 | I38: =SUMIFS(Tariffs!$G$6:$G$45,Tariffs!$B$6:$B$45,B38,Tariffs!$C$6:$C$45,A38) -> 0.12 | J38: =G38*(1+H38) -> 24.287411 | K38: =G38*(1+I38) -> 24.287411 | L38: =IF(Assumptions!$C$9="Eligible preference",J38,K38) -> 24.287411 | M38: =Assumptions!B26 -> 0 | N38: =Assumptions!C26 -> 0 | O38: =IF(B38="China",-1,M38) -> -1 | P38: =IF(B38="China",D38,IF(M38>0,MAX(0,MIN(Assumptions!$C$10-D38,Assumptions!$C$11,IF(Assumptions!$F$14="Yes",(Assumptions!$C$14-1)*D38,1))/M38),1)) -> 0.069159901 | Q38: =$E54*O38 -> -0.069159901 | R38: =D38+Q38 -> 0 | S38: =D38*L38 -> 1.6797149 | T38: =R38*L38+MAX(0,Q38)*L38*N38 -> 0 | U38: =O38*L38+M38*L38*N38 -> -24.287411 | V38: =D38^2 -> 0.0047830918 | W38: =2*D38*O38 -> -0.1383198 | X38: =O38^2 -> 1 | Y38: =IF(Candidate_Gates!N38="Pass",MAX(0,Q38),0) -> 0 | Z38: =D38*J38 -> 1.6797149 | AA38: =O38*J38+M38*J38*N38 -> -24.287411 | AB38: =D38*K38 -> 1.6797149 | AC38: =O38*K38+M38*K38*N38 -> -24.287411 | AD38: =IF(AND(C38>=0,F38>0,E38>0,ISNUMBER(G38),COUNTIFS(Trade_Periods!$B$6:$B$125,Assumptions!$C$6,Trade_Periods!$C$6:$C$125,B38,Trade_Periods!$D$6:$D$125,A38)=1,COUNTIFS(Tariffs!$B$6:$B$45,B38,Tariffs!$C$6:$C$45,A38)=1),"Ready","Missing data") -> Ready | AE38: =IF(D38>0,R38/D38,"n.a.") -> 0 | AF38: =IF(M38>0,IF(D38>0,R38/D38,IF(R38=0,0,"n.a.")),0) -> 0 | AG38: =IF(AND(Assumptions!$F$14="Yes",M38>0),MAX(0,R38-Assumptions!$C$14*D38),0) -> 0
A39: 62052000 | B39: India | C39: =SUMIFS(Trade_Periods!$F$6:$F$125,Trade_Periods!$B$6:$B$125,"FY2025",Trade_Periods!$C$6:$C$125,B39,Trade_Periods!$D$6:$D$125,A39) -> 1414140 | D39: =C39/SUM(C36:C45) -> 0.16719111 | E39: =IF(Assumptions!$C$7="Reported",SUMIFS(Trade_Periods!$E$6:$E$125,Trade_Periods!$B$6:$B$125,Assumptions!$C$6,Trade_Periods!$C$6:$C$125,B39,Trade_Periods!$D$6:$D$125,A39),SUMIFS(Trade_Periods!$L$6:$L$125,Trade_Periods!$B$6:$B$125,Assumptions!$C$6,Trade_Periods!$C$6:$C$125,B39,Trade_Periods!$D$6:$D$125,A39)) -> 16147727 | F39: =IF(Assumptions!$C$7="Reported",SUMIFS(Trade_Periods!$F$6:$F$125,Trade_Periods!$B$6:$B$125,Assumptions!$C$6,Trade_Periods!$C$6:$C$125,B39,Trade_Periods!$D$6:$D$125,A39),SUMIFS(Trade_Periods!$M$6:$M$125,Trade_Periods!$B$6:$B$125,Assumptions!$C$6,Trade_Periods!$C$6:$C$125,B39,Trade_Periods!$D$6:$D$125,A39)) -> 737427 | G39: =IF(F39>0,E39/F39,"n.a.") -> 21.897391 | H39: =IF(Assumptions!$C$8="2025",SUMIFS(Tariffs!$D$6:$D$45,Tariffs!$B$6:$B$45,B39,Tariffs!$C$6:$C$45,A39),IF(Assumptions!$C$8="1 Jan to 14 Jul 2026",SUMIFS(Tariffs!$E$6:$E$45,Tariffs!$B$6:$B$45,B39,Tariffs!$C$6:$C$45,A39),SUMIFS(Tariffs!$F$6:$F$45,Tariffs!$B$6:$B$45,B39,Tariffs!$C$6:$C$45,A39))) -> 0 | I39: =SUMIFS(Tariffs!$G$6:$G$45,Tariffs!$B$6:$B$45,B39,Tariffs!$C$6:$C$45,A39) -> 0.12 | J39: =G39*(1+H39) -> 21.897391 | K39: =G39*(1+I39) -> 24.525077 | L39: =IF(Assumptions!$C$9="Eligible preference",J39,K39) -> 21.897391 | M39: =Assumptions!B27 -> 0.5 | N39: =Assumptions!C27 -> 0 | O39: =IF(B39="China",-1,M39) -> 0.5 | P39: =IF(B39="China",D39,IF(M39>0,MAX(0,MIN(Assumptions!$C$10-D39,Assumptions!$C$11,IF(Assumptions!$F$14="Yes",(Assumptions!$C$14-1)*D39,1))/M39),1)) -> 0.2 | Q39: =$E54*O39 -> 0.03457995 | R39: =D39+Q39 -> 0.20177106 | S39: =D39*L39 -> 3.661049 | T39: =R39*L39+MAX(0,Q39)*L39*N39 -> 4.4182596 | U39: =O39*L39+M39*L39*N39 -> 10.948695 | V39: =D39^2 -> 0.027952866 | W39: =2*D39*O39 -> 0.16719111 | X39: =O39^2 -> 0.25 | Y39: =IF(Candidate_Gates!N39="Pass",MAX(0,Q39),0) -> 0 | Z39: =D39*J39 -> 3.661049 | AA39: =O39*J39+M39*J39*N39 -> 10.948695 | AB39: =D39*K39 -> 4.1003748 | AC39: =O39*K39+M39*K39*N39 -> 12.262539 | AD39: =IF(AND(C39>=0,F39>0,E39>0,ISNUMBER(G39),COUNTIFS(Trade_Periods!$B$6:$B$125,Assumptions!$C$6,Trade_Periods!$C$6:$C$125,B39,Trade_Periods!$D$6:$D$125,A39)=1,COUNTIFS(Tariffs!$B$6:$B$45,B39,Tariffs!$C$6:$C$45,A39)=1),"Ready","Missing data") -> Ready | AE39: =IF(D39>0,R39/D39,"n.a.") -> 1.2068289 | AF39: =IF(M39>0,IF(D39>0,R39/D39,IF(R39=0,0,"n.a.")),0) -> 1.2068289 | AG39: =IF(AND(Assumptions!$F$14="Yes",M39>0),MAX(0,R39-Assumptions!$C$14*D39),0) -> 0
A40: 62052000 | B40: Morocco | C40: =SUMIFS(Trade_Periods!$F$6:$F$125,Trade_Periods!$B$6:$B$125,"FY2025",Trade_Periods!$C$6:$C$125,B40,Trade_Periods!$D$6:$D$125,A40) -> 33234 | D40: =C40/SUM(C36:C45) -> 0.0039291932 | E40: =IF(Assumptions!$C$7="Reported",SUMIFS(Trade_Periods!$E$6:$E$125,Trade_Periods!$B$6:$B$125,Assumptions!$C$6,Trade_Periods!$C$6:$C$125,B40,Trade_Periods!$D$6:$D$125,A40),SUMIFS(Trade_Periods!$L$6:$L$125,Trade_Periods!$B$6:$B$125,Assumptions!$C$6,Trade_Periods!$C$6:$C$125,B40,Trade_Periods!$D$6:$D$125,A40)) -> 561115 | F40: =IF(Assumptions!$C$7="Reported",SUMIFS(Trade_Periods!$F$6:$F$125,Trade_Periods!$B$6:$B$125,Assumptions!$C$6,Trade_Periods!$C$6:$C$125,B40,Trade_Periods!$D$6:$D$125,A40),SUMIFS(Trade_Periods!$M$6:$M$125,Trade_Periods!$B$6:$B$125,Assumptions!$C$6,Trade_Periods!$C$6:$C$125,B40,Trade_Periods!$D$6:$D$125,A40)) -> 15750 | G40: =IF(F40>0,E40/F40,"n.a.") -> 35.626349 | H40: =IF(Assumptions!$C$8="2025",SUMIFS(Tariffs!$D$6:$D$45,Tariffs!$B$6:$B$45,B40,Tariffs!$C$6:$C$45,A40),IF(Assumptions!$C$8="1 Jan to 14 Jul 2026",SUMIFS(Tariffs!$E$6:$E$45,Tariffs!$B$6:$B$45,B40,Tariffs!$C$6:$C$45,A40),SUMIFS(Tariffs!$F$6:$F$45,Tariffs!$B$6:$B$45,B40,Tariffs!$C$6:$C$45,A40))) -> 0 | I40: =SUMIFS(Tariffs!$G$6:$G$45,Tariffs!$B$6:$B$45,B40,Tariffs!$C$6:$C$45,A40) -> 0.12 | J40: =G40*(1+H40) -> 35.626349 | K40: =G40*(1+I40) -> 39.901511 | L40: =IF(Assumptions!$C$9="Eligible preference",J40,K40) -> 35.626349 | M40: =Assumptions!B28 -> 0 | N40: =Assumptions!C28 -> 0 | O40: =IF(B40="China",-1,M40) -> 0 | P40: =IF(B40="China",D40,IF(M40>0,MAX(0,MIN(Assumptions!$C$10-D40,Assumptions!$C$11,IF(Assumptions!$F$14="Yes",(Assumptions!$C$14-1)*D40,1))/M40),1)) -> 1 | Q40: =$E54*O40 -> 0 | R40: =D40+Q40 -> 0.0039291932 | S40: =D40*L40 -> 0.13998281 | T40: =R40*L40+MAX(0,Q40)*L40*N40 -> 0.13998281 | U40: =O40*L40+M40*L40*N40 -> 0 | V40: =D40^2 -> 1.5438559e-05 | W40: =2*D40*O40 -> 0 | X40: =O40^2 -> 0 | Y40: =IF(Candidate_Gates!N40="Pass",MAX(0,Q40),0) -> 0 | Z40: =D40*J40 -> 0.13998281 | AA40: =O40*J40+M40*J40*N40 -> 0 | AB40: =D40*K40 -> 0.15678075 | AC40: =O40*K40+M40*K40*N40 -> 0 | AD40: =IF(AND(C40>=0,F40>0,E40>0,ISNUMBER(G40),COUNTIFS(Trade_Periods!$B$6:$B$125,Assumptions!$C$6,Trade_Periods!$C$6:$C$125,B40,Trade_Periods!$D$6:$D$125,A40)=1,COUNTIFS(Tariffs!$B$6:$B$45,B40,Tariffs!$C$6:$C$45,A40)=1),"Ready","Missing data") -> Ready | AE40: =IF(D40>0,R40/D40,"n.a.") -> 1 | AF40: =IF(M40>0,IF(D40>0,R40/D40,IF(R40=0,0,"n.a.")),0) -> 0 | AG40: =IF(AND(Assumptions!$F$14="Yes",M40>0),MAX(0,R40-Assumptions!$C$14*D40),0) -> 0
A41: 62052000 | B41: Myanmar | C41: =SUMIFS(Trade_Periods!$F$6:$F$125,Trade_Periods!$B$6:$B$125,"FY2025",Trade_Periods!$C$6:$C$125,B41,Trade_Periods!$D$6:$D$125,A41) -> 54446 | D41: =C41/SUM(C36:C45) -> 0.006437048 | E41: =IF(Assumptions!$C$7="Reported",SUMIFS(Trade_Periods!$E$6:$E$125,Trade_Periods!$B$6:$B$125,Assumptions!$C$6,Trade_Periods!$C$6:$C$125,B41,Trade_Periods!$D$6:$D$125,A41),SUMIFS(Trade_Periods!$L$6:$L$125,Trade_Periods!$B$6:$B$125,Assumptions!$C$6,Trade_Periods!$C$6:$C$125,B41,Trade_Periods!$D$6:$D$125,A41)) -> 438060 | F41: =IF(Assumptions!$C$7="Reported",SUMIFS(Trade_Periods!$F$6:$F$125,Trade_Periods!$B$6:$B$125,Assumptions!$C$6,Trade_Periods!$C$6:$C$125,B41,Trade_Periods!$D$6:$D$125,A41),SUMIFS(Trade_Periods!$M$6:$M$125,Trade_Periods!$B$6:$B$125,Assumptions!$C$6,Trade_Periods!$C$6:$C$125,B41,Trade_Periods!$D$6:$D$125,A41)) -> 30188 | G41: =IF(F41>0,E41/F41,"n.a.") -> 14.511064 | H41: =IF(Assumptions!$C$8="2025",SUMIFS(Tariffs!$D$6:$D$45,Tariffs!$B$6:$B$45,B41,Tariffs!$C$6:$C$45,A41),IF(Assumptions!$C$8="1 Jan to 14 Jul 2026",SUMIFS(Tariffs!$E$6:$E$45,Tariffs!$B$6:$B$45,B41,Tariffs!$C$6:$C$45,A41),SUMIFS(Tariffs!$F$6:$F$45,Tariffs!$B$6:$B$45,B41,Tariffs!$C$6:$C$45,A41))) -> 0 | I41: =SUMIFS(Tariffs!$G$6:$G$45,Tariffs!$B$6:$B$45,B41,Tariffs!$C$6:$C$45,A41) -> 0.12 | J41: =G41*(1+H41) -> 14.511064 | K41: =G41*(1+I41) -> 16.252392 | L41: =IF(Assumptions!$C$9="Eligible preference",J41,K41) -> 14.511064 | M41: =Assumptions!B29 -> 0 | N41: =Assumptions!C29 -> 0 | O41: =IF(B41="China",-1,M41) -> 0 | P41: =IF(B41="China",D41,IF(M41>0,MAX(0,MIN(Assumptions!$C$10-D41,Assumptions!$C$11,IF(Assumptions!$F$14="Yes",(Assumptions!$C$14-1)*D41,1))/M41),1)) -> 1 | Q41: =$E54*O41 -> 0 | R41: =D41+Q41 -> 0.006437048 | S41: =D41*L41 -> 0.093408415 | T41: =R41*L41+MAX(0,Q41)*L41*N41 -> 0.093408415 | U41: =O41*L41+M41*L41*N41 -> 0 | V41: =D41^2 -> 4.1435586e-05 | W41: =2*D41*O41 -> 0 | X41: =O41^2 -> 0 | Y41: =IF(Candidate_Gates!N41="Pass",MAX(0,Q41),0) -> 0 | Z41: =D41*J41 -> 0.093408415 | AA41: =O41*J41+M41*J41*N41 -> 0 | AB41: =D41*K41 -> 0.10461742 | AC41: =O41*K41+M41*K41*N41 -> 0 | AD41: =IF(AND(C41>=0,F41>0,E41>0,ISNUMBER(G41),COUNTIFS(Trade_Periods!$B$6:$B$125,Assumptions!$C$6,Trade_Periods!$C$6:$C$125,B41,Trade_Periods!$D$6:$D$125,A41)=1,COUNTIFS(Tariffs!$B$6:$B$45,B41,Tariffs!$C$6:$C$45,A41)=1),"Ready","Missing data") -> Ready | AE41: =IF(D41>0,R41/D41,"n.a.") -> 1 | AF41: =IF(M41>0,IF(D41>0,R41/D41,IF(R41=0,0,"n.a.")),0) -> 0 | AG41: =IF(AND(Assumptions!$F$14="Yes",M41>0),MAX(0,R41-Assumptions!$C$14*D41),0) -> 0
A42: 62052000 | B42: Pakistan | C42: =SUMIFS(Trade_Periods!$F$6:$F$125,Trade_Periods!$B$6:$B$125,"FY2025",Trade_Periods!$C$6:$C$125,B42,Trade_Periods!$D$6:$D$125,A42) -> 69348 | D42: =C42/SUM(C36:C45) -> 0.0081988833 | E42: =IF(Assumptions!$C$7="Reported",SUMIFS(Trade_Periods!$E$6:$E$125,Trade_Periods!$B$6:$B$125,Assumptions!$C$6,Trade_Periods!$C$6:$C$125,B42,Trade_Periods!$D$6:$D$125,A42),SUMIFS(Trade_Periods!$L$6:$L$125,Trade_Periods!$B$6:$B$125,Assumptions!$C$6,Trade_Periods!$C$6:$C$125,B42,Trade_Periods!$D$6:$D$125,A42)) -> 358538 | F42: =IF(Assumptions!$C$7="Reported",SUMIFS(Trade_Periods!$F$6:$F$125,Trade_Periods!$B$6:$B$125,Assumptions!$C$6,Trade_Periods!$C$6:$C$125,B42,Trade_Periods!$D$6:$D$125,A42),SUMIFS(Trade_Periods!$M$6:$M$125,Trade_Periods!$B$6:$B$125,Assumptions!$C$6,Trade_Periods!$C$6:$C$125,B42,Trade_Periods!$D$6:$D$125,A42)) -> 25923 | G42: =IF(F42>0,E42/F42,"n.a.") -> 13.830884 | H42: =IF(Assumptions!$C$8="2025",SUMIFS(Tariffs!$D$6:$D$45,Tariffs!$B$6:$B$45,B42,Tariffs!$C$6:$C$45,A42),IF(Assumptions!$C$8="1 Jan to 14 Jul 2026",SUMIFS(Tariffs!$E$6:$E$45,Tariffs!$B$6:$B$45,B42,Tariffs!$C$6:$C$45,A42),SUMIFS(Tariffs!$F$6:$F$45,Tariffs!$B$6:$B$45,B42,Tariffs!$C$6:$C$45,A42))) -> 0 | I42: =SUMIFS(Tariffs!$G$6:$G$45,Tariffs!$B$6:$B$45,B42,Tariffs!$C$6:$C$45,A42) -> 0.12 | J42: =G42*(1+H42) -> 13.830884 | K42: =G42*(1+I42) -> 15.49059 | L42: =IF(Assumptions!$C$9="Eligible preference",J42,K42) -> 13.830884 | M42: =Assumptions!B30 -> 0 | N42: =Assumptions!C30 -> 0 | O42: =IF(B42="China",-1,M42) -> 0 | P42: =IF(B42="China",D42,IF(M42>0,MAX(0,MIN(Assumptions!$C$10-D42,Assumptions!$C$11,IF(Assumptions!$F$14="Yes",(Assumptions!$C$14-1)*D42,1))/M42),1)) -> 1 | Q42: =$E54*O42 -> 0 | R42: =D42+Q42 -> 0.0081988833 | S42: =D42*L42 -> 0.1133978 | T42: =R42*L42+MAX(0,Q42)*L42*N42 -> 0.1133978 | U42: =O42*L42+M42*L42*N42 -> 0 | V42: =D42^2 -> 6.7221688e-05 | W42: =2*D42*O42 -> 0 | X42: =O42^2 -> 0 | Y42: =IF(Candidate_Gates!N42="Pass",MAX(0,Q42),0) -> 0 | Z42: =D42*J42 -> 0.1133978 | AA42: =O42*J42+M42*J42*N42 -> 0 | AB42: =D42*K42 -> 0.12700554 | AC42: =O42*K42+M42*K42*N42 -> 0 | AD42: =IF(AND(C42>=0,F42>0,E42>0,ISNUMBER(G42),COUNTIFS(Trade_Periods!$B$6:$B$125,Assumptions!$C$6,Trade_Periods!$C$6:$C$125,B42,Trade_Periods!$D$6:$D$125,A42)=1,COUNTIFS(Tariffs!$B$6:$B$45,B42,Tariffs!$C$6:$C$45,A42)=1),"Ready","Missing data") -> Ready | AE42: =IF(D42>0,R42/D42,"n.a.") -> 1 | AF42: =IF(M42>0,IF(D42>0,R42/D42,IF(R42=0,0,"n.a.")),0) -> 0 | AG42: =IF(AND(Assumptions!$F$14="Yes",M42>0),MAX(0,R42-Assumptions!$C$14*D42),0) -> 0
A43: 62052000 | B43: Sri Lanka | C43: =SUMIFS(Trade_Periods!$F$6:$F$125,Trade_Periods!$B$6:$B$125,"FY2025",Trade_Periods!$C$6:$C$125,B43,Trade_Periods!$D$6:$D$125,A43) -> 213562 | D43: =C43/SUM(C36:C45) -> 0.025249033 | E43: =IF(Assumptions!$C$7="Reported",SUMIFS(Trade_Periods!$E$6:$E$125,Trade_Periods!$B$6:$B$125,Assumptions!$C$6,Trade_Periods!$C$6:$C$125,B43,Trade_Periods!$D$6:$D$125,A43),SUMIFS(Trade_Periods!$L$6:$L$125,Trade_Periods!$B$6:$B$125,Assumptions!$C$6,Trade_Periods!$C$6:$C$125,B43,Trade_Periods!$D$6:$D$125,A43)) -> 1556820 | F43: =IF(Assumptions!$C$7="Reported",SUMIFS(Trade_Periods!$F$6:$F$125,Trade_Periods!$B$6:$B$125,Assumptions!$C$6,Trade_Periods!$C$6:$C$125,B43,Trade_Periods!$D$6:$D$125,A43),SUMIFS(Trade_Periods!$M$6:$M$125,Trade_Periods!$B$6:$B$125,Assumptions!$C$6,Trade_Periods!$C$6:$C$125,B43,Trade_Periods!$D$6:$D$125,A43)) -> 79138 | G43: =IF(F43>0,E43/F43,"n.a.") -> 19.672218 | H43: =IF(Assumptions!$C$8="2025",SUMIFS(Tariffs!$D$6:$D$45,Tariffs!$B$6:$B$45,B43,Tariffs!$C$6:$C$45,A43),IF(Assumptions!$C$8="1 Jan to 14 Jul 2026",SUMIFS(Tariffs!$E$6:$E$45,Tariffs!$B$6:$B$45,B43,Tariffs!$C$6:$C$45,A43),SUMIFS(Tariffs!$F$6:$F$45,Tariffs!$B$6:$B$45,B43,Tariffs!$C$6:$C$45,A43))) -> 0 | I43: =SUMIFS(Tariffs!$G$6:$G$45,Tariffs!$B$6:$B$45,B43,Tariffs!$C$6:$C$45,A43) -> 0.12 | J43: =G43*(1+H43) -> 19.672218 | K43: =G43*(1+I43) -> 22.032884 | L43: =IF(Assumptions!$C$9="Eligible preference",J43,K43) -> 19.672218 | M43: =Assumptions!B31 -> 0 | N43: =Assumptions!C31 -> 0 | O43: =IF(B43="China",-1,M43) -> 0 | P43: =IF(B43="China",D43,IF(M43>0,MAX(0,MIN(Assumptions!$C$10-D43,Assumptions!$C$11,IF(Assumptions!$F$14="Yes",(Assumptions!$C$14-1)*D43,1))/M43),1)) -> 1 | Q43: =$E54*O43 -> 0 | R43: =D43+Q43 -> 0.025249033 | S43: =D43*L43 -> 0.49670448 | T43: =R43*L43+MAX(0,Q43)*L43*N43 -> 0.49670448 | U43: =O43*L43+M43*L43*N43 -> 0 | V43: =D43^2 -> 0.00063751365 | W43: =2*D43*O43 -> 0 | X43: =O43^2 -> 0 | Y43: =IF(Candidate_Gates!N43="Pass",MAX(0,Q43),0) -> 0 | Z43: =D43*J43 -> 0.49670448 | AA43: =O43*J43+M43*J43*N43 -> 0 | AB43: =D43*K43 -> 0.55630902 | AC43: =O43*K43+M43*K43*N43 -> 0 | AD43: =IF(AND(C43>=0,F43>0,E43>0,ISNUMBER(G43),COUNTIFS(Trade_Periods!$B$6:$B$125,Assumptions!$C$6,Trade_Periods!$C$6:$C$125,B43,Trade_Periods!$D$6:$D$125,A43)=1,COUNTIFS(Tariffs!$B$6:$B$45,B43,Tariffs!$C$6:$C$45,A43)=1),"Ready","Missing data") -> Ready | AE43: =IF(D43>0,R43/D43,"n.a.") -> 1 | AF43: =IF(M43>0,IF(D43>0,R43/D43,IF(R43=0,0,"n.a.")),0) -> 0 | AG43: =IF(AND(Assumptions!$F$14="Yes",M43>0),MAX(0,R43-Assumptions!$C$14*D43),0) -> 0
A44: 62052000 | B44: Turkey | C44: =SUMIFS(Trade_Periods!$F$6:$F$125,Trade_Periods!$B$6:$B$125,"FY2025",Trade_Periods!$C$6:$C$125,B44,Trade_Periods!$D$6:$D$125,A44) -> 343310 | D44: =C44/SUM(C36:C45) -> 0.040588894 | E44: =IF(Assumptions!$C$7="Reported",SUMIFS(Trade_Periods!$E$6:$E$125,Trade_Periods!$B$6:$B$125,Assumptions!$C$6,Trade_Periods!$C$6:$C$125,B44,Trade_Periods!$D$6:$D$125,A44),SUMIFS(Trade_Periods!$L$6:$L$125,Trade_Periods!$B$6:$B$125,Assumptions!$C$6,Trade_Periods!$C$6:$C$125,B44,Trade_Periods!$D$6:$D$125,A44)) -> 5825379 | F44: =IF(Assumptions!$C$7="Reported",SUMIFS(Trade_Periods!$F$6:$F$125,Trade_Periods!$B$6:$B$125,Assumptions!$C$6,Trade_Periods!$C$6:$C$125,B44,Trade_Periods!$D$6:$D$125,A44),SUMIFS(Trade_Periods!$M$6:$M$125,Trade_Periods!$B$6:$B$125,Assumptions!$C$6,Trade_Periods!$C$6:$C$125,B44,Trade_Periods!$D$6:$D$125,A44)) -> 147992 | G44: =IF(F44>0,E44/F44,"n.a.") -> 39.362797 | H44: =IF(Assumptions!$C$8="2025",SUMIFS(Tariffs!$D$6:$D$45,Tariffs!$B$6:$B$45,B44,Tariffs!$C$6:$C$45,A44),IF(Assumptions!$C$8="1 Jan to 14 Jul 2026",SUMIFS(Tariffs!$E$6:$E$45,Tariffs!$B$6:$B$45,B44,Tariffs!$C$6:$C$45,A44),SUMIFS(Tariffs!$F$6:$F$45,Tariffs!$B$6:$B$45,B44,Tariffs!$C$6:$C$45,A44))) -> 0 | I44: =SUMIFS(Tariffs!$G$6:$G$45,Tariffs!$B$6:$B$45,B44,Tariffs!$C$6:$C$45,A44) -> 0.12 | J44: =G44*(1+H44) -> 39.362797 | K44: =G44*(1+I44) -> 44.086332 | L44: =IF(Assumptions!$C$9="Eligible preference",J44,K44) -> 39.362797 | M44: =Assumptions!B32 -> 0.25 | N44: =Assumptions!C32 -> 0 | O44: =IF(B44="China",-1,M44) -> 0.25 | P44: =IF(B44="China",D44,IF(M44>0,MAX(0,MIN(Assumptions!$C$10-D44,Assumptions!$C$11,IF(Assumptions!$F$14="Yes",(Assumptions!$C$14-1)*D44,1))/M44),1)) -> 0.32471115 | Q44: =$E54*O44 -> 0.017289975 | R44: =D44+Q44 -> 0.057878869 | S44: =D44*L44 -> 1.5976924 | T44: =R44*L44+MAX(0,Q44)*L44*N44 -> 2.2782742 | U44: =O44*L44+M44*L44*N44 -> 9.8406992 | V44: =D44^2 -> 0.0016474583 | W44: =2*D44*O44 -> 0.020294447 | X44: =O44^2 -> 0.0625 | Y44: =IF(Candidate_Gates!N44="Pass",MAX(0,Q44),0) -> 0 | Z44: =D44*J44 -> 1.5976924 | AA44: =O44*J44+M44*J44*N44 -> 9.8406992 | AB44: =D44*K44 -> 1.7894155 | AC44: =O44*K44+M44*K44*N44 -> 11.021583 | AD44: =IF(AND(C44>=0,F44>0,E44>0,ISNUMBER(G44),COUNTIFS(Trade_Periods!$B$6:$B$125,Assumptions!$C$6,Trade_Periods!$C$6:$C$125,B44,Trade_Periods!$D$6:$D$125,A44)=1,COUNTIFS(Tariffs!$B$6:$B$45,B44,Tariffs!$C$6:$C$45,A44)=1),"Ready","Missing data") -> Ready | AE44: =IF(D44>0,R44/D44,"n.a.") -> 1.425978 | AF44: =IF(M44>0,IF(D44>0,R44/D44,IF(R44=0,0,"n.a.")),0) -> 1.425978 | AG44: =IF(AND(Assumptions!$F$14="Yes",M44>0),MAX(0,R44-Assumptions!$C$14*D44),0) -> 0
A45: 62052000 | B45: Vietnam | C45: =SUMIFS(Trade_Periods!$F$6:$F$125,Trade_Periods!$B$6:$B$125,"FY2025",Trade_Periods!$C$6:$C$125,B45,Trade_Periods!$D$6:$D$125,A45) -> 440294 | D45: =C45/SUM(C36:C45) -> 0.05205513 | E45: =IF(Assumptions!$C$7="Reported",SUMIFS(Trade_Periods!$E$6:$E$125,Trade_Periods!$B$6:$B$125,Assumptions!$C$6,Trade_Periods!$C$6:$C$125,B45,Trade_Periods!$D$6:$D$125,A45),SUMIFS(Trade_Periods!$L$6:$L$125,Trade_Periods!$B$6:$B$125,Assumptions!$C$6,Trade_Periods!$C$6:$C$125,B45,Trade_Periods!$D$6:$D$125,A45)) -> 5885338 | F45: =IF(Assumptions!$C$7="Reported",SUMIFS(Trade_Periods!$F$6:$F$125,Trade_Periods!$B$6:$B$125,Assumptions!$C$6,Trade_Periods!$C$6:$C$125,B45,Trade_Periods!$D$6:$D$125,A45),SUMIFS(Trade_Periods!$M$6:$M$125,Trade_Periods!$B$6:$B$125,Assumptions!$C$6,Trade_Periods!$C$6:$C$125,B45,Trade_Periods!$D$6:$D$125,A45)) -> 196825 | G45: =IF(F45>0,E45/F45,"n.a.") -> 29.901374 | H45: =IF(Assumptions!$C$8="2025",SUMIFS(Tariffs!$D$6:$D$45,Tariffs!$B$6:$B$45,B45,Tariffs!$C$6:$C$45,A45),IF(Assumptions!$C$8="1 Jan to 14 Jul 2026",SUMIFS(Tariffs!$E$6:$E$45,Tariffs!$B$6:$B$45,B45,Tariffs!$C$6:$C$45,A45),SUMIFS(Tariffs!$F$6:$F$45,Tariffs!$B$6:$B$45,B45,Tariffs!$C$6:$C$45,A45))) -> 0 | I45: =SUMIFS(Tariffs!$G$6:$G$45,Tariffs!$B$6:$B$45,B45,Tariffs!$C$6:$C$45,A45) -> 0.12 | J45: =G45*(1+H45) -> 29.901374 | K45: =G45*(1+I45) -> 33.489539 | L45: =IF(Assumptions!$C$9="Eligible preference",J45,K45) -> 29.901374 | M45: =Assumptions!B33 -> 0.25 | N45: =Assumptions!C33 -> 0 | O45: =IF(B45="China",-1,M45) -> 0.25 | P45: =IF(B45="China",D45,IF(M45>0,MAX(0,MIN(Assumptions!$C$10-D45,Assumptions!$C$11,IF(Assumptions!$F$14="Yes",(Assumptions!$C$14-1)*D45,1))/M45),1)) -> 0.4 | Q45: =$E54*O45 -> 0.017289975 | R45: =D45+Q45 -> 0.069345105 | S45: =D45*L45 -> 1.5565199 | T45: =R45*L45+MAX(0,Q45)*L45*N45 -> 2.0735139 | U45: =O45*L45+M45*L45*N45 -> 7.4753436 | V45: =D45^2 -> 0.0027097365 | W45: =2*D45*O45 -> 0.026027565 | X45: =O45^2 -> 0.0625 | Y45: =IF(Candidate_Gates!N45="Pass",MAX(0,Q45),0) -> 0 | Z45: =D45*J45 -> 1.5565199 | AA45: =O45*J45+M45*J45*N45 -> 7.4753436 | AB45: =D45*K45 -> 1.7433023 | AC45: =O45*K45+M45*K45*N45 -> 8.3723848 | AD45: =IF(AND(C45>=0,F45>0,E45>0,ISNUMBER(G45),COUNTIFS(Trade_Periods!$B$6:$B$125,Assumptions!$C$6,Trade_Periods!$C$6:$C$125,B45,Trade_Periods!$D$6:$D$125,A45)=1,COUNTIFS(Tariffs!$B$6:$B$45,B45,Tariffs!$C$6:$C$45,A45)=1),"Ready","Missing data") -> Ready | AE45: =IF(D45>0,R45/D45,"n.a.") -> 1.3321474 | AF45: =IF(M45>0,IF(D45>0,R45/D45,IF(R45=0,0,"n.a.")),0) -> 1.3321474 | AG45: =IF(AND(Assumptions!$F$14="Yes",M45>0),MAX(0,R45-Assumptions!$C$14*D45),0) -> 0
A50: CN8 | B50: Base cost £/kg | C50: Shift cost £/kg | D50: Feasible shift | E50: Active shift | F50: Scenario £/kg | G50: Baseline HHI | H50: HHI linear | I50: HHI square | J50: Scenario HHI | K50: Eligible base | L50: Eligible shift | M50: MFN base | N50: MFN shift | O50: Release | P50: Input status
A51: 61091000 | B51: =SUM(S6:S15) -> 12.348136 | C51: =SUM(U6:U15) -> -0.32430549 | D51: =MIN(P6:P15) -> 0.032221227 | E51: =IF(P51="Ready",MIN(Assumptions!$C$12,D51),"n.a.") -> 0.032221227 | F51: =B51+E51*C51 -> 12.337687 | G51: =SUM(V6:V15) -> 0.38176838 | H51: =SUM(W6:W15) -> 0.078495229 | I51: =SUM(X6:X15) -> 1.375 | J51: =G51+E51*H51+E51^2*I51 -> 0.38572512 | K51: =SUM(Z6:Z15) -> 12.348136 | L51: =SUM(AA6:AA15) -> -0.32430549 | M51: =SUM(AB6:AB15) -> 13.756643 | N51: =SUM(AC6:AC15) -> 1.9107224 | O51: =IF(AND(P51="Ready",E51>0,ABS(SUM(Y6:Y15)-E51)<0.000000001),"Evidence recorded","Hold") -> Hold | P51: =IF(AND(Assumptions!$C$13="Valid",COUNTIF(AD6:AD15,"Ready")=10),"Ready","Invalid inputs") -> Ready
A52: 61103099 | B52: =SUM(S16:S25) -> 13.87787 | C52: =SUM(U16:U25) -> -4.5369603 | D52: =MIN(P16:P25) -> 0.014153298 | E52: =IF(P52="Ready",MIN(Assumptions!$C$12,D52),"n.a.") -> 0.014153298 | F52: =B52+E52*C52 -> 13.813657 | G52: =SUM(V16:V25) -> 0.26747899 | H52: =SUM(W16:W25) -> -0.64258925 | I52: =SUM(X16:X25) -> 1.375 | J52: =G52+E52*H52+E52^2*I52 -> 0.25865966 | K52: =SUM(Z16:Z25) -> 13.87787 | L52: =SUM(AA16:AA25) -> -4.5369603 | M52: =SUM(AB16:AB25) -> 14.703553 | N52: =SUM(AC16:AC25) -> -2.78807 | O52: =IF(AND(P52="Ready",E52>0,ABS(SUM(Y16:Y25)-E52)<0.000000001),"Evidence recorded","Hold") -> Hold | P52: =IF(AND(Assumptions!$C$13="Valid",COUNTIF(AD16:AD25,"Ready")=10),"Ready","Invalid inputs") -> Ready
A53: 62044300 | B53: =SUM(S26:S35) -> 27.522648 | C53: =SUM(U26:U35) -> -1.3510197 | D53: =MIN(P26:P35) -> 0.2 | E53: =IF(P53="Ready",MIN(Assumptions!$C$12,D53),"n.a.") -> 0.1 | F53: =B53+E53*C53 -> 27.387546 | G53: =SUM(V26:V35) -> 0.27751606 | H53: =SUM(W26:W35) -> -0.77330165 | I53: =SUM(X26:X35) -> 1.375 | J53: =G53+E53*H53+E53^2*I53 -> 0.21393589 | K53: =SUM(Z26:Z35) -> 27.522648 | L53: =SUM(AA26:AA35) -> -1.3510197 | M53: =SUM(AB26:AB35) -> 29.0298 | N53: =SUM(AC26:AC35) -> 2.1041631 | O53: =IF(AND(P53="Ready",E53>0,ABS(SUM(Y26:Y35)-E53)<0.000000001),"Evidence recorded","Hold") -> Hold | P53: =IF(AND(Assumptions!$C$13="Valid",COUNTIF(AD26:AD35,"Ready")=10),"Ready","Invalid inputs") -> Ready
A54: 62052000 | B54: =SUM(S36:S45) -> 20.453083 | C54: =SUM(U36:U45) -> 3.977327 | D54: =MIN(P36:P45) -> 0.069159901 | E54: =IF(P54="Ready",MIN(Assumptions!$C$12,D54),"n.a.") -> 0.069159901 | F54: =B54+E54*C54 -> 20.728155 | G54: =SUM(V36:V45) -> 0.34394381 | H54: =SUM(W36:W45) -> 0.075193318 | I54: =SUM(X36:X45) -> 1.375 | J54: =G54+E54*H54+E54^2*I54 -> 0.35572092 | K54: =SUM(Z36:Z45) -> 20.453083 | L54: =SUM(AA36:AA45) -> 3.977327 | M54: =SUM(AB36:AB45) -> 22.705887 | N54: =SUM(AC36:AC45) -> 7.3690956 | O54: =IF(AND(P54="Ready",E54>0,ABS(SUM(Y36:Y45)-E54)<0.000000001),"Evidence recorded","Hold") -> Hold | P54: =IF(AND(Assumptions!$C$13="Valid",COUNTIF(AD36:AD45,"Ready")=10),"Ready","Invalid inputs") -> Ready
A56: Shares are fractions of fixed product-level volume. Cost is linear in the transfer; HHI is quadratic. The comparison below evaluates the same unit-shift costs and limits for all three requested sizes.
A59: Scenario | B59: CN8 | C59: Requested shift | D59: Feasible shift | E59: Applied shift | F59: Eligible cost change | G59: MFN cost change | H59: Active cost change | I59: Scenario HHI | J59: HHI change (points) | K59: Shift status | L59: Eligible index | M59: MFN index | N59: Release
A60: Cautious | B60: 61091000 | C60: =IF(Assumptions!B17="","n.a.",Assumptions!B17) -> 0.05 | D60: =D51 -> 0.032221227 | E60: =IF(AND(P51="Ready",ISNUMBER(C60),C60>=0,C60<=1),MIN(C60,D60),"n.a.") -> 0.032221227 | F60: =E60*L51/K51 -> -0.00084624275 | G60: =E60*N51/M51 -> 0.0044753518 | H60: =E60*C51/B51 -> -0.00084624275 | I60: =G51+E60*H51+E60^2*I51 -> 0.38572512 | J60: =(I60-G51)*10000 -> 39.567478 | K60: =IF(E60<C60-0.000000001,"Capped","Full shift") -> Capped | L60: =100*(1+F60) -> 99.915376 | M60: =100*(1+G60) -> 100.44754 | N60: =IF(AND(E60>0,ABS(SUMIFS($M$6:$M$15,Candidate_Gates!$N$6:$N$15,"Pass")-1)<0.000000001),"Evidence recorded","Hold") -> Hold
A61: Cautious | B61: 61103099 | C61: =IF(Assumptions!B17="","n.a.",Assumptions!B17) -> 0.05 | D61: =D52 -> 0.014153298 | E61: =IF(AND(P52="Ready",ISNUMBER(C61),C61>=0,C61<=1),MIN(C61,D61),"n.a.") -> 0.014153298 | F61: =E61*L52/K52 -> -0.0046270035 | G61: =E61*N52/M52 -> -0.0026837315 | H61: =E61*C52/B52 -> -0.0046270035 | I61: =G52+E61*H52+E61^2*I52 -> 0.25865966 | J61: =(I61-G52)*10000 -> -88.19323 | K61: =IF(E61<C61-0.000000001,"Capped","Full shift") -> Capped | L61: =100*(1+F61) -> 99.5373 | M61: =100*(1+G61) -> 99.731627 | N61: =IF(AND(E61>0,ABS(SUMIFS($M$16:$M$25,Candidate_Gates!$N$16:$N$25,"Pass")-1)<0.000000001),"Evidence recorded","Hold") -> Hold
A62: Cautious | B62: 62044300 | C62: =IF(Assumptions!B17="","n.a.",Assumptions!B17) -> 0.05 | D62: =D53 -> 0.2 | E62: =IF(AND(P53="Ready",ISNUMBER(C62),C62>=0,C62<=1),MIN(C62,D62),"n.a.") -> 0.05 | F62: =E62*L53/K53 -> -0.002454378 | G62: =E62*N53/M53 -> 0.0036241433 | H62: =E62*C53/B53 -> -0.002454378 | I62: =G53+E62*H53+E62^2*I53 -> 0.24228848 | J62: =(I62-G53)*10000 -> -352.27583 | K62: =IF(E62<C62-0.000000001,"Capped","Full shift") -> Full shift | L62: =100*(1+F62) -> 99.754562 | M62: =100*(1+G62) -> 100.36241 | N62: =IF(AND(E62>0,ABS(SUMIFS($M$26:$M$35,Candidate_Gates!$N$26:$N$35,"Pass")-1)<0.000000001),"Evidence recorded","Hold") -> Hold
A63: Cautious | B63: 62052000 | C63: =IF(Assumptions!B17="","n.a.",Assumptions!B17) -> 0.05 | D63: =D54 -> 0.069159901 | E63: =IF(AND(P54="Ready",ISNUMBER(C63),C63>=0,C63<=1),MIN(C63,D63),"n.a.") -> 0.05 | F63: =E63*L54/K54 -> 0.0097230501 | G63: =E63*N54/M54 -> 0.016227279 | H63: =E63*C54/B54 -> 0.0097230501 | I63: =G54+E63*H54+E63^2*I54 -> 0.35114097 | J63: =(I63-G54)*10000 -> 71.971659 | K63: =IF(E63<C63-0.000000001,"Capped","Full shift") -> Full shift | L63: =100*(1+F63) -> 100.97231 | M63: =100*(1+G63) -> 101.62273 | N63: =IF(AND(E63>0,ABS(SUMIFS($M$36:$M$45,Candidate_Gates!$N$36:$N$45,"Pass")-1)<0.000000001),"Evidence recorded","Hold") -> Hold
A64: Balanced | B64: 61091000 | C64: =IF(Assumptions!B18="","n.a.",Assumptions!B18) -> 0.1 | D64: =D51 -> 0.032221227 | E64: =IF(AND(P51="Ready",ISNUMBER(C64),C64>=0,C64<=1),MIN(C64,D64),"n.a.") -> 0.032221227 | F64: =E64*L51/K51 -> -0.00084624275 | G64: =E64*N51/M51 -> 0.0044753518 | H64: =E64*C51/B51 -> -0.00084624275 | I64: =G51+E64*H51+E64^2*I51 -> 0.38572512 | J64: =(I64-G51)*10000 -> 39.567478 | K64: =IF(E64<C64-0.000000001,"Capped","Full shift") -> Capped | L64: =100*(1+F64) -> 99.915376 | M64: =100*(1+G64) -> 100.44754 | N64: =IF(AND(E64>0,ABS(SUMIFS($M$6:$M$15,Candidate_Gates!$N$6:$N$15,"Pass")-1)<0.000000001),"Evidence recorded","Hold") -> Hold
A65: Balanced | B65: 61103099 | C65: =IF(Assumptions!B18="","n.a.",Assumptions!B18) -> 0.1 | D65: =D52 -> 0.014153298 | E65: =IF(AND(P52="Ready",ISNUMBER(C65),C65>=0,C65<=1),MIN(C65,D65),"n.a.") -> 0.014153298 | F65: =E65*L52/K52 -> -0.0046270035 | G65: =E65*N52/M52 -> -0.0026837315 | H65: =E65*C52/B52 -> -0.0046270035 | I65: =G52+E65*H52+E65^2*I52 -> 0.25865966 | J65: =(I65-G52)*10000 -> -88.19323 | K65: =IF(E65<C65-0.000000001,"Capped","Full shift") -> Capped | L65: =100*(1+F65) -> 99.5373 | M65: =100*(1+G65) -> 99.731627 | N65: =IF(AND(E65>0,ABS(SUMIFS($M$16:$M$25,Candidate_Gates!$N$16:$N$25,"Pass")-1)<0.000000001),"Evidence recorded","Hold") -> Hold
A66: Balanced | B66: 62044300 | C66: =IF(Assumptions!B18="","n.a.",Assumptions!B18) -> 0.1 | D66: =D53 -> 0.2 | E66: =IF(AND(P53="Ready",ISNUMBER(C66),C66>=0,C66<=1),MIN(C66,D66),"n.a.") -> 0.1 | F66: =E66*L53/K53 -> -0.0049087561 | G66: =E66*N53/M53 -> 0.0072482866 | H66: =E66*C53/B53 -> -0.0049087561 | I66: =G53+E66*H53+E66^2*I53 -> 0.21393589 | J66: =(I66-G53)*10000 -> -635.80165 | K66: =IF(E66<C66-0.000000001,"Capped","Full shift") -> Full shift | L66: =100*(1+F66) -> 99.509124 | M66: =100*(1+G66) -> 100.72483 | N66: =IF(AND(E66>0,ABS(SUMIFS($M$26:$M$35,Candidate_Gates!$N$26:$N$35,"Pass")-1)<0.000000001),"Evidence recorded","Hold") -> Hold
A67: Balanced | B67: 62052000 | C67: =IF(Assumptions!B18="","n.a.",Assumptions!B18) -> 0.1 | D67: =D54 -> 0.069159901 | E67: =IF(AND(P54="Ready",ISNUMBER(C67),C67>=0,C67<=1),MIN(C67,D67),"n.a.") -> 0.069159901 | F67: =E67*L54/K54 -> 0.013448904 | G67: =E67*N54/M54 -> 0.022445541 | H67: =E67*C54/B54 -> 0.013448904 | I67: =G54+E67*H54+E67^2*I54 -> 0.35572092 | J67: =(I67-G54)*10000 -> 117.77114 | K67: =IF(E67<C67-0.000000001,"Capped","Full shift") -> Capped | L67: =100*(1+F67) -> 101.34489 | M67: =100*(1+G67) -> 102.24455 | N67: =IF(AND(E67>0,ABS(SUMIFS($M$36:$M$45,Candidate_Gates!$N$36:$N$45,"Pass")-1)<0.000000001),"Evidence recorded","Hold") -> Hold
A68: Accelerated | B68: 61091000 | C68: =IF(Assumptions!B19="","n.a.",Assumptions!B19) -> 0.15 | D68: =D51 -> 0.032221227 | E68: =IF(AND(P51="Ready",ISNUMBER(C68),C68>=0,C68<=1),MIN(C68,D68),"n.a.") -> 0.032221227 | F68: =E68*L51/K51 -> -0.00084624275 | G68: =E68*N51/M51 -> 0.0044753518 | H68: =E68*C51/B51 -> -0.00084624275 | I68: =G51+E68*H51+E68^2*I51 -> 0.38572512 | J68: =(I68-G51)*10000 -> 39.567478 | K68: =IF(E68<C68-0.000000001,"Capped","Full shift") -> Capped | L68: =100*(1+F68) -> 99.915376 | M68: =100*(1+G68) -> 100.44754 | N68: =IF(AND(E68>0,ABS(SUMIFS($M$6:$M$15,Candidate_Gates!$N$6:$N$15,"Pass")-1)<0.000000001),"Evidence recorded","Hold") -> Hold
A69: Accelerated | B69: 61103099 | C69: =IF(Assumptions!B19="","n.a.",Assumptions!B19) -> 0.15 | D69: =D52 -> 0.014153298 | E69: =IF(AND(P52="Ready",ISNUMBER(C69),C69>=0,C69<=1),MIN(C69,D69),"n.a.") -> 0.014153298 | F69: =E69*L52/K52 -> -0.0046270035 | G69: =E69*N52/M52 -> -0.0026837315 | H69: =E69*C52/B52 -> -0.0046270035 | I69: =G52+E69*H52+E69^2*I52 -> 0.25865966 | J69: =(I69-G52)*10000 -> -88.19323 | K69: =IF(E69<C69-0.000000001,"Capped","Full shift") -> Capped | L69: =100*(1+F69) -> 99.5373 | M69: =100*(1+G69) -> 99.731627 | N69: =IF(AND(E69>0,ABS(SUMIFS($M$16:$M$25,Candidate_Gates!$N$16:$N$25,"Pass")-1)<0.000000001),"Evidence recorded","Hold") -> Hold
A70: Accelerated | B70: 62044300 | C70: =IF(Assumptions!B19="","n.a.",Assumptions!B19) -> 0.15 | D70: =D53 -> 0.2 | E70: =IF(AND(P53="Ready",ISNUMBER(C70),C70>=0,C70<=1),MIN(C70,D70),"n.a.") -> 0.15 | F70: =E70*L53/K53 -> -0.0073631341 | G70: =E70*N53/M53 -> 0.01087243 | H70: =E70*C53/B53 -> -0.0073631341 | I70: =G53+E70*H53+E70^2*I53 -> 0.19245831 | J70: =(I70-G53)*10000 -> -850.57748 | K70: =IF(E70<C70-0.000000001,"Capped","Full shift") -> Full shift | L70: =100*(1+F70) -> 99.263687 | M70: =100*(1+G70) -> 101.08724 | N70: =IF(AND(E70>0,ABS(SUMIFS($M$26:$M$35,Candidate_Gates!$N$26:$N$35,"Pass")-1)<0.000000001),"Evidence recorded","Hold") -> Hold
A71: Accelerated | B71: 62052000 | C71: =IF(Assumptions!B19="","n.a.",Assumptions!B19) -> 0.15 | D71: =D54 -> 0.069159901 | E71: =IF(AND(P54="Ready",ISNUMBER(C71),C71>=0,C71<=1),MIN(C71,D71),"n.a.") -> 0.069159901 | F71: =E71*L54/K54 -> 0.013448904 | G71: =E71*N54/M54 -> 0.022445541 | H71: =E71*C54/B54 -> 0.013448904 | I71: =G54+E71*H54+E71^2*I54 -> 0.35572092 | J71: =(I71-G54)*10000 -> 117.77114 | K71: =IF(E71<C71-0.000000001,"Capped","Full shift") -> Capped | L71: =100*(1+F71) -> 101.34489 | M71: =100*(1+G71) -> 102.24455 | N71: =IF(AND(E71>0,ABS(SUMIFS($M$36:$M$45,Candidate_Gates!$N$36:$N$45,"Pass")-1)<0.000000001),"Evidence recorded","Hold") -> Hold
A74: Cost scope: observed border unit value × (1 + tariff), plus any explicit premium on incremental volume. International freight is already inside HMRC border value. VAT, inland delivery, lead time, working capital, FX and transition costs are not estimated.
A75: Prices may differ because of quality and product mix within a CN8 code. A lower index is a benchmark result, not an achievable supplier saving. Candidate capability, origin and RS01–RS08 require separate evidence.

Sheet Candidate_Gates
A2: Candidate evidence and release controls
A4: Country/CN8 placeholders await identified sites and dated evidence. WP007 is the policy basis. No public-evidence candidate is cleared for new allocation.
A5: CN8 | B5: Country | C5: Site ID | D5: Origin evidence | E5: CN8 capability | F5: RS01 | G5: RS02 | H5: RS03 | I5: RS04 | J5: RS05 | K5: RS06 | L5: RS07 | M5: RS08 | N5: Overall | O5: Release | P5: Evidence reference | Q5: Decision date
A6: 61091000 | B6: Bangladesh | D6: Pending | E6: Pending | F6: Pending | G6: Pending | H6: Pending | I6: Pending | J6: Pending | K6: Pending | L6: Pending | M6: Pending | N6: =IF(B6="Myanmar","Excluded",IF(COUNTIF(D6:M6,"Fail")>0,"Fail",IF(OR(C6="",P6="",NOT(ISNUMBER(Q6)),COUNTIF(D6:M6,"Pending")>0,COUNTBLANK(D6:M6)>0),"Pending",IF(COUNTIF(D6:M6,"Conditional")>0,"Conditional",IF(COUNTIF(D6:M6,"Pass")=10,"Pass","Pending"))))) -> Pending | O6: =IF(N6="Pass","Evidence recorded","Hold") -> Hold
A7: 61091000 | B7: Cambodia | D7: Pending | E7: Pending | F7: Pending | G7: Pending | H7: Pending | I7: Pending | J7: Pending | K7: Pending | L7: Pending | M7: Pending | N7: =IF(B7="Myanmar","Excluded",IF(COUNTIF(D7:M7,"Fail")>0,"Fail",IF(OR(C7="",P7="",NOT(ISNUMBER(Q7)),COUNTIF(D7:M7,"Pending")>0,COUNTBLANK(D7:M7)>0),"Pending",IF(COUNTIF(D7:M7,"Conditional")>0,"Conditional",IF(COUNTIF(D7:M7,"Pass")=10,"Pass","Pending"))))) -> Pending | O7: =IF(N7="Pass","Evidence recorded","Hold") -> Hold
A8: 61091000 | B8: China | D8: Pending | E8: Pending | F8: Pending | G8: Pending | H8: Pending | I8: Pending | J8: Pending | K8: Pending | L8: Pending | M8: Pending | N8: =IF(B8="Myanmar","Excluded",IF(COUNTIF(D8:M8,"Fail")>0,"Fail",IF(OR(C8="",P8="",NOT(ISNUMBER(Q8)),COUNTIF(D8:M8,"Pending")>0,COUNTBLANK(D8:M8)>0),"Pending",IF(COUNTIF(D8:M8,"Conditional")>0,"Conditional",IF(COUNTIF(D8:M8,"Pass")=10,"Pass","Pending"))))) -> Pending | O8: =IF(N8="Pass","Evidence recorded","Hold") -> Hold
A9: 61091000 | B9: India | D9: Pending | E9: Pending | F9: Pending | G9: Pending | H9: Pending | I9: Pending | J9: Pending | K9: Pending | L9: Pending | M9: Pending | N9: =IF(B9="Myanmar","Excluded",IF(COUNTIF(D9:M9,"Fail")>0,"Fail",IF(OR(C9="",P9="",NOT(ISNUMBER(Q9)),COUNTIF(D9:M9,"Pending")>0,COUNTBLANK(D9:M9)>0),"Pending",IF(COUNTIF(D9:M9,"Conditional")>0,"Conditional",IF(COUNTIF(D9:M9,"Pass")=10,"Pass","Pending"))))) -> Pending | O9: =IF(N9="Pass","Evidence recorded","Hold") -> Hold
A10: 61091000 | B10: Morocco | D10: Pending | E10: Pending | F10: Pending | G10: Pending | H10: Pending | I10: Pending | J10: Pending | K10: Pending | L10: Pending | M10: Pending | N10: =IF(B10="Myanmar","Excluded",IF(COUNTIF(D10:M10,"Fail")>0,"Fail",IF(OR(C10="",P10="",NOT(ISNUMBER(Q10)),COUNTIF(D10:M10,"Pending")>0,COUNTBLANK(D10:M10)>0),"Pending",IF(COUNTIF(D10:M10,"Conditional")>0,"Conditional",IF(COUNTIF(D10:M10,"Pass")=10,"Pass","Pending"))))) -> Pending | O10: =IF(N10="Pass","Evidence recorded","Hold") -> Hold
A11: 61091000 | B11: Myanmar | D11: Pending | E11: Pending | F11: Pending | G11: Pending | H11: Pending | I11: Pending | J11: Pending | K11: Pending | L11: Pending | M11: Pending | N11: =IF(B11="Myanmar","Excluded",IF(COUNTIF(D11:M11,"Fail")>0,"Fail",IF(OR(C11="",P11="",NOT(ISNUMBER(Q11)),COUNTIF(D11:M11,"Pending")>0,COUNTBLANK(D11:M11)>0),"Pending",IF(COUNTIF(D11:M11,"Conditional")>0,"Conditional",IF(COUNTIF(D11:M11,"Pass")=10,"Pass","Pending"))))) -> Excluded | O11: =IF(N11="Pass","Evidence recorded","Hold") -> Hold
A12: 61091000 | B12: Pakistan | D12: Pending | E12: Pending | F12: Pending | G12: Pending | H12: Pending | I12: Pending | J12: Pending | K12: Pending | L12: Pending | M12: Pending | N12: =IF(B12="Myanmar","Excluded",IF(COUNTIF(D12:M12,"Fail")>0,"Fail",IF(OR(C12="",P12="",NOT(ISNUMBER(Q12)),COUNTIF(D12:M12,"Pending")>0,COUNTBLANK(D12:M12)>0),"Pending",IF(COUNTIF(D12:M12,"Conditional")>0,"Conditional",IF(COUNTIF(D12:M12,"Pass")=10,"Pass","Pending"))))) -> Pending | O12: =IF(N12="Pass","Evidence recorded","Hold") -> Hold
A13: 61091000 | B13: Sri Lanka | D13: Pending | E13: Pending | F13: Pending | G13: Pending | H13: Pending | I13: Pending | J13: Pending | K13: Pending | L13: Pending | M13: Pending | N13: =IF(B13="Myanmar","Excluded",IF(COUNTIF(D13:M13,"Fail")>0,"Fail",IF(OR(C13="",P13="",NOT(ISNUMBER(Q13)),COUNTIF(D13:M13,"Pending")>0,COUNTBLANK(D13:M13)>0),"Pending",IF(COUNTIF(D13:M13,"Conditional")>0,"Conditional",IF(COUNTIF(D13:M13,"Pass")=10,"Pass","Pending"))))) -> Pending | O13: =IF(N13="Pass","Evidence recorded","Hold") -> Hold
A14: 61091000 | B14: Turkey | D14: Pending | E14: Pending | F14: Pending | G14: Pending | H14: Pending | I14: Pending | J14: Pending | K14: Pending | L14: Pending | M14: Pending | N14: =IF(B14="Myanmar","Excluded",IF(COUNTIF(D14:M14,"Fail")>0,"Fail",IF(OR(C14="",P14="",NOT(ISNUMBER(Q14)),COUNTIF(D14:M14,"Pending")>0,COUNTBLANK(D14:M14)>0),"Pending",IF(COUNTIF(D14:M14,"Conditional")>0,"Conditional",IF(COUNTIF(D14:M14,"Pass")=10,"Pass","Pending"))))) -> Pending | O14: =IF(N14="Pass","Evidence recorded","Hold") -> Hold
A15: 61091000 | B15: Vietnam | D15: Pending | E15: Pending | F15: Pending | G15: Pending | H15: Pending | I15: Pending | J15: Pending | K15: Pending | L15: Pending | M15: Pending | N15: =IF(B15="Myanmar","Excluded",IF(COUNTIF(D15:M15,"Fail")>0,"Fail",IF(OR(C15="",P15="",NOT(ISNUMBER(Q15)),COUNTIF(D15:M15,"Pending")>0,COUNTBLANK(D15:M15)>0),"Pending",IF(COUNTIF(D15:M15,"Conditional")>0,"Conditional",IF(COUNTIF(D15:M15,"Pass")=10,"Pass","Pending"))))) -> Pending | O15: =IF(N15="Pass","Evidence recorded","Hold") -> Hold
A16: 61103099 | B16: Bangladesh | D16: Pending | E16: Pending | F16: Pending | G16: Pending | H16: Pending | I16: Pending | J16: Pending | K16: Pending | L16: Pending | M16: Pending | N16: =IF(B16="Myanmar","Excluded",IF(COUNTIF(D16:M16,"Fail")>0,"Fail",IF(OR(C16="",P16="",NOT(ISNUMBER(Q16)),COUNTIF(D16:M16,"Pending")>0,COUNTBLANK(D16:M16)>0),"Pending",IF(COUNTIF(D16:M16,"Conditional")>0,"Conditional",IF(COUNTIF(D16:M16,"Pass")=10,"Pass","Pending"))))) -> Pending | O16: =IF(N16="Pass","Evidence recorded","Hold") -> Hold
A17: 61103099 | B17: Cambodia | D17: Pending | E17: Pending | F17: Pending | G17: Pending | H17: Pending | I17: Pending | J17: Pending | K17: Pending | L17: Pending | M17: Pending | N17: =IF(B17="Myanmar","Excluded",IF(COUNTIF(D17:M17,"Fail")>0,"Fail",IF(OR(C17="",P17="",NOT(ISNUMBER(Q17)),COUNTIF(D17:M17,"Pending")>0,COUNTBLANK(D17:M17)>0),"Pending",IF(COUNTIF(D17:M17,"Conditional")>0,"Conditional",IF(COUNTIF(D17:M17,"Pass")=10,"Pass","Pending"))))) -> Pending | O17: =IF(N17="Pass","Evidence recorded","Hold") -> Hold
... A45: 62052000 | B45: Vietnam | D45: Pending | E45: Pending | F45: Pending | G45: Pending | H45: Pending | I45: Pending | J45: Pending | K45: Pending | L45: Pending | M45: Pending | N45: =IF(B45="Myanmar","Excluded",IF(COUNTIF(D45:M45,"Fail")>0,"Fail",IF(OR(C45="",P45="",NOT(ISNUMBER(Q45)),COUNTIF(D45:M45,"Pending")>0,COUNTBLANK(D45:M45)>0),"Pending",IF(COUNTIF(D45:M45,"Conditional")>0,"Conditional",IF(COUNTIF(D45:M45,"Pass")=10,"Pass","Pending"))))) -> Pending | O45: =IF(N45="Pass","Evidence recorded","Hold") -> Hold
A47: Source: NEXT_WP007_Responsible_Sourcing_Gates_v1.0.xlsx, Gate_Matrix RS01-RS08; decisions D008/D020 in docs/Research_Question_and_Scope.md. Myanmar cannot be released by changing a gate cell.
A48: RS01 approval; RS02 audit; RS03 forced/child labour and recruitment; RS04 working conditions; RS05 worker voice; RS06 material traceability; RS07 remediation/integrity; RS08 enhanced due diligence.
A49: RS03–RS08 remain unassessable from published annotations. Populate gates only against named site/product evidence and a recorded decision. Pass requires all ten evidence checks, a Site ID, evidence reference and decision date.
A50: A full scenario remains on hold until every receiving candidate passes. A pass for one receiver does not release a partial reallocation. SC remains undefined; the 16 historical annotation reviews remain Pending.

Sheet Trade_Periods
A2: Period benchmarks and common-month sensitivity
A4: Reported fields: WP006 partner_trade_period_reported export. Common-month sums: Monthly_Data, identical months across ten partners and World for each product/period.
A5: Join key | B5: Period | C5: Country | D5: CN8 | E5: Reported value (£) | F5: Reported mass (kg) | G5: Months | H5: Review months | I5: Export unit value (£/kg) | J5: Start month | K5: End month | L5: Common value (£) | M5: Common mass (kg) | N5: Common months | O5: Common UV (£/kg) | P5: Export UV difference | Q5: Key occurrences | R5: Absolute UV difference
A6: FY2025|Bangladesh|61091000 | B6: FY2025 | C6: Bangladesh | D6: 61091000 | E6: 455361217 | F6: 44227971 | G6: 12 | H6: 0 | I6: 10.295775 | J6: 202501 | K6: 202512 | L6: =SUMIFS(Monthly_Data!$E$6:$E$797,Monthly_Data!$B$6:$B$797,">="&J6,Monthly_Data!$B$6:$B$797,"<="&K6,Monthly_Data!$C$6:$C$797,D6,Monthly_Data!$D$6:$D$797,C6,Monthly_Data!$I$6:$I$797,1) -> 279600730 | M6: =SUMIFS(Monthly_Data!$F$6:$F$797,Monthly_Data!$B$6:$B$797,">="&J6,Monthly_Data!$B$6:$B$797,"<="&K6,Monthly_Data!$C$6:$C$797,D6,Monthly_Data!$D$6:$D$797,C6,Monthly_Data!$I$6:$I$797,1) -> 27161127 | N6: =COUNTIFS(Monthly_Data!$B$6:$B$797,">="&J6,Monthly_Data!$B$6:$B$797,"<="&K6,Monthly_Data!$C$6:$C$797,D6,Monthly_Data!$D$6:$D$797,C6,Monthly_Data!$I$6:$I$797,1) -> 8 | O6: =IF(M6>0,L6/M6,"n.a.") -> 10.294151 | P6: =IF(F6>0,E6/F6-I6,"n.a.") -> 0 | Q6: =COUNTIF($A$6:$A$125,A6) -> 1 | R6: =ABS(P6) -> 0
A7: FY2025|Cambodia|61091000 | B7: FY2025 | C7: Cambodia | D7: 61091000 | E7: 10485143 | F7: 547756 | G7: 12 | H7: 0 | I7: 19.141996 | J7: 202501 | K7: 202512 | L7: =SUMIFS(Monthly_Data!$E$6:$E$797,Monthly_Data!$B$6:$B$797,">="&J7,Monthly_Data!$B$6:$B$797,"<="&K7,Monthly_Data!$C$6:$C$797,D7,Monthly_Data!$D$6:$D$797,C7,Monthly_Data!$I$6:$I$797,1) -> 7039886 | M7: =SUMIFS(Monthly_Data!$F$6:$F$797,Monthly_Data!$B$6:$B$797,">="&J7,Monthly_Data!$B$6:$B$797,"<="&K7,Monthly_Data!$C$6:$C$797,D7,Monthly_Data!$D$6:$D$797,C7,Monthly_Data!$I$6:$I$797,1) -> 377183 | N7: =COUNTIFS(Monthly_Data!$B$6:$B$797,">="&J7,Monthly_Data!$B$6:$B$797,"<="&K7,Monthly_Data!$C$6:$C$797,D7,Monthly_Data!$D$6:$D$797,C7,Monthly_Data!$I$6:$I$797,1) -> 8 | O7: =IF(M7>0,L7/M7,"n.a.") -> 18.664378 | P7: =IF(F7>0,E7/F7-I7,"n.a.") -> 0 | Q7: =COUNTIF($A$6:$A$125,A7) -> 1 | R7: =ABS(P7) -> 0
A8: FY2025|China|61091000 | B8: FY2025 | C8: China | D8: 61091000 | E8: 44790747 | F8: 2430960 | G8: 12 | H8: 0 | I8: 18.425127 | J8: 202501 | K8: 202512 | L8: =SUMIFS(Monthly_Data!$E$6:$E$797,Monthly_Data!$B$6:$B$797,">="&J8,Monthly_Data!$B$6:$B$797,"<="&K8,Monthly_Data!$C$6:$C$797,D8,Monthly_Data!$D$6:$D$797,C8,Monthly_Data!$I$6:$I$797,1) -> 29921795 | M8: =SUMIFS(Monthly_Data!$F$6:$F$797,Monthly_Data!$B$6:$B$797,">="&J8,Monthly_Data!$B$6:$B$797,"<="&K8,Monthly_Data!$C$6:$C$797,D8,Monthly_Data!$D$6:$D$797,C8,Monthly_Data!$I$6:$I$797,1) -> 1676887 | N8: =COUNTIFS(Monthly_Data!$B$6:$B$797,">="&J8,Monthly_Data!$B$6:$B$797,"<="&K8,Monthly_Data!$C$6:$C$797,D8,Monthly_Data!$D$6:$D$797,C8,Monthly_Data!$I$6:$I$797,1) -> 8 | O8: =IF(M8>0,L8/M8,"n.a.") -> 17.843656 | P8: =IF(F8>0,E8/F8-I8,"n.a.") -> 0 | Q8: =COUNTIF($A$6:$A$125,A8) -> 1 | R8: =ABS(P8) -> 0
A9: FY2025|India|61091000 | B9: FY2025 | C9: India | D9: 61091000 | E9: 100902224 | F9: 7735285 | G9: 12 | H9: 0 | I9: 13.044409 | J9: 202501 | K9: 202512 | L9: =SUMIFS(Monthly_Data!$E$6:$E$797,Monthly_Data!$B$6:$B$797,">="&J9,Monthly_Data!$B$6:$B$797,"<="&K9,Monthly_Data!$C$6:$C$797,D9,Monthly_Data!$D$6:$D$797,C9,Monthly_Data!$I$6:$I$797,1) -> 58584726 | M9: =SUMIFS(Monthly_Data!$F$6:$F$797,Monthly_Data!$B$6:$B$797,">="&J9,Monthly_Data!$B$6:$B$797,"<="&K9,Monthly_Data!$C$6:$C$797,D9,Monthly_Data!$D$6:$D$797,C9,Monthly_Data!$I$6:$I$797,1) -> 4442271 | N9: =COUNTIFS(Monthly_Data!$B$6:$B$797,">="&J9,Monthly_Data!$B$6:$B$797,"<="&K9,Monthly_Data!$C$6:$C$797,D9,Monthly_Data!$D$6:$D$797,C9,Monthly_Data!$I$6:$I$797,1) -> 8 | O9: =IF(M9>0,L9/M9,"n.a.") -> 13.188013 | P9: =IF(F9>0,E9/F9-I9,"n.a.") -> 0 | Q9: =COUNTIF($A$6:$A$125,A9) -> 1 | R9: =ABS(P9) -> 0
A10: FY2025|Morocco|61091000 | B10: FY2025 | C10: Morocco | D10: 61091000 | E10: 11996927 | F10: 1265062 | G10: 12 | H10: 1 | I10: 9.483272 | J10: 202501 | K10: 202512 | L10: =SUMIFS(Monthly_Data!$E$6:$E$797,Monthly_Data!$B$6:$B$797,">="&J10,Monthly_Data!$B$6:$B$797,"<="&K10,Monthly_Data!$C$6:$C$797,D10,Monthly_Data!$D$6:$D$797,C10,Monthly_Data!$I$6:$I$797,1) -> 7506840 | M10: =SUMIFS(Monthly_Data!$F$6:$F$797,Monthly_Data!$B$6:$B$797,">="&J10,Monthly_Data!$B$6:$B$797,"<="&K10,Monthly_Data!$C$6:$C$797,D10,Monthly_Data!$D$6:$D$797,C10,Monthly_Data!$I$6:$I$797,1) -> 801681 | N10: =COUNTIFS(Monthly_Data!$B$6:$B$797,">="&J10,Monthly_Data!$B$6:$B$797,"<="&K10,Monthly_Data!$C$6:$C$797,D10,Monthly_Data!$D$6:$D$797,C10,Monthly_Data!$I$6:$I$797,1) -> 8 | O10: =IF(M10>0,L10/M10,"n.a.") -> 9.3638742 | P10: =IF(F10>0,E10/F10-I10,"n.a.") -> 0 | Q10: =COUNTIF($A$6:$A$125,A10) -> 1 | R10: =ABS(P10) -> 0
A11: FY2025|Myanmar|61091000 | B11: FY2025 | C11: Myanmar | D11: 61091000 | E11: 377935 | F11: 29326 | G11: 12 | H11: 0 | I11: 12.88737 | J11: 202501 | K11: 202512 | L11: =SUMIFS(Monthly_Data!$E$6:$E$797,Monthly_Data!$B$6:$B$797,">="&J11,Monthly_Data!$B$6:$B$797,"<="&K11,Monthly_Data!$C$6:$C$797,D11,Monthly_Data!$D$6:$D$797,C11,Monthly_Data!$I$6:$I$797,1) -> 254441 | M11: =SUMIFS(Monthly_Data!$F$6:$F$797,Monthly_Data!$B$6:$B$797,">="&J11,Monthly_Data!$B$6:$B$797,"<="&K11,Monthly_Data!$C$6:$C$797,D11,Monthly_Data!$D$6:$D$797,C11,Monthly_Data!$I$6:$I$797,1) -> 20714 | N11: =COUNTIFS(Monthly_Data!$B$6:$B$797,">="&J11,Monthly_Data!$B$6:$B$797,"<="&K11,Monthly_Data!$C$6:$C$797,D11,Monthly_Data!$D$6:$D$797,C11,Monthly_Data!$I$6:$I$797,1) -> 8 | O11: =IF(M11>0,L11/M11,"n.a.") -> 12.283528 | P11: =IF(F11>0,E11/F11-I11,"n.a.") -> 0 | Q11: =COUNTIF($A$6:$A$125,A11) -> 1 | R11: =ABS(P11) -> 0
A12: FY2025|Pakistan|61091000 | B12: FY2025 | C12: Pakistan | D12: 61091000 | E12: 50802167 | F12: 10896985 | G12: 12 | H12: 4 | I12: 4.6620388 | J12: 202501 | K12: 202512 | L12: =SUMIFS(Monthly_Data!$E$6:$E$797,Monthly_Data!$B$6:$B$797,">="&J12,Monthly_Data!$B$6:$B$797,"<="&K12,Monthly_Data!$C$6:$C$797,D12,Monthly_Data!$D$6:$D$797,C12,Monthly_Data!$I$6:$I$797,1) -> 31440750 | M12: =SUMIFS(Monthly_Data!$F$6:$F$797,Monthly_Data!$B$6:$B$797,">="&J12,Monthly_Data!$B$6:$B$797,"<="&K12,Monthly_Data!$C$6:$C$797,D12,Monthly_Data!$D$6:$D$797,C12,Monthly_Data!$I$6:$I$797,1) -> 2884303 | N12: =COUNTIFS(Monthly_Data!$B$6:$B$797,">="&J12,Monthly_Data!$B$6:$B$797,"<="&K12,Monthly_Data!$C$6:$C$797,D12,Monthly_Data!$D$6:$D$797,C12,Monthly_Data!$I$6:$I$797,1) -> 8 | O12: =IF(M12>0,L12/M12,"n.a.") -> 10.90064 | P12: =IF(F12>0,E12/F12-I12,"n.a.") -> 0 | Q12: =COUNTIF($A$6:$A$125,A12) -> 1 | R12: =ABS(P12) -> 0
A13: FY2025|Sri Lanka|61091000 | B13: FY2025 | C13: Sri Lanka | D13: 61091000 | E13: 22682066 | F13: 2215013 | G13: 12 | H13: 0 | I13: 10.24015 | J13: 202501 | K13: 202512 | L13: =SUMIFS(Monthly_Data!$E$6:$E$797,Monthly_Data!$B$6:$B$797,">="&J13,Monthly_Data!$B$6:$B$797,"<="&K13,Monthly_Data!$C$6:$C$797,D13,Monthly_Data!$D$6:$D$797,C13,Monthly_Data!$I$6:$I$797,1) -> 14028089 | M13: =SUMIFS(Monthly_Data!$F$6:$F$797,Monthly_Data!$B$6:$B$797,">="&J13,Monthly_Data!$B$6:$B$797,"<="&K13,Monthly_Data!$C$6:$C$797,D13,Monthly_Data!$D$6:$D$797,C13,Monthly_Data!$I$6:$I$797,1) -> 1406635 | N13: =COUNTIFS(Monthly_Data!$B$6:$B$797,">="&J13,Monthly_Data!$B$6:$B$797,"<="&K13,Monthly_Data!$C$6:$C$797,D13,Monthly_Data!$D$6:$D$797,C13,Monthly_Data!$I$6:$I$797,1) -> 8 | O13: =IF(M13>0,L13/M13,"n.a.") -> 9.9727996 | P13: =IF(F13>0,E13/F13-I13,"n.a.") -> 0 | Q13: =COUNTIF($A$6:$A$125,A13) -> 1 | R13: =ABS(P13) -> 0
A14: FY2025|Turkey|61091000 | B14: FY2025 | C14: Turkey | D14: 61091000 | E14: 109167119 | F14: 4927477 | G14: 12 | H14: 0 | I14: 22.15477 | J14: 202501 | K14: 202512 | L14: =SUMIFS(Monthly_Data!$E$6:$E$797,Monthly_Data!$B$6:$B$797,">="&J14,Monthly_Data!$B$6:$B$797,"<="&K14,Monthly_Data!$C$6:$C$797,D14,Monthly_Data!$D$6:$D$797,C14,Monthly_Data!$I$6:$I$797,1) -> 65407784 | M14: =SUMIFS(Monthly_Data!$F$6:$F$797,Monthly_Data!$B$6:$B$797,">="&J14,Monthly_Data!$B$6:$B$797,"<="&K14,Monthly_Data!$C$6:$C$797,D14,Monthly_Data!$D$6:$D$797,C14,Monthly_Data!$I$6:$I$797,1) -> 3077282 | N14: =COUNTIFS(Monthly_Data!$B$6:$B$797,">="&J14,Monthly_Data!$B$6:$B$797,"<="&K14,Monthly_Data!$C$6:$C$797,D14,Monthly_Data!$D$6:$D$797,C14,Monthly_Data!$I$6:$I$797,1) -> 8 | O14: =IF(M14>0,L14/M14,"n.a.") -> 21.25505 | P14: =IF(F14>0,E14/F14-I14,"n.a.") -> 0 | Q14: =COUNTIF($A$6:$A$125,A14) -> 1 | R14: =ABS(P14) -> 0
A15: FY2025|Vietnam|61091000 | B15: FY2025 | C15: Vietnam | D15: 61091000 | E15: 23980546 | F15: 1170082 | G15: 12 | H15: 0 | I15: 20.494757 | J15: 202501 | K15: 202512 | L15: =SUMIFS(Monthly_Data!$E$6:$E$797,Monthly_Data!$B$6:$B$797,">="&J15,Monthly_Data!$B$6:$B$797,"<="&K15,Monthly_Data!$C$6:$C$797,D15,Monthly_Data!$D$6:$D$797,C15,Monthly_Data!$I$6:$I$797,1) -> 13064717 | M15: =SUMIFS(Monthly_Data!$F$6:$F$797,Monthly_Data!$B$6:$B$797,">="&J15,Monthly_Data!$B$6:$B$797,"<="&K15,Monthly_Data!$C$6:$C$797,D15,Monthly_Data!$D$6:$D$797,C15,Monthly_Data!$I$6:$I$797,1) -> 641927 | N15: =COUNTIFS(Monthly_Data!$B$6:$B$797,">="&J15,Monthly_Data!$B$6:$B$797,"<="&K15,Monthly_Data!$C$6:$C$797,D15,Monthly_Data!$D$6:$D$797,C15,Monthly_Data!$I$6:$I$797,1) -> 8 | O15: =IF(M15>0,L15/M15,"n.a.") -> 20.352341 | P15: =IF(F15>0,E15/F15-I15,"n.a.") -> 0 | Q15: =COUNTIF($A$6:$A$125,A15) -> 1 | R15: =ABS(P15) -> 0
A16: FY2025|Bangladesh|61103099 | B16: FY2025 | C16: Bangladesh | D16: 61103099 | E16: 164836619 | F16: 13246692 | G16: 12 | H16: 0 | I16: 12.443606 | J16: 202501 | K16: 202512 | L16: =SUMIFS(Monthly_Data!$E$6:$E$797,Monthly_Data!$B$6:$B$797,">="&J16,Monthly_Data!$B$6:$B$797,"<="&K16,Monthly_Data!$C$6:$C$797,D16,Monthly_Data!$D$6:$D$797,C16,Monthly_Data!$I$6:$I$797,1) -> 104488465 | M16: =SUMIFS(Monthly_Data!$F$6:$F$797,Monthly_Data!$B$6:$B$797,">="&J16,Monthly_Data!$B$6:$B$797,"<="&K16,Monthly_Data!$C$6:$C$797,D16,Monthly_Data!$D$6:$D$797,C16,Monthly_Data!$I$6:$I$797,1) -> 8519362 | N16: =COUNTIFS(Monthly_Data!$B$6:$B$797,">="&J16,Monthly_Data!$B$6:$B$797,"<="&K16,Monthly_Data!$C$6:$C$797,D16,Monthly_Data!$D$6:$D$797,C16,Monthly_Data!$I$6:$I$797,1) -> 9 | O16: =IF(M16>0,L16/M16,"n.a.") -> 12.264823 | P16: =IF(F16>0,E16/F16-I16,"n.a.") -> 0 | Q16: =COUNTIF($A$6:$A$125,A16) -> 1 | R16: =ABS(P16) -> 0
A17: FY2025|Cambodia|61103099 | B17: FY2025 | C17: Cambodia | D17: 61103099 | E17: 72460733 | F17: 6288565 | G17: 12 | H17: 0 | I17: 11.522618 | J17: 202501 | K17: 202512 | L17: =SUMIFS(Monthly_Data!$E$6:$E$797,Monthly_Data!$B$6:$B$797,">="&J17,Monthly_Data!$B$6:$B$797,"<="&K17,Monthly_Data!$C$6:$C$797,D17,Monthly_Data!$D$6:$D$797,C17,Monthly_Data!$I$6:$I$797,1) -> 46317552 | M17: =SUMIFS(Monthly_Data!$F$6:$F$797,Monthly_Data!$B$6:$B$797,">="&J17,Monthly_Data!$B$6:$B$797,"<="&K17,Monthly_Data!$C$6:$C$797,D17,Monthly_Data!$D$6:$D$797,C17,Monthly_Data!$I$6:$I$797,1) -> 3874664 | N17: =COUNTIFS(Monthly_Data!$B$6:$B$797,">="&J17,Monthly_Data!$B$6:$B$797,"<="&K17,Monthly_Data!$C$6:$C$797,D17,Monthly_Data!$D$6:$D$797,C17,Monthly_Data!$I$6:$I$797,1) -> 9 | O17: =IF(M17>0,L17/M17,"n.a.") -> 11.953953 | P17: =IF(F17>0,E17/F17-I17,"n.a.") -> 0 | Q17: =COUNTIF($A$6:$A$125,A17) -> 1 | R17: =ABS(P17) -> 0
... A125: H1 2026|Vietnam|62052000 | B125: H1 2026 | C125: Vietnam | D125: 62052000 | E125: 5885338 | F125: 196825 | G125: 6 | H125: 0 | I125: 29.901374 | J125: 202601 | K125: 202606 | L125: =SUMIFS(Monthly_Data!$E$6:$E$797,Monthly_Data!$B$6:$B$797,">="&J125,Monthly_Data!$B$6:$B$797,"<="&K125,Monthly_Data!$C$6:$C$797,D125,Monthly_Data!$D$6:$D$797,C125,Monthly_Data!$I$6:$I$797,1) -> 4696585 | M125: =SUMIFS(Monthly_Data!$F$6:$F$797,Monthly_Data!$B$6:$B$797,">="&J125,Monthly_Data!$B$6:$B$797,"<="&K125,Monthly_Data!$C$6:$C$797,D125,Monthly_Data!$D$6:$D$797,C125,Monthly_Data!$I$6:$I$797,1) -> 156499 | N125: =COUNTIFS(Monthly_Data!$B$6:$B$797,">="&J125,Monthly_Data!$B$6:$B$797,"<="&K125,Monthly_Data!$C$6:$C$797,D125,Monthly_Data!$D$6:$D$797,C125,Monthly_Data!$I$6:$I$797,1) -> 5 | O125: =IF(M125>0,L125/M125,"n.a.") -> 30.01032 | P125: =IF(F125>0,E125/F125-I125,"n.a.") -> 0 | Q125: =COUNTIF($A$6:$A$125,A125) -> 1 | R125: =ABS(P125) -> 0

Sheet Monthly_Data
A2: Monthly trade observations
A4: Source: WP006 Inputs, governed WP005 partner and World monthly CSVs. Jan 2025–Jun 2026. Original values and REVIEW flags retained.
A5: Observation key | B5: Month ID | C5: CN8 | D5: Partner | E5: Import value (£) | F5: Net mass (kg) | G5: Review flag | H5: API present | I5: Common keep
A6: 61091000_BD_202501_IMPORT | B6: 202501 | C6: 61091000 | D6: Bangladesh | E6: 37635639 | F6: 3598131 | G6: WITHIN_BAND | H6: 1 | I6: =IF(AND(COUNTIFS($B$6:$B$797,B6,$C$6:$C$797,C6)=11,COUNTIFS($B$6:$B$797,B6,$C$6:$C$797,C6,$G$6:$G$797,"REVIEW")=0,COUNTIFS($B$6:$B$797,B6,$C$6:$C$797,C6,$H$6:$H$797,1)=11,COUNTIFS($B$6:$B$797,B6,$C$6:$C$797,C6,$F$6:$F$797,">0")=11),1,0) -> 1
A7: 61091000_KH_202501_IMPORT | B7: 202501 | C7: 61091000 | D7: Cambodia | E7: 815302 | F7: 48927 | G7: WITHIN_BAND | H7: 1 | I7: =IF(AND(COUNTIFS($B$6:$B$797,B7,$C$6:$C$797,C7)=11,COUNTIFS($B$6:$B$797,B7,$C$6:$C$797,C7,$G$6:$G$797,"REVIEW")=0,COUNTIFS($B$6:$B$797,B7,$C$6:$C$797,C7,$H$6:$H$797,1)=11,COUNTIFS($B$6:$B$797,B7,$C$6:$C$797,C7,$F$6:$F$797,">0")=11),1,0) -> 1
A8: 61091000_CN_202501_IMPORT | B8: 202501 | C8: 61091000 | D8: China | E8: 4906522 | F8: 287181 | G8: WITHIN_BAND | H8: 1 | I8: =IF(AND(COUNTIFS($B$6:$B$797,B8,$C$6:$C$797,C8)=11,COUNTIFS($B$6:$B$797,B8,$C$6:$C$797,C8,$G$6:$G$797,"REVIEW")=0,COUNTIFS($B$6:$B$797,B8,$C$6:$C$797,C8,$H$6:$H$797,1)=11,COUNTIFS($B$6:$B$797,B8,$C$6:$C$797,C8,$F$6:$F$797,">0")=11),1,0) -> 1
A9: 61091000_IN_202501_IMPORT | B9: 202501 | C9: 61091000 | D9: India | E9: 6612624 | F9: 447550 | G9: WITHIN_BAND | H9: 1 | I9: =IF(AND(COUNTIFS($B$6:$B$797,B9,$C$6:$C$797,C9)=11,COUNTIFS($B$6:$B$797,B9,$C$6:$C$797,C9,$G$6:$G$797,"REVIEW")=0,COUNTIFS($B$6:$B$797,B9,$C$6:$C$797,C9,$H$6:$H$797,1)=11,COUNTIFS($B$6:$B$797,B9,$C$6:$C$797,C9,$F$6:$F$797,">0")=11),1,0) -> 1
A10: 61091000_MA_202501_IMPORT | B10: 202501 | C10: 61091000 | D10: Morocco | E10: 595595 | F10: 58622 | G10: WITHIN_BAND | H10: 1 | I10: =IF(AND(COUNTIFS($B$6:$B$797,B10,$C$6:$C$797,C10)=11,COUNTIFS($B$6:$B$797,B10,$C$6:$C$797,C10,$G$6:$G$797,"REVIEW")=0,COUNTIFS($B$6:$B$797,B10,$C$6:$C$797,C10,$H$6:$H$797,1)=11,COUNTIFS($B$6:$B$797,B10,$C$6:$C$797,C10,$F$6:$F$797,">0")=11),1,0) -> 1
A11: 61091000_MM_202501_IMPORT | B11: 202501 | C11: 61091000 | D11: Myanmar | E11: 47447 | F11: 3108 | G11: WITHIN_BAND | H11: 1 | I11: =IF(AND(COUNTIFS($B$6:$B$797,B11,$C$6:$C$797,C11)=11,COUNTIFS($B$6:$B$797,B11,$C$6:$C$797,C11,$G$6:$G$797,"REVIEW")=0,COUNTIFS($B$6:$B$797,B11,$C$6:$C$797,C11,$H$6:$H$797,1)=11,COUNTIFS($B$6:$B$797,B11,$C$6:$C$797,C11,$F$6:$F$797,">0")=11),1,0) -> 1
A12: 61091000_PK_202501_IMPORT | B12: 202501 | C12: 61091000 | D12: Pakistan | E12: 4215403 | F12: 375044 | G12: WITHIN_BAND | H12: 1 | I12: =IF(AND(COUNTIFS($B$6:$B$797,B12,$C$6:$C$797,C12)=11,COUNTIFS($B$6:$B$797,B12,$C$6:$C$797,C12,$G$6:$G$797,"REVIEW")=0,COUNTIFS($B$6:$B$797,B12,$C$6:$C$797,C12,$H$6:$H$797,1)=11,COUNTIFS($B$6:$B$797,B12,$C$6:$C$797,C12,$F$6:$F$797,">0")=11),1,0) -> 1
A13: 61091000_LK_202501_IMPORT | B13: 202501 | C13: 61091000 | D13: Sri Lanka | E13: 1867891 | F13: 190782 | G13: WITHIN_BAND | H13: 1 | I13: =IF(AND(COUNTIFS($B$6:$B$797,B13,$C$6:$C$797,C13)=11,COUNTIFS($B$6:$B$797,B13,$C$6:$C$797,C13,$G$6:$G$797,"REVIEW")=0,COUNTIFS($B$6:$B$797,B13,$C$6:$C$797,C13,$H$6:$H$797,1)=11,COUNTIFS($B$6:$B$797,B13,$C$6:$C$797,C13,$F$6:$F$797,">0")=11),1,0) -> 1
A14: 61091000_TR_202501_IMPORT | B14: 202501 | C14: 61091000 | D14: Turkey | E14: 9498438 | F14: 427107 | G14: WITHIN_BAND | H14: 1 | I14: =IF(AND(COUNTIFS($B$6:$B$797,B14,$C$6:$C$797,C14)=11,COUNTIFS($B$6:$B$797,B14,$C$6:$C$797,C14,$G$6:$G$797,"REVIEW")=0,COUNTIFS($B$6:$B$797,B14,$C$6:$C$797,C14,$H$6:$H$797,1)=11,COUNTIFS($B$6:$B$797,B14,$C$6:$C$797,C14,$F$6:$F$797,">0")=11),1,0) -> 1
A15: 61091000_VN_202501_IMPORT | B15: 202501 | C15: 61091000 | D15: Vietnam | E15: 1759203 | F15: 80140 | G15: WITHIN_BAND | H15: 1 | I15: =IF(AND(COUNTIFS($B$6:$B$797,B15,$C$6:$C$797,C15)=11,COUNTIFS($B$6:$B$797,B15,$C$6:$C$797,C15,$G$6:$G$797,"REVIEW")=0,COUNTIFS($B$6:$B$797,B15,$C$6:$C$797,C15,$H$6:$H$797,1)=11,COUNTIFS($B$6:$B$797,B15,$C$6:$C$797,C15,$F$6:$F$797,">0")=11),1,0) -> 1
A16: 61091000_WORLD_202501_IMPORT | B16: 202501 | C16: 61091000 | D16: World | E16: 97780137 | F16: 6822727 | G16: WITHIN_BAND | H16: 1 | I16: =IF(AND(COUNTIFS($B$6:$B$797,B16,$C$6:$C$797,C16)=11,COUNTIFS($B$6:$B$797,B16,$C$6:$C$797,C16,$G$6:$G$797,"REVIEW")=0,COUNTIFS($B$6:$B$797,B16,$C$6:$C$797,C16,$H$6:$H$797,1)=11,COUNTIFS($B$6:$B$797,B16,$C$6:$C$797,C16,$F$6:$F$797,">0")=11),1,0) -> 1
A17: 61091000_BD_202502_IMPORT | B17: 202502 | C17: 61091000 | D17: Bangladesh | E17: 34909984 | F17: 3246390 | G17: WITHIN_BAND | H17: 1 | I17: =IF(AND(COUNTIFS($B$6:$B$797,B17,$C$6:$C$797,C17)=11,COUNTIFS($B$6:$B$797,B17,$C$6:$C$797,C17,$G$6:$G$797,"REVIEW")=0,COUNTIFS($B$6:$B$797,B17,$C$6:$C$797,C17,$H$6:$H$797,1)=11,COUNTIFS($B$6:$B$797,B17,$C$6:$C$797,C17,$F$6:$F$797,">0")=11),1,0) -> 1
... A797: 62052000_WORLD_202606_IMPORT | B797: 202606 | C797: 62052000 | D797: World | E797: 18430383 | F797: 704182 | G797: WITHIN_BAND | H797: 1 | I797: =IF(AND(COUNTIFS($B$6:$B$797,B797,$C$6:$C$797,C797)=11,COUNTIFS($B$6:$B$797,B797,$C$6:$C$797,C797,$G$6:$G$797,"REVIEW")=0,COUNTIFS($B$6:$B$797,B797,$C$6:$C$797,C797,$H$6:$H$797,1)=11,COUNTIFS($B$6:$B$797,B797,$C$6:$C$797,C797,$F$6:$F$797,">0")=11),1,0) -> 1

Sheet Tariffs
A2: Locked tariff assumptions
A4: Source: NEXT_WP004_Category_Tariff_Lock(3).xlsx, Tariff_Matrix and Origin_Rules. Frozen project snapshot. Fallback is the 12% UKGT rate recorded in WP004.
A5: Join key | B5: Country | C5: CN8 | D5: 2025 eligible | E5: Pre-15 Jul 2026 | F5: From 15 Jul 2026 | G5: MFN fallback | H5: Preference conditional | I5: Source IDs | J5: Evidence queries | K5: WP004 location
A6: Bangladesh|61091000 | B6: Bangladesh | C6: 61091000 | D6: 0 | E6: 0 | F6: 0 | G6: 0.12 | H6: Yes | I6: EXT_UKGT; EXT_DCTS_2026; EXT_DCTS_ROO; EXT_UN_LDC_BGD | J6: T01; T02 | K6: Tariff_Matrix!A2:N2
A7: Cambodia|61091000 | B7: Cambodia | C7: 61091000 | D7: 0 | E7: 0 | F7: 0 | G7: 0.12 | H7: Yes | I7: EXT_UKGT; EXT_DCTS_2026 | J7: T01; T02 | K7: Tariff_Matrix!A6:N6
A8: China|61091000 | B8: China | C8: 61091000 | D8: 0.12 | E8: 0.12 | F8: 0.12 | G8: 0.12 | H8: No | I8: EXT_UKGT | J8: T01; T02 | K8: Tariff_Matrix!A10:N10
A9: India|61091000 | B9: India | C9: 61091000 | D9: 0.096 | E9: 0.096 | F9: 0 | G9: 0.12 | H9: Yes | I9: EXT_UKGT; EXT_DCTS_GRAD; EXT_CETA_ANNEX2A; EXT_CETA_TARIFF; EXT_CETA_PSR | J9: T01; T02 | K9: Tariff_Matrix!A14:N14
A10: Morocco|61091000 | B10: Morocco | C10: 61091000 | D10: 0 | E10: 0 | F10: 0 | G10: 0.12 | H10: Yes | I10: EXT_UKGT; EXT_UK_MOROCCO | J10: T01; T02 | K10: Tariff_Matrix!A18:N18
A11: Myanmar|61091000 | B11: Myanmar | C11: 61091000 | D11: 0 | E11: 0 | F11: 0 | G11: 0.12 | H11: Yes | I11: EXT_UKGT; EXT_DCTS_2026 | J11: T01; T02 | K11: Tariff_Matrix!A22:N22
A12: Pakistan|61091000 | B12: Pakistan | C12: 61091000 | D12: 0 | E12: 0 | F12: 0 | G12: 0.12 | H12: Yes | I12: EXT_UKGT; EXT_DCTS_2026 | J12: T01; T02 | K12: Tariff_Matrix!A26:N26
A13: Sri Lanka|61091000 | B13: Sri Lanka | C13: 61091000 | D13: 0 | E13: 0 | F13: 0 | G13: 0.12 | H13: Yes | I13: EXT_UKGT; EXT_DCTS_2026 | J13: T01; T02 | K13: Tariff_Matrix!A30:N30
A14: Turkey|61091000 | B14: Turkey | C14: 61091000 | D14: 0 | E14: 0 | F14: 0 | G14: 0.12 | H14: Yes | I14: EXT_UKGT; EXT_UK_TURKEY | J14: T01; T02 | K14: Tariff_Matrix!A34:N34
A15: Vietnam|61091000 | B15: Vietnam | C15: 61091000 | D15: 0 | E15: 0 | F15: 0 | G15: 0.12 | H15: Yes | I15: EXT_UKGT; EXT_UK_VIETNAM | J15: T01; T02 | K15: Tariff_Matrix!A38:N38
A16: Bangladesh|61103099 | B16: Bangladesh | C16: 61103099 | D16: 0 | E16: 0 | F16: 0 | G16: 0.12 | H16: Yes | I16: EXT_UKGT; EXT_DCTS_2026; EXT_DCTS_ROO; EXT_UN_LDC_BGD | J16: T03 | K16: Tariff_Matrix!A3:N3
A17: Cambodia|61103099 | B17: Cambodia | C17: 61103099 | D17: 0 | E17: 0 | F17: 0 | G17: 0.12 | H17: Yes | I17: EXT_UKGT; EXT_DCTS_2026 | J17: T03 | K17: Tariff_Matrix!A7:N7
... A45: Vietnam|62052000 | B45: Vietnam | C45: 62052000 | D45: 0 | E45: 0 | F45: 0 | G45: 0.12 | H45: Yes | I45: EXT_UKGT; EXT_UK_VIETNAM | J45: T05; T06 | K45: Tariff_Matrix!A41:N41
A49: Country | B49: APPAREL sites | C49: Source suppliers | D49: Resolved groups
A50: Bangladesh | B50: 192 | C50: 83 | D50: 83
A51: Cambodia | B51: 62 | C51: 29 | D51: 29
A52: China | B52: 507 | C52: 260 | D52: 256
A53: India | B53: 212 | C53: 127 | D53: 124
A54: Morocco | B54: 17 | C54: 16 | D54: 16
A55: Myanmar | B55: 13 | C55: 3 | D55: 3
A56: Pakistan | B56: 44 | C56: 37 | D56: 36
A57: Sri Lanka | B57: 66 | C57: 29 | D57: 29
A58: Turkey | B58: 70 | C58: 55 | D58: 55
A59: Vietnam | B59: 34 | C59: 25 | D59: 25
A61: Footprint source: NEXT_WP006_supplier_country_product_footprint.csv, APPAREL rows. These counts establish disclosed presence only. They do not establish locked-CN8 capability, spare capacity or sourcing clearance.
A62: India: preference is conditional on CETA origin evidence. Vietnam 62044300: 3% in 2025 and 1.5% in the 2026 snapshot. Bangladesh: recheck preference tier/rates in 2029; no automatic tariff cliff is modelled.
A63: Dispatch geography does not prove manufacturing origin. Eligible rates assume a candidate would satisfy the relevant origin rules; MFN is the fallback where preference cannot be claimed.

Sheet QC_Checks
A2: WP008 model controls
A5: Check | B5: Actual | C5: Expected | D5: Result | E5: Coverage
A6: Reported period records | B6: =COUNTA(Trade_Periods!A6:A125) -> 120 | C6: 120 | D6: =IF(ABS(B6-C6)<=0,"PASS","FAIL") -> PASS | E6: 3 periods × 4 codes × 10 countries
A7: Monthly observations | B7: =COUNTA(Monthly_Data!A6:A797) -> 792 | C7: 792 | D7: =IF(ABS(B7-C7)<=0,"PASS","FAIL") -> PASS | E7: 18 months × 4 codes × 11 geographies
A8: Tariff records | B8: =COUNTA(Tariffs!A6:A45) -> 40 | C8: 40 | D8: =IF(ABS(B8-C8)<=0,"PASS","FAIL") -> PASS | E8: Four codes × ten countries
A9: Unique period keys | B9: =COUNTIF(Trade_Periods!Q6:Q125,1) -> 120 | C9: 120 | D9: =IF(ABS(B9-C9)<=0,"PASS","FAIL") -> PASS | E9: Stable period/country/code keys
A10: Export UV reconciliation | B10: =SUM(Trade_Periods!R6:R125) -> 0 | C10: 0 | D10: =IF(ABS(B10-C10)<=1e-8,"PASS","FAIL") -> PASS | E10: Recomputed value / mass versus WP006 weighted UV
A11: Input assumptions | B11: =Assumptions!C13 -> Valid | C11: Valid | D11: =IF(B11=C11,"PASS","FAIL") -> PASS | E11: Weights, ranges and Myanmar/donor exclusions
A12: 61091000: baseline shares | B12: =SUM(Cost_Model!D6:D15) -> 1 | C12: 1 | D12: =IF(ABS(B12-C12)<=1e-9,"PASS","FAIL") -> PASS | E12: Each product baseline sums to 100%
A13: 61091000: scenario shares | B13: =SUM(Cost_Model!R6:R15) -> 1 | C13: 1 | D13: =IF(ABS(B13-C13)<=1e-9,"PASS","FAIL") -> PASS | E13: Each product scenario sums to 100%
A14: 61091000: negative shares | B14: =COUNTIF(Cost_Model!R6:R15,"<0") -> 0 | C14: 0 | D14: =IF(ABS(B14-C14)<=0,"PASS","FAIL") -> PASS | E14: No negative country allocations
A15: 61091000: cost bridge | B15: =SUM(Cost_Model!T6:T15)-Cost_Model!F51 -> 0 | C15: 0 | D15: =IF(ABS(B15-C15)<=1e-9,"PASS","FAIL") -> PASS | E15: Country contributions versus linear bridge
A16: 61091000: HHI bridge | B16: =SUMPRODUCT(Cost_Model!R6:R15,Cost_Model!R6:R15)-Cost_Model!J51 -> 5.5511151e-17 | C16: 0 | D16: =IF(ABS(B16-C16)<=1e-9,"PASS","FAIL") -> PASS | E16: Direct sum of squared shares versus quadratic bridge
A17: 61091000: Myanmar increment | B17: =Cost_Model!Q11 -> 0 | C17: 0 | D17: =IF(ABS(B17-C17)<=0,"PASS","FAIL") -> PASS | E17: D020: no additional allocation
A18: 61091000: model data | B18: =Cost_Model!P51 -> Ready | C18: Ready | D18: =IF(B18=C18,"PASS","FAIL") -> PASS | E18: All ten country input records present
A19: 61103099: baseline shares | B19: =SUM(Cost_Model!D16:D25) -> 1 | C19: 1 | D19: =IF(ABS(B19-C19)<=1e-9,"PASS","FAIL") -> PASS | E19: Each product baseline sums to 100%
A20: 61103099: scenario shares | B20: =SUM(Cost_Model!R16:R25) -> 1 | C20: 1 | D20: =IF(ABS(B20-C20)<=1e-9,"PASS","FAIL") -> PASS | E20: Each product scenario sums to 100%
A21: 61103099: negative shares | B21: =COUNTIF(Cost_Model!R16:R25,"<0") -> 0 | C21: 0 | D21: =IF(ABS(B21-C21)<=0,"PASS","FAIL") -> PASS | E21: No negative country allocations
A22: 61103099: cost bridge | B22: =SUM(Cost_Model!T16:T25)-Cost_Model!F52 -> 1.7763568e-15 | C22: 0 | D22: =IF(ABS(B22-C22)<=1e-9,"PASS","FAIL") -> PASS | E22: Country contributions versus linear bridge
A23: 61103099: HHI bridge | B23: =SUMPRODUCT(Cost_Model!R16:R25,Cost_Model!R16:R25)-Cost_Model!J52 -> 0 | C23: 0 | D23: =IF(ABS(B23-C23)<=1e-9,"PASS","FAIL") -> PASS | E23: Direct sum of squared shares versus quadratic bridge
A24: 61103099: Myanmar increment | B24: =Cost_Model!Q21 -> 0 | C24: 0 | D24: =IF(ABS(B24-C24)<=0,"PASS","FAIL") -> PASS | E24: D020: no additional allocation
A25: 61103099: model data | B25: =Cost_Model!P52 -> Ready | C25: Ready | D25: =IF(B25=C25,"PASS","FAIL") -> PASS | E25: All ten country input records present
A26: 62044300: baseline shares | B26: =SUM(Cost_Model!D26:D35) -> 1 | C26: 1 | D26: =IF(ABS(B26-C26)<=1e-9,"PASS","FAIL") -> PASS | E26: Each product baseline sums to 100%
A27: 62044300: scenario shares | B27: =SUM(Cost_Model!R26:R35) -> 1 | C27: 1 | D27: =IF(ABS(B27-C27)<=1e-9,"PASS","FAIL") -> PASS | E27: Each product scenario sums to 100%
A28: 62044300: negative shares | B28: =COUNTIF(Cost_Model!R26:R35,"<0") -> 0 | C28: 0 | D28: =IF(ABS(B28-C28)<=0,"PASS","FAIL") -> PASS | E28: No negative country allocations
A29: 62044300: cost bridge | B29: =SUM(Cost_Model!T26:T35)-Cost_Model!F53 -> -7.1054274e-15 | C29: 0 | D29: =IF(ABS(B29-C29)<=1e-9,"PASS","FAIL") -> PASS | E29: Country contributions versus linear bridge
A30: 62044300: HHI bridge | B30: =SUMPRODUCT(Cost_Model!R26:R35,Cost_Model!R26:R35)-Cost_Model!J53 -> -1.3877788e-16 | C30: 0 | D30: =IF(ABS(B30-C30)<=1e-9,"PASS","FAIL") -> PASS | E30: Direct sum of squared shares versus quadratic bridge
A31: 62044300: Myanmar increment | B31: =Cost_Model!Q31 -> 0 | C31: 0 | D31: =IF(ABS(B31-C31)<=0,"PASS","FAIL") -> PASS | E31: D020: no additional allocation
A32: 62044300: model data | B32: =Cost_Model!P53 -> Ready | C32: Ready | D32: =IF(B32=C32,"PASS","FAIL") -> PASS | E32: All ten country input records present
A33: 62052000: baseline shares | B33: =SUM(Cost_Model!D36:D45) -> 1 | C33: 1 | D33: =IF(ABS(B33-C33)<=1e-9,"PASS","FAIL") -> PASS | E33: Each product baseline sums to 100%
A34: 62052000: scenario shares | B34: =SUM(Cost_Model!R36:R45) -> 1 | C34: 1 | D34: =IF(ABS(B34-C34)<=1e-9,"PASS","FAIL") -> PASS | E34: Each product scenario sums to 100%
A35: 62052000: negative shares | B35: =COUNTIF(Cost_Model!R36:R45,"<0") -> 0 | C35: 0 | D35: =IF(ABS(B35-C35)<=0,"PASS","FAIL") -> PASS | E35: No negative country allocations
A36: 62052000: cost bridge | B36: =SUM(Cost_Model!T36:T45)-Cost_Model!F54 -> -3.5527137e-15 | C36: 0 | D36: =IF(ABS(B36-C36)<=1e-9,"PASS","FAIL") -> PASS | E36: Country contributions versus linear bridge
A37: 62052000: HHI bridge | B37: =SUMPRODUCT(Cost_Model!R36:R45,Cost_Model!R36:R45)-Cost_Model!J54 -> 0 | C37: 0 | D37: =IF(ABS(B37-C37)<=1e-9,"PASS","FAIL") -> PASS | E37: Direct sum of squared shares versus quadratic bridge
A38: 62052000: Myanmar increment | B38: =Cost_Model!Q41 -> 0 | C38: 0 | D38: =IF(ABS(B38-C38)<=0,"PASS","FAIL") -> PASS | E38: D020: no additional allocation
A39: 62052000: model data | B39: =Cost_Model!P54 -> Ready | C39: Ready | D39: =IF(B39=C39,"PASS","FAIL") -> PASS | E39: All ten country input records present
A40: All candidate gates represented | B40: =COUNTA(Candidate_Gates!F5:M5) -> 8 | C40: 8 | D40: =IF(ABS(B40-C40)<=0,"PASS","FAIL") -> PASS | E40: RS01–RS08 explicit for every candidate placeholder
A41: Complete pending evidence matrix | B41: =COUNTIF(Candidate_Gates!D6:M45,"Pending") -> 400 | C41: 400 | D41: =IF(ABS(B41-C41)<=0,"PASS","FAIL") -> PASS | E41: Initial snapshot: 40 × 10 pending evidence fields
A43: Receiver multiple-cap excess | B43: =SUM(Cost_Model!AG6:AG45) -> 0 | C43: 0 | D43: =IF(ABS(B43-C43)<0.000000001,"PASS","FAIL") -> PASS | E43: Sum of excess receiver shares over the enabled cap.
A47: Controls review the model independently and do not feed the outputs. Pending evidence is an expected limitation, not a compliance failure. Candidate-evidence counts document this initial public-evidence snapshot.

Sheet ReadMe
A2: WP008 method and source record
A5: Topic | B5: Definition
A6: Version | B6: 1.1. Revised 18 September 2026. Adds receiver growth safeguard, HHI interpretation and corrected Q2.6/Q5.2 handover.
A7: Question | B7: What do 5/10/15 percentage-point reductions in China’s category share imply for benchmark cost and concentration, subject to explicit limits and sourcing gates?
A8: Baseline | B8: Within each locked CN8, FY2025 import mass for a country divided by the ten-country total. This is a UK trade proxy. World is used for diagnostic month screening, not as an eleventh allocation destination.
A9: Price periods | B9: FY2025, H1 2025 and H1 2026 are separate selectable observations. Overlapping periods are never summed. FY2025 allocation weights stay fixed when the price period or sensitivity changes.
A10: Unit value | B10: Period import value divided by period net mass. No average of monthly unit values. HMRC trade is not NEXT procurement, and dispatch country is not verified manufacturing origin.
A11: Tariff comparison | B11: The locked WP004 2025/pre-15 July 2026/post-15 July 2026 rates can be applied to any selected price period. These are constant-price policy comparisons, not estimates of historical paid duties or a fresh legal-rate verification.
A12: Origin | B12: Eligible preference assumes all applicable origin requirements are met. MFN fallback is 12% for the selected codes. Responsible-sourcing clearance does not establish customs origin.
A13: Cost scope | B13: Border unit value × (1 + tariff). International freight must not be added again. A premium can be applied to incremental receiver volume. VAT, inland logistics, lead-time effects, working capital, FX and transition costs require further evidence.
A14: Allocation direction | B14: China decreases by s; India increases by 0.5s, Turkey by 0.25s, Vietnam by 0.25s under default receiver weights. Other countries are unchanged. This mix tests policy exposure and diversification; no optimality or capability claim is made.
A15: Feasible shift | B15: Minimum of requested shift, China baseline share, and receiver headroom / receiver weight. Headroom is limited by the 35% ceiling, 10pp addition cap and, when enabled, (maximum multiple − 1) × baseline share. The default 3× safeguard is an assumption, not verified capacity. Zero-baseline receivers cannot grow while it is enabled.
A16: Scenario comparison | B16: One cost/constraint build calculates baseline cost and unit-shift cost. The three comparison cases apply their feasible shift to those same coefficients. HHI uses the equivalent quadratic formula. All comparisons recalculate with the inputs.
... A30: NEXT_WP007_Responsible_Sourcing_Gates_v1.0(1).xlsx | B30: 4df2f2a706f61877f7c95f710dd267499cdc3ff1825d3887b2489491849542ef
A34: Trade_Periods preserves 120 reported rows from NEXT_WP006_partner_trade_period_reported.csv. Monthly_Data preserves the 792 relevant partner/World observations from the governed WP005 monthly inputs packaged with WP006.
A35: Tariffs preserves 40 country/CN8 rows from WP004 Tariff_Matrix, with the 12% fallback from Origin_Rules. APPAREL footprint counts come from NEXT_WP006_supplier_country_product_footprint.csv.
A36: Candidate_Gates implements WP007 mandatory gates and D008/D020 (docs/Research_Question_and_Scope.md). Dated candidate evidence is required before clearance.
A37: Additional references: WP004 Basket_Representativeness, China row (337,824,810 / 394,606,825 = 85.61% synthetic-pair value); Commodity_Shortlist!G2:G5. D010, H5 and Q2.6/Q5.2: docs/Research_Question_and_Scope.md.
