Workbook

Sheet README
A1: NEXT WP005 — HMRC Monthly Trade Extraction
A2: Controlled monthly evidence for the four locked CN8 codes, with source reconciliation and quality checks.
A4: Field | B4: Value
A5: Work package | B5: WP005 — monthly HMRC extraction and SQL-ready preparation
A6: Status | B6: Final monthly-trade evidence; QC complete; fixed extracts used in WP006 SQL core
A7: Data cut | B7: 2019-01 through 2026-06 (90 months)
A8: Reporting treatment | B8: 2019-2025 complete calendar years; 2026 H1/YTD June reported separately
A9: Core CN8 codes | B9: 61091000, 61103099, 62044300, 62052000
A10: Reserve code | B10: 62063000 remains inactive and was not extracted
A11: Selected partner countries | B11: Bangladesh, Cambodia, China, India, Morocco, Myanmar, Pakistan, Sri Lanka, Turkey and Vietnam
A12: World denominator | B12: EU imports (FlowTypeId 1) plus non-EU imports (FlowTypeId 3), stored separately from partner-country facts
A13: Raw evidence | B13: 3,588 partner rows; 720 World-flow rows; no pagination
A14: Final analytical rows | B14: 3,600 partner rows; 360 World rows
A15: No-API-record combinations | B15: 12; retained explicitly with zero measures and record_status=NO_API_RECORD
... A19: Primary key | B19: cn8_code + partner_country_iso2 + month_id + flow
A21: Formula and interpretation rules
A22: Metric | B22: Rule | C22: Control | D22: Interpretation
A23: Observed unit value | B23: import_value_gbp / net_mass_kg | C23: Calculate only where net mass is positive. | D23: Market import unit value; not NEXT FOB or an item price.
A24: Aggregated unit value | B24: SUM(import_value_gbp) / SUM(net_mass_kg) | C24: Never average row-level unit values. | D24: Avoids mix-weighting error.
A25: Partner value share | B25: partner import value / World import value | C25: Join on CN8 and month. | D25: World is a denominator, never an additional partner row.
A26: Mass coverage | B26: value with positive mass / total value | C26: Locked pass threshold 99.5%. | D26: A zero-value no-API-record month does not reduce coverage.
A27: Rest of World | B27: World value - sum(selected ten partner values) | C27: Must never be negative. | D27: Captures countries outside the selected set without downloading every country.
A28: 2026 comparison | B28: 2026 H1 versus 2025 H1 | C28: Do not compare H1 2026 with full-year 2025. | D28: No post-CETA outturn claim; CETA began 15 July 2026.
A29: Unit-value exception review | B29: monthly unit value / full-period reference median | C29: Primary 2.5x multiplier with 2x/3x/4x sensitivity counts; retain official-data base | D29: Diagnostic only; REVIEW is not proof of error
A30: Sheet guide
A31: Sheet / group | B31: Purpose
A32: Scope_Contract | B32: Locked boundary, terminology and handoff rules
A33: Source_Register / Query_Manifest | B33: Evidence lineage, replay URLs, hashes, bytes and row counts
A34: dim_* | B34: Stable code, geography and month dimensions
A35: raw_* | B35: Unaltered API-returned grouped records represented as rows
A36: fct_* | B36: Final one-row-per-grain tables; suitable for SQL loading
A37: Reconciliation | B37: Population controls, annual context, 2025 tie-back and missing-record detail
A38: Mass_Coverage_QC / QC_Checks | B38: Coverage gate and formal validation evidence
A39: Data_Dictionary / SQL_Load_Map | B39: Field meanings, types, keys and target tables
A40: Unit_Value_Review_QC | B40: Review counts, threshold sensitivity, material examples and downstream handling

Sheet Scope_Contract
A1: WP005 Scope Contract
A2: Operational contract inherited from WP004 and refined only where HMRC field semantics required a more accurate label.
A4: Contract_ID | B4: Area | C4: Locked treatment | D4: Control / implication | E4: Status
A5: W5C01 | B5: Product scope | C5: Exactly four core CN8s: 61091000, 61103099, 62044300, 62052000 | D5: Reserve 62063000 remains inactive | E5: Confirmed
A6: W5C02 | B6: Period | C6: Monthly 2019-01 to 2026-06 | D6: 2019-2025 full calendar years; 2026 H1 separately | E6: Confirmed
A7: W5C03 | B7: Trade flow | C7: UK imports only | D7: FlowTypeId 3 for the ten non-EU partners; FlowTypeIds 1+3 for World | E7: Confirmed
A8: W5C04 | B8: Partner scope | C8: Ten named partner countries plus a separate inclusive World denominator | D8: Do not extract every country; derive Rest of World by subtraction | E8: Confirmed
A9: W5C05 | B9: Country meaning | C9: Use partner_country / country_of_dispatch terminology | D9: Do not present HMRC partner country as manufacturing origin | E9: Confirmed for WP005
A10: W5C06 | B10: Extraction grain | C10: Raw: month x CN8 x partner/flow x suppression index | D10: Final: month x CN8 x partner x import flow | E10: Confirmed
A11: W5C07 | B11: Measures | C11: Value, NetMass, SuppUnit and SuppressionIndex | D11: Retain raw measures before derivation | E11: Confirmed
A12: W5C08 | B12: Valuation | C12: HMRC import statistical value is CIF-style and excludes UK duty/tax | D12: Do not add international freight again | E12: Confirmed
A13: W5C09 | B13: No API row | C13: Retain a complete 3,600-row panel with api_row_present_flag and record_status | D13: Zero measures are analytical placeholders only where the API returned no grouped record | E13: Confirmed
A14: W5C10 | B14: Mass gate | C14: Value with positive mass / total value must be at least 99.5% | D14: Review any value-without-mass observation; reserve-code trigger remains available | E14: Confirmed
A15: W5C11 | B15: 2026 comparison | C15: Compare H1 2026 only with H1 2025 or other H1 periods | D15: No post-CETA behavioural inference | E15: Confirmed
... A18: W5C14 | B18: Unit-value exception review | C18: Use 2.50x from the full-period median (reciprocal lower bound 0.40x) as a provisional monthly review parameter within CN8 x partner and CN8 x World; disclose 2x/2.5x/3x/4x sensitivity counts. | D18: Diagnostic only: retain official observations in the base case; REVIEW is not proof of error; show a separately labelled exclusion sensitivity. | E18: Approved for diagnostic use

Sheet Source_Register
A1: WP005 Source Register
A2: Only the two monthly API extracts are new evidence; WP004 lookups and official methodology are reused without duplication.
A4: Source_ID | B4: Source_Type | C4: Official source | D4: Publisher | E4: Reporting period / date | F4: Local evidence filename | G4: Official / replay URL | H4: Used for | I4: Status | J4: Known limitation
A5: EXT_HMRC_OTS_WP005_PARTNER_MONTHLY | B5: Trade data | C5: HMRC UK Trade Info OTS API | D5: HM Revenue & Customs | E5: 2019-01 to 2026-06 | F5: EXT_HMRC_OTS_WP005_Core4_10PartnerCountries_Monthly_2019-01_to_2026-06_Raw_2026-08-26.json | G5: https://api.uktradeinfo.com/OTS?%24apply=filter%28MonthId+ge+201901+and+MonthId+le+202606+and+FlowTypeId+eq+3+and+%28CountryId+eq+52+or+CountryId+eq+204+or+CountryId+eq+662+or+CountryId+eq+664+or+CountryId+eq+666+or+CountryId+eq+669+or+CountryId+eq+676+or+CountryId+eq+690+or+CountryId+eq+696+or+CountryId+eq+720%29+and+%28CommodityId+eq+61091000+or+CommodityId+eq+61103099+or+CommodityId+eq+62044300+or+CommodityId+eq+62052000%29%29%2Fgroupby%28%28MonthId%2CCommodityId%2CCountryId%2CFlowTypeId%2CSuppressionIndex%29%2Caggregate%28Value+with+sum+as+Value%2CNetMass+with+sum+as+NetMass%2CSuppUnit+with+sum+as+SuppUnit%29%29 | H5: Monthly core-four imports for ten selected partner countries | I5: Retrieved and reconciled | J5: Country field is country-of-dispatch / partner basis
A6: EXT_HMRC_OTS_WP005_WORLD_MONTHLY | B6: Trade data | C6: HMRC UK Trade Info OTS API | D6: HM Revenue & Customs | E6: 2019-01 to 2026-06 | F6: EXT_HMRC_OTS_WP005_Core4_World_Monthly_2019-01_to_2026-06_Raw_2026-08-26.json | G6: https://api.uktradeinfo.com/OTS?%24apply=filter%28MonthId+ge+201901+and+MonthId+le+202606+and+%28FlowTypeId+eq+1+or+FlowTypeId+eq+3%29+and+%28CommodityId+eq+61091000+or+CommodityId+eq+61103099+or+CommodityId+eq+62044300+or+CommodityId+eq+62052000%29%29%2Fgroupby%28%28MonthId%2CCommodityId%2CFlowTypeId%2CSuppressionIndex%29%2Caggregate%28Value+with+sum+as+Value%2CNetMass+with+sum+as+NetMass%2CSuppUnit+with+sum+as+SuppUnit%29%29 | H6: Monthly inclusive World denominator | I6: Retrieved and reconciled | J6: EU and non-EU flows combined only after extraction
A7: EXT_HMRC_OTS | B7: Reference data | C7: WP004 commodity and country lookups | D7: HM Revenue & Customs | E7: Current at 2026-08-25 | F7: NEXT_WP004_API_Evidence_JSON_Closed_2026-08-26.zip | G7: https://www.uktradeinfo.com/api-documentation | H7: CN8 descriptions and HMRC country/ISO mapping | I7: Reused; no duplicate download | J7: Live reference data can change
A8: EXT_HMRC_API | B8: API documentation | C8: HM Revenue and Customs UK Trade Info API | D8: HM Revenue & Customs | E8: Current | F8: HMRC_UK_Trade_Info_API_Documentation_2026.pdf | G8: https://www.uktradeinfo.com/api-documentation | H8: Endpoint, pagination and field mechanics | I8: Reviewed | J8: Web documentation may be updated
A9: EXT_HMRC_SPEC | B9: Methodology | C9: Overseas trade in goods methodology and quality report | D9: HM Revenue & Customs | E9: Published 2025-12-09 | F9: HMRC_OTS_Methodology_and_Quality_Report_2025.pdf | G9: https://www.gov.uk/government/statistics/overseas-trade-statistics-methodologies/overseas-trade-in-goods-statistics-methodology-and-quality-report--3 | H9: CIF valuation, mass estimation, suppression, revisions and comparability | I9: Reviewed | J9: Provisional figures may be revised
A10: EXT_HMRC_JUN26 | B10: Release notice | C10: UK overseas trade in goods statistics: June 2026 | D10: HM Revenue & Customs | E10: Published 2026-08-13 | F10: HMRC_UK_OTS_June_2026_Release.pdf | G10: https://www.uktradeinfo.com/news/uk-overseas-trade-in-goods-statistics-june-2026/ | H10: Confirms latest complete month for the extraction | I10: Reviewed | J10: Summary release, not the detailed CN8 data
A11: EXT_HMRC_COD | B11: Methodology evidence | C11: UK imports by country of origin and country of dispatch, 2024 | D11: HM Revenue & Customs | E11: Published 2026-05-21 | F11: HMRC_UK_Imports_CoO_vs_CoD_2024.pdf | G11: https://www.gov.uk/government/statistics/uk-import-trade-in-goods-by-country-of-origin-and-country-of-dispatch-2024/uk-import-trade-in-goods-by-country-of-origin-and-country-of-dispatch-2024 | H11: Supports partner-country / country-of-dispatch labelling | I11: Reviewed | J11: Ad hoc 2024 comparison; not the WP005 monthly dataset

Sheet Query_Manifest
A1: HMRC Query Manifest
A2: Canonical replay information for the two immutable WP005 raw JSON responses.
A4: Query_ID | B4: Source_ID | C4: Purpose | D4: Endpoint | E4: Filter / scope | F4: Grouping / aggregation | G4: Canonical replay URL | H4: Evidence file | I4: SHA256 | J4: Bytes | K4: Rows | L4: NextLink present? | M4: Reporting period | N4: Retrieval timestamp UTC | O4: Reconciliation | P4: Notes
A5: W5Q01 | B5: EXT_HMRC_OTS_WP005_PARTNER_MONTHLY | C5: Core-four monthly imports for ten selected non-EU partner countries | D5: /OTS | E5: MonthId 201901-202606; FlowTypeId=3; four locked CN8s; ten selected CountryIds | F5: Group by MonthId, CommodityId, CountryId, FlowTypeId, SuppressionIndex; sum Value, NetMass, SuppUnit | G5: https://api.uktradeinfo.com/OTS?%24apply=filter%28MonthId+ge+201901+and+MonthId+le+202606+and+FlowTypeId+eq+3+and+%28CountryId+eq+52+or+CountryId+eq+204+or+CountryId+eq+662+or+CountryId+eq+664+or+CountryId+eq+666+or+CountryId+eq+669+or+CountryId+eq+676+or+CountryId+eq+690+or+CountryId+eq+696+or+CountryId+eq+720%29+and+%28CommodityId+eq+61091000+or+CommodityId+eq+61103099+or+CommodityId+eq+62044300+or+CommodityId+eq+62052000%29%29%2Fgroupby%28%28MonthId%2CCommodityId%2CCountryId%2CFlowTypeId%2CSuppressionIndex%29%2Caggregate%28Value+with+sum+as+Value%2CNetMass+with+sum+as+NetMass%2CSuppUnit+with+sum+as+SuppUnit%29%29 | H5: EXT_HMRC_OTS_WP005_Core4_10PartnerCountries_Monthly_2019-01_to_2026-06_Raw_2026-08-26.json | I5: 37109cf0da13cf9f51e353589b8ea54d539ec01a8d387ec531ab90b45d449469 | J5: 596978 | K5: 3588 | L5: No | M5: 2019-01 to 2026-06 | N5: 46260.818 | O5: PASS - 2025 values/mass reconcile to WP004 | P5: Partner-country field follows HMRC OTS country-of-dispatch convention; do not label as manufacturing origin.
A6: W5Q02 | B6: EXT_HMRC_OTS_WP005_WORLD_MONTHLY | C6: Core-four monthly World denominator across EU and non-EU import flows | D6: /OTS | E6: MonthId 201901-202606; FlowTypeId=1 or 3; four locked CN8s; no country filter | F6: Group by MonthId, CommodityId, FlowTypeId, SuppressionIndex; sum Value, NetMass, SuppUnit | G6: https://api.uktradeinfo.com/OTS?%24apply=filter%28MonthId+ge+201901+and+MonthId+le+202606+and+%28FlowTypeId+eq+1+or+FlowTypeId+eq+3%29+and+%28CommodityId+eq+61091000+or+CommodityId+eq+61103099+or+CommodityId+eq+62044300+or+CommodityId+eq+62052000%29%29%2Fgroupby%28%28MonthId%2CCommodityId%2CFlowTypeId%2CSuppressionIndex%29%2Caggregate%28Value+with+sum+as+Value%2CNetMass+with+sum+as+NetMass%2CSuppUnit+with+sum+as+SuppUnit%29%29 | H6: EXT_HMRC_OTS_WP005_Core4_World_Monthly_2019-01_to_2026-06_Raw_2026-08-26.json | I6: 678a6a10ed9288e5083f7b7a0f444d61563eb4fc71b39d901001c3ac086634d2 | J6: 110968 | K6: 720 | L6: No | M6: 2019-01 to 2026-06 | N6: 46260.819 | O6: PASS - 2025 values/mass reconcile to WP004 | P6: EU and non-EU flows are kept in raw evidence and combined only in the World fact table.

Sheet dim_commodity
A1: cn8_code | B1: hs2_code | C1: hs4_code | D1: hs6_code | E1: description | F1: construction | G1: fibre | H1: basket_role | I1: inclusion_status
A2: 61091000 | B2: 61 | C2: 6109 | D2: 610910 | E2: T-shirts, singlets and other vests of cotton, knitted or crocheted | F2: Knitted | G2: Cotton | H2: Bangladesh-vs-India zero-duty contest | I2: Core
A3: 61103099 | B3: 61 | C3: 6110 | D3: 611030 | E3: Women's/girls' jerseys, pullovers, cardigans and similar of man-made fibres, residual line | F3: Knitted | G3: Man-made fibres | H3: China capability / duty exposure probe | I3: Core
A4: 62044300 | B4: 62 | C4: 6204 | D4: 620443 | E4: Women's/girls' dresses of synthetic fibres, not knitted or crocheted | F4: Woven | G4: Synthetic fibres | H4: China capability / duty exposure probe | I4: Core
A5: 62052000 | B5: 62 | C5: 6205 | D5: 620520 | E5: Men's/boys' shirts of cotton, not knitted or crocheted | F5: Woven | G5: Cotton | H5: Bangladesh-vs-India zero-duty contest | I5: Core
A6: 62063000 | B6: 62 | C6: 6206 | D6: 620630 | E6: Women's/girls' blouses and shirts of cotton, not knitted or crocheted | F6: Woven | G6: Cotton | H6: Reserve India representation code | I6: Reserve - inactive; not extracted

Sheet dim_partner_country
A1: partner_country_id | B1: country_code_numeric | C1: partner_country_iso2 | D1: partner_country_name | E1: hmrc_flow_type_id | F1: scope_status | G1: geographical_basis
A2: 52 | B2: 052 | C2: TR | D2: Turkey | E2: 3 | F2: Selected partner country | G2: HMRC OTS country of dispatch / partner-country basis
A3: 204 | B3: 204 | C3: MA | D3: Morocco | E3: 3 | F3: Selected partner country | G3: HMRC OTS country of dispatch / partner-country basis
A4: 662 | B4: 662 | C4: PK | D4: Pakistan | E4: 3 | F4: Selected partner country | G4: HMRC OTS country of dispatch / partner-country basis
A5: 664 | B5: 664 | C5: IN | D5: India | E5: 3 | F5: Selected partner country | G5: HMRC OTS country of dispatch / partner-country basis
A6: 666 | B6: 666 | C6: BD | D6: Bangladesh | E6: 3 | F6: Selected partner country | G6: HMRC OTS country of dispatch / partner-country basis
A7: 669 | B7: 669 | C7: LK | D7: Sri Lanka | E7: 3 | F7: Selected partner country | G7: HMRC OTS country of dispatch / partner-country basis
A8: 676 | B8: 676 | C8: MM | D8: Myanmar | E8: 3 | F8: Selected partner country | G8: HMRC OTS country of dispatch / partner-country basis
A9: 690 | B9: 690 | C9: VN | D9: Vietnam | E9: 3 | F9: Selected partner country | G9: HMRC OTS country of dispatch / partner-country basis
A10: 696 | B10: 696 | C10: KH | D10: Cambodia | E10: 3 | F10: Selected partner country | G10: HMRC OTS country of dispatch / partner-country basis
A11: 720 | B11: 720 | C11: CN | D11: China | E11: 3 | F11: Selected partner country | G11: HMRC OTS country of dispatch / partner-country basis

Sheet dim_month
A1: month_id | B1: month_date | C1: calendar_year | D1: month_number | E1: month_name | F1: calendar_quarter | G1: half_year | H1: complete_calendar_year_flag | I1: ytd_2026_flag | J1: like_for_like_h1_flag
A2: 201901 | B2: 43466 | C2: 2019 | D2: 1 | E2: January | F2: Q1 | G2: H1 | H2: 1 | I2: 0 | J2: 1
A3: 201902 | B3: 43497 | C3: 2019 | D3: 2 | E3: February | F3: Q1 | G3: H1 | H3: 1 | I3: 0 | J3: 1
A4: 201903 | B4: 43525 | C4: 2019 | D4: 3 | E4: March | F4: Q1 | G4: H1 | H4: 1 | I4: 0 | J4: 1
A5: 201904 | B5: 43556 | C5: 2019 | D5: 4 | E5: April | F5: Q2 | G5: H1 | H5: 1 | I5: 0 | J5: 1
A6: 201905 | B6: 43586 | C6: 2019 | D6: 5 | E6: May | F6: Q2 | G6: H1 | H6: 1 | I6: 0 | J6: 1
A7: 201906 | B7: 43617 | C7: 2019 | D7: 6 | E7: June | F7: Q2 | G7: H1 | H7: 1 | I7: 0 | J7: 1
A8: 201907 | B8: 43647 | C8: 2019 | D8: 7 | E8: July | F8: Q3 | G8: H2 | H8: 1 | I8: 0 | J8: 0
A9: 201908 | B9: 43678 | C9: 2019 | D9: 8 | E9: August | F9: Q3 | G9: H2 | H9: 1 | I9: 0 | J9: 0
A10: 201909 | B10: 43709 | C10: 2019 | D10: 9 | E10: September | F10: Q3 | G10: H2 | H10: 1 | I10: 0 | J10: 0
A11: 201910 | B11: 43739 | C11: 2019 | D11: 10 | E11: October | F11: Q4 | G11: H2 | H11: 1 | I11: 0 | J11: 0
A12: 201911 | B12: 43770 | C12: 2019 | D12: 11 | E12: November | F12: Q4 | G12: H2 | H12: 1 | I12: 0 | J12: 0
A13: 201912 | B13: 43800 | C13: 2019 | D13: 12 | E13: December | F13: Q4 | G13: H2 | H13: 1 | I13: 0 | J13: 0
... A91: 202606 | B91: 46174 | C91: 2026 | D91: 6 | E91: June | F91: Q2 | G91: H1 | H91: 0 | I91: 1 | J91: 1

Sheet raw_partner_monthly
A1: source_query_id | B1: source_record_no | C1: month_id | D1: commodity_id | E1: country_id | F1: flow_type_id | G1: suppression_index | H1: supp_unit | I1: net_mass | J1: value_gbp | K1: source_file
A2: W5Q01 | B2: 1 | C2: 201901 | D2: 61091000 | E2: 52 | F2: 3 | G2: 0 | H2: 3275398 | I2: 583502 | J2: 11803255 | K2: EXT_HMRC_OTS_WP005_Core4_10PartnerCountries_Monthly_2019-01_to_2026-06_Raw_2026-08-26.json
A3: W5Q01 | B3: 2 | C3: 201901 | D3: 61091000 | E3: 204 | F3: 3 | G3: 0 | H3: 419760 | I3: 65037 | J3: 585401 | K3: EXT_HMRC_OTS_WP005_Core4_10PartnerCountries_Monthly_2019-01_to_2026-06_Raw_2026-08-26.json
A4: W5Q01 | B4: 3 | C4: 201901 | D4: 61091000 | E4: 662 | F4: 3 | G4: 0 | H4: 876746 | I4: 237071 | J4: 2434227 | K4: EXT_HMRC_OTS_WP005_Core4_10PartnerCountries_Monthly_2019-01_to_2026-06_Raw_2026-08-26.json
A5: W5Q01 | B5: 4 | C5: 201901 | D5: 61091000 | E5: 664 | F5: 3 | G5: 0 | H5: 5479197 | I5: 809198 | J5: 11462560 | K5: EXT_HMRC_OTS_WP005_Core4_10PartnerCountries_Monthly_2019-01_to_2026-06_Raw_2026-08-26.json
A6: W5Q01 | B6: 5 | C6: 201901 | D6: 61091000 | E6: 666 | F6: 3 | G6: 0 | H6: 20912727 | I6: 3063058 | J6: 31071303 | K6: EXT_HMRC_OTS_WP005_Core4_10PartnerCountries_Monthly_2019-01_to_2026-06_Raw_2026-08-26.json
A7: W5Q01 | B7: 6 | C7: 201901 | D7: 61091000 | E7: 669 | F7: 3 | G7: 0 | H7: 1425640 | I7: 195374 | J7: 2899724 | K7: EXT_HMRC_OTS_WP005_Core4_10PartnerCountries_Monthly_2019-01_to_2026-06_Raw_2026-08-26.json
A8: W5Q01 | B8: 7 | C8: 201901 | D8: 61091000 | E8: 676 | F8: 3 | G8: 0 | H8: 72843 | I8: 8991 | J8: 130735 | K8: EXT_HMRC_OTS_WP005_Core4_10PartnerCountries_Monthly_2019-01_to_2026-06_Raw_2026-08-26.json
A9: W5Q01 | B9: 8 | C9: 201901 | D9: 61091000 | E9: 690 | F9: 3 | G9: 0 | H9: 907773 | I9: 129933 | J9: 2130290 | K9: EXT_HMRC_OTS_WP005_Core4_10PartnerCountries_Monthly_2019-01_to_2026-06_Raw_2026-08-26.json
A10: W5Q01 | B10: 9 | C10: 201901 | D10: 61091000 | E10: 696 | F10: 3 | G10: 0 | H10: 596102 | I10: 116043 | J10: 1625044 | K10: EXT_HMRC_OTS_WP005_Core4_10PartnerCountries_Monthly_2019-01_to_2026-06_Raw_2026-08-26.json
A11: W5Q01 | B11: 10 | C11: 201901 | D11: 61091000 | E11: 720 | F11: 3 | G11: 0 | H11: 2250468 | I11: 421440 | J11: 7421237 | K11: EXT_HMRC_OTS_WP005_Core4_10PartnerCountries_Monthly_2019-01_to_2026-06_Raw_2026-08-26.json
A12: W5Q01 | B12: 11 | C12: 201901 | D12: 61103099 | E12: 52 | F12: 3 | G12: 0 | H12: 1619995 | I12: 514509 | J12: 9735289 | K12: EXT_HMRC_OTS_WP005_Core4_10PartnerCountries_Monthly_2019-01_to_2026-06_Raw_2026-08-26.json
A13: W5Q01 | B13: 12 | C13: 201901 | D13: 61103099 | E13: 204 | F13: 3 | G13: 0 | H13: 63819 | I13: 21338 | J13: 425648 | K13: EXT_HMRC_OTS_WP005_Core4_10PartnerCountries_Monthly_2019-01_to_2026-06_Raw_2026-08-26.json
... A3589: W5Q01 | B3589: 3588 | C3589: 202606 | D3589: 62052000 | E3589: 720 | F3589: 3 | G3589: 0 | H3589: 133261 | I3589: 44185 | J3589: 824050 | K3589: EXT_HMRC_OTS_WP005_Core4_10PartnerCountries_Monthly_2019-01_to_2026-06_Raw_2026-08-26.json

Sheet raw_world_monthly
A1: source_query_id | B1: source_record_no | C1: month_id | D1: commodity_id | E1: flow_type_id | F1: suppression_index | G1: supp_unit | H1: net_mass | I1: value_gbp | J1: source_file
A2: W5Q02 | B2: 1 | C2: 201901 | D2: 61091000 | E2: 1 | F2: 0 | G2: 6244608 | H2: 1481908 | I2: 35985209 | J2: EXT_HMRC_OTS_WP005_Core4_World_Monthly_2019-01_to_2026-06_Raw_2026-08-26.json
A3: W5Q02 | B3: 2 | C3: 201901 | D3: 61091000 | E3: 3 | F3: 0 | G3: 38767222 | H3: 6093137 | I3: 80208250 | J3: EXT_HMRC_OTS_WP005_Core4_World_Monthly_2019-01_to_2026-06_Raw_2026-08-26.json
A4: W5Q02 | B4: 3 | C4: 201901 | D4: 61103099 | E4: 1 | F4: 0 | G4: 1405722 | H4: 576538 | I4: 13578781 | J4: EXT_HMRC_OTS_WP005_Core4_World_Monthly_2019-01_to_2026-06_Raw_2026-08-26.json
A5: W5Q02 | B5: 4 | C5: 201901 | D5: 61103099 | E5: 3 | F5: 0 | G5: 9119844 | H5: 3055918 | I5: 47371893 | J5: EXT_HMRC_OTS_WP005_Core4_World_Monthly_2019-01_to_2026-06_Raw_2026-08-26.json
A6: W5Q02 | B6: 5 | C6: 201901 | D6: 62044300 | E6: 1 | F6: 0 | G6: 825232 | H6: 370783 | I6: 12076146 | J6: EXT_HMRC_OTS_WP005_Core4_World_Monthly_2019-01_to_2026-06_Raw_2026-08-26.json
A7: W5Q02 | B7: 6 | C7: 201901 | D7: 62044300 | E7: 3 | F7: 0 | G7: 3192668 | H7: 1052946 | I7: 29720603 | J7: EXT_HMRC_OTS_WP005_Core4_World_Monthly_2019-01_to_2026-06_Raw_2026-08-26.json
A8: W5Q02 | B8: 7 | C8: 201901 | D8: 62052000 | E8: 1 | F8: 0 | G8: 642842 | H8: 247078 | I8: 11020709 | J8: EXT_HMRC_OTS_WP005_Core4_World_Monthly_2019-01_to_2026-06_Raw_2026-08-26.json
A9: W5Q02 | B9: 8 | C9: 201901 | D9: 62052000 | E9: 3 | F9: 0 | G9: 4548480 | H9: 1380647 | I9: 27996728 | J9: EXT_HMRC_OTS_WP005_Core4_World_Monthly_2019-01_to_2026-06_Raw_2026-08-26.json
A10: W5Q02 | B10: 9 | C10: 201902 | D10: 61091000 | E10: 1 | F10: 0 | G10: 5912322 | H10: 1388810 | I10: 36142839 | J10: EXT_HMRC_OTS_WP005_Core4_World_Monthly_2019-01_to_2026-06_Raw_2026-08-26.json
A11: W5Q02 | B11: 10 | C11: 201902 | D11: 61091000 | E11: 3 | F11: 0 | G11: 39948795 | H11: 6198768 | I11: 75712600 | J11: EXT_HMRC_OTS_WP005_Core4_World_Monthly_2019-01_to_2026-06_Raw_2026-08-26.json
A12: W5Q02 | B12: 11 | C12: 201902 | D12: 61103099 | E12: 1 | F12: 0 | G12: 1028059 | H12: 381789 | I12: 9258019 | J12: EXT_HMRC_OTS_WP005_Core4_World_Monthly_2019-01_to_2026-06_Raw_2026-08-26.json
A13: W5Q02 | B13: 12 | C13: 201902 | D13: 61103099 | E13: 3 | F13: 0 | G13: 5550700 | H13: 1785137 | I13: 26284848 | J13: EXT_HMRC_OTS_WP005_Core4_World_Monthly_2019-01_to_2026-06_Raw_2026-08-26.json
... A721: W5Q02 | B721: 720 | C721: 202606 | D721: 62052000 | E721: 3 | F721: 0 | G721: 1767724 | H721: 592015 | I721: 12257949 | J721: EXT_HMRC_OTS_WP005_Core4_World_Monthly_2019-01_to_2026-06_Raw_2026-08-26.json

Sheet fct_partner_monthly
A1: monthly_import_key | B1: month_date | C1: month_id | D1: calendar_year | E1: calendar_month | F1: cn8_code | G1: hs4_code | H1: partner_country_id | I1: partner_country_iso2 | J1: partner_country_name | K1: flow | L1: flow_type_id | M1: api_row_present_flag | N1: record_status | O1: suppression_index_list | P1: suppression_flag | Q1: import_value_gbp | R1: net_mass_kg | S1: supplementary_quantity | T1: mass_status | U1: unit_value_gbp_per_kg | V1: world_import_value_gbp | W1: partner_value_share | X1: source_query_id | Y1: source_file | Z1: reference_median_unit_value_gbp_per_kg | AA1: unit_value_ratio_to_reference_median | AB1: unit_value_review_flag_2_5x
A2: 61091000_TR_201901_IMPORT | B2: 43466 | C2: 201901 | D2: 2019 | E2: 1 | F2: 61091000 | G2: 6109 | H2: 52 | I2: TR | J2: Turkey | K2: IMPORT | L2: 3 | M2: 1 | N2: REPORTED | O2: 0 | P2: 0 | Q2: 11803255 | R2: 583502 | S2: 3275398 | T2: USABLE | U2: =IF(R2>0,Q2/R2,"") -> 20.228303 | V2: =SUMIFS(fct_world_monthly!$J$2:$J$361,fct_world_monthly!$C$2:$C$361,C2,fct_world_monthly!$F$2:$F$361,F2) -> 116193459 | W2: =IF(V2>0,Q2/V2,"") -> 0.10158278 | X2: W5Q01 | Y2: EXT_HMRC_OTS_WP005_Core4_10PartnerCountries_Monthly_2019-01_to_2026-06_Raw_2026-08-26.json | Z2: =IF(U2="","",SUMIFS(Unit_Value_Review_QC!$K$10:$K$53,Unit_Value_Review_QC!$I$10:$I$53,"PARTNER|"&F2&"|"&I2)) -> 20.461445 | AA2: =IFERROR(U2/Z2,"") -> 0.98860578 | AB2: =IF(OR(N2<>"REPORTED",U2=""),"NOT_APPLICABLE",IF(OR(AA2<Unit_Value_Review_QC!$I$6,AA2>Unit_Value_Review_QC!$I$5),"REVIEW","WITHIN_BAND")) -> WITHIN_BAND
A3: 61091000_MA_201901_IMPORT | B3: 43466 | C3: 201901 | D3: 2019 | E3: 1 | F3: 61091000 | G3: 6109 | H3: 204 | I3: MA | J3: Morocco | K3: IMPORT | L3: 3 | M3: 1 | N3: REPORTED | O3: 0 | P3: 0 | Q3: 585401 | R3: 65037 | S3: 419760 | T3: USABLE | U3: =IF(R3>0,Q3/R3,"") -> 9.0010456 | V3: =SUMIFS(fct_world_monthly!$J$2:$J$361,fct_world_monthly!$C$2:$C$361,C3,fct_world_monthly!$F$2:$F$361,F3) -> 116193459 | W3: =IF(V3>0,Q3/V3,"") -> 0.005038158 | X3: W5Q01 | Y3: EXT_HMRC_OTS_WP005_Core4_10PartnerCountries_Monthly_2019-01_to_2026-06_Raw_2026-08-26.json | Z3: =IF(U3="","",SUMIFS(Unit_Value_Review_QC!$K$10:$K$53,Unit_Value_Review_QC!$I$10:$I$53,"PARTNER|"&F3&"|"&I3)) -> 7.8392981 | AA3: =IFERROR(U3/Z3,"") -> 1.1481953 | AB3: =IF(OR(N3<>"REPORTED",U3=""),"NOT_APPLICABLE",IF(OR(AA3<Unit_Value_Review_QC!$I$6,AA3>Unit_Value_Review_QC!$I$5),"REVIEW","WITHIN_BAND")) -> WITHIN_BAND
A4: 61091000_PK_201901_IMPORT | B4: 43466 | C4: 201901 | D4: 2019 | E4: 1 | F4: 61091000 | G4: 6109 | H4: 662 | I4: PK | J4: Pakistan | K4: IMPORT | L4: 3 | M4: 1 | N4: REPORTED | O4: 0 | P4: 0 | Q4: 2434227 | R4: 237071 | S4: 876746 | T4: USABLE | U4: =IF(R4>0,Q4/R4,"") -> 10.267924 | V4: =SUMIFS(fct_world_monthly!$J$2:$J$361,fct_world_monthly!$C$2:$C$361,C4,fct_world_monthly!$F$2:$F$361,F4) -> 116193459 | W4: =IF(V4>0,Q4/V4,"") -> 0.020949777 | X4: W5Q01 | Y4: EXT_HMRC_OTS_WP005_Core4_10PartnerCountries_Monthly_2019-01_to_2026-06_Raw_2026-08-26.json | Z4: =IF(U4="","",SUMIFS(Unit_Value_Review_QC!$K$10:$K$53,Unit_Value_Review_QC!$I$10:$I$53,"PARTNER|"&F4&"|"&I4)) -> 10.235891 | AA4: =IFERROR(U4/Z4,"") -> 1.0031294 | AB4: =IF(OR(N4<>"REPORTED",U4=""),"NOT_APPLICABLE",IF(OR(AA4<Unit_Value_Review_QC!$I$6,AA4>Unit_Value_Review_QC!$I$5),"REVIEW","WITHIN_BAND")) -> WITHIN_BAND
A5: 61091000_IN_201901_IMPORT | B5: 43466 | C5: 201901 | D5: 2019 | E5: 1 | F5: 61091000 | G5: 6109 | H5: 664 | I5: IN | J5: India | K5: IMPORT | L5: 3 | M5: 1 | N5: REPORTED | O5: 0 | P5: 0 | Q5: 11462560 | R5: 809198 | S5: 5479197 | T5: USABLE | U5: =IF(R5>0,Q5/R5,"") -> 14.165334 | V5: =SUMIFS(fct_world_monthly!$J$2:$J$361,fct_world_monthly!$C$2:$C$361,C5,fct_world_monthly!$F$2:$F$361,F5) -> 116193459 | W5: =IF(V5>0,Q5/V5,"") -> 0.098650648 | X5: W5Q01 | Y5: EXT_HMRC_OTS_WP005_Core4_10PartnerCountries_Monthly_2019-01_to_2026-06_Raw_2026-08-26.json | Z5: =IF(U5="","",SUMIFS(Unit_Value_Review_QC!$K$10:$K$53,Unit_Value_Review_QC!$I$10:$I$53,"PARTNER|"&F5&"|"&I5)) -> 13.59406 | AA5: =IFERROR(U5/Z5,"") -> 1.0420238 | AB5: =IF(OR(N5<>"REPORTED",U5=""),"NOT_APPLICABLE",IF(OR(AA5<Unit_Value_Review_QC!$I$6,AA5>Unit_Value_Review_QC!$I$5),"REVIEW","WITHIN_BAND")) -> WITHIN_BAND
A6: 61091000_BD_201901_IMPORT | B6: 43466 | C6: 201901 | D6: 2019 | E6: 1 | F6: 61091000 | G6: 6109 | H6: 666 | I6: BD | J6: Bangladesh | K6: IMPORT | L6: 3 | M6: 1 | N6: REPORTED | O6: 0 | P6: 0 | Q6: 31071303 | R6: 3063058 | S6: 20912727 | T6: USABLE | U6: =IF(R6>0,Q6/R6,"") -> 10.143883 | V6: =SUMIFS(fct_world_monthly!$J$2:$J$361,fct_world_monthly!$C$2:$C$361,C6,fct_world_monthly!$F$2:$F$361,F6) -> 116193459 | W6: =IF(V6>0,Q6/V6,"") -> 0.26741009 | X6: W5Q01 | Y6: EXT_HMRC_OTS_WP005_Core4_10PartnerCountries_Monthly_2019-01_to_2026-06_Raw_2026-08-26.json | Z6: =IF(U6="","",SUMIFS(Unit_Value_Review_QC!$K$10:$K$53,Unit_Value_Review_QC!$I$10:$I$53,"PARTNER|"&F6&"|"&I6)) -> 10.323148 | AA6: =IFERROR(U6/Z6,"") -> 0.98263474 | AB6: =IF(OR(N6<>"REPORTED",U6=""),"NOT_APPLICABLE",IF(OR(AA6<Unit_Value_Review_QC!$I$6,AA6>Unit_Value_Review_QC!$I$5),"REVIEW","WITHIN_BAND")) -> WITHIN_BAND
A7: 61091000_LK_201901_IMPORT | B7: 43466 | C7: 201901 | D7: 2019 | E7: 1 | F7: 61091000 | G7: 6109 | H7: 669 | I7: LK | J7: Sri Lanka | K7: IMPORT | L7: 3 | M7: 1 | N7: REPORTED | O7: 0 | P7: 0 | Q7: 2899724 | R7: 195374 | S7: 1425640 | T7: USABLE | U7: =IF(R7>0,Q7/R7,"") -> 14.841913 | V7: =SUMIFS(fct_world_monthly!$J$2:$J$361,fct_world_monthly!$C$2:$C$361,C7,fct_world_monthly!$F$2:$F$361,F7) -> 116193459 | W7: =IF(V7>0,Q7/V7,"") -> 0.024956 | X7: W5Q01 | Y7: EXT_HMRC_OTS_WP005_Core4_10PartnerCountries_Monthly_2019-01_to_2026-06_Raw_2026-08-26.json | Z7: =IF(U7="","",SUMIFS(Unit_Value_Review_QC!$K$10:$K$53,Unit_Value_Review_QC!$I$10:$I$53,"PARTNER|"&F7&"|"&I7)) -> 13.552232 | AA7: =IFERROR(U7/Z7,"") -> 1.0951638 | AB7: =IF(OR(N7<>"REPORTED",U7=""),"NOT_APPLICABLE",IF(OR(AA7<Unit_Value_Review_QC!$I$6,AA7>Unit_Value_Review_QC!$I$5),"REVIEW","WITHIN_BAND")) -> WITHIN_BAND
A8: 61091000_MM_201901_IMPORT | B8: 43466 | C8: 201901 | D8: 2019 | E8: 1 | F8: 61091000 | G8: 6109 | H8: 676 | I8: MM | J8: Myanmar | K8: IMPORT | L8: 3 | M8: 1 | N8: REPORTED | O8: 0 | P8: 0 | Q8: 130735 | R8: 8991 | S8: 72843 | T8: USABLE | U8: =IF(R8>0,Q8/R8,"") -> 14.540652 | V8: =SUMIFS(fct_world_monthly!$J$2:$J$361,fct_world_monthly!$C$2:$C$361,C8,fct_world_monthly!$F$2:$F$361,F8) -> 116193459 | W8: =IF(V8>0,Q8/V8,"") -> 0.0011251494 | X8: W5Q01 | Y8: EXT_HMRC_OTS_WP005_Core4_10PartnerCountries_Monthly_2019-01_to_2026-06_Raw_2026-08-26.json | Z8: =IF(U8="","",SUMIFS(Unit_Value_Review_QC!$K$10:$K$53,Unit_Value_Review_QC!$I$10:$I$53,"PARTNER|"&F8&"|"&I8)) -> 16.294942 | AA8: =IFERROR(U8/Z8,"") -> 0.89234142 | AB8: =IF(OR(N8<>"REPORTED",U8=""),"NOT_APPLICABLE",IF(OR(AA8<Unit_Value_Review_QC!$I$6,AA8>Unit_Value_Review_QC!$I$5),"REVIEW","WITHIN_BAND")) -> WITHIN_BAND
A9: 61091000_VN_201901_IMPORT | B9: 43466 | C9: 201901 | D9: 2019 | E9: 1 | F9: 61091000 | G9: 6109 | H9: 690 | I9: VN | J9: Vietnam | K9: IMPORT | L9: 3 | M9: 1 | N9: REPORTED | O9: 0 | P9: 0 | Q9: 2130290 | R9: 129933 | S9: 907773 | T9: USABLE | U9: =IF(R9>0,Q9/R9,"") -> 16.395296 | V9: =SUMIFS(fct_world_monthly!$J$2:$J$361,fct_world_monthly!$C$2:$C$361,C9,fct_world_monthly!$F$2:$F$361,F9) -> 116193459 | W9: =IF(V9>0,Q9/V9,"") -> 0.018333992 | X9: W5Q01 | Y9: EXT_HMRC_OTS_WP005_Core4_10PartnerCountries_Monthly_2019-01_to_2026-06_Raw_2026-08-26.json | Z9: =IF(U9="","",SUMIFS(Unit_Value_Review_QC!$K$10:$K$53,Unit_Value_Review_QC!$I$10:$I$53,"PARTNER|"&F9&"|"&I9)) -> 21.029827 | AA9: =IFERROR(U9/Z9,"") -> 0.77962106 | AB9: =IF(OR(N9<>"REPORTED",U9=""),"NOT_APPLICABLE",IF(OR(AA9<Unit_Value_Review_QC!$I$6,AA9>Unit_Value_Review_QC!$I$5),"REVIEW","WITHIN_BAND")) -> WITHIN_BAND
A10: 61091000_KH_201901_IMPORT | B10: 43466 | C10: 201901 | D10: 2019 | E10: 1 | F10: 61091000 | G10: 6109 | H10: 696 | I10: KH | J10: Cambodia | K10: IMPORT | L10: 3 | M10: 1 | N10: REPORTED | O10: 0 | P10: 0 | Q10: 1625044 | R10: 116043 | S10: 596102 | T10: USABLE | U10: =IF(R10>0,Q10/R10,"") -> 14.003809 | V10: =SUMIFS(fct_world_monthly!$J$2:$J$361,fct_world_monthly!$C$2:$C$361,C10,fct_world_monthly!$F$2:$F$361,F10) -> 116193459 | W10: =IF(V10>0,Q10/V10,"") -> 0.013985675 | X10: W5Q01 | Y10: EXT_HMRC_OTS_WP005_Core4_10PartnerCountries_Monthly_2019-01_to_2026-06_Raw_2026-08-26.json | Z10: =IF(U10="","",SUMIFS(Unit_Value_Review_QC!$K$10:$K$53,Unit_Value_Review_QC!$I$10:$I$53,"PARTNER|"&F10&"|"&I10)) -> 18.091181 | AA10: =IFERROR(U10/Z10,"") -> 0.77406824 | AB10: =IF(OR(N10<>"REPORTED",U10=""),"NOT_APPLICABLE",IF(OR(AA10<Unit_Value_Review_QC!$I$6,AA10>Unit_Value_Review_QC!$I$5),"REVIEW","WITHIN_BAND")) -> WITHIN_BAND
A11: 61091000_CN_201901_IMPORT | B11: 43466 | C11: 201901 | D11: 2019 | E11: 1 | F11: 61091000 | G11: 6109 | H11: 720 | I11: CN | J11: China | K11: IMPORT | L11: 3 | M11: 1 | N11: REPORTED | O11: 0 | P11: 0 | Q11: 7421237 | R11: 421440 | S11: 2250468 | T11: USABLE | U11: =IF(R11>0,Q11/R11,"") -> 17.609237 | V11: =SUMIFS(fct_world_monthly!$J$2:$J$361,fct_world_monthly!$C$2:$C$361,C11,fct_world_monthly!$F$2:$F$361,F11) -> 116193459 | W11: =IF(V11>0,Q11/V11,"") -> 0.063869662 | X11: W5Q01 | Y11: EXT_HMRC_OTS_WP005_Core4_10PartnerCountries_Monthly_2019-01_to_2026-06_Raw_2026-08-26.json | Z11: =IF(U11="","",SUMIFS(Unit_Value_Review_QC!$K$10:$K$53,Unit_Value_Review_QC!$I$10:$I$53,"PARTNER|"&F11&"|"&I11)) -> 18.213915 | AA11: =IFERROR(U11/Z11,"") -> 0.96680133 | AB11: =IF(OR(N11<>"REPORTED",U11=""),"NOT_APPLICABLE",IF(OR(AA11<Unit_Value_Review_QC!$I$6,AA11>Unit_Value_Review_QC!$I$5),"REVIEW","WITHIN_BAND")) -> WITHIN_BAND
A12: 61103099_TR_201901_IMPORT | B12: 43466 | C12: 201901 | D12: 2019 | E12: 1 | F12: 61103099 | G12: 6110 | H12: 52 | I12: TR | J12: Turkey | K12: IMPORT | L12: 3 | M12: 1 | N12: REPORTED | O12: 0 | P12: 0 | Q12: 9735289 | R12: 514509 | S12: 1619995 | T12: USABLE | U12: =IF(R12>0,Q12/R12,"") -> 18.921514 | V12: =SUMIFS(fct_world_monthly!$J$2:$J$361,fct_world_monthly!$C$2:$C$361,C12,fct_world_monthly!$F$2:$F$361,F12) -> 60950674 | W12: =IF(V12>0,Q12/V12,"") -> 0.15972406 | X12: W5Q01 | Y12: EXT_HMRC_OTS_WP005_Core4_10PartnerCountries_Monthly_2019-01_to_2026-06_Raw_2026-08-26.json | Z12: =IF(U12="","",SUMIFS(Unit_Value_Review_QC!$K$10:$K$53,Unit_Value_Review_QC!$I$10:$I$53,"PARTNER|"&F12&"|"&I12)) -> 19.213268 | AA12: =IFERROR(U12/Z12,"") -> 0.98481494 | AB12: =IF(OR(N12<>"REPORTED",U12=""),"NOT_APPLICABLE",IF(OR(AA12<Unit_Value_Review_QC!$I$6,AA12>Unit_Value_Review_QC!$I$5),"REVIEW","WITHIN_BAND")) -> WITHIN_BAND
A13: 61103099_MA_201901_IMPORT | B13: 43466 | C13: 201901 | D13: 2019 | E13: 1 | F13: 61103099 | G13: 6110 | H13: 204 | I13: MA | J13: Morocco | K13: IMPORT | L13: 3 | M13: 1 | N13: REPORTED | O13: 0 | P13: 0 | Q13: 425648 | R13: 21338 | S13: 63819 | T13: USABLE | U13: =IF(R13>0,Q13/R13,"") -> 19.947886 | V13: =SUMIFS(fct_world_monthly!$J$2:$J$361,fct_world_monthly!$C$2:$C$361,C13,fct_world_monthly!$F$2:$F$361,F13) -> 60950674 | W13: =IF(V13>0,Q13/V13,"") -> 0.0069834831 | X13: W5Q01 | Y13: EXT_HMRC_OTS_WP005_Core4_10PartnerCountries_Monthly_2019-01_to_2026-06_Raw_2026-08-26.json | Z13: =IF(U13="","",SUMIFS(Unit_Value_Review_QC!$K$10:$K$53,Unit_Value_Review_QC!$I$10:$I$53,"PARTNER|"&F13&"|"&I13)) -> 16.024819 | AA13: =IFERROR(U13/Z13,"") -> 1.244812 | AB13: =IF(OR(N13<>"REPORTED",U13=""),"NOT_APPLICABLE",IF(OR(AA13<Unit_Value_Review_QC!$I$6,AA13>Unit_Value_Review_QC!$I$5),"REVIEW","WITHIN_BAND")) -> WITHIN_BAND
... A612: 61103099_TR_202004_IMPORT | B612: 43922 | C612: 202004 | D612: 2020 | E612: 4 | F612: 61103099 | G612: 6110 | H612: 52 | I612: TR | J612: Turkey | K612: IMPORT | L612: 3 | M612: 1 | N612: REPORTED | O612: 0 | P612: 0 | Q612: 767299 | R612: 37826 | S612: 146605 | T612: USABLE | U612: =IF(R612>0,Q612/R612,"") -> 20.284963 | V612: =SUMIFS(fct_world_monthly!$J$2:$J$361,fct_world_monthly!$C$2:$C$361,C612,fct_world_monthly!$F$2:$F$361,F612) -> 10416097 | W612: =IF(V612>0,Q612/V612,"") -> 0.073664733 | X612: W5Q01 | Y612: EXT_HMRC_OTS_WP005_Core4_10PartnerCountries_Monthly_2019-01_to_2026-06_Raw_2026-08-26.json | Z612: =IF(U612="","",SUMIFS(Unit_Value_Review_QC!$K$10:$K$53,Unit_Value_Review_QC!$I$10:$I$53,"PARTNER|"&F612&"|"&I612)) -> 19.213268 | AA612: =IFERROR(U612/Z612,"") -> 1.0557789 | AB612: =IF(OR(N612<>"REPORTED",U612=""),"NOT_APPLICABLE",IF(OR(AA612<Unit_Value_Review_QC!$I$6,AA612>Unit_Value_Review_QC!$I$5),"REVIEW","WITHIN_BAND")) -> WITHIN_BAND
A613: 61103099_MA_202004_IMPORT | B613: 43922 | C613: 202004 | D613: 2020 | E613: 4 | F613: 61103099 | G613: 6110 | H613: 204 | I613: MA | J613: Morocco | K613: IMPORT | L613: 3 | M613: 0 | N613: NO_API_RECORD | P613: 0 | Q613: 0 | R613: 0 | S613: 0 | T613: NO_REPORTED_TRADE | U613: =IF(R613>0,Q613/R613,"") | V613: =SUMIFS(fct_world_monthly!$J$2:$J$361,fct_world_monthly!$C$2:$C$361,C613,fct_world_monthly!$F$2:$F$361,F613) -> 10416097 | W613: =IF(V613>0,Q613/V613,"") -> 0 | X613: W5Q01 | Y613: EXT_HMRC_OTS_WP005_Core4_10PartnerCountries_Monthly_2019-01_to_2026-06_Raw_2026-08-26.json | Z613: =IF(U613="","",SUMIFS(Unit_Value_Review_QC!$K$10:$K$53,Unit_Value_Review_QC!$I$10:$I$53,"PARTNER|"&F613&"|"&I613)) | AA613: =IFERROR(U613/Z613,"") | AB613: =IF(OR(N613<>"REPORTED",U613=""),"NOT_APPLICABLE",IF(OR(AA613<Unit_Value_Review_QC!$I$6,AA613>Unit_Value_Review_QC!$I$5),"REVIEW","WITHIN_BAND")) -> NOT_APPLICABLE
A614: 61103099_PK_202004_IMPORT | B614: 43922 | C614: 202004 | D614: 2020 | E614: 4 | F614: 61103099 | G614: 6110 | H614: 662 | I614: PK | J614: Pakistan | K614: IMPORT | L614: 3 | M614: 1 | N614: REPORTED | O614: 0 | P614: 0 | Q614: 261060 | R614: 17126 | S614: 53707 | T614: USABLE | U614: =IF(R614>0,Q614/R614,"") -> 15.243489 | V614: =SUMIFS(fct_world_monthly!$J$2:$J$361,fct_world_monthly!$C$2:$C$361,C614,fct_world_monthly!$F$2:$F$361,F614) -> 10416097 | W614: =IF(V614>0,Q614/V614,"") -> 0.025063131 | X614: W5Q01 | Y614: EXT_HMRC_OTS_WP005_Core4_10PartnerCountries_Monthly_2019-01_to_2026-06_Raw_2026-08-26.json | Z614: =IF(U614="","",SUMIFS(Unit_Value_Review_QC!$K$10:$K$53,Unit_Value_Review_QC!$I$10:$I$53,"PARTNER|"&F614&"|"&I614)) -> 13.240688 | AA614: =IFERROR(U614/Z614,"") -> 1.1512611 | AB614: =IF(OR(N614<>"REPORTED",U614=""),"NOT_APPLICABLE",IF(OR(AA614<Unit_Value_Review_QC!$I$6,AA614>Unit_Value_Review_QC!$I$5),"REVIEW","WITHIN_BAND")) -> WITHIN_BAND
A615: 61103099_IN_202004_IMPORT | B615: 43922 | C615: 202004 | D615: 2020 | E615: 4 | F615: 61103099 | G615: 6110 | H615: 664 | I615: IN | J615: India | K615: IMPORT | L615: 3 | M615: 1 | N615: REPORTED | O615: 0 | P615: 0 | Q615: 150405 | R615: 17414 | S615: 41324 | T615: USABLE | U615: =IF(R615>0,Q615/R615,"") -> 8.6370162 | V615: =SUMIFS(fct_world_monthly!$J$2:$J$361,fct_world_monthly!$C$2:$C$361,C615,fct_world_monthly!$F$2:$F$361,F615) -> 10416097 | W615: =IF(V615>0,Q615/V615,"") -> 0.01443967 | X615: W5Q01 | Y615: EXT_HMRC_OTS_WP005_Core4_10PartnerCountries_Monthly_2019-01_to_2026-06_Raw_2026-08-26.json | Z615: =IF(U615="","",SUMIFS(Unit_Value_Review_QC!$K$10:$K$53,Unit_Value_Review_QC!$I$10:$I$53,"PARTNER|"&F615&"|"&I615)) -> 13.033767 | AA615: =IFERROR(U615/Z615,"") -> 0.66266461 | AB615: =IF(OR(N615<>"REPORTED",U615=""),"NOT_APPLICABLE",IF(OR(AA615<Unit_Value_Review_QC!$I$6,AA615>Unit_Value_Review_QC!$I$5),"REVIEW","WITHIN_BAND")) -> WITHIN_BAND
A616: 61103099_BD_202004_IMPORT | B616: 43922 | C616: 202004 | D616: 2020 | E616: 4 | F616: 61103099 | G616: 6110 | H616: 666 | I616: BD | J616: Bangladesh | K616: IMPORT | L616: 3 | M616: 1 | N616: REPORTED | O616: 0 | P616: 0 | Q616: 2706858 | R616: 171581 | S616: 565280 | T616: USABLE | U616: =IF(R616>0,Q616/R616,"") -> 15.775978 | V616: =SUMIFS(fct_world_monthly!$J$2:$J$361,fct_world_monthly!$C$2:$C$361,C616,fct_world_monthly!$F$2:$F$361,F616) -> 10416097 | W616: =IF(V616>0,Q616/V616,"") -> 0.25987258 | X616: W5Q01 | Y616: EXT_HMRC_OTS_WP005_Core4_10PartnerCountries_Monthly_2019-01_to_2026-06_Raw_2026-08-26.json | Z616: =IF(U616="","",SUMIFS(Unit_Value_Review_QC!$K$10:$K$53,Unit_Value_Review_QC!$I$10:$I$53,"PARTNER|"&F616&"|"&I616)) -> 12.503788 | AA616: =IFERROR(U616/Z616,"") -> 1.2616958 | AB616: =IF(OR(N616<>"REPORTED",U616=""),"NOT_APPLICABLE",IF(OR(AA616<Unit_Value_Review_QC!$I$6,AA616>Unit_Value_Review_QC!$I$5),"REVIEW","WITHIN_BAND")) -> WITHIN_BAND
A617: 61103099_LK_202004_IMPORT | B617: 43922 | C617: 202004 | D617: 2020 | E617: 4 | F617: 61103099 | G617: 6110 | H617: 669 | I617: LK | J617: Sri Lanka | K617: IMPORT | L617: 3 | M617: 1 | N617: REPORTED | O617: 0 | P617: 0 | Q617: 98215 | R617: 4439 | S617: 19915 | T617: USABLE | U617: =IF(R617>0,Q617/R617,"") -> 22.125479 | V617: =SUMIFS(fct_world_monthly!$J$2:$J$361,fct_world_monthly!$C$2:$C$361,C617,fct_world_monthly!$F$2:$F$361,F617) -> 10416097 | W617: =IF(V617>0,Q617/V617,"") -> 0.0094291557 | X617: W5Q01 | Y617: EXT_HMRC_OTS_WP005_Core4_10PartnerCountries_Monthly_2019-01_to_2026-06_Raw_2026-08-26.json | Z617: =IF(U617="","",SUMIFS(Unit_Value_Review_QC!$K$10:$K$53,Unit_Value_Review_QC!$I$10:$I$53,"PARTNER|"&F617&"|"&I617)) -> 16.584044 | AA617: =IFERROR(U617/Z617,"") -> 1.3341426 | AB617: =IF(OR(N617<>"REPORTED",U617=""),"NOT_APPLICABLE",IF(OR(AA617<Unit_Value_Review_QC!$I$6,AA617>Unit_Value_Review_QC!$I$5),"REVIEW","WITHIN_BAND")) -> WITHIN_BAND
A618: 61103099_MM_202004_IMPORT | B618: 43922 | C618: 202004 | D618: 2020 | E618: 4 | F618: 61103099 | G618: 6110 | H618: 676 | I618: MM | J618: Myanmar | K618: IMPORT | L618: 3 | M618: 1 | N618: REPORTED | O618: 0 | P618: 0 | Q618: 904458 | R618: 110916 | S618: 272243 | T618: USABLE | U618: =IF(R618>0,Q618/R618,"") -> 8.1544412 | V618: =SUMIFS(fct_world_monthly!$J$2:$J$361,fct_world_monthly!$C$2:$C$361,C618,fct_world_monthly!$F$2:$F$361,F618) -> 10416097 | W618: =IF(V618>0,Q618/V618,"") -> 0.086832717 | X618: W5Q01 | Y618: EXT_HMRC_OTS_WP005_Core4_10PartnerCountries_Monthly_2019-01_to_2026-06_Raw_2026-08-26.json | Z618: =IF(U618="","",SUMIFS(Unit_Value_Review_QC!$K$10:$K$53,Unit_Value_Review_QC!$I$10:$I$53,"PARTNER|"&F618&"|"&I618)) -> 12.70545 | AA618: =IFERROR(U618/Z618,"") -> 0.64180654 | AB618: =IF(OR(N618<>"REPORTED",U618=""),"NOT_APPLICABLE",IF(OR(AA618<Unit_Value_Review_QC!$I$6,AA618>Unit_Value_Review_QC!$I$5),"REVIEW","WITHIN_BAND")) -> WITHIN_BAND
A619: 61103099_VN_202004_IMPORT | B619: 43922 | C619: 202004 | D619: 2020 | E619: 4 | F619: 61103099 | G619: 6110 | H619: 690 | I619: VN | J619: Vietnam | K619: IMPORT | L619: 3 | M619: 1 | N619: REPORTED | O619: 0 | P619: 0 | Q619: 207938 | R619: 7327 | S619: 28468 | T619: USABLE | U619: =IF(R619>0,Q619/R619,"") -> 28.379692 | V619: =SUMIFS(fct_world_monthly!$J$2:$J$361,fct_world_monthly!$C$2:$C$361,C619,fct_world_monthly!$F$2:$F$361,F619) -> 10416097 | W619: =IF(V619>0,Q619/V619,"") -> 0.01996314 | X619: W5Q01 | Y619: EXT_HMRC_OTS_WP005_Core4_10PartnerCountries_Monthly_2019-01_to_2026-06_Raw_2026-08-26.json | Z619: =IF(U619="","",SUMIFS(Unit_Value_Review_QC!$K$10:$K$53,Unit_Value_Review_QC!$I$10:$I$53,"PARTNER|"&F619&"|"&I619)) -> 23.234222 | AA619: =IFERROR(U619/Z619,"") -> 1.2214608 | AB619: =IF(OR(N619<>"REPORTED",U619=""),"NOT_APPLICABLE",IF(OR(AA619<Unit_Value_Review_QC!$I$6,AA619>Unit_Value_Review_QC!$I$5),"REVIEW","WITHIN_BAND")) -> WITHIN_BAND
A620: 61103099_KH_202004_IMPORT | B620: 43922 | C620: 202004 | D620: 2020 | E620: 4 | F620: 61103099 | G620: 6110 | H620: 696 | I620: KH | J620: Cambodia | K620: IMPORT | L620: 3 | M620: 1 | N620: REPORTED | O620: 0 | P620: 0 | Q620: 570988 | R620: 29089 | S620: 109818 | T620: USABLE | U620: =IF(R620>0,Q620/R620,"") -> 19.629001 | V620: =SUMIFS(fct_world_monthly!$J$2:$J$361,fct_world_monthly!$C$2:$C$361,C620,fct_world_monthly!$F$2:$F$361,F620) -> 10416097 | W620: =IF(V620>0,Q620/V620,"") -> 0.054817846 | X620: W5Q01 | Y620: EXT_HMRC_OTS_WP005_Core4_10PartnerCountries_Monthly_2019-01_to_2026-06_Raw_2026-08-26.json | Z620: =IF(U620="","",SUMIFS(Unit_Value_Review_QC!$K$10:$K$53,Unit_Value_Review_QC!$I$10:$I$53,"PARTNER|"&F620&"|"&I620)) -> 12.33939 | AA620: =IFERROR(U620/Z620,"") -> 1.5907594 | AB620: =IF(OR(N620<>"REPORTED",U620=""),"NOT_APPLICABLE",IF(OR(AA620<Unit_Value_Review_QC!$I$6,AA620>Unit_Value_Review_QC!$I$5),"REVIEW","WITHIN_BAND")) -> WITHIN_BAND
A621: 61103099_CN_202004_IMPORT | B621: 43922 | C621: 202004 | D621: 2020 | E621: 4 | F621: 61103099 | G621: 6110 | H621: 720 | I621: CN | J621: China | K621: IMPORT | L621: 3 | M621: 1 | N621: REPORTED | O621: 0 | P621: 0 | Q621: 1397383 | R621: 82987 | S621: 232477 | T621: USABLE | U621: =IF(R621>0,Q621/R621,"") -> 16.838577 | V621: =SUMIFS(fct_world_monthly!$J$2:$J$361,fct_world_monthly!$C$2:$C$361,C621,fct_world_monthly!$F$2:$F$361,F621) -> 10416097 | W621: =IF(V621>0,Q621/V621,"") -> 0.1341561 | X621: W5Q01 | Y621: EXT_HMRC_OTS_WP005_Core4_10PartnerCountries_Monthly_2019-01_to_2026-06_Raw_2026-08-26.json | Z621: =IF(U621="","",SUMIFS(Unit_Value_Review_QC!$K$10:$K$53,Unit_Value_Review_QC!$I$10:$I$53,"PARTNER|"&F621&"|"&I621)) -> 15.158853 | AA621: =IFERROR(U621/Z621,"") -> 1.1108082 | AB621: =IF(OR(N621<>"REPORTED",U621=""),"NOT_APPLICABLE",IF(OR(AA621<Unit_Value_Review_QC!$I$6,AA621>Unit_Value_Review_QC!$I$5),"REVIEW","WITHIN_BAND")) -> WITHIN_BAND
A622: 62044300_TR_202004_IMPORT | B622: 43922 | C622: 202004 | D622: 2020 | E622: 4 | F622: 62044300 | G622: 6204 | H622: 52 | I622: TR | J622: Turkey | K622: IMPORT | L622: 3 | M622: 1 | N622: REPORTED | O622: 0 | P622: 0 | Q622: 606218 | R622: 22721 | S622: 65702 | T622: USABLE | U622: =IF(R622>0,Q622/R622,"") -> 26.680956 | V622: =SUMIFS(fct_world_monthly!$J$2:$J$361,fct_world_monthly!$C$2:$C$361,C622,fct_world_monthly!$F$2:$F$361,F622) -> 13954909 | W622: =IF(V622>0,Q622/V622,"") -> 0.043441201 | X622: W5Q01 | Y622: EXT_HMRC_OTS_WP005_Core4_10PartnerCountries_Monthly_2019-01_to_2026-06_Raw_2026-08-26.json | Z622: =IF(U622="","",SUMIFS(Unit_Value_Review_QC!$K$10:$K$53,Unit_Value_Review_QC!$I$10:$I$53,"PARTNER|"&F622&"|"&I622)) -> 31.867133 | AA622: =IFERROR(U622/Z622,"") -> 0.83725624 | AB622: =IF(OR(N622<>"REPORTED",U622=""),"NOT_APPLICABLE",IF(OR(AA622<Unit_Value_Review_QC!$I$6,AA622>Unit_Value_Review_QC!$I$5),"REVIEW","WITHIN_BAND")) -> WITHIN_BAND
A623: 62044300_MA_202004_IMPORT | B623: 43922 | C623: 202004 | D623: 2020 | E623: 4 | F623: 62044300 | G623: 6204 | H623: 204 | I623: MA | J623: Morocco | K623: IMPORT | L623: 3 | M623: 1 | N623: REPORTED | O623: 0 | P623: 0 | Q623: 40113 | R623: 1513 | S623: 6727 | T623: USABLE | U623: =IF(R623>0,Q623/R623,"") -> 26.512227 | V623: =SUMIFS(fct_world_monthly!$J$2:$J$361,fct_world_monthly!$C$2:$C$361,C623,fct_world_monthly!$F$2:$F$361,F623) -> 13954909 | W623: =IF(V623>0,Q623/V623,"") -> 0.0028744723 | X623: W5Q01 | Y623: EXT_HMRC_OTS_WP005_Core4_10PartnerCountries_Monthly_2019-01_to_2026-06_Raw_2026-08-26.json | Z623: =IF(U623="","",SUMIFS(Unit_Value_Review_QC!$K$10:$K$53,Unit_Value_Review_QC!$I$10:$I$53,"PARTNER|"&F623&"|"&I623)) -> 19.682232 | AA623: =IFERROR(U623/Z623,"") -> 1.3470133 | AB623: =IF(OR(N623<>"REPORTED",U623=""),"NOT_APPLICABLE",IF(OR(AA623<Unit_Value_Review_QC!$I$6,AA623>Unit_Value_Review_QC!$I$5),"REVIEW","WITHIN_BAND")) -> WITHIN_BAND
A624: 62044300_PK_202004_IMPORT | B624: 43922 | C624: 202004 | D624: 2020 | E624: 4 | F624: 62044300 | G624: 6204 | H624: 662 | I624: PK | J624: Pakistan | K624: IMPORT | L624: 3 | M624: 1 | N624: REPORTED | O624: 0 | P624: 0 | Q624: 32231 | R624: 939 | S624: 7600 | T624: USABLE | U624: =IF(R624>0,Q624/R624,"") -> 34.324814 | V624: =SUMIFS(fct_world_monthly!$J$2:$J$361,fct_world_monthly!$C$2:$C$361,C624,fct_world_monthly!$F$2:$F$361,F624) -> 13954909 | W624: =IF(V624>0,Q624/V624,"") -> 0.0023096532 | X624: W5Q01 | Y624: EXT_HMRC_OTS_WP005_Core4_10PartnerCountries_Monthly_2019-01_to_2026-06_Raw_2026-08-26.json | Z624: =IF(U624="","",SUMIFS(Unit_Value_Review_QC!$K$10:$K$53,Unit_Value_Review_QC!$I$10:$I$53,"PARTNER|"&F624&"|"&I624)) -> 19.366411 | AA624: =IFERROR(U624/Z624,"") -> 1.772389 | AB624: =IF(OR(N624<>"REPORTED",U624=""),"NOT_APPLICABLE",IF(OR(AA624<Unit_Value_Review_QC!$I$6,AA624>Unit_Value_Review_QC!$I$5),"REVIEW","WITHIN_BAND")) -> WITHIN_BAND
A625: 62044300_IN_202004_IMPORT | B625: 43922 | C625: 202004 | D625: 2020 | E625: 4 | F625: 62044300 | G625: 6204 | H625: 664 | I625: IN | J625: India | K625: IMPORT | L625: 3 | M625: 1 | N625: REPORTED | O625: 0 | P625: 0 | Q625: 1254536 | R625: 50745 | S625: 220038 | T625: USABLE | U625: =IF(R625>0,Q625/R625,"") -> 24.722357 | V625: =SUMIFS(fct_world_monthly!$J$2:$J$361,fct_world_monthly!$C$2:$C$361,C625,fct_world_monthly!$F$2:$F$361,F625) -> 13954909 | W625: =IF(V625>0,Q625/V625,"") -> 0.089899261 | X625: W5Q01 | Y625: EXT_HMRC_OTS_WP005_Core4_10PartnerCountries_Monthly_2019-01_to_2026-06_Raw_2026-08-26.json | Z625: =IF(U625="","",SUMIFS(Unit_Value_Review_QC!$K$10:$K$53,Unit_Value_Review_QC!$I$10:$I$53,"PARTNER|"&F625&"|"&I625)) -> 29.827361 | AA625: =IFERROR(U625/Z625,"") -> 0.82884828 | AB625: =IF(OR(N625<>"REPORTED",U625=""),"NOT_APPLICABLE",IF(OR(AA625<Unit_Value_Review_QC!$I$6,AA625>Unit_Value_Review_QC!$I$5),"REVIEW","WITHIN_BAND")) -> WITHIN_BAND
... A632: 62052000_TR_202004_IMPORT | B632: 43922 | C632: 202004 | D632: 2020 | E632: 4 | F632: 62052000 | G632: 6205 | H632: 52 | I632: TR | J632: Turkey | K632: IMPORT | L632: 3 | M632: 1 | N632: REPORTED | O632: 0 | P632: 0 | Q632: 244355 | R632: 7688 | S632: 24809 | T632: USABLE | U632: =IF(R632>0,Q632/R632,"") -> 31.783949 | V632: =SUMIFS(fct_world_monthly!$J$2:$J$361,fct_world_monthly!$C$2:$C$361,C632,fct_world_monthly!$F$2:$F$361,F632) -> 16075495 | W632: =IF(V632>0,Q632/V632,"") -> 0.015200465 | X632: W5Q01 | Y632: EXT_HMRC_OTS_WP005_Core4_10PartnerCountries_Monthly_2019-01_to_2026-06_Raw_2026-08-26.json | Z632: =IF(U632="","",SUMIFS(Unit_Value_Review_QC!$K$10:$K$53,Unit_Value_Review_QC!$I$10:$I$53,"PARTNER|"&F632&"|"&I632)) -> 35.036767 | AA632: =IFERROR(U632/Z632,"") -> 0.90715988 | AB632: =IF(OR(N632<>"REPORTED",U632=""),"NOT_APPLICABLE",IF(OR(AA632<Unit_Value_Review_QC!$I$6,AA632>Unit_Value_Review_QC!$I$5),"REVIEW","WITHIN_BAND")) -> WITHIN_BAND
A633: 62052000_MA_202004_IMPORT | B633: 43922 | C633: 202004 | D633: 2020 | E633: 4 | F633: 62052000 | G633: 6205 | H633: 204 | I633: MA | J633: Morocco | K633: IMPORT | L633: 3 | M633: 0 | N633: NO_API_RECORD | P633: 0 | Q633: 0 | R633: 0 | S633: 0 | T633: NO_REPORTED_TRADE | U633: =IF(R633>0,Q633/R633,"") | V633: =SUMIFS(fct_world_monthly!$J$2:$J$361,fct_world_monthly!$C$2:$C$361,C633,fct_world_monthly!$F$2:$F$361,F633) -> 16075495 | W633: =IF(V633>0,Q633/V633,"") -> 0 | X633: W5Q01 | Y633: EXT_HMRC_OTS_WP005_Core4_10PartnerCountries_Monthly_2019-01_to_2026-06_Raw_2026-08-26.json | Z633: =IF(U633="","",SUMIFS(Unit_Value_Review_QC!$K$10:$K$53,Unit_Value_Review_QC!$I$10:$I$53,"PARTNER|"&F633&"|"&I633)) | AA633: =IFERROR(U633/Z633,"") | AB633: =IF(OR(N633<>"REPORTED",U633=""),"NOT_APPLICABLE",IF(OR(AA633<Unit_Value_Review_QC!$I$6,AA633>Unit_Value_Review_QC!$I$5),"REVIEW","WITHIN_BAND")) -> NOT_APPLICABLE
A634: 62052000_PK_202004_IMPORT | B634: 43922 | C634: 202004 | D634: 2020 | E634: 4 | F634: 62052000 | G634: 6205 | H634: 662 | I634: PK | J634: Pakistan | K634: IMPORT | L634: 3 | M634: 1 | N634: REPORTED | O634: 0 | P634: 0 | Q634: 27981 | R634: 2747 | S634: 10354 | T634: USABLE | U634: =IF(R634>0,Q634/R634,"") -> 10.186021 | V634: =SUMIFS(fct_world_monthly!$J$2:$J$361,fct_world_monthly!$C$2:$C$361,C634,fct_world_monthly!$F$2:$F$361,F634) -> 16075495 | W634: =IF(V634>0,Q634/V634,"") -> 0.0017405996 | X634: W5Q01 | Y634: EXT_HMRC_OTS_WP005_Core4_10PartnerCountries_Monthly_2019-01_to_2026-06_Raw_2026-08-26.json | Z634: =IF(U634="","",SUMIFS(Unit_Value_Review_QC!$K$10:$K$53,Unit_Value_Review_QC!$I$10:$I$53,"PARTNER|"&F634&"|"&I634)) -> 11.552282 | AA634: =IFERROR(U634/Z634,"") -> 0.88173236 | AB634: =IF(OR(N634<>"REPORTED",U634=""),"NOT_APPLICABLE",IF(OR(AA634<Unit_Value_Review_QC!$I$6,AA634>Unit_Value_Review_QC!$I$5),"REVIEW","WITHIN_BAND")) -> WITHIN_BAND
A635: 62052000_IN_202004_IMPORT | B635: 43922 | C635: 202004 | D635: 2020 | E635: 4 | F635: 62052000 | G635: 6205 | H635: 664 | I635: IN | J635: India | K635: IMPORT | L635: 3 | M635: 1 | N635: REPORTED | O635: 0 | P635: 0 | Q635: 2340786 | R635: 116783 | S635: 499870 | T635: USABLE | U635: =IF(R635>0,Q635/R635,"") -> 20.043893 | V635: =SUMIFS(fct_world_monthly!$J$2:$J$361,fct_world_monthly!$C$2:$C$361,C635,fct_world_monthly!$F$2:$F$361,F635) -> 16075495 | W635: =IF(V635>0,Q635/V635,"") -> 0.14561206 | X635: W5Q01 | Y635: EXT_HMRC_OTS_WP005_Core4_10PartnerCountries_Monthly_2019-01_to_2026-06_Raw_2026-08-26.json | Z635: =IF(U635="","",SUMIFS(Unit_Value_Review_QC!$K$10:$K$53,Unit_Value_Review_QC!$I$10:$I$53,"PARTNER|"&F635&"|"&I635)) -> 20.753901 | AA635: =IFERROR(U635/Z635,"") -> 0.96578919 | AB635: =IF(OR(N635<>"REPORTED",U635=""),"NOT_APPLICABLE",IF(OR(AA635<Unit_Value_Review_QC!$I$6,AA635>Unit_Value_Review_QC!$I$5),"REVIEW","WITHIN_BAND")) -> WITHIN_BAND
A636: 62052000_BD_202004_IMPORT | B636: 43922 | C636: 202004 | D636: 2020 | E636: 4 | F636: 62052000 | G636: 6205 | H636: 666 | I636: BD | J636: Bangladesh | K636: IMPORT | L636: 3 | M636: 1 | N636: REPORTED | O636: 0 | P636: 0 | Q636: 7220758 | R636: 416077 | S636: 1685440 | T636: USABLE | U636: =IF(R636>0,Q636/R636,"") -> 17.354379 | V636: =SUMIFS(fct_world_monthly!$J$2:$J$361,fct_world_monthly!$C$2:$C$361,C636,fct_world_monthly!$F$2:$F$361,F636) -> 16075495 | W636: =IF(V636>0,Q636/V636,"") -> 0.44917796 | X636: W5Q01 | Y636: EXT_HMRC_OTS_WP005_Core4_10PartnerCountries_Monthly_2019-01_to_2026-06_Raw_2026-08-26.json | Z636: =IF(U636="","",SUMIFS(Unit_Value_Review_QC!$K$10:$K$53,Unit_Value_Review_QC!$I$10:$I$53,"PARTNER|"&F636&"|"&I636)) -> 16.653215 | AA636: =IFERROR(U636/Z636,"") -> 1.0421038 | AB636: =IF(OR(N636<>"REPORTED",U636=""),"NOT_APPLICABLE",IF(OR(AA636<Unit_Value_Review_QC!$I$6,AA636>Unit_Value_Review_QC!$I$5),"REVIEW","WITHIN_BAND")) -> WITHIN_BAND
A637: 62052000_LK_202004_IMPORT | B637: 43922 | C637: 202004 | D637: 2020 | E637: 4 | F637: 62052000 | G637: 6205 | H637: 669 | I637: LK | J637: Sri Lanka | K637: IMPORT | L637: 3 | M637: 1 | N637: REPORTED | O637: 0 | P637: 0 | Q637: 74616 | R637: 2856 | S637: 12573 | T637: USABLE | U637: =IF(R637>0,Q637/R637,"") -> 26.12605 | V637: =SUMIFS(fct_world_monthly!$J$2:$J$361,fct_world_monthly!$C$2:$C$361,C637,fct_world_monthly!$F$2:$F$361,F637) -> 16075495 | W637: =IF(V637>0,Q637/V637,"") -> 0.0046415989 | X637: W5Q01 | Y637: EXT_HMRC_OTS_WP005_Core4_10PartnerCountries_Monthly_2019-01_to_2026-06_Raw_2026-08-26.json | Z637: =IF(U637="","",SUMIFS(Unit_Value_Review_QC!$K$10:$K$53,Unit_Value_Review_QC!$I$10:$I$53,"PARTNER|"&F637&"|"&I637)) -> 20.668788 | AA637: =IFERROR(U637/Z637,"") -> 1.264034 | AB637: =IF(OR(N637<>"REPORTED",U637=""),"NOT_APPLICABLE",IF(OR(AA637<Unit_Value_Review_QC!$I$6,AA637>Unit_Value_Review_QC!$I$5),"REVIEW","WITHIN_BAND")) -> WITHIN_BAND
A638: 62052000_MM_202004_IMPORT | B638: 43922 | C638: 202004 | D638: 2020 | E638: 4 | F638: 62052000 | G638: 6205 | H638: 676 | I638: MM | J638: Myanmar | K638: IMPORT | L638: 3 | M638: 1 | N638: REPORTED | O638: 0 | P638: 0 | Q638: 40912 | R638: 1606 | S638: 5111 | T638: USABLE | U638: =IF(R638>0,Q638/R638,"") -> 25.474471 | V638: =SUMIFS(fct_world_monthly!$J$2:$J$361,fct_world_monthly!$C$2:$C$361,C638,fct_world_monthly!$F$2:$F$361,F638) -> 16075495 | W638: =IF(V638>0,Q638/V638,"") -> 0.0025449916 | X638: W5Q01 | Y638: EXT_HMRC_OTS_WP005_Core4_10PartnerCountries_Monthly_2019-01_to_2026-06_Raw_2026-08-26.json | Z638: =IF(U638="","",SUMIFS(Unit_Value_Review_QC!$K$10:$K$53,Unit_Value_Review_QC!$I$10:$I$53,"PARTNER|"&F638&"|"&I638)) -> 22.71684 | AA638: =IFERROR(U638/Z638,"") -> 1.1213915 | AB638: =IF(OR(N638<>"REPORTED",U638=""),"NOT_APPLICABLE",IF(OR(AA638<Unit_Value_Review_QC!$I$6,AA638>Unit_Value_Review_QC!$I$5),"REVIEW","WITHIN_BAND")) -> WITHIN_BAND
A639: 62052000_VN_202004_IMPORT | B639: 43922 | C639: 202004 | D639: 2020 | E639: 4 | F639: 62052000 | G639: 6205 | H639: 690 | I639: VN | J639: Vietnam | K639: IMPORT | L639: 3 | M639: 1 | N639: REPORTED | O639: 0 | P639: 0 | Q639: 771026 | R639: 32091 | S639: 92249 | T639: USABLE | U639: =IF(R639>0,Q639/R639,"") -> 24.026238 | V639: =SUMIFS(fct_world_monthly!$J$2:$J$361,fct_world_monthly!$C$2:$C$361,C639,fct_world_monthly!$F$2:$F$361,F639) -> 16075495 | W639: =IF(V639>0,Q639/V639,"") -> 0.047962815 | X639: W5Q01 | Y639: EXT_HMRC_OTS_WP005_Core4_10PartnerCountries_Monthly_2019-01_to_2026-06_Raw_2026-08-26.json | Z639: =IF(U639="","",SUMIFS(Unit_Value_Review_QC!$K$10:$K$53,Unit_Value_Review_QC!$I$10:$I$53,"PARTNER|"&F639&"|"&I639)) -> 28.158454 | AA639: =IFERROR(U639/Z639,"") -> 0.85325132 | AB639: =IF(OR(N639<>"REPORTED",U639=""),"NOT_APPLICABLE",IF(OR(AA639<Unit_Value_Review_QC!$I$6,AA639>Unit_Value_Review_QC!$I$5),"REVIEW","WITHIN_BAND")) -> WITHIN_BAND
A640: 62052000_KH_202004_IMPORT | B640: 43922 | C640: 202004 | D640: 2020 | E640: 4 | F640: 62052000 | G640: 6205 | H640: 696 | I640: KH | J640: Cambodia | K640: IMPORT | L640: 3 | M640: 1 | N640: REPORTED | O640: 0 | P640: 0 | Q640: 630392 | R640: 22012 | S640: 78764 | T640: USABLE | U640: =IF(R640>0,Q640/R640,"") -> 28.638561 | V640: =SUMIFS(fct_world_monthly!$J$2:$J$361,fct_world_monthly!$C$2:$C$361,C640,fct_world_monthly!$F$2:$F$361,F640) -> 16075495 | W640: =IF(V640>0,Q640/V640,"") -> 0.039214469 | X640: W5Q01 | Y640: EXT_HMRC_OTS_WP005_Core4_10PartnerCountries_Monthly_2019-01_to_2026-06_Raw_2026-08-26.json | Z640: =IF(U640="","",SUMIFS(Unit_Value_Review_QC!$K$10:$K$53,Unit_Value_Review_QC!$I$10:$I$53,"PARTNER|"&F640&"|"&I640)) -> 25.266639 | AA640: =IFERROR(U640/Z640,"") -> 1.1334535 | AB640: =IF(OR(N640<>"REPORTED",U640=""),"NOT_APPLICABLE",IF(OR(AA640<Unit_Value_Review_QC!$I$6,AA640>Unit_Value_Review_QC!$I$5),"REVIEW","WITHIN_BAND")) -> WITHIN_BAND
A641: 62052000_CN_202004_IMPORT | B641: 43922 | C641: 202004 | D641: 2020 | E641: 4 | F641: 62052000 | G641: 6205 | H641: 720 | I641: CN | J641: China | K641: IMPORT | L641: 3 | M641: 1 | N641: REPORTED | O641: 0 | P641: 0 | Q641: 1591171 | R641: 55747 | S641: 166614 | T641: USABLE | U641: =IF(R641>0,Q641/R641,"") -> 28.54272 | V641: =SUMIFS(fct_world_monthly!$J$2:$J$361,fct_world_monthly!$C$2:$C$361,C641,fct_world_monthly!$F$2:$F$361,F641) -> 16075495 | W641: =IF(V641>0,Q641/V641,"") -> 0.098981151 | X641: W5Q01 | Y641: EXT_HMRC_OTS_WP005_Core4_10PartnerCountries_Monthly_2019-01_to_2026-06_Raw_2026-08-26.json | Z641: =IF(U641="","",SUMIFS(Unit_Value_Review_QC!$K$10:$K$53,Unit_Value_Review_QC!$I$10:$I$53,"PARTNER|"&F641&"|"&I641)) -> 23.211498 | AA641: =IFERROR(U641/Z641,"") -> 1.2296802 | AB641: =IF(OR(N641<>"REPORTED",U641=""),"NOT_APPLICABLE",IF(OR(AA641<Unit_Value_Review_QC!$I$6,AA641>Unit_Value_Review_QC!$I$5),"REVIEW","WITHIN_BAND")) -> WITHIN_BAND
A642: 61091000_TR_202005_IMPORT | B642: 43952 | C642: 202005 | D642: 2020 | E642: 5 | F642: 61091000 | G642: 6109 | H642: 52 | I642: TR | J642: Turkey | K642: IMPORT | L642: 3 | M642: 1 | N642: REPORTED | O642: 0 | P642: 0 | Q642: 4784475 | R642: 255321 | S642: 1339386 | T642: USABLE | U642: =IF(R642>0,Q642/R642,"") -> 18.739058 | V642: =SUMIFS(fct_world_monthly!$J$2:$J$361,fct_world_monthly!$C$2:$C$361,C642,fct_world_monthly!$F$2:$F$361,F642) -> 61113796 | W642: =IF(V642>0,Q642/V642,"") -> 0.07828797 | X642: W5Q01 | Y642: EXT_HMRC_OTS_WP005_Core4_10PartnerCountries_Monthly_2019-01_to_2026-06_Raw_2026-08-26.json | Z642: =IF(U642="","",SUMIFS(Unit_Value_Review_QC!$K$10:$K$53,Unit_Value_Review_QC!$I$10:$I$53,"PARTNER|"&F642&"|"&I642)) -> 20.461445 | AA642: =IFERROR(U642/Z642,"") -> 0.91582281 | AB642: =IF(OR(N642<>"REPORTED",U642=""),"NOT_APPLICABLE",IF(OR(AA642<Unit_Value_Review_QC!$I$6,AA642>Unit_Value_Review_QC!$I$5),"REVIEW","WITHIN_BAND")) -> WITHIN_BAND
A643: 61091000_MA_202005_IMPORT | B643: 43952 | C643: 202005 | D643: 2020 | E643: 5 | F643: 61091000 | G643: 6109 | H643: 204 | I643: MA | J643: Morocco | K643: IMPORT | L643: 3 | M643: 1 | N643: REPORTED | O643: 0 | P643: 0 | Q643: 233742 | R643: 41599 | S643: 249780 | T643: USABLE | U643: =IF(R643>0,Q643/R643,"") -> 5.6189331 | V643: =SUMIFS(fct_world_monthly!$J$2:$J$361,fct_world_monthly!$C$2:$C$361,C643,fct_world_monthly!$F$2:$F$361,F643) -> 61113796 | W643: =IF(V643>0,Q643/V643,"") -> 0.0038247011 | X643: W5Q01 | Y643: EXT_HMRC_OTS_WP005_Core4_10PartnerCountries_Monthly_2019-01_to_2026-06_Raw_2026-08-26.json | Z643: =IF(U643="","",SUMIFS(Unit_Value_Review_QC!$K$10:$K$53,Unit_Value_Review_QC!$I$10:$I$53,"PARTNER|"&F643&"|"&I643)) -> 7.8392981 | AA643: =IFERROR(U643/Z643,"") -> 0.71676483 | AB643: =IF(OR(N643<>"REPORTED",U643=""),"NOT_APPLICABLE",IF(OR(AA643<Unit_Value_Review_QC!$I$6,AA643>Unit_Value_Review_QC!$I$5),"REVIEW","WITHIN_BAND")) -> WITHIN_BAND
A644: 61091000_PK_202005_IMPORT | B644: 43952 | C644: 202005 | D644: 2020 | E644: 5 | F644: 61091000 | G644: 6109 | H644: 662 | I644: PK | J644: Pakistan | K644: IMPORT | L644: 3 | M644: 1 | N644: REPORTED | O644: 0 | P644: 0 | Q644: 2854895 | R644: 239491 | S644: 872914 | T644: USABLE | U644: =IF(R644>0,Q644/R644,"") -> 11.920678 | V644: =SUMIFS(fct_world_monthly!$J$2:$J$361,fct_world_monthly!$C$2:$C$361,C644,fct_world_monthly!$F$2:$F$361,F644) -> 61113796 | W644: =IF(V644>0,Q644/V644,"") -> 0.046714411 | X644: W5Q01 | Y644: EXT_HMRC_OTS_WP005_Core4_10PartnerCountries_Monthly_2019-01_to_2026-06_Raw_2026-08-26.json | Z644: =IF(U644="","",SUMIFS(Unit_Value_Review_QC!$K$10:$K$53,Unit_Value_Review_QC!$I$10:$I$53,"PARTNER|"&F644&"|"&I644)) -> 10.235891 | AA644: =IFERROR(U644/Z644,"") -> 1.1645959 | AB644: =IF(OR(N644<>"REPORTED",U644=""),"NOT_APPLICABLE",IF(OR(AA644<Unit_Value_Review_QC!$I$6,AA644>Unit_Value_Review_QC!$I$5),"REVIEW","WITHIN_BAND")) -> WITHIN_BAND
A645: 61091000_IN_202005_IMPORT | B645: 43952 | C645: 202005 | D645: 2020 | E645: 5 | F645: 61091000 | G645: 6109 | H645: 664 | I645: IN | J645: India | K645: IMPORT | L645: 3 | M645: 1 | N645: REPORTED | O645: 0 | P645: 0 | Q645: 1986857 | R645: 151687 | S645: 1039876 | T645: USABLE | U645: =IF(R645>0,Q645/R645,"") -> 13.0984 | V645: =SUMIFS(fct_world_monthly!$J$2:$J$361,fct_world_monthly!$C$2:$C$361,C645,fct_world_monthly!$F$2:$F$361,F645) -> 61113796 | W645: =IF(V645>0,Q645/V645,"") -> 0.032510777 | X645: W5Q01 | Y645: EXT_HMRC_OTS_WP005_Core4_10PartnerCountries_Monthly_2019-01_to_2026-06_Raw_2026-08-26.json | Z645: =IF(U645="","",SUMIFS(Unit_Value_Review_QC!$K$10:$K$53,Unit_Value_Review_QC!$I$10:$I$53,"PARTNER|"&F645&"|"&I645)) -> 13.59406 | AA645: =IFERROR(U645/Z645,"") -> 0.9635385 | AB645: =IF(OR(N645<>"REPORTED",U645=""),"NOT_APPLICABLE",IF(OR(AA645<Unit_Value_Review_QC!$I$6,AA645>Unit_Value_Review_QC!$I$5),"REVIEW","WITHIN_BAND")) -> WITHIN_BAND
... A652: 61103099_TR_202005_IMPORT | B652: 43952 | C652: 202005 | D652: 2020 | E652: 5 | F652: 61103099 | G652: 6110 | H652: 52 | I652: TR | J652: Turkey | K652: IMPORT | L652: 3 | M652: 1 | N652: REPORTED | O652: 0 | P652: 0 | Q652: 335852 | R652: 15752 | S652: 47197 | T652: USABLE | U652: =IF(R652>0,Q652/R652,"") -> 21.321229 | V652: =SUMIFS(fct_world_monthly!$J$2:$J$361,fct_world_monthly!$C$2:$C$361,C652,fct_world_monthly!$F$2:$F$361,F652) -> 8685086 | W652: =IF(V652>0,Q652/V652,"") -> 0.038669968 | X652: W5Q01 | Y652: EXT_HMRC_OTS_WP005_Core4_10PartnerCountries_Monthly_2019-01_to_2026-06_Raw_2026-08-26.json | Z652: =IF(U652="","",SUMIFS(Unit_Value_Review_QC!$K$10:$K$53,Unit_Value_Review_QC!$I$10:$I$53,"PARTNER|"&F652&"|"&I652)) -> 19.213268 | AA652: =IFERROR(U652/Z652,"") -> 1.1097138 | AB652: =IF(OR(N652<>"REPORTED",U652=""),"NOT_APPLICABLE",IF(OR(AA652<Unit_Value_Review_QC!$I$6,AA652>Unit_Value_Review_QC!$I$5),"REVIEW","WITHIN_BAND")) -> WITHIN_BAND
A653: 61103099_MA_202005_IMPORT | B653: 43952 | C653: 202005 | D653: 2020 | E653: 5 | F653: 61103099 | G653: 6110 | H653: 204 | I653: MA | J653: Morocco | K653: IMPORT | L653: 3 | M653: 0 | N653: NO_API_RECORD | P653: 0 | Q653: 0 | R653: 0 | S653: 0 | T653: NO_REPORTED_TRADE | U653: =IF(R653>0,Q653/R653,"") | V653: =SUMIFS(fct_world_monthly!$J$2:$J$361,fct_world_monthly!$C$2:$C$361,C653,fct_world_monthly!$F$2:$F$361,F653) -> 8685086 | W653: =IF(V653>0,Q653/V653,"") -> 0 | X653: W5Q01 | Y653: EXT_HMRC_OTS_WP005_Core4_10PartnerCountries_Monthly_2019-01_to_2026-06_Raw_2026-08-26.json | Z653: =IF(U653="","",SUMIFS(Unit_Value_Review_QC!$K$10:$K$53,Unit_Value_Review_QC!$I$10:$I$53,"PARTNER|"&F653&"|"&I653)) | AA653: =IFERROR(U653/Z653,"") | AB653: =IF(OR(N653<>"REPORTED",U653=""),"NOT_APPLICABLE",IF(OR(AA653<Unit_Value_Review_QC!$I$6,AA653>Unit_Value_Review_QC!$I$5),"REVIEW","WITHIN_BAND")) -> NOT_APPLICABLE
A654: 61103099_PK_202005_IMPORT | B654: 43952 | C654: 202005 | D654: 2020 | E654: 5 | F654: 61103099 | G654: 6110 | H654: 662 | I654: PK | J654: Pakistan | K654: IMPORT | L654: 3 | M654: 1 | N654: REPORTED | O654: 0 | P654: 0 | Q654: 179797 | R654: 10328 | S654: 33298 | T654: USABLE | U654: =IF(R654>0,Q654/R654,"") -> 17.408695 | V654: =SUMIFS(fct_world_monthly!$J$2:$J$361,fct_world_monthly!$C$2:$C$361,C654,fct_world_monthly!$F$2:$F$361,F654) -> 8685086 | W654: =IF(V654>0,Q654/V654,"") -> 0.02070181 | X654: W5Q01 | Y654: EXT_HMRC_OTS_WP005_Core4_10PartnerCountries_Monthly_2019-01_to_2026-06_Raw_2026-08-26.json | Z654: =IF(U654="","",SUMIFS(Unit_Value_Review_QC!$K$10:$K$53,Unit_Value_Review_QC!$I$10:$I$53,"PARTNER|"&F654&"|"&I654)) -> 13.240688 | AA654: =IFERROR(U654/Z654,"") -> 1.3147878 | AB654: =IF(OR(N654<>"REPORTED",U654=""),"NOT_APPLICABLE",IF(OR(AA654<Unit_Value_Review_QC!$I$6,AA654>Unit_Value_Review_QC!$I$5),"REVIEW","WITHIN_BAND")) -> WITHIN_BAND
A655: 61103099_IN_202005_IMPORT | B655: 43952 | C655: 202005 | D655: 2020 | E655: 5 | F655: 61103099 | G655: 6110 | H655: 664 | I655: IN | J655: India | K655: IMPORT | L655: 3 | M655: 1 | N655: REPORTED | O655: 0 | P655: 0 | Q655: 62184 | R655: 8326 | S655: 19246 | T655: USABLE | U655: =IF(R655>0,Q655/R655,"") -> 7.4686524 | V655: =SUMIFS(fct_world_monthly!$J$2:$J$361,fct_world_monthly!$C$2:$C$361,C655,fct_world_monthly!$F$2:$F$361,F655) -> 8685086 | W655: =IF(V655>0,Q655/V655,"") -> 0.00715986 | X655: W5Q01 | Y655: EXT_HMRC_OTS_WP005_Core4_10PartnerCountries_Monthly_2019-01_to_2026-06_Raw_2026-08-26.json | Z655: =IF(U655="","",SUMIFS(Unit_Value_Review_QC!$K$10:$K$53,Unit_Value_Review_QC!$I$10:$I$53,"PARTNER|"&F655&"|"&I655)) -> 13.033767 | AA655: =IFERROR(U655/Z655,"") -> 0.57302332 | AB655: =IF(OR(N655<>"REPORTED",U655=""),"NOT_APPLICABLE",IF(OR(AA655<Unit_Value_Review_QC!$I$6,AA655>Unit_Value_Review_QC!$I$5),"REVIEW","WITHIN_BAND")) -> WITHIN_BAND
A656: 61103099_BD_202005_IMPORT | B656: 43952 | C656: 202005 | D656: 2020 | E656: 5 | F656: 61103099 | G656: 6110 | H656: 666 | I656: BD | J656: Bangladesh | K656: IMPORT | L656: 3 | M656: 1 | N656: REPORTED | O656: 0 | P656: 0 | Q656: 1990786 | R656: 150280 | S656: 405164 | T656: USABLE | U656: =IF(R656>0,Q656/R656,"") -> 13.247179 | V656: =SUMIFS(fct_world_monthly!$J$2:$J$361,fct_world_monthly!$C$2:$C$361,C656,fct_world_monthly!$F$2:$F$361,F656) -> 8685086 | W656: =IF(V656>0,Q656/V656,"") -> 0.22921892 | X656: W5Q01 | Y656: EXT_HMRC_OTS_WP005_Core4_10PartnerCountries_Monthly_2019-01_to_2026-06_Raw_2026-08-26.json | Z656: =IF(U656="","",SUMIFS(Unit_Value_Review_QC!$K$10:$K$53,Unit_Value_Review_QC!$I$10:$I$53,"PARTNER|"&F656&"|"&I656)) -> 12.503788 | AA656: =IFERROR(U656/Z656,"") -> 1.0594532 | AB656: =IF(OR(N656<>"REPORTED",U656=""),"NOT_APPLICABLE",IF(OR(AA656<Unit_Value_Review_QC!$I$6,AA656>Unit_Value_Review_QC!$I$5),"REVIEW","WITHIN_BAND")) -> WITHIN_BAND
A657: 61103099_LK_202005_IMPORT | B657: 43952 | C657: 202005 | D657: 2020 | E657: 5 | F657: 61103099 | G657: 6110 | H657: 669 | I657: LK | J657: Sri Lanka | K657: IMPORT | L657: 3 | M657: 1 | N657: REPORTED | O657: 0 | P657: 0 | Q657: 52311 | R657: 4519 | S657: 18140 | T657: USABLE | U657: =IF(R657>0,Q657/R657,"") -> 11.575791 | V657: =SUMIFS(fct_world_monthly!$J$2:$J$361,fct_world_monthly!$C$2:$C$361,C657,fct_world_monthly!$F$2:$F$361,F657) -> 8685086 | W657: =IF(V657>0,Q657/V657,"") -> 0.0060230837 | X657: W5Q01 | Y657: EXT_HMRC_OTS_WP005_Core4_10PartnerCountries_Monthly_2019-01_to_2026-06_Raw_2026-08-26.json | Z657: =IF(U657="","",SUMIFS(Unit_Value_Review_QC!$K$10:$K$53,Unit_Value_Review_QC!$I$10:$I$53,"PARTNER|"&F657&"|"&I657)) -> 16.584044 | AA657: =IFERROR(U657/Z657,"") -> 0.69800775 | AB657: =IF(OR(N657<>"REPORTED",U657=""),"NOT_APPLICABLE",IF(OR(AA657<Unit_Value_Review_QC!$I$6,AA657>Unit_Value_Review_QC!$I$5),"REVIEW","WITHIN_BAND")) -> WITHIN_BAND
A658: 61103099_MM_202005_IMPORT | B658: 43952 | C658: 202005 | D658: 2020 | E658: 5 | F658: 61103099 | G658: 6110 | H658: 676 | I658: MM | J658: Myanmar | K658: IMPORT | L658: 3 | M658: 1 | N658: REPORTED | O658: 0 | P658: 0 | Q658: 132939 | R658: 7003 | S658: 33163 | T658: USABLE | U658: =IF(R658>0,Q658/R658,"") -> 18.98315 | V658: =SUMIFS(fct_world_monthly!$J$2:$J$361,fct_world_monthly!$C$2:$C$361,C658,fct_world_monthly!$F$2:$F$361,F658) -> 8685086 | W658: =IF(V658>0,Q658/V658,"") -> 0.015306584 | X658: W5Q01 | Y658: EXT_HMRC_OTS_WP005_Core4_10PartnerCountries_Monthly_2019-01_to_2026-06_Raw_2026-08-26.json | Z658: =IF(U658="","",SUMIFS(Unit_Value_Review_QC!$K$10:$K$53,Unit_Value_Review_QC!$I$10:$I$53,"PARTNER|"&F658&"|"&I658)) -> 12.70545 | AA658: =IFERROR(U658/Z658,"") -> 1.494095 | AB658: =IF(OR(N658<>"REPORTED",U658=""),"NOT_APPLICABLE",IF(OR(AA658<Unit_Value_Review_QC!$I$6,AA658>Unit_Value_Review_QC!$I$5),"REVIEW","WITHIN_BAND")) -> WITHIN_BAND
A659: 61103099_VN_202005_IMPORT | B659: 43952 | C659: 202005 | D659: 2020 | E659: 5 | F659: 61103099 | G659: 6110 | H659: 690 | I659: VN | J659: Vietnam | K659: IMPORT | L659: 3 | M659: 1 | N659: REPORTED | O659: 0 | P659: 0 | Q659: 276451 | R659: 9321 | S659: 39492 | T659: USABLE | U659: =IF(R659>0,Q659/R659,"") -> 29.658942 | V659: =SUMIFS(fct_world_monthly!$J$2:$J$361,fct_world_monthly!$C$2:$C$361,C659,fct_world_monthly!$F$2:$F$361,F659) -> 8685086 | W659: =IF(V659>0,Q659/V659,"") -> 0.031830543 | X659: W5Q01 | Y659: EXT_HMRC_OTS_WP005_Core4_10PartnerCountries_Monthly_2019-01_to_2026-06_Raw_2026-08-26.json | Z659: =IF(U659="","",SUMIFS(Unit_Value_Review_QC!$K$10:$K$53,Unit_Value_Review_QC!$I$10:$I$53,"PARTNER|"&F659&"|"&I659)) -> 23.234222 | AA659: =IFERROR(U659/Z659,"") -> 1.2765197 | AB659: =IF(OR(N659<>"REPORTED",U659=""),"NOT_APPLICABLE",IF(OR(AA659<Unit_Value_Review_QC!$I$6,AA659>Unit_Value_Review_QC!$I$5),"REVIEW","WITHIN_BAND")) -> WITHIN_BAND
A660: 61103099_KH_202005_IMPORT | B660: 43952 | C660: 202005 | D660: 2020 | E660: 5 | F660: 61103099 | G660: 6110 | H660: 696 | I660: KH | J660: Cambodia | K660: IMPORT | L660: 3 | M660: 1 | N660: REPORTED | O660: 0 | P660: 0 | Q660: 635918 | R660: 35070 | S660: 127047 | T660: USABLE | U660: =IF(R660>0,Q660/R660,"") -> 18.13282 | V660: =SUMIFS(fct_world_monthly!$J$2:$J$361,fct_world_monthly!$C$2:$C$361,C660,fct_world_monthly!$F$2:$F$361,F660) -> 8685086 | W660: =IF(V660>0,Q660/V660,"") -> 0.07321954 | X660: W5Q01 | Y660: EXT_HMRC_OTS_WP005_Core4_10PartnerCountries_Monthly_2019-01_to_2026-06_Raw_2026-08-26.json | Z660: =IF(U660="","",SUMIFS(Unit_Value_Review_QC!$K$10:$K$53,Unit_Value_Review_QC!$I$10:$I$53,"PARTNER|"&F660&"|"&I660)) -> 12.33939 | AA660: =IFERROR(U660/Z660,"") -> 1.469507 | AB660: =IF(OR(N660<>"REPORTED",U660=""),"NOT_APPLICABLE",IF(OR(AA660<Unit_Value_Review_QC!$I$6,AA660>Unit_Value_Review_QC!$I$5),"REVIEW","WITHIN_BAND")) -> WITHIN_BAND
A661: 61103099_CN_202005_IMPORT | B661: 43952 | C661: 202005 | D661: 2020 | E661: 5 | F661: 61103099 | G661: 6110 | H661: 720 | I661: CN | J661: China | K661: IMPORT | L661: 3 | M661: 1 | N661: REPORTED | O661: 0 | P661: 0 | Q661: 953643 | R661: 66441 | S661: 169448 | T661: USABLE | U661: =IF(R661>0,Q661/R661,"") -> 14.353231 | V661: =SUMIFS(fct_world_monthly!$J$2:$J$361,fct_world_monthly!$C$2:$C$361,C661,fct_world_monthly!$F$2:$F$361,F661) -> 8685086 | W661: =IF(V661>0,Q661/V661,"") -> 0.10980237 | X661: W5Q01 | Y661: EXT_HMRC_OTS_WP005_Core4_10PartnerCountries_Monthly_2019-01_to_2026-06_Raw_2026-08-26.json | Z661: =IF(U661="","",SUMIFS(Unit_Value_Review_QC!$K$10:$K$53,Unit_Value_Review_QC!$I$10:$I$53,"PARTNER|"&F661&"|"&I661)) -> 15.158853 | AA661: =IFERROR(U661/Z661,"") -> 0.94685469 | AB661: =IF(OR(N661<>"REPORTED",U661=""),"NOT_APPLICABLE",IF(OR(AA661<Unit_Value_Review_QC!$I$6,AA661>Unit_Value_Review_QC!$I$5),"REVIEW","WITHIN_BAND")) -> WITHIN_BAND
A662: 62044300_TR_202005_IMPORT | B662: 43952 | C662: 202005 | D662: 2020 | E662: 5 | F662: 62044300 | G662: 6204 | H662: 52 | I662: TR | J662: Turkey | K662: IMPORT | L662: 3 | M662: 1 | N662: REPORTED | O662: 0 | P662: 0 | Q662: 718545 | R662: 35213 | S662: 64159 | T662: USABLE | U662: =IF(R662>0,Q662/R662,"") -> 20.405674 | V662: =SUMIFS(fct_world_monthly!$J$2:$J$361,fct_world_monthly!$C$2:$C$361,C662,fct_world_monthly!$F$2:$F$361,F662) -> 17210812 | W662: =IF(V662>0,Q662/V662,"") -> 0.041749628 | X662: W5Q01 | Y662: EXT_HMRC_OTS_WP005_Core4_10PartnerCountries_Monthly_2019-01_to_2026-06_Raw_2026-08-26.json | Z662: =IF(U662="","",SUMIFS(Unit_Value_Review_QC!$K$10:$K$53,Unit_Value_Review_QC!$I$10:$I$53,"PARTNER|"&F662&"|"&I662)) -> 31.867133 | AA662: =IFERROR(U662/Z662,"") -> 0.64033605 | AB662: =IF(OR(N662<>"REPORTED",U662=""),"NOT_APPLICABLE",IF(OR(AA662<Unit_Value_Review_QC!$I$6,AA662>Unit_Value_Review_QC!$I$5),"REVIEW","WITHIN_BAND")) -> WITHIN_BAND
A663: 62044300_MA_202005_IMPORT | B663: 43952 | C663: 202005 | D663: 2020 | E663: 5 | F663: 62044300 | G663: 6204 | H663: 204 | I663: MA | J663: Morocco | K663: IMPORT | L663: 3 | M663: 1 | N663: REPORTED | O663: 0 | P663: 0 | Q663: 47168 | R663: 3518 | S663: 10152 | T663: USABLE | U663: =IF(R663>0,Q663/R663,"") -> 13.407618 | V663: =SUMIFS(fct_world_monthly!$J$2:$J$361,fct_world_monthly!$C$2:$C$361,C663,fct_world_monthly!$F$2:$F$361,F663) -> 17210812 | W663: =IF(V663>0,Q663/V663,"") -> 0.0027406028 | X663: W5Q01 | Y663: EXT_HMRC_OTS_WP005_Core4_10PartnerCountries_Monthly_2019-01_to_2026-06_Raw_2026-08-26.json | Z663: =IF(U663="","",SUMIFS(Unit_Value_Review_QC!$K$10:$K$53,Unit_Value_Review_QC!$I$10:$I$53,"PARTNER|"&F663&"|"&I663)) -> 19.682232 | AA663: =IFERROR(U663/Z663,"") -> 0.68120415 | AB663: =IF(OR(N663<>"REPORTED",U663=""),"NOT_APPLICABLE",IF(OR(AA663<Unit_Value_Review_QC!$I$6,AA663>Unit_Value_Review_QC!$I$5),"REVIEW","WITHIN_BAND")) -> WITHIN_BAND
A664: 62044300_PK_202005_IMPORT | B664: 43952 | C664: 202005 | D664: 2020 | E664: 5 | F664: 62044300 | G664: 6204 | H664: 662 | I664: PK | J664: Pakistan | K664: IMPORT | L664: 3 | M664: 1 | N664: REPORTED | O664: 0 | P664: 0 | Q664: 65283 | R664: 4072 | S664: 14115 | T664: USABLE | U664: =IF(R664>0,Q664/R664,"") -> 16.032171 | V664: =SUMIFS(fct_world_monthly!$J$2:$J$361,fct_world_monthly!$C$2:$C$361,C664,fct_world_monthly!$F$2:$F$361,F664) -> 17210812 | W664: =IF(V664>0,Q664/V664,"") -> 0.0037931389 | X664: W5Q01 | Y664: EXT_HMRC_OTS_WP005_Core4_10PartnerCountries_Monthly_2019-01_to_2026-06_Raw_2026-08-26.json | Z664: =IF(U664="","",SUMIFS(Unit_Value_Review_QC!$K$10:$K$53,Unit_Value_Review_QC!$I$10:$I$53,"PARTNER|"&F664&"|"&I664)) -> 19.366411 | AA664: =IFERROR(U664/Z664,"") -> 0.82783385 | AB664: =IF(OR(N664<>"REPORTED",U664=""),"NOT_APPLICABLE",IF(OR(AA664<Unit_Value_Review_QC!$I$6,AA664>Unit_Value_Review_QC!$I$5),"REVIEW","WITHIN_BAND")) -> WITHIN_BAND
A665: 62044300_IN_202005_IMPORT | B665: 43952 | C665: 202005 | D665: 2020 | E665: 5 | F665: 62044300 | G665: 6204 | H665: 664 | I665: IN | J665: India | K665: IMPORT | L665: 3 | M665: 1 | N665: REPORTED | O665: 0 | P665: 0 | Q665: 1417746 | R665: 64639 | S665: 373487 | T665: USABLE | U665: =IF(R665>0,Q665/R665,"") -> 21.933291 | V665: =SUMIFS(fct_world_monthly!$J$2:$J$361,fct_world_monthly!$C$2:$C$361,C665,fct_world_monthly!$F$2:$F$361,F665) -> 17210812 | W665: =IF(V665>0,Q665/V665,"") -> 0.082375312 | X665: W5Q01 | Y665: EXT_HMRC_OTS_WP005_Core4_10PartnerCountries_Monthly_2019-01_to_2026-06_Raw_2026-08-26.json | Z665: =IF(U665="","",SUMIFS(Unit_Value_Review_QC!$K$10:$K$53,Unit_Value_Review_QC!$I$10:$I$53,"PARTNER|"&F665&"|"&I665)) -> 29.827361 | AA665: =IFERROR(U665/Z665,"") -> 0.73534132 | AB665: =IF(OR(N665<>"REPORTED",U665=""),"NOT_APPLICABLE",IF(OR(AA665<Unit_Value_Review_QC!$I$6,AA665>Unit_Value_Review_QC!$I$5),"REVIEW","WITHIN_BAND")) -> WITHIN_BAND
... A887: 61091000_LK_202011_IMPORT | B887: 44136 | C887: 202011 | D887: 2020 | E887: 11 | F887: 61091000 | G887: 6109 | H887: 669 | I887: LK | J887: Sri Lanka | K887: IMPORT | L887: 3 | M887: 1 | N887: REPORTED | O887: 0 | P887: 0 | Q887: 1525086 | R887: 113622 | S887: 567312 | T887: USABLE | U887: =IF(R887>0,Q887/R887,"") -> 13.422453 | V887: =SUMIFS(fct_world_monthly!$J$2:$J$361,fct_world_monthly!$C$2:$C$361,C887,fct_world_monthly!$F$2:$F$361,F887) -> 98609551 | W887: =IF(V887>0,Q887/V887,"") -> 0.015465906 | X887: W5Q01 | Y887: EXT_HMRC_OTS_WP005_Core4_10PartnerCountries_Monthly_2019-01_to_2026-06_Raw_2026-08-26.json | Z887: =IF(U887="","",SUMIFS(Unit_Value_Review_QC!$K$10:$K$53,Unit_Value_Review_QC!$I$10:$I$53,"PARTNER|"&F887&"|"&I887)) -> 13.552232 | AA887: =IFERROR(U887/Z887,"") -> 0.99042381 | AB887: =IF(OR(N887<>"REPORTED",U887=""),"NOT_APPLICABLE",IF(OR(AA887<Unit_Value_Review_QC!$I$6,AA887>Unit_Value_Review_QC!$I$5),"REVIEW","WITHIN_BAND")) -> WITHIN_BAND
A888: 61091000_MM_202011_IMPORT | B888: 44136 | C888: 202011 | D888: 2020 | E888: 11 | F888: 61091000 | G888: 6109 | H888: 676 | I888: MM | J888: Myanmar | K888: IMPORT | L888: 3 | M888: 0 | N888: NO_API_RECORD | P888: 0 | Q888: 0 | R888: 0 | S888: 0 | T888: NO_REPORTED_TRADE | U888: =IF(R888>0,Q888/R888,"") | V888: =SUMIFS(fct_world_monthly!$J$2:$J$361,fct_world_monthly!$C$2:$C$361,C888,fct_world_monthly!$F$2:$F$361,F888) -> 98609551 | W888: =IF(V888>0,Q888/V888,"") -> 0 | X888: W5Q01 | Y888: EXT_HMRC_OTS_WP005_Core4_10PartnerCountries_Monthly_2019-01_to_2026-06_Raw_2026-08-26.json | Z888: =IF(U888="","",SUMIFS(Unit_Value_Review_QC!$K$10:$K$53,Unit_Value_Review_QC!$I$10:$I$53,"PARTNER|"&F888&"|"&I888)) | AA888: =IFERROR(U888/Z888,"") | AB888: =IF(OR(N888<>"REPORTED",U888=""),"NOT_APPLICABLE",IF(OR(AA888<Unit_Value_Review_QC!$I$6,AA888>Unit_Value_Review_QC!$I$5),"REVIEW","WITHIN_BAND")) -> NOT_APPLICABLE
A889: 61091000_VN_202011_IMPORT | B889: 44136 | C889: 202011 | D889: 2020 | E889: 11 | F889: 61091000 | G889: 6109 | H889: 690 | I889: VN | J889: Vietnam | K889: IMPORT | L889: 3 | M889: 1 | N889: REPORTED | O889: 0 | P889: 0 | Q889: 949902 | R889: 45544 | S889: 377033 | T889: USABLE | U889: =IF(R889>0,Q889/R889,"") -> 20.856798 | V889: =SUMIFS(fct_world_monthly!$J$2:$J$361,fct_world_monthly!$C$2:$C$361,C889,fct_world_monthly!$F$2:$F$361,F889) -> 98609551 | W889: =IF(V889>0,Q889/V889,"") -> 0.0096329614 | X889: W5Q01 | Y889: EXT_HMRC_OTS_WP005_Core4_10PartnerCountries_Monthly_2019-01_to_2026-06_Raw_2026-08-26.json | Z889: =IF(U889="","",SUMIFS(Unit_Value_Review_QC!$K$10:$K$53,Unit_Value_Review_QC!$I$10:$I$53,"PARTNER|"&F889&"|"&I889)) -> 21.029827 | AA889: =IFERROR(U889/Z889,"") -> 0.9917722 | AB889: =IF(OR(N889<>"REPORTED",U889=""),"NOT_APPLICABLE",IF(OR(AA889<Unit_Value_Review_QC!$I$6,AA889>Unit_Value_Review_QC!$I$5),"REVIEW","WITHIN_BAND")) -> WITHIN_BAND
A890: 61091000_KH_202011_IMPORT | B890: 44136 | C890: 202011 | D890: 2020 | E890: 11 | F890: 61091000 | G890: 6109 | H890: 696 | I890: KH | J890: Cambodia | K890: IMPORT | L890: 3 | M890: 1 | N890: REPORTED | O890: 0 | P890: 0 | Q890: 494473 | R890: 23630 | S890: 123306 | T890: USABLE | U890: =IF(R890>0,Q890/R890,"") -> 20.925645 | V890: =SUMIFS(fct_world_monthly!$J$2:$J$361,fct_world_monthly!$C$2:$C$361,C890,fct_world_monthly!$F$2:$F$361,F890) -> 98609551 | W890: =IF(V890>0,Q890/V890,"") -> 0.0050144534 | X890: W5Q01 | Y890: EXT_HMRC_OTS_WP005_Core4_10PartnerCountries_Monthly_2019-01_to_2026-06_Raw_2026-08-26.json | Z890: =IF(U890="","",SUMIFS(Unit_Value_Review_QC!$K$10:$K$53,Unit_Value_Review_QC!$I$10:$I$53,"PARTNER|"&F890&"|"&I890)) -> 18.091181 | AA890: =IFERROR(U890/Z890,"") -> 1.1566765 | AB890: =IF(OR(N890<>"REPORTED",U890=""),"NOT_APPLICABLE",IF(OR(AA890<Unit_Value_Review_QC!$I$6,AA890>Unit_Value_Review_QC!$I$5),"REVIEW","WITHIN_BAND")) -> WITHIN_BAND
A891: 61091000_CN_202011_IMPORT | B891: 44136 | C891: 202011 | D891: 2020 | E891: 11 | F891: 61091000 | G891: 6109 | H891: 720 | I891: CN | J891: China | K891: IMPORT | L891: 3 | M891: 1 | N891: REPORTED | O891: 0 | P891: 0 | Q891: 5010506 | R891: 325891 | S891: 1385483 | T891: USABLE | U891: =IF(R891>0,Q891/R891,"") -> 15.374791 | V891: =SUMIFS(fct_world_monthly!$J$2:$J$361,fct_world_monthly!$C$2:$C$361,C891,fct_world_monthly!$F$2:$F$361,F891) -> 98609551 | W891: =IF(V891>0,Q891/V891,"") -> 0.050811569 | X891: W5Q01 | Y891: EXT_HMRC_OTS_WP005_Core4_10PartnerCountries_Monthly_2019-01_to_2026-06_Raw_2026-08-26.json | Z891: =IF(U891="","",SUMIFS(Unit_Value_Review_QC!$K$10:$K$53,Unit_Value_Review_QC!$I$10:$I$53,"PARTNER|"&F891&"|"&I891)) -> 18.213915 | AA891: =IFERROR(U891/Z891,"") -> 0.84412334 | AB891: =IF(OR(N891<>"REPORTED",U891=""),"NOT_APPLICABLE",IF(OR(AA891<Unit_Value_Review_QC!$I$6,AA891>Unit_Value_Review_QC!$I$5),"REVIEW","WITHIN_BAND")) -> WITHIN_BAND
A892: 61103099_TR_202011_IMPORT | B892: 44136 | C892: 202011 | D892: 2020 | E892: 11 | F892: 61103099 | G892: 6110 | H892: 52 | I892: TR | J892: Turkey | K892: IMPORT | L892: 3 | M892: 1 | N892: REPORTED | O892: 0 | P892: 0 | Q892: 11104252 | R892: 599092 | S892: 1812805 | T892: USABLE | U892: =IF(R892>0,Q892/R892,"") -> 18.535137 | V892: =SUMIFS(fct_world_monthly!$J$2:$J$361,fct_world_monthly!$C$2:$C$361,C892,fct_world_monthly!$F$2:$F$361,F892) -> 68079471 | W892: =IF(V892>0,Q892/V892,"") -> 0.1631072 | X892: W5Q01 | Y892: EXT_HMRC_OTS_WP005_Core4_10PartnerCountries_Monthly_2019-01_to_2026-06_Raw_2026-08-26.json | Z892: =IF(U892="","",SUMIFS(Unit_Value_Review_QC!$K$10:$K$53,Unit_Value_Review_QC!$I$10:$I$53,"PARTNER|"&F892&"|"&I892)) -> 19.213268 | AA892: =IFERROR(U892/Z892,"") -> 0.96470503 | AB892: =IF(OR(N892<>"REPORTED",U892=""),"NOT_APPLICABLE",IF(OR(AA892<Unit_Value_Review_QC!$I$6,AA892>Unit_Value_Review_QC!$I$5),"REVIEW","WITHIN_BAND")) -> WITHIN_BAND
A893: 61103099_MA_202011_IMPORT | B893: 44136 | C893: 202011 | D893: 2020 | E893: 11 | F893: 61103099 | G893: 6110 | H893: 204 | I893: MA | J893: Morocco | K893: IMPORT | L893: 3 | M893: 1 | N893: REPORTED | O893: 0 | P893: 0 | Q893: 49807 | R893: 7653 | S893: 20759 | T893: USABLE | U893: =IF(R893>0,Q893/R893,"") -> 6.5081667 | V893: =SUMIFS(fct_world_monthly!$J$2:$J$361,fct_world_monthly!$C$2:$C$361,C893,fct_world_monthly!$F$2:$F$361,F893) -> 68079471 | W893: =IF(V893>0,Q893/V893,"") -> 0.00073160087 | X893: W5Q01 | Y893: EXT_HMRC_OTS_WP005_Core4_10PartnerCountries_Monthly_2019-01_to_2026-06_Raw_2026-08-26.json | Z893: =IF(U893="","",SUMIFS(Unit_Value_Review_QC!$K$10:$K$53,Unit_Value_Review_QC!$I$10:$I$53,"PARTNER|"&F893&"|"&I893)) -> 16.024819 | AA893: =IFERROR(U893/Z893,"") -> 0.40613045 | AB893: =IF(OR(N893<>"REPORTED",U893=""),"NOT_APPLICABLE",IF(OR(AA893<Unit_Value_Review_QC!$I$6,AA893>Unit_Value_Review_QC!$I$5),"REVIEW","WITHIN_BAND")) -> WITHIN_BAND
A894: 61103099_PK_202011_IMPORT | B894: 44136 | C894: 202011 | D894: 2020 | E894: 11 | F894: 61103099 | G894: 6110 | H894: 662 | I894: PK | J894: Pakistan | K894: IMPORT | L894: 3 | M894: 1 | N894: REPORTED | O894: 0 | P894: 0 | Q894: 650328 | R894: 71325 | S894: 172596 | T894: USABLE | U894: =IF(R894>0,Q894/R894,"") -> 9.1178128 | V894: =SUMIFS(fct_world_monthly!$J$2:$J$361,fct_world_monthly!$C$2:$C$361,C894,fct_world_monthly!$F$2:$F$361,F894) -> 68079471 | W894: =IF(V894>0,Q894/V894,"") -> 0.0095524832 | X894: W5Q01 | Y894: EXT_HMRC_OTS_WP005_Core4_10PartnerCountries_Monthly_2019-01_to_2026-06_Raw_2026-08-26.json | Z894: =IF(U894="","",SUMIFS(Unit_Value_Review_QC!$K$10:$K$53,Unit_Value_Review_QC!$I$10:$I$53,"PARTNER|"&F894&"|"&I894)) -> 13.240688 | AA894: =IFERROR(U894/Z894,"") -> 0.68862076 | AB894: =IF(OR(N894<>"REPORTED",U894=""),"NOT_APPLICABLE",IF(OR(AA894<Unit_Value_Review_QC!$I$6,AA894>Unit_Value_Review_QC!$I$5),"REVIEW","WITHIN_BAND")) -> WITHIN_BAND
A895: 61103099_IN_202011_IMPORT | B895: 44136 | C895: 202011 | D895: 2020 | E895: 11 | F895: 61103099 | G895: 6110 | H895: 664 | I895: IN | J895: India | K895: IMPORT | L895: 3 | M895: 1 | N895: REPORTED | O895: 0 | P895: 0 | Q895: 178327 | R895: 12057 | S895: 36982 | T895: USABLE | U895: =IF(R895>0,Q895/R895,"") -> 14.790329 | V895: =SUMIFS(fct_world_monthly!$J$2:$J$361,fct_world_monthly!$C$2:$C$361,C895,fct_world_monthly!$F$2:$F$361,F895) -> 68079471 | W895: =IF(V895>0,Q895/V895,"") -> 0.0026193946 | X895: W5Q01 | Y895: EXT_HMRC_OTS_WP005_Core4_10PartnerCountries_Monthly_2019-01_to_2026-06_Raw_2026-08-26.json | Z895: =IF(U895="","",SUMIFS(Unit_Value_Review_QC!$K$10:$K$53,Unit_Value_Review_QC!$I$10:$I$53,"PARTNER|"&F895&"|"&I895)) -> 13.033767 | AA895: =IFERROR(U895/Z895,"") -> 1.1347701 | AB895: =IF(OR(N895<>"REPORTED",U895=""),"NOT_APPLICABLE",IF(OR(AA895<Unit_Value_Review_QC!$I$6,AA895>Unit_Value_Review_QC!$I$5),"REVIEW","WITHIN_BAND")) -> WITHIN_BAND
A896: 61103099_BD_202011_IMPORT | B896: 44136 | C896: 202011 | D896: 2020 | E896: 11 | F896: 61103099 | G896: 6110 | H896: 666 | I896: BD | J896: Bangladesh | K896: IMPORT | L896: 3 | M896: 1 | N896: REPORTED | O896: 0 | P896: 0 | Q896: 9732876 | R896: 842322 | S896: 2211094 | T896: USABLE | U896: =IF(R896>0,Q896/R896,"") -> 11.554816 | V896: =SUMIFS(fct_world_monthly!$J$2:$J$361,fct_world_monthly!$C$2:$C$361,C896,fct_world_monthly!$F$2:$F$361,F896) -> 68079471 | W896: =IF(V896>0,Q896/V896,"") -> 0.14296345 | X896: W5Q01 | Y896: EXT_HMRC_OTS_WP005_Core4_10PartnerCountries_Monthly_2019-01_to_2026-06_Raw_2026-08-26.json | Z896: =IF(U896="","",SUMIFS(Unit_Value_Review_QC!$K$10:$K$53,Unit_Value_Review_QC!$I$10:$I$53,"PARTNER|"&F896&"|"&I896)) -> 12.503788 | AA896: =IFERROR(U896/Z896,"") -> 0.92410523 | AB896: =IF(OR(N896<>"REPORTED",U896=""),"NOT_APPLICABLE",IF(OR(AA896<Unit_Value_Review_QC!$I$6,AA896>Unit_Value_Review_QC!$I$5),"REVIEW","WITHIN_BAND")) -> WITHIN_BAND
A897: 61103099_LK_202011_IMPORT | B897: 44136 | C897: 202011 | D897: 2020 | E897: 11 | F897: 61103099 | G897: 6110 | H897: 669 | I897: LK | J897: Sri Lanka | K897: IMPORT | L897: 3 | M897: 1 | N897: REPORTED | O897: 0 | P897: 0 | Q897: 408992 | R897: 27391 | S897: 90917 | T897: USABLE | U897: =IF(R897>0,Q897/R897,"") -> 14.93162 | V897: =SUMIFS(fct_world_monthly!$J$2:$J$361,fct_world_monthly!$C$2:$C$361,C897,fct_world_monthly!$F$2:$F$361,F897) -> 68079471 | W897: =IF(V897>0,Q897/V897,"") -> 0.0060075672 | X897: W5Q01 | Y897: EXT_HMRC_OTS_WP005_Core4_10PartnerCountries_Monthly_2019-01_to_2026-06_Raw_2026-08-26.json | Z897: =IF(U897="","",SUMIFS(Unit_Value_Review_QC!$K$10:$K$53,Unit_Value_Review_QC!$I$10:$I$53,"PARTNER|"&F897&"|"&I897)) -> 16.584044 | AA897: =IFERROR(U897/Z897,"") -> 0.90036061 | AB897: =IF(OR(N897<>"REPORTED",U897=""),"NOT_APPLICABLE",IF(OR(AA897<Unit_Value_Review_QC!$I$6,AA897>Unit_Value_Review_QC!$I$5),"REVIEW","WITHIN_BAND")) -> WITHIN_BAND
A898: 61103099_MM_202011_IMPORT | B898: 44136 | C898: 202011 | D898: 2020 | E898: 11 | F898: 61103099 | G898: 6110 | H898: 676 | I898: MM | J898: Myanmar | K898: IMPORT | L898: 3 | M898: 1 | N898: REPORTED | O898: 0 | P898: 0 | Q898: 1266307 | R898: 80031 | S898: 256214 | T898: USABLE | U898: =IF(R898>0,Q898/R898,"") -> 15.822706 | V898: =SUMIFS(fct_world_monthly!$J$2:$J$361,fct_world_monthly!$C$2:$C$361,C898,fct_world_monthly!$F$2:$F$361,F898) -> 68079471 | W898: =IF(V898>0,Q898/V898,"") -> 0.018600424 | X898: W5Q01 | Y898: EXT_HMRC_OTS_WP005_Core4_10PartnerCountries_Monthly_2019-01_to_2026-06_Raw_2026-08-26.json | Z898: =IF(U898="","",SUMIFS(Unit_Value_Review_QC!$K$10:$K$53,Unit_Value_Review_QC!$I$10:$I$53,"PARTNER|"&F898&"|"&I898)) -> 12.70545 | AA898: =IFERROR(U898/Z898,"") -> 1.2453479 | AB898: =IF(OR(N898<>"REPORTED",U898=""),"NOT_APPLICABLE",IF(OR(AA898<Unit_Value_Review_QC!$I$6,AA898>Unit_Value_Review_QC!$I$5),"REVIEW","WITHIN_BAND")) -> WITHIN_BAND
A899: 61103099_VN_202011_IMPORT | B899: 44136 | C899: 202011 | D899: 2020 | E899: 11 | F899: 61103099 | G899: 6110 | H899: 690 | I899: VN | J899: Vietnam | K899: IMPORT | L899: 3 | M899: 1 | N899: REPORTED | O899: 0 | P899: 0 | Q899: 439157 | R899: 24913 | S899: 82850 | T899: USABLE | U899: =IF(R899>0,Q899/R899,"") -> 17.627624 | V899: =SUMIFS(fct_world_monthly!$J$2:$J$361,fct_world_monthly!$C$2:$C$361,C899,fct_world_monthly!$F$2:$F$361,F899) -> 68079471 | W899: =IF(V899>0,Q899/V899,"") -> 0.0064506524 | X899: W5Q01 | Y899: EXT_HMRC_OTS_WP005_Core4_10PartnerCountries_Monthly_2019-01_to_2026-06_Raw_2026-08-26.json | Z899: =IF(U899="","",SUMIFS(Unit_Value_Review_QC!$K$10:$K$53,Unit_Value_Review_QC!$I$10:$I$53,"PARTNER|"&F899&"|"&I899)) -> 23.234222 | AA899: =IFERROR(U899/Z899,"") -> 0.75869226 | AB899: =IF(OR(N899<>"REPORTED",U899=""),"NOT_APPLICABLE",IF(OR(AA899<Unit_Value_Review_QC!$I$6,AA899>Unit_Value_Review_QC!$I$5),"REVIEW","WITHIN_BAND")) -> WITHIN_BAND
A900: 61103099_KH_202011_IMPORT | B900: 44136 | C900: 202011 | D900: 2020 | E900: 11 | F900: 61103099 | G900: 6110 | H900: 696 | I900: KH | J900: Cambodia | K900: IMPORT | L900: 3 | M900: 1 | N900: REPORTED | O900: 0 | P900: 0 | Q900: 4879459 | R900: 350396 | S900: 976570 | T900: USABLE | U900: =IF(R900>0,Q900/R900,"") -> 13.925556 | V900: =SUMIFS(fct_world_monthly!$J$2:$J$361,fct_world_monthly!$C$2:$C$361,C900,fct_world_monthly!$F$2:$F$361,F900) -> 68079471 | W900: =IF(V900>0,Q900/V900,"") -> 0.071672986 | X900: W5Q01 | Y900: EXT_HMRC_OTS_WP005_Core4_10PartnerCountries_Monthly_2019-01_to_2026-06_Raw_2026-08-26.json | Z900: =IF(U900="","",SUMIFS(Unit_Value_Review_QC!$K$10:$K$53,Unit_Value_Review_QC!$I$10:$I$53,"PARTNER|"&F900&"|"&I900)) -> 12.33939 | AA900: =IFERROR(U900/Z900,"") -> 1.1285449 | AB900: =IF(OR(N900<>"REPORTED",U900=""),"NOT_APPLICABLE",IF(OR(AA900<Unit_Value_Review_QC!$I$6,AA900>Unit_Value_Review_QC!$I$5),"REVIEW","WITHIN_BAND")) -> WITHIN_BAND
... A1073: 62052000_MA_202103_IMPORT | B1073: 44256 | C1073: 202103 | D1073: 2021 | E1073: 3 | F1073: 62052000 | G1073: 6205 | H1073: 204 | I1073: MA | J1073: Morocco | K1073: IMPORT | L1073: 3 | M1073: 1 | N1073: REPORTED | O1073: 0 | P1073: 0 | Q1073: 89759 | R1073: 4995 | S1073: 8666 | T1073: USABLE | U1073: =IF(R1073>0,Q1073/R1073,"") -> 17.96977 | V1073: =SUMIFS(fct_world_monthly!$J$2:$J$361,fct_world_monthly!$C$2:$C$361,C1073,fct_world_monthly!$F$2:$F$361,F1073) -> 13204822 | W1073: =IF(V1073>0,Q1073/V1073,"") -> 0.0067974411 | X1073: W5Q01 | Y1073: EXT_HMRC_OTS_WP005_Core4_10PartnerCountries_Monthly_2019-01_to_2026-06_Raw_2026-08-26.json | Z1073: =IF(U1073="","",SUMIFS(Unit_Value_Review_QC!$K$10:$K$53,Unit_Value_Review_QC!$I$10:$I$53,"PARTNER|"&F1073&"|"&I1073)) -> 33.195881 | AA1073: =IFERROR(U1073/Z1073,"") -> 0.54132529 | AB1073: =IF(OR(N1073<>"REPORTED",U1073=""),"NOT_APPLICABLE",IF(OR(AA1073<Unit_Value_Review_QC!$I$6,AA1073>Unit_Value_Review_QC!$I$5),"REVIEW","WITHIN_BAND")) -> WITHIN_BAND
A1074: 62052000_PK_202103_IMPORT | B1074: 44256 | C1074: 202103 | D1074: 2021 | E1074: 3 | F1074: 62052000 | G1074: 6205 | H1074: 662 | I1074: PK | J1074: Pakistan | K1074: IMPORT | L1074: 3 | M1074: 0 | N1074: NO_API_RECORD | P1074: 0 | Q1074: 0 | R1074: 0 | S1074: 0 | T1074: NO_REPORTED_TRADE | U1074: =IF(R1074>0,Q1074/R1074,"") | V1074: =SUMIFS(fct_world_monthly!$J$2:$J$361,fct_world_monthly!$C$2:$C$361,C1074,fct_world_monthly!$F$2:$F$361,F1074) -> 13204822 | W1074: =IF(V1074>0,Q1074/V1074,"") -> 0 | X1074: W5Q01 | Y1074: EXT_HMRC_OTS_WP005_Core4_10PartnerCountries_Monthly_2019-01_to_2026-06_Raw_2026-08-26.json | Z1074: =IF(U1074="","",SUMIFS(Unit_Value_Review_QC!$K$10:$K$53,Unit_Value_Review_QC!$I$10:$I$53,"PARTNER|"&F1074&"|"&I1074)) | AA1074: =IFERROR(U1074/Z1074,"") | AB1074: =IF(OR(N1074<>"REPORTED",U1074=""),"NOT_APPLICABLE",IF(OR(AA1074<Unit_Value_Review_QC!$I$6,AA1074>Unit_Value_Review_QC!$I$5),"REVIEW","WITHIN_BAND")) -> NOT_APPLICABLE
A1075: 62052000_IN_202103_IMPORT | B1075: 44256 | C1075: 202103 | D1075: 2021 | E1075: 3 | F1075: 62052000 | G1075: 6205 | H1075: 664 | I1075: IN | J1075: India | K1075: IMPORT | L1075: 3 | M1075: 1 | N1075: REPORTED | O1075: 0 | P1075: 0 | Q1075: 1696696 | R1075: 84112 | S1075: 326424 | T1075: USABLE | U1075: =IF(R1075>0,Q1075/R1075,"") -> 20.171866 | V1075: =SUMIFS(fct_world_monthly!$J$2:$J$361,fct_world_monthly!$C$2:$C$361,C1075,fct_world_monthly!$F$2:$F$361,F1075) -> 13204822 | W1075: =IF(V1075>0,Q1075/V1075,"") -> 0.12849064 | X1075: W5Q01 | Y1075: EXT_HMRC_OTS_WP005_Core4_10PartnerCountries_Monthly_2019-01_to_2026-06_Raw_2026-08-26.json | Z1075: =IF(U1075="","",SUMIFS(Unit_Value_Review_QC!$K$10:$K$53,Unit_Value_Review_QC!$I$10:$I$53,"PARTNER|"&F1075&"|"&I1075)) -> 20.753901 | AA1075: =IFERROR(U1075/Z1075,"") -> 0.97195539 | AB1075: =IF(OR(N1075<>"REPORTED",U1075=""),"NOT_APPLICABLE",IF(OR(AA1075<Unit_Value_Review_QC!$I$6,AA1075>Unit_Value_Review_QC!$I$5),"REVIEW","WITHIN_BAND")) -> WITHIN_BAND
A1076: 62052000_BD_202103_IMPORT | B1076: 44256 | C1076: 202103 | D1076: 2021 | E1076: 3 | F1076: 62052000 | G1076: 6205 | H1076: 666 | I1076: BD | J1076: Bangladesh | K1076: IMPORT | L1076: 3 | M1076: 1 | N1076: REPORTED | O1076: 0 | P1076: 0 | Q1076: 3584915 | R1076: 242056 | S1076: 907062 | T1076: USABLE | U1076: =IF(R1076>0,Q1076/R1076,"") -> 14.810271 | V1076: =SUMIFS(fct_world_monthly!$J$2:$J$361,fct_world_monthly!$C$2:$C$361,C1076,fct_world_monthly!$F$2:$F$361,F1076) -> 13204822 | W1076: =IF(V1076>0,Q1076/V1076,"") -> 0.2714853 | X1076: W5Q01 | Y1076: EXT_HMRC_OTS_WP005_Core4_10PartnerCountries_Monthly_2019-01_to_2026-06_Raw_2026-08-26.json | Z1076: =IF(U1076="","",SUMIFS(Unit_Value_Review_QC!$K$10:$K$53,Unit_Value_Review_QC!$I$10:$I$53,"PARTNER|"&F1076&"|"&I1076)) -> 16.653215 | AA1076: =IFERROR(U1076/Z1076,"") -> 0.88933407 | AB1076: =IF(OR(N1076<>"REPORTED",U1076=""),"NOT_APPLICABLE",IF(OR(AA1076<Unit_Value_Review_QC!$I$6,AA1076>Unit_Value_Review_QC!$I$5),"REVIEW","WITHIN_BAND")) -> WITHIN_BAND
A1077: 62052000_LK_202103_IMPORT | B1077: 44256 | C1077: 202103 | D1077: 2021 | E1077: 3 | F1077: 62052000 | G1077: 6205 | H1077: 669 | I1077: LK | J1077: Sri Lanka | K1077: IMPORT | L1077: 3 | M1077: 1 | N1077: REPORTED | O1077: 0 | P1077: 0 | Q1077: 128785 | R1077: 6868 | S1077: 18284 | T1077: USABLE | U1077: =IF(R1077>0,Q1077/R1077,"") -> 18.751456 | V1077: =SUMIFS(fct_world_monthly!$J$2:$J$361,fct_world_monthly!$C$2:$C$361,C1077,fct_world_monthly!$F$2:$F$361,F1077) -> 13204822 | W1077: =IF(V1077>0,Q1077/V1077,"") -> 0.0097528766 | X1077: W5Q01 | Y1077: EXT_HMRC_OTS_WP005_Core4_10PartnerCountries_Monthly_2019-01_to_2026-06_Raw_2026-08-26.json | Z1077: =IF(U1077="","",SUMIFS(Unit_Value_Review_QC!$K$10:$K$53,Unit_Value_Review_QC!$I$10:$I$53,"PARTNER|"&F1077&"|"&I1077)) -> 20.668788 | AA1077: =IFERROR(U1077/Z1077,"") -> 0.9072354 | AB1077: =IF(OR(N1077<>"REPORTED",U1077=""),"NOT_APPLICABLE",IF(OR(AA1077<Unit_Value_Review_QC!$I$6,AA1077>Unit_Value_Review_QC!$I$5),"REVIEW","WITHIN_BAND")) -> WITHIN_BAND
A1078: 62052000_MM_202103_IMPORT | B1078: 44256 | C1078: 202103 | D1078: 2021 | E1078: 3 | F1078: 62052000 | G1078: 6205 | H1078: 676 | I1078: MM | J1078: Myanmar | K1078: IMPORT | L1078: 3 | M1078: 1 | N1078: REPORTED | O1078: 0 | P1078: 0 | Q1078: 18574 | R1078: 829 | S1078: 3763 | T1078: USABLE | U1078: =IF(R1078>0,Q1078/R1078,"") -> 22.405308 | V1078: =SUMIFS(fct_world_monthly!$J$2:$J$361,fct_world_monthly!$C$2:$C$361,C1078,fct_world_monthly!$F$2:$F$361,F1078) -> 13204822 | W1078: =IF(V1078>0,Q1078/V1078,"") -> 0.0014066074 | X1078: W5Q01 | Y1078: EXT_HMRC_OTS_WP005_Core4_10PartnerCountries_Monthly_2019-01_to_2026-06_Raw_2026-08-26.json | Z1078: =IF(U1078="","",SUMIFS(Unit_Value_Review_QC!$K$10:$K$53,Unit_Value_Review_QC!$I$10:$I$53,"PARTNER|"&F1078&"|"&I1078)) -> 22.71684 | AA1078: =IFERROR(U1078/Z1078,"") -> 0.98628629 | AB1078: =IF(OR(N1078<>"REPORTED",U1078=""),"NOT_APPLICABLE",IF(OR(AA1078<Unit_Value_Review_QC!$I$6,AA1078>Unit_Value_Review_QC!$I$5),"REVIEW","WITHIN_BAND")) -> WITHIN_BAND
A1079: 62052000_VN_202103_IMPORT | B1079: 44256 | C1079: 202103 | D1079: 2021 | E1079: 3 | F1079: 62052000 | G1079: 6205 | H1079: 690 | I1079: VN | J1079: Vietnam | K1079: IMPORT | L1079: 3 | M1079: 1 | N1079: REPORTED | O1079: 0 | P1079: 0 | Q1079: 388523 | R1079: 15598 | S1079: 49136 | T1079: USABLE | U1079: =IF(R1079>0,Q1079/R1079,"") -> 24.908514 | V1079: =SUMIFS(fct_world_monthly!$J$2:$J$361,fct_world_monthly!$C$2:$C$361,C1079,fct_world_monthly!$F$2:$F$361,F1079) -> 13204822 | W1079: =IF(V1079>0,Q1079/V1079,"") -> 0.029422812 | X1079: W5Q01 | Y1079: EXT_HMRC_OTS_WP005_Core4_10PartnerCountries_Monthly_2019-01_to_2026-06_Raw_2026-08-26.json | Z1079: =IF(U1079="","",SUMIFS(Unit_Value_Review_QC!$K$10:$K$53,Unit_Value_Review_QC!$I$10:$I$53,"PARTNER|"&F1079&"|"&I1079)) -> 28.158454 | AA1079: =IFERROR(U1079/Z1079,"") -> 0.88458387 | AB1079: =IF(OR(N1079<>"REPORTED",U1079=""),"NOT_APPLICABLE",IF(OR(AA1079<Unit_Value_Review_QC!$I$6,AA1079>Unit_Value_Review_QC!$I$5),"REVIEW","WITHIN_BAND")) -> WITHIN_BAND
A1080: 62052000_KH_202103_IMPORT | B1080: 44256 | C1080: 202103 | D1080: 2021 | E1080: 3 | F1080: 62052000 | G1080: 6205 | H1080: 696 | I1080: KH | J1080: Cambodia | K1080: IMPORT | L1080: 3 | M1080: 1 | N1080: REPORTED | O1080: 0 | P1080: 0 | Q1080: 177060 | R1080: 6083 | S1080: 26954 | T1080: USABLE | U1080: =IF(R1080>0,Q1080/R1080,"") -> 29.107348 | V1080: =SUMIFS(fct_world_monthly!$J$2:$J$361,fct_world_monthly!$C$2:$C$361,C1080,fct_world_monthly!$F$2:$F$361,F1080) -> 13204822 | W1080: =IF(V1080>0,Q1080/V1080,"") -> 0.013408738 | X1080: W5Q01 | Y1080: EXT_HMRC_OTS_WP005_Core4_10PartnerCountries_Monthly_2019-01_to_2026-06_Raw_2026-08-26.json | Z1080: =IF(U1080="","",SUMIFS(Unit_Value_Review_QC!$K$10:$K$53,Unit_Value_Review_QC!$I$10:$I$53,"PARTNER|"&F1080&"|"&I1080)) -> 25.266639 | AA1080: =IFERROR(U1080/Z1080,"") -> 1.1520071 | AB1080: =IF(OR(N1080<>"REPORTED",U1080=""),"NOT_APPLICABLE",IF(OR(AA1080<Unit_Value_Review_QC!$I$6,AA1080>Unit_Value_Review_QC!$I$5),"REVIEW","WITHIN_BAND")) -> WITHIN_BAND
A1081: 62052000_CN_202103_IMPORT | B1081: 44256 | C1081: 202103 | D1081: 2021 | E1081: 3 | F1081: 62052000 | G1081: 6205 | H1081: 720 | I1081: CN | J1081: China | K1081: IMPORT | L1081: 3 | M1081: 1 | N1081: REPORTED | O1081: 0 | P1081: 0 | Q1081: 1159220 | R1081: 52378 | S1081: 170177 | T1081: USABLE | U1081: =IF(R1081>0,Q1081/R1081,"") -> 22.131811 | V1081: =SUMIFS(fct_world_monthly!$J$2:$J$361,fct_world_monthly!$C$2:$C$361,C1081,fct_world_monthly!$F$2:$F$361,F1081) -> 13204822 | W1081: =IF(V1081>0,Q1081/V1081,"") -> 0.087787628 | X1081: W5Q01 | Y1081: EXT_HMRC_OTS_WP005_Core4_10PartnerCountries_Monthly_2019-01_to_2026-06_Raw_2026-08-26.json | Z1081: =IF(U1081="","",SUMIFS(Unit_Value_Review_QC!$K$10:$K$53,Unit_Value_Review_QC!$I$10:$I$53,"PARTNER|"&F1081&"|"&I1081)) -> 23.211498 | AA1081: =IFERROR(U1081/Z1081,"") -> 0.95348484 | AB1081: =IF(OR(N1081<>"REPORTED",U1081=""),"NOT_APPLICABLE",IF(OR(AA1081<Unit_Value_Review_QC!$I$6,AA1081>Unit_Value_Review_QC!$I$5),"REVIEW","WITHIN_BAND")) -> WITHIN_BAND
A1082: 61091000_TR_202104_IMPORT | B1082: 44287 | C1082: 202104 | D1082: 2021 | E1082: 4 | F1082: 61091000 | G1082: 6109 | H1082: 52 | I1082: TR | J1082: Turkey | K1082: IMPORT | L1082: 3 | M1082: 1 | N1082: REPORTED | O1082: 0 | P1082: 0 | Q1082: 13828441 | R1082: 734728 | S1082: 3896851 | T1082: USABLE | U1082: =IF(R1082>0,Q1082/R1082,"") -> 18.821171 | V1082: =SUMIFS(fct_world_monthly!$J$2:$J$361,fct_world_monthly!$C$2:$C$361,C1082,fct_world_monthly!$F$2:$F$361,F1082) -> 117457126 | W1082: =IF(V1082>0,Q1082/V1082,"") -> 0.11773182 | X1082: W5Q01 | Y1082: EXT_HMRC_OTS_WP005_Core4_10PartnerCountries_Monthly_2019-01_to_2026-06_Raw_2026-08-26.json | Z1082: =IF(U1082="","",SUMIFS(Unit_Value_Review_QC!$K$10:$K$53,Unit_Value_Review_QC!$I$10:$I$53,"PARTNER|"&F1082&"|"&I1082)) -> 20.461445 | AA1082: =IFERROR(U1082/Z1082,"") -> 0.91983586 | AB1082: =IF(OR(N1082<>"REPORTED",U1082=""),"NOT_APPLICABLE",IF(OR(AA1082<Unit_Value_Review_QC!$I$6,AA1082>Unit_Value_Review_QC!$I$5),"REVIEW","WITHIN_BAND")) -> WITHIN_BAND
A1083: 61091000_MA_202104_IMPORT | B1083: 44287 | C1083: 202104 | D1083: 2021 | E1083: 4 | F1083: 61091000 | G1083: 6109 | H1083: 204 | I1083: MA | J1083: Morocco | K1083: IMPORT | L1083: 3 | M1083: 1 | N1083: REPORTED | O1083: 0 | P1083: 0 | Q1083: 1284581 | R1083: 217364 | S1083: 1494671 | T1083: USABLE | U1083: =IF(R1083>0,Q1083/R1083,"") -> 5.9098149 | V1083: =SUMIFS(fct_world_monthly!$J$2:$J$361,fct_world_monthly!$C$2:$C$361,C1083,fct_world_monthly!$F$2:$F$361,F1083) -> 117457126 | W1083: =IF(V1083>0,Q1083/V1083,"") -> 0.010936595 | X1083: W5Q01 | Y1083: EXT_HMRC_OTS_WP005_Core4_10PartnerCountries_Monthly_2019-01_to_2026-06_Raw_2026-08-26.json | Z1083: =IF(U1083="","",SUMIFS(Unit_Value_Review_QC!$K$10:$K$53,Unit_Value_Review_QC!$I$10:$I$53,"PARTNER|"&F1083&"|"&I1083)) -> 7.8392981 | AA1083: =IFERROR(U1083/Z1083,"") -> 0.75387041 | AB1083: =IF(OR(N1083<>"REPORTED",U1083=""),"NOT_APPLICABLE",IF(OR(AA1083<Unit_Value_Review_QC!$I$6,AA1083>Unit_Value_Review_QC!$I$5),"REVIEW","WITHIN_BAND")) -> WITHIN_BAND
A1084: 61091000_PK_202104_IMPORT | B1084: 44287 | C1084: 202104 | D1084: 2021 | E1084: 4 | F1084: 61091000 | G1084: 6109 | H1084: 662 | I1084: PK | J1084: Pakistan | K1084: IMPORT | L1084: 3 | M1084: 1 | N1084: REPORTED | O1084: 0 | P1084: 0 | Q1084: 3476574 | R1084: 390941 | S1084: 1422498 | T1084: USABLE | U1084: =IF(R1084>0,Q1084/R1084,"") -> 8.8928355 | V1084: =SUMIFS(fct_world_monthly!$J$2:$J$361,fct_world_monthly!$C$2:$C$361,C1084,fct_world_monthly!$F$2:$F$361,F1084) -> 117457126 | W1084: =IF(V1084>0,Q1084/V1084,"") -> 0.029598664 | X1084: W5Q01 | Y1084: EXT_HMRC_OTS_WP005_Core4_10PartnerCountries_Monthly_2019-01_to_2026-06_Raw_2026-08-26.json | Z1084: =IF(U1084="","",SUMIFS(Unit_Value_Review_QC!$K$10:$K$53,Unit_Value_Review_QC!$I$10:$I$53,"PARTNER|"&F1084&"|"&I1084)) -> 10.235891 | AA1084: =IFERROR(U1084/Z1084,"") -> 0.86878955 | AB1084: =IF(OR(N1084<>"REPORTED",U1084=""),"NOT_APPLICABLE",IF(OR(AA1084<Unit_Value_Review_QC!$I$6,AA1084>Unit_Value_Review_QC!$I$5),"REVIEW","WITHIN_BAND")) -> WITHIN_BAND
A1085: 61091000_IN_202104_IMPORT | B1085: 44287 | C1085: 202104 | D1085: 2021 | E1085: 4 | F1085: 61091000 | G1085: 6109 | H1085: 664 | I1085: IN | J1085: India | K1085: IMPORT | L1085: 3 | M1085: 1 | N1085: REPORTED | O1085: 0 | P1085: 0 | Q1085: 10109884 | R1085: 870953 | S1085: 5320262 | T1085: USABLE | U1085: =IF(R1085>0,Q1085/R1085,"") -> 11.607841 | V1085: =SUMIFS(fct_world_monthly!$J$2:$J$361,fct_world_monthly!$C$2:$C$361,C1085,fct_world_monthly!$F$2:$F$361,F1085) -> 117457126 | W1085: =IF(V1085>0,Q1085/V1085,"") -> 0.086072973 | X1085: W5Q01 | Y1085: EXT_HMRC_OTS_WP005_Core4_10PartnerCountries_Monthly_2019-01_to_2026-06_Raw_2026-08-26.json | Z1085: =IF(U1085="","",SUMIFS(Unit_Value_Review_QC!$K$10:$K$53,Unit_Value_Review_QC!$I$10:$I$53,"PARTNER|"&F1085&"|"&I1085)) -> 13.59406 | AA1085: =IFERROR(U1085/Z1085,"") -> 0.85389069 | AB1085: =IF(OR(N1085<>"REPORTED",U1085=""),"NOT_APPLICABLE",IF(OR(AA1085<Unit_Value_Review_QC!$I$6,AA1085>Unit_Value_Review_QC!$I$5),"REVIEW","WITHIN_BAND")) -> WITHIN_BAND
A1086: 61091000_BD_202104_IMPORT | B1086: 44287 | C1086: 202104 | D1086: 2021 | E1086: 4 | F1086: 61091000 | G1086: 6109 | H1086: 666 | I1086: BD | J1086: Bangladesh | K1086: IMPORT | L1086: 3 | M1086: 1 | N1086: REPORTED | O1086: 0 | P1086: 0 | Q1086: 35756096 | R1086: 3979721 | S1086: 25691927 | T1086: USABLE | U1086: =IF(R1086>0,Q1086/R1086,"") -> 8.9845735 | V1086: =SUMIFS(fct_world_monthly!$J$2:$J$361,fct_world_monthly!$C$2:$C$361,C1086,fct_world_monthly!$F$2:$F$361,F1086) -> 117457126 | W1086: =IF(V1086>0,Q1086/V1086,"") -> 0.30441828 | X1086: W5Q01 | Y1086: EXT_HMRC_OTS_WP005_Core4_10PartnerCountries_Monthly_2019-01_to_2026-06_Raw_2026-08-26.json | Z1086: =IF(U1086="","",SUMIFS(Unit_Value_Review_QC!$K$10:$K$53,Unit_Value_Review_QC!$I$10:$I$53,"PARTNER|"&F1086&"|"&I1086)) -> 10.323148 | AA1086: =IFERROR(U1086/Z1086,"") -> 0.87033277 | AB1086: =IF(OR(N1086<>"REPORTED",U1086=""),"NOT_APPLICABLE",IF(OR(AA1086<Unit_Value_Review_QC!$I$6,AA1086>Unit_Value_Review_QC!$I$5),"REVIEW","WITHIN_BAND")) -> WITHIN_BAND
... A1292: 61103099_TR_202109_IMPORT | B1292: 44440 | C1292: 202109 | D1292: 2021 | E1292: 9 | F1292: 61103099 | G1292: 6110 | H1292: 52 | I1292: TR | J1292: Turkey | K1292: IMPORT | L1292: 3 | M1292: 1 | N1292: REPORTED | O1292: 0 | P1292: 0 | Q1292: 6904926 | R1292: 357013 | S1292: 1040019 | T1292: USABLE | U1292: =IF(R1292>0,Q1292/R1292,"") -> 19.340825 | V1292: =SUMIFS(fct_world_monthly!$J$2:$J$361,fct_world_monthly!$C$2:$C$361,C1292,fct_world_monthly!$F$2:$F$361,F1292) -> 74698348 | W1292: =IF(V1292>0,Q1292/V1292,"") -> 0.092437466 | X1292: W5Q01 | Y1292: EXT_HMRC_OTS_WP005_Core4_10PartnerCountries_Monthly_2019-01_to_2026-06_Raw_2026-08-26.json | Z1292: =IF(U1292="","",SUMIFS(Unit_Value_Review_QC!$K$10:$K$53,Unit_Value_Review_QC!$I$10:$I$53,"PARTNER|"&F1292&"|"&I1292)) -> 19.213268 | AA1292: =IFERROR(U1292/Z1292,"") -> 1.006639 | AB1292: =IF(OR(N1292<>"REPORTED",U1292=""),"NOT_APPLICABLE",IF(OR(AA1292<Unit_Value_Review_QC!$I$6,AA1292>Unit_Value_Review_QC!$I$5),"REVIEW","WITHIN_BAND")) -> WITHIN_BAND
A1293: 61103099_MA_202109_IMPORT | B1293: 44440 | C1293: 202109 | D1293: 2021 | E1293: 9 | F1293: 61103099 | G1293: 6110 | H1293: 204 | I1293: MA | J1293: Morocco | K1293: IMPORT | L1293: 3 | M1293: 0 | N1293: NO_API_RECORD | P1293: 0 | Q1293: 0 | R1293: 0 | S1293: 0 | T1293: NO_REPORTED_TRADE | U1293: =IF(R1293>0,Q1293/R1293,"") | V1293: =SUMIFS(fct_world_monthly!$J$2:$J$361,fct_world_monthly!$C$2:$C$361,C1293,fct_world_monthly!$F$2:$F$361,F1293) -> 74698348 | W1293: =IF(V1293>0,Q1293/V1293,"") -> 0 | X1293: W5Q01 | Y1293: EXT_HMRC_OTS_WP005_Core4_10PartnerCountries_Monthly_2019-01_to_2026-06_Raw_2026-08-26.json | Z1293: =IF(U1293="","",SUMIFS(Unit_Value_Review_QC!$K$10:$K$53,Unit_Value_Review_QC!$I$10:$I$53,"PARTNER|"&F1293&"|"&I1293)) | AA1293: =IFERROR(U1293/Z1293,"") | AB1293: =IF(OR(N1293<>"REPORTED",U1293=""),"NOT_APPLICABLE",IF(OR(AA1293<Unit_Value_Review_QC!$I$6,AA1293>Unit_Value_Review_QC!$I$5),"REVIEW","WITHIN_BAND")) -> NOT_APPLICABLE
A1294: 61103099_PK_202109_IMPORT | B1294: 44440 | C1294: 202109 | D1294: 2021 | E1294: 9 | F1294: 61103099 | G1294: 6110 | H1294: 662 | I1294: PK | J1294: Pakistan | K1294: IMPORT | L1294: 3 | M1294: 1 | N1294: REPORTED | O1294: 0 | P1294: 0 | Q1294: 914783 | R1294: 92043 | S1294: 204296 | T1294: USABLE | U1294: =IF(R1294>0,Q1294/R1294,"") -> 9.9386482 | V1294: =SUMIFS(fct_world_monthly!$J$2:$J$361,fct_world_monthly!$C$2:$C$361,C1294,fct_world_monthly!$F$2:$F$361,F1294) -> 74698348 | W1294: =IF(V1294>0,Q1294/V1294,"") -> 0.012246362 | X1294: W5Q01 | Y1294: EXT_HMRC_OTS_WP005_Core4_10PartnerCountries_Monthly_2019-01_to_2026-06_Raw_2026-08-26.json | Z1294: =IF(U1294="","",SUMIFS(Unit_Value_Review_QC!$K$10:$K$53,Unit_Value_Review_QC!$I$10:$I$53,"PARTNER|"&F1294&"|"&I1294)) -> 13.240688 | AA1294: =IFERROR(U1294/Z1294,"") -> 0.75061417 | AB1294: =IF(OR(N1294<>"REPORTED",U1294=""),"NOT_APPLICABLE",IF(OR(AA1294<Unit_Value_Review_QC!$I$6,AA1294>Unit_Value_Review_QC!$I$5),"REVIEW","WITHIN_BAND")) -> WITHIN_BAND
A1295: 61103099_IN_202109_IMPORT | B1295: 44440 | C1295: 202109 | D1295: 2021 | E1295: 9 | F1295: 61103099 | G1295: 6110 | H1295: 664 | I1295: IN | J1295: India | K1295: IMPORT | L1295: 3 | M1295: 1 | N1295: REPORTED | O1295: 0 | P1295: 0 | Q1295: 170939 | R1295: 19170 | S1295: 34261 | T1295: USABLE | U1295: =IF(R1295>0,Q1295/R1295,"") -> 8.9170057 | V1295: =SUMIFS(fct_world_monthly!$J$2:$J$361,fct_world_monthly!$C$2:$C$361,C1295,fct_world_monthly!$F$2:$F$361,F1295) -> 74698348 | W1295: =IF(V1295>0,Q1295/V1295,"") -> 0.0022883906 | X1295: W5Q01 | Y1295: EXT_HMRC_OTS_WP005_Core4_10PartnerCountries_Monthly_2019-01_to_2026-06_Raw_2026-08-26.json | Z1295: =IF(U1295="","",SUMIFS(Unit_Value_Review_QC!$K$10:$K$53,Unit_Value_Review_QC!$I$10:$I$53,"PARTNER|"&F1295&"|"&I1295)) -> 13.033767 | AA1295: =IFERROR(U1295/Z1295,"") -> 0.68414647 | AB1295: =IF(OR(N1295<>"REPORTED",U1295=""),"NOT_APPLICABLE",IF(OR(AA1295<Unit_Value_Review_QC!$I$6,AA1295>Unit_Value_Review_QC!$I$5),"REVIEW","WITHIN_BAND")) -> WITHIN_BAND
A1296: 61103099_BD_202109_IMPORT | B1296: 44440 | C1296: 202109 | D1296: 2021 | E1296: 9 | F1296: 61103099 | G1296: 6110 | H1296: 666 | I1296: BD | J1296: Bangladesh | K1296: IMPORT | L1296: 3 | M1296: 1 | N1296: REPORTED | O1296: 0 | P1296: 0 | Q1296: 12788661 | R1296: 1216156 | S1296: 3099061 | T1296: USABLE | U1296: =IF(R1296>0,Q1296/R1296,"") -> 10.515642 | V1296: =SUMIFS(fct_world_monthly!$J$2:$J$361,fct_world_monthly!$C$2:$C$361,C1296,fct_world_monthly!$F$2:$F$361,F1296) -> 74698348 | W1296: =IF(V1296>0,Q1296/V1296,"") -> 0.17120407 | X1296: W5Q01 | Y1296: EXT_HMRC_OTS_WP005_Core4_10PartnerCountries_Monthly_2019-01_to_2026-06_Raw_2026-08-26.json | Z1296: =IF(U1296="","",SUMIFS(Unit_Value_Review_QC!$K$10:$K$53,Unit_Value_Review_QC!$I$10:$I$53,"PARTNER|"&F1296&"|"&I1296)) -> 12.503788 | AA1296: =IFERROR(U1296/Z1296,"") -> 0.84099647 | AB1296: =IF(OR(N1296<>"REPORTED",U1296=""),"NOT_APPLICABLE",IF(OR(AA1296<Unit_Value_Review_QC!$I$6,AA1296>Unit_Value_Review_QC!$I$5),"REVIEW","WITHIN_BAND")) -> WITHIN_BAND
A1297: 61103099_LK_202109_IMPORT | B1297: 44440 | C1297: 202109 | D1297: 2021 | E1297: 9 | F1297: 61103099 | G1297: 6110 | H1297: 669 | I1297: LK | J1297: Sri Lanka | K1297: IMPORT | L1297: 3 | M1297: 1 | N1297: REPORTED | O1297: 0 | P1297: 0 | Q1297: 134782 | R1297: 8415 | S1297: 33086 | T1297: USABLE | U1297: =IF(R1297>0,Q1297/R1297,"") -> 16.016875 | V1297: =SUMIFS(fct_world_monthly!$J$2:$J$361,fct_world_monthly!$C$2:$C$361,C1297,fct_world_monthly!$F$2:$F$361,F1297) -> 74698348 | W1297: =IF(V1297>0,Q1297/V1297,"") -> 0.0018043505 | X1297: W5Q01 | Y1297: EXT_HMRC_OTS_WP005_Core4_10PartnerCountries_Monthly_2019-01_to_2026-06_Raw_2026-08-26.json | Z1297: =IF(U1297="","",SUMIFS(Unit_Value_Review_QC!$K$10:$K$53,Unit_Value_Review_QC!$I$10:$I$53,"PARTNER|"&F1297&"|"&I1297)) -> 16.584044 | AA1297: =IFERROR(U1297/Z1297,"") -> 0.96580031 | AB1297: =IF(OR(N1297<>"REPORTED",U1297=""),"NOT_APPLICABLE",IF(OR(AA1297<Unit_Value_Review_QC!$I$6,AA1297>Unit_Value_Review_QC!$I$5),"REVIEW","WITHIN_BAND")) -> WITHIN_BAND
A1298: 61103099_MM_202109_IMPORT | B1298: 44440 | C1298: 202109 | D1298: 2021 | E1298: 9 | F1298: 61103099 | G1298: 6110 | H1298: 676 | I1298: MM | J1298: Myanmar | K1298: IMPORT | L1298: 3 | M1298: 1 | N1298: REPORTED | O1298: 0 | P1298: 0 | Q1298: 1347932 | R1298: 165555 | S1298: 390936 | T1298: USABLE | U1298: =IF(R1298>0,Q1298/R1298,"") -> 8.1418985 | V1298: =SUMIFS(fct_world_monthly!$J$2:$J$361,fct_world_monthly!$C$2:$C$361,C1298,fct_world_monthly!$F$2:$F$361,F1298) -> 74698348 | W1298: =IF(V1298>0,Q1298/V1298,"") -> 0.018045004 | X1298: W5Q01 | Y1298: EXT_HMRC_OTS_WP005_Core4_10PartnerCountries_Monthly_2019-01_to_2026-06_Raw_2026-08-26.json | Z1298: =IF(U1298="","",SUMIFS(Unit_Value_Review_QC!$K$10:$K$53,Unit_Value_Review_QC!$I$10:$I$53,"PARTNER|"&F1298&"|"&I1298)) -> 12.70545 | AA1298: =IFERROR(U1298/Z1298,"") -> 0.64081935 | AB1298: =IF(OR(N1298<>"REPORTED",U1298=""),"NOT_APPLICABLE",IF(OR(AA1298<Unit_Value_Review_QC!$I$6,AA1298>Unit_Value_Review_QC!$I$5),"REVIEW","WITHIN_BAND")) -> WITHIN_BAND
A1299: 61103099_VN_202109_IMPORT | B1299: 44440 | C1299: 202109 | D1299: 2021 | E1299: 9 | F1299: 61103099 | G1299: 6110 | H1299: 690 | I1299: VN | J1299: Vietnam | K1299: IMPORT | L1299: 3 | M1299: 1 | N1299: REPORTED | O1299: 0 | P1299: 0 | Q1299: 697799 | R1299: 45461 | S1299: 147060 | T1299: USABLE | U1299: =IF(R1299>0,Q1299/R1299,"") -> 15.349398 | V1299: =SUMIFS(fct_world_monthly!$J$2:$J$361,fct_world_monthly!$C$2:$C$361,C1299,fct_world_monthly!$F$2:$F$361,F1299) -> 74698348 | W1299: =IF(V1299>0,Q1299/V1299,"") -> 0.0093415587 | X1299: W5Q01 | Y1299: EXT_HMRC_OTS_WP005_Core4_10PartnerCountries_Monthly_2019-01_to_2026-06_Raw_2026-08-26.json | Z1299: =IF(U1299="","",SUMIFS(Unit_Value_Review_QC!$K$10:$K$53,Unit_Value_Review_QC!$I$10:$I$53,"PARTNER|"&F1299&"|"&I1299)) -> 23.234222 | AA1299: =IFERROR(U1299/Z1299,"") -> 0.66063751 | AB1299: =IF(OR(N1299<>"REPORTED",U1299=""),"NOT_APPLICABLE",IF(OR(AA1299<Unit_Value_Review_QC!$I$6,AA1299>Unit_Value_Review_QC!$I$5),"REVIEW","WITHIN_BAND")) -> WITHIN_BAND
A1300: 61103099_KH_202109_IMPORT | B1300: 44440 | C1300: 202109 | D1300: 2021 | E1300: 9 | F1300: 61103099 | G1300: 6110 | H1300: 696 | I1300: KH | J1300: Cambodia | K1300: IMPORT | L1300: 3 | M1300: 1 | N1300: REPORTED | O1300: 0 | P1300: 0 | Q1300: 6121648 | R1300: 521948 | S1300: 1310015 | T1300: USABLE | U1300: =IF(R1300>0,Q1300/R1300,"") -> 11.728463 | V1300: =SUMIFS(fct_world_monthly!$J$2:$J$361,fct_world_monthly!$C$2:$C$361,C1300,fct_world_monthly!$F$2:$F$361,F1300) -> 74698348 | W1300: =IF(V1300>0,Q1300/V1300,"") -> 0.081951585 | X1300: W5Q01 | Y1300: EXT_HMRC_OTS_WP005_Core4_10PartnerCountries_Monthly_2019-01_to_2026-06_Raw_2026-08-26.json | Z1300: =IF(U1300="","",SUMIFS(Unit_Value_Review_QC!$K$10:$K$53,Unit_Value_Review_QC!$I$10:$I$53,"PARTNER|"&F1300&"|"&I1300)) -> 12.33939 | AA1300: =IFERROR(U1300/Z1300,"") -> 0.95048972 | AB1300: =IF(OR(N1300<>"REPORTED",U1300=""),"NOT_APPLICABLE",IF(OR(AA1300<Unit_Value_Review_QC!$I$6,AA1300>Unit_Value_Review_QC!$I$5),"REVIEW","WITHIN_BAND")) -> WITHIN_BAND
A1301: 61103099_CN_202109_IMPORT | B1301: 44440 | C1301: 202109 | D1301: 2021 | E1301: 9 | F1301: 61103099 | G1301: 6110 | H1301: 720 | I1301: CN | J1301: China | K1301: IMPORT | L1301: 3 | M1301: 1 | N1301: REPORTED | O1301: 0 | P1301: 0 | Q1301: 27924666 | R1301: 2019772 | S1301: 5399663 | T1301: USABLE | U1301: =IF(R1301>0,Q1301/R1301,"") -> 13.825653 | V1301: =SUMIFS(fct_world_monthly!$J$2:$J$361,fct_world_monthly!$C$2:$C$361,C1301,fct_world_monthly!$F$2:$F$361,F1301) -> 74698348 | W1301: =IF(V1301>0,Q1301/V1301,"") -> 0.37383244 | X1301: W5Q01 | Y1301: EXT_HMRC_OTS_WP005_Core4_10PartnerCountries_Monthly_2019-01_to_2026-06_Raw_2026-08-26.json | Z1301: =IF(U1301="","",SUMIFS(Unit_Value_Review_QC!$K$10:$K$53,Unit_Value_Review_QC!$I$10:$I$53,"PARTNER|"&F1301&"|"&I1301)) -> 15.158853 | AA1301: =IFERROR(U1301/Z1301,"") -> 0.91205139 | AB1301: =IF(OR(N1301<>"REPORTED",U1301=""),"NOT_APPLICABLE",IF(OR(AA1301<Unit_Value_Review_QC!$I$6,AA1301>Unit_Value_Review_QC!$I$5),"REVIEW","WITHIN_BAND")) -> WITHIN_BAND
A1302: 62044300_TR_202109_IMPORT | B1302: 44440 | C1302: 202109 | D1302: 2021 | E1302: 9 | F1302: 62044300 | G1302: 6204 | H1302: 52 | I1302: TR | J1302: Turkey | K1302: IMPORT | L1302: 3 | M1302: 1 | N1302: REPORTED | O1302: 0 | P1302: 0 | Q1302: 1886918 | R1302: 67769 | S1302: 197015 | T1302: USABLE | U1302: =IF(R1302>0,Q1302/R1302,"") -> 27.84338 | V1302: =SUMIFS(fct_world_monthly!$J$2:$J$361,fct_world_monthly!$C$2:$C$361,C1302,fct_world_monthly!$F$2:$F$361,F1302) -> 28932285 | W1302: =IF(V1302>0,Q1302/V1302,"") -> 0.065218423 | X1302: W5Q01 | Y1302: EXT_HMRC_OTS_WP005_Core4_10PartnerCountries_Monthly_2019-01_to_2026-06_Raw_2026-08-26.json | Z1302: =IF(U1302="","",SUMIFS(Unit_Value_Review_QC!$K$10:$K$53,Unit_Value_Review_QC!$I$10:$I$53,"PARTNER|"&F1302&"|"&I1302)) -> 31.867133 | AA1302: =IFERROR(U1302/Z1302,"") -> 0.87373344 | AB1302: =IF(OR(N1302<>"REPORTED",U1302=""),"NOT_APPLICABLE",IF(OR(AA1302<Unit_Value_Review_QC!$I$6,AA1302>Unit_Value_Review_QC!$I$5),"REVIEW","WITHIN_BAND")) -> WITHIN_BAND
A1303: 62044300_MA_202109_IMPORT | B1303: 44440 | C1303: 202109 | D1303: 2021 | E1303: 9 | F1303: 62044300 | G1303: 6204 | H1303: 204 | I1303: MA | J1303: Morocco | K1303: IMPORT | L1303: 3 | M1303: 1 | N1303: REPORTED | O1303: 0 | P1303: 0 | Q1303: 1317745 | R1303: 82036 | S1303: 252189 | T1303: USABLE | U1303: =IF(R1303>0,Q1303/R1303,"") -> 16.063009 | V1303: =SUMIFS(fct_world_monthly!$J$2:$J$361,fct_world_monthly!$C$2:$C$361,C1303,fct_world_monthly!$F$2:$F$361,F1303) -> 28932285 | W1303: =IF(V1303>0,Q1303/V1303,"") -> 0.045545832 | X1303: W5Q01 | Y1303: EXT_HMRC_OTS_WP005_Core4_10PartnerCountries_Monthly_2019-01_to_2026-06_Raw_2026-08-26.json | Z1303: =IF(U1303="","",SUMIFS(Unit_Value_Review_QC!$K$10:$K$53,Unit_Value_Review_QC!$I$10:$I$53,"PARTNER|"&F1303&"|"&I1303)) -> 19.682232 | AA1303: =IFERROR(U1303/Z1303,"") -> 0.81611726 | AB1303: =IF(OR(N1303<>"REPORTED",U1303=""),"NOT_APPLICABLE",IF(OR(AA1303<Unit_Value_Review_QC!$I$6,AA1303>Unit_Value_Review_QC!$I$5),"REVIEW","WITHIN_BAND")) -> WITHIN_BAND
A1304: 62044300_PK_202109_IMPORT | B1304: 44440 | C1304: 202109 | D1304: 2021 | E1304: 9 | F1304: 62044300 | G1304: 6204 | H1304: 662 | I1304: PK | J1304: Pakistan | K1304: IMPORT | L1304: 3 | M1304: 1 | N1304: REPORTED | O1304: 0 | P1304: 0 | Q1304: 134997 | R1304: 5665 | S1304: 17820 | T1304: USABLE | U1304: =IF(R1304>0,Q1304/R1304,"") -> 23.830009 | V1304: =SUMIFS(fct_world_monthly!$J$2:$J$361,fct_world_monthly!$C$2:$C$361,C1304,fct_world_monthly!$F$2:$F$361,F1304) -> 28932285 | W1304: =IF(V1304>0,Q1304/V1304,"") -> 0.004665964 | X1304: W5Q01 | Y1304: EXT_HMRC_OTS_WP005_Core4_10PartnerCountries_Monthly_2019-01_to_2026-06_Raw_2026-08-26.json | Z1304: =IF(U1304="","",SUMIFS(Unit_Value_Review_QC!$K$10:$K$53,Unit_Value_Review_QC!$I$10:$I$53,"PARTNER|"&F1304&"|"&I1304)) -> 19.366411 | AA1304: =IFERROR(U1304/Z1304,"") -> 1.2304814 | AB1304: =IF(OR(N1304<>"REPORTED",U1304=""),"NOT_APPLICABLE",IF(OR(AA1304<Unit_Value_Review_QC!$I$6,AA1304>Unit_Value_Review_QC!$I$5),"REVIEW","WITHIN_BAND")) -> WITHIN_BAND
A1305: 62044300_IN_202109_IMPORT | B1305: 44440 | C1305: 202109 | D1305: 2021 | E1305: 9 | F1305: 62044300 | G1305: 6204 | H1305: 664 | I1305: IN | J1305: India | K1305: IMPORT | L1305: 3 | M1305: 1 | N1305: REPORTED | O1305: 0 | P1305: 0 | Q1305: 2647158 | R1305: 87543 | S1305: 255391 | T1305: USABLE | U1305: =IF(R1305>0,Q1305/R1305,"") -> 30.238374 | V1305: =SUMIFS(fct_world_monthly!$J$2:$J$361,fct_world_monthly!$C$2:$C$361,C1305,fct_world_monthly!$F$2:$F$361,F1305) -> 28932285 | W1305: =IF(V1305>0,Q1305/V1305,"") -> 0.091494951 | X1305: W5Q01 | Y1305: EXT_HMRC_OTS_WP005_Core4_10PartnerCountries_Monthly_2019-01_to_2026-06_Raw_2026-08-26.json | Z1305: =IF(U1305="","",SUMIFS(Unit_Value_Review_QC!$K$10:$K$53,Unit_Value_Review_QC!$I$10:$I$53,"PARTNER|"&F1305&"|"&I1305)) -> 29.827361 | AA1305: =IFERROR(U1305/Z1305,"") -> 1.0137797 | AB1305: =IF(OR(N1305<>"REPORTED",U1305=""),"NOT_APPLICABLE",IF(OR(AA1305<Unit_Value_Review_QC!$I$6,AA1305>Unit_Value_Review_QC!$I$5),"REVIEW","WITHIN_BAND")) -> WITHIN_BAND
... A1317: 62052000_LK_202109_IMPORT | B1317: 44440 | C1317: 202109 | D1317: 2021 | E1317: 9 | F1317: 62052000 | G1317: 6205 | H1317: 669 | I1317: LK | J1317: Sri Lanka | K1317: IMPORT | L1317: 3 | M1317: 1 | N1317: REPORTED | O1317: 0 | P1317: 0 | Q1317: 294139 | R1317: 11798 | S1317: 34102 | T1317: USABLE | U1317: =IF(R1317>0,Q1317/R1317,"") -> 24.93126 | V1317: =SUMIFS(fct_world_monthly!$J$2:$J$361,fct_world_monthly!$C$2:$C$361,C1317,fct_world_monthly!$F$2:$F$361,F1317) -> 18925295 | W1317: =IF(V1317>0,Q1317/V1317,"") -> 0.015542109 | X1317: W5Q01 | Y1317: EXT_HMRC_OTS_WP005_Core4_10PartnerCountries_Monthly_2019-01_to_2026-06_Raw_2026-08-26.json | Z1317: =IF(U1317="","",SUMIFS(Unit_Value_Review_QC!$K$10:$K$53,Unit_Value_Review_QC!$I$10:$I$53,"PARTNER|"&F1317&"|"&I1317)) -> 20.668788 | AA1317: =IFERROR(U1317/Z1317,"") -> 1.2062275 | AB1317: =IF(OR(N1317<>"REPORTED",U1317=""),"NOT_APPLICABLE",IF(OR(AA1317<Unit_Value_Review_QC!$I$6,AA1317>Unit_Value_Review_QC!$I$5),"REVIEW","WITHIN_BAND")) -> WITHIN_BAND
A1318: 62052000_MM_202109_IMPORT | B1318: 44440 | C1318: 202109 | D1318: 2021 | E1318: 9 | F1318: 62052000 | G1318: 6205 | H1318: 676 | I1318: MM | J1318: Myanmar | K1318: IMPORT | L1318: 3 | M1318: 0 | N1318: NO_API_RECORD | P1318: 0 | Q1318: 0 | R1318: 0 | S1318: 0 | T1318: NO_REPORTED_TRADE | U1318: =IF(R1318>0,Q1318/R1318,"") | V1318: =SUMIFS(fct_world_monthly!$J$2:$J$361,fct_world_monthly!$C$2:$C$361,C1318,fct_world_monthly!$F$2:$F$361,F1318) -> 18925295 | W1318: =IF(V1318>0,Q1318/V1318,"") -> 0 | X1318: W5Q01 | Y1318: EXT_HMRC_OTS_WP005_Core4_10PartnerCountries_Monthly_2019-01_to_2026-06_Raw_2026-08-26.json | Z1318: =IF(U1318="","",SUMIFS(Unit_Value_Review_QC!$K$10:$K$53,Unit_Value_Review_QC!$I$10:$I$53,"PARTNER|"&F1318&"|"&I1318)) | AA1318: =IFERROR(U1318/Z1318,"") | AB1318: =IF(OR(N1318<>"REPORTED",U1318=""),"NOT_APPLICABLE",IF(OR(AA1318<Unit_Value_Review_QC!$I$6,AA1318>Unit_Value_Review_QC!$I$5),"REVIEW","WITHIN_BAND")) -> NOT_APPLICABLE
A1319: 62052000_VN_202109_IMPORT | B1319: 44440 | C1319: 202109 | D1319: 2021 | E1319: 9 | F1319: 62052000 | G1319: 6205 | H1319: 690 | I1319: VN | J1319: Vietnam | K1319: IMPORT | L1319: 3 | M1319: 1 | N1319: REPORTED | O1319: 0 | P1319: 0 | Q1319: 960694 | R1319: 34879 | S1319: 106821 | T1319: USABLE | U1319: =IF(R1319>0,Q1319/R1319,"") -> 27.543622 | V1319: =SUMIFS(fct_world_monthly!$J$2:$J$361,fct_world_monthly!$C$2:$C$361,C1319,fct_world_monthly!$F$2:$F$361,F1319) -> 18925295 | W1319: =IF(V1319>0,Q1319/V1319,"") -> 0.050762432 | X1319: W5Q01 | Y1319: EXT_HMRC_OTS_WP005_Core4_10PartnerCountries_Monthly_2019-01_to_2026-06_Raw_2026-08-26.json | Z1319: =IF(U1319="","",SUMIFS(Unit_Value_Review_QC!$K$10:$K$53,Unit_Value_Review_QC!$I$10:$I$53,"PARTNER|"&F1319&"|"&I1319)) -> 28.158454 | AA1319: =IFERROR(U1319/Z1319,"") -> 0.9781653 | AB1319: =IF(OR(N1319<>"REPORTED",U1319=""),"NOT_APPLICABLE",IF(OR(AA1319<Unit_Value_Review_QC!$I$6,AA1319>Unit_Value_Review_QC!$I$5),"REVIEW","WITHIN_BAND")) -> WITHIN_BAND
...

Sheet fct_world_monthly
A1: world_monthly_key | B1: month_date | C1: month_id | D1: calendar_year | E1: calendar_month | F1: cn8_code | G1: hs4_code | H1: eu_import_value_gbp | I1: non_eu_import_value_gbp | J1: world_import_value_gbp | K1: eu_net_mass_kg | L1: non_eu_net_mass_kg | M1: world_net_mass_kg | N1: eu_supplementary_quantity | O1: non_eu_supplementary_quantity | P1: world_supplementary_quantity | Q1: unit_value_gbp_per_kg | R1: eu_suppression_index_list | S1: non_eu_suppression_index_list | T1: suppression_flag | U1: source_query_id | V1: source_file | W1: reference_median_unit_value_gbp_per_kg | X1: unit_value_ratio_to_reference_median | Y1: unit_value_review_flag_2_5x
A2: 61091000_WORLD_201901_IMPORT | B2: 43466 | C2: 201901 | D2: 2019 | E2: 1 | F2: 61091000 | G2: 6109 | H2: 35985209 | I2: 80208250 | J2: =H2+I2 -> 116193459 | K2: 1481908 | L2: 6093137 | M2: =K2+L2 -> 7575045 | N2: 6244608 | O2: 38767222 | P2: =N2+O2 -> 45011830 | Q2: =IF(M2>0,J2/M2,"") -> 15.338979 | R2: 0 | S2: 0 | T2: 0 | U2: W5Q02 | V2: EXT_HMRC_OTS_WP005_Core4_World_Monthly_2019-01_to_2026-06_Raw_2026-08-26.json | W2: =IF(Q2="","",SUMIFS(Unit_Value_Review_QC!$K$10:$K$53,Unit_Value_Review_QC!$I$10:$I$53,"WORLD|"&F2)) -> 15.322317 | X2: =IFERROR(Q2/W2,"") -> 1.0010874 | Y2: =IF(Q2="","NOT_APPLICABLE",IF(OR(X2<Unit_Value_Review_QC!$I$6,X2>Unit_Value_Review_QC!$I$5),"REVIEW","WITHIN_BAND")) -> WITHIN_BAND
A3: 61103099_WORLD_201901_IMPORT | B3: 43466 | C3: 201901 | D3: 2019 | E3: 1 | F3: 61103099 | G3: 6110 | H3: 13578781 | I3: 47371893 | J3: =H3+I3 -> 60950674 | K3: 576538 | L3: 3055918 | M3: =K3+L3 -> 3632456 | N3: 1405722 | O3: 9119844 | P3: =N3+O3 -> 10525566 | Q3: =IF(M3>0,J3/M3,"") -> 16.779467 | R3: 0 | S3: 0 | T3: 0 | U3: W5Q02 | V3: EXT_HMRC_OTS_WP005_Core4_World_Monthly_2019-01_to_2026-06_Raw_2026-08-26.json | W3: =IF(Q3="","",SUMIFS(Unit_Value_Review_QC!$K$10:$K$53,Unit_Value_Review_QC!$I$10:$I$53,"WORLD|"&F3)) -> 15.61112 | X3: =IFERROR(Q3/W3,"") -> 1.0748407 | Y3: =IF(Q3="","NOT_APPLICABLE",IF(OR(X3<Unit_Value_Review_QC!$I$6,X3>Unit_Value_Review_QC!$I$5),"REVIEW","WITHIN_BAND")) -> WITHIN_BAND
A4: 62044300_WORLD_201901_IMPORT | B4: 43466 | C4: 201901 | D4: 2019 | E4: 1 | F4: 62044300 | G4: 6204 | H4: 12076146 | I4: 29720603 | J4: =H4+I4 -> 41796749 | K4: 370783 | L4: 1052946 | M4: =K4+L4 -> 1423729 | N4: 825232 | O4: 3192668 | P4: =N4+O4 -> 4017900 | Q4: =IF(M4>0,J4/M4,"") -> 29.357237 | R4: 0 | S4: 0 | T4: 0 | U4: W5Q02 | V4: EXT_HMRC_OTS_WP005_Core4_World_Monthly_2019-01_to_2026-06_Raw_2026-08-26.json | W4: =IF(Q4="","",SUMIFS(Unit_Value_Review_QC!$K$10:$K$53,Unit_Value_Review_QC!$I$10:$I$53,"WORLD|"&F4)) -> 31.446186 | X4: =IFERROR(Q4/W4,"") -> 0.93357066 | Y4: =IF(Q4="","NOT_APPLICABLE",IF(OR(X4<Unit_Value_Review_QC!$I$6,X4>Unit_Value_Review_QC!$I$5),"REVIEW","WITHIN_BAND")) -> WITHIN_BAND
A5: 62052000_WORLD_201901_IMPORT | B5: 43466 | C5: 201901 | D5: 2019 | E5: 1 | F5: 62052000 | G5: 6205 | H5: 11020709 | I5: 27996728 | J5: =H5+I5 -> 39017437 | K5: 247078 | L5: 1380647 | M5: =K5+L5 -> 1627725 | N5: 642842 | O5: 4548480 | P5: =N5+O5 -> 5191322 | Q5: =IF(M5>0,J5/M5,"") -> 23.970534 | R5: 0 | S5: 0 | T5: 0 | U5: W5Q02 | V5: EXT_HMRC_OTS_WP005_Core4_World_Monthly_2019-01_to_2026-06_Raw_2026-08-26.json | W5: =IF(Q5="","",SUMIFS(Unit_Value_Review_QC!$K$10:$K$53,Unit_Value_Review_QC!$I$10:$I$53,"WORLD|"&F5)) -> 25.220887 | X5: =IFERROR(Q5/W5,"") -> 0.95042388 | Y5: =IF(Q5="","NOT_APPLICABLE",IF(OR(X5<Unit_Value_Review_QC!$I$6,X5>Unit_Value_Review_QC!$I$5),"REVIEW","WITHIN_BAND")) -> WITHIN_BAND
A6: 61091000_WORLD_201902_IMPORT | B6: 43497 | C6: 201902 | D6: 2019 | E6: 2 | F6: 61091000 | G6: 6109 | H6: 36142839 | I6: 75712600 | J6: =H6+I6 -> 111855439 | K6: 1388810 | L6: 6198768 | M6: =K6+L6 -> 7587578 | N6: 5912322 | O6: 39948795 | P6: =N6+O6 -> 45861117 | Q6: =IF(M6>0,J6/M6,"") -> 14.741916 | R6: 0 | S6: 0 | T6: 0 | U6: W5Q02 | V6: EXT_HMRC_OTS_WP005_Core4_World_Monthly_2019-01_to_2026-06_Raw_2026-08-26.json | W6: =IF(Q6="","",SUMIFS(Unit_Value_Review_QC!$K$10:$K$53,Unit_Value_Review_QC!$I$10:$I$53,"WORLD|"&F6)) -> 15.322317 | X6: =IFERROR(Q6/W6,"") -> 0.96212054 | Y6: =IF(Q6="","NOT_APPLICABLE",IF(OR(X6<Unit_Value_Review_QC!$I$6,X6>Unit_Value_Review_QC!$I$5),"REVIEW","WITHIN_BAND")) -> WITHIN_BAND
A7: 61103099_WORLD_201902_IMPORT | B7: 43497 | C7: 201902 | D7: 2019 | E7: 2 | F7: 61103099 | G7: 6110 | H7: 9258019 | I7: 26284848 | J7: =H7+I7 -> 35542867 | K7: 381789 | L7: 1785137 | M7: =K7+L7 -> 2166926 | N7: 1028059 | O7: 5550700 | P7: =N7+O7 -> 6578759 | Q7: =IF(M7>0,J7/M7,"") -> 16.402437 | R7: 0 | S7: 0 | T7: 0 | U7: W5Q02 | V7: EXT_HMRC_OTS_WP005_Core4_World_Monthly_2019-01_to_2026-06_Raw_2026-08-26.json | W7: =IF(Q7="","",SUMIFS(Unit_Value_Review_QC!$K$10:$K$53,Unit_Value_Review_QC!$I$10:$I$53,"WORLD|"&F7)) -> 15.61112 | X7: =IFERROR(Q7/W7,"") -> 1.0506893 | Y7: =IF(Q7="","NOT_APPLICABLE",IF(OR(X7<Unit_Value_Review_QC!$I$6,X7>Unit_Value_Review_QC!$I$5),"REVIEW","WITHIN_BAND")) -> WITHIN_BAND
A8: 62044300_WORLD_201902_IMPORT | B8: 43497 | C8: 201902 | D8: 2019 | E8: 2 | F8: 62044300 | G8: 6204 | H8: 15163030 | I8: 26978152 | J8: =H8+I8 -> 42141182 | K8: 446516 | L8: 1086982 | M8: =K8+L8 -> 1533498 | N8: 948638 | O8: 3378009 | P8: =N8+O8 -> 4326647 | Q8: =IF(M8>0,J8/M8,"") -> 27.480428 | R8: 0 | S8: 0 | T8: 0 | U8: W5Q02 | V8: EXT_HMRC_OTS_WP005_Core4_World_Monthly_2019-01_to_2026-06_Raw_2026-08-26.json | W8: =IF(Q8="","",SUMIFS(Unit_Value_Review_QC!$K$10:$K$53,Unit_Value_Review_QC!$I$10:$I$53,"WORLD|"&F8)) -> 31.446186 | X8: =IFERROR(Q8/W8,"") -> 0.87388749 | Y8: =IF(Q8="","NOT_APPLICABLE",IF(OR(X8<Unit_Value_Review_QC!$I$6,X8>Unit_Value_Review_QC!$I$5),"REVIEW","WITHIN_BAND")) -> WITHIN_BAND
A9: 62052000_WORLD_201902_IMPORT | B9: 43497 | C9: 201902 | D9: 2019 | E9: 2 | F9: 62052000 | G9: 6205 | H9: 9950168 | I9: 22614196 | J9: =H9+I9 -> 32564364 | K9: 230545 | L9: 1162201 | M9: =K9+L9 -> 1392746 | N9: 566519 | O9: 4189477 | P9: =N9+O9 -> 4755996 | Q9: =IF(M9>0,J9/M9,"") -> 23.381409 | R9: 0 | S9: 0 | T9: 0 | U9: W5Q02 | V9: EXT_HMRC_OTS_WP005_Core4_World_Monthly_2019-01_to_2026-06_Raw_2026-08-26.json | W9: =IF(Q9="","",SUMIFS(Unit_Value_Review_QC!$K$10:$K$53,Unit_Value_Review_QC!$I$10:$I$53,"WORLD|"&F9)) -> 25.220887 | X9: =IFERROR(Q9/W9,"") -> 0.92706528 | Y9: =IF(Q9="","NOT_APPLICABLE",IF(OR(X9<Unit_Value_Review_QC!$I$6,X9>Unit_Value_Review_QC!$I$5),"REVIEW","WITHIN_BAND")) -> WITHIN_BAND
A10: 61091000_WORLD_201903_IMPORT | B10: 43525 | C10: 201903 | D10: 2019 | E10: 3 | F10: 61091000 | G10: 6109 | H10: 35656189 | I10: 94555811 | J10: =H10+I10 -> 130212000 | K10: 1542618 | L10: 7847635 | M10: =K10+L10 -> 9390253 | N10: 6063338 | O10: 51097496 | P10: =N10+O10 -> 57160834 | Q10: =IF(M10>0,J10/M10,"") -> 13.866719 | R10: 0 | S10: 0 | T10: 0 | U10: W5Q02 | V10: EXT_HMRC_OTS_WP005_Core4_World_Monthly_2019-01_to_2026-06_Raw_2026-08-26.json | W10: =IF(Q10="","",SUMIFS(Unit_Value_Review_QC!$K$10:$K$53,Unit_Value_Review_QC!$I$10:$I$53,"WORLD|"&F10)) -> 15.322317 | X10: =IFERROR(Q10/W10,"") -> 0.90500143 | Y10: =IF(Q10="","NOT_APPLICABLE",IF(OR(X10<Unit_Value_Review_QC!$I$6,X10>Unit_Value_Review_QC!$I$5),"REVIEW","WITHIN_BAND")) -> WITHIN_BAND
A11: 61103099_WORLD_201903_IMPORT | B11: 43525 | C11: 201903 | D11: 2019 | E11: 3 | F11: 61103099 | G11: 6110 | H11: 7583681 | I11: 18327629 | J11: =H11+I11 -> 25911310 | K11: 300099 | L11: 1174824 | M11: =K11+L11 -> 1474923 | N11: 817667 | O11: 3796154 | P11: =N11+O11 -> 4613821 | Q11: =IF(M11>0,J11/M11,"") -> 17.567907 | R11: 0 | S11: 0 | T11: 0 | U11: W5Q02 | V11: EXT_HMRC_OTS_WP005_Core4_World_Monthly_2019-01_to_2026-06_Raw_2026-08-26.json | W11: =IF(Q11="","",SUMIFS(Unit_Value_Review_QC!$K$10:$K$53,Unit_Value_Review_QC!$I$10:$I$53,"WORLD|"&F11)) -> 15.61112 | X11: =IFERROR(Q11/W11,"") -> 1.1253457 | Y11: =IF(Q11="","NOT_APPLICABLE",IF(OR(X11<Unit_Value_Review_QC!$I$6,X11>Unit_Value_Review_QC!$I$5),"REVIEW","WITHIN_BAND")) -> WITHIN_BAND
A12: 62044300_WORLD_201903_IMPORT | B12: 43525 | C12: 201903 | D12: 2019 | E12: 3 | F12: 62044300 | G12: 6204 | H12: 15528384 | I12: 28695627 | J12: =H12+I12 -> 44224011 | K12: 585336 | L12: 1123478 | M12: =K12+L12 -> 1708814 | N12: 1248002 | O12: 3812639 | P12: =N12+O12 -> 5060641 | Q12: =IF(M12>0,J12/M12,"") -> 25.879944 | R12: 0 | S12: 0 | T12: 0 | U12: W5Q02 | V12: EXT_HMRC_OTS_WP005_Core4_World_Monthly_2019-01_to_2026-06_Raw_2026-08-26.json | W12: =IF(Q12="","",SUMIFS(Unit_Value_Review_QC!$K$10:$K$53,Unit_Value_Review_QC!$I$10:$I$53,"WORLD|"&F12)) -> 31.446186 | X12: =IFERROR(Q12/W12,"") -> 0.82299152 | Y12: =IF(Q12="","NOT_APPLICABLE",IF(OR(X12<Unit_Value_Review_QC!$I$6,X12>Unit_Value_Review_QC!$I$5),"REVIEW","WITHIN_BAND")) -> WITHIN_BAND
A13: 62052000_WORLD_201903_IMPORT | B13: 43525 | C13: 201903 | D13: 2019 | E13: 3 | F13: 62052000 | G13: 6205 | H13: 10598262 | I13: 26560775 | J13: =H13+I13 -> 37159037 | K13: 7297700 | L13: 1414253 | M13: =K13+L13 -> 8711953 | N13: 629871 | O13: 5090016 | P13: =N13+O13 -> 5719887 | Q13: =IF(M13>0,J13/M13,"") -> 4.2652936 | R13: 0 | S13: 0 | T13: 0 | U13: W5Q02 | V13: EXT_HMRC_OTS_WP005_Core4_World_Monthly_2019-01_to_2026-06_Raw_2026-08-26.json | W13: =IF(Q13="","",SUMIFS(Unit_Value_Review_QC!$K$10:$K$53,Unit_Value_Review_QC!$I$10:$I$53,"WORLD|"&F13)) -> 25.220887 | X13: =IFERROR(Q13/W13,"") -> 0.16911751 | Y13: =IF(Q13="","NOT_APPLICABLE",IF(OR(X13<Unit_Value_Review_QC!$I$6,X13>Unit_Value_Review_QC!$I$5),"REVIEW","WITHIN_BAND")) -> REVIEW
... A361: 62052000_WORLD_202606_IMPORT | B361: 46174 | C361: 202606 | D361: 2026 | E361: 6 | F361: 62052000 | G361: 6205 | H361: 6172434 | I361: 12257949 | J361: =H361+I361 -> 18430383 | K361: 112167 | L361: 592015 | M361: =K361+L361 -> 704182 | N361: 324617 | O361: 1767724 | P361: =N361+O361 -> 2092341 | Q361: =IF(M361>0,J361/M361,"") -> 26.172755 | R361: 0 | S361: 0 | T361: 0 | U361: W5Q02 | V361: EXT_HMRC_OTS_WP005_Core4_World_Monthly_2019-01_to_2026-06_Raw_2026-08-26.json | W361: =IF(Q361="","",SUMIFS(Unit_Value_Review_QC!$K$10:$K$53,Unit_Value_Review_QC!$I$10:$I$53,"WORLD|"&F361)) -> 25.220887 | X361: =IFERROR(Q361/W361,"") -> 1.0377412 | Y361: =IF(Q361="","NOT_APPLICABLE",IF(OR(X361<Unit_Value_Review_QC!$I$6,X361>Unit_Value_Review_QC!$I$5),"REVIEW","WITHIN_BAND")) -> WITHIN_BAND

Sheet Reconciliation
A1: WP005 Reconciliation and Population Controls
A2: All annual and H1 values are sums of the monthly facts; 2025 is tied exactly to the locked WP004 evidence.
A4: Control | B4: Expected | C4: Actual | D4: Variance | E4: Status | F4: Evidence
A5: W5Q01 raw rows | B5: 3588 | C5: =COUNTA(raw_partner_monthly!$A$2:$A$3589) -> 3588 | D5: =C5-B5 -> 0 | E5: =IF(ABS(D5)<=1,"PASS","REVIEW") -> PASS | F5: raw_partner_monthly
A6: W5Q02 raw rows | B6: 720 | C6: =COUNTA(raw_world_monthly!$A$2:$A$721) -> 720 | D6: =C6-B6 -> 0 | E6: =IF(ABS(D6)<=1,"PASS","REVIEW") -> PASS | F6: raw_world_monthly
A7: Partner fact rows | B7: 3600 | C7: =COUNTA(fct_partner_monthly!$A$2:$A$3601) -> 3600 | D7: =C7-B7 -> 0 | E7: =IF(ABS(D7)<=1,"PASS","REVIEW") -> PASS | F7: fct_partner_monthly
A8: World fact rows | B8: 360 | C8: =COUNTA(fct_world_monthly!$A$2:$A$361) -> 360 | D8: =C8-B8 -> 0 | E8: =IF(ABS(D8)<=1,"PASS","REVIEW") -> PASS | F8: fct_world_monthly
A9: Month dimension rows | B9: 90 | C9: =COUNTA(dim_month!$A$2:$A$91) -> 90 | D9: =C9-B9 -> 0 | E9: =IF(ABS(D9)<=1,"PASS","REVIEW") -> PASS | F9: dim_month
A10: No-API-record combinations retained | B10: 12 | C10: =COUNTIF(fct_partner_monthly!$N$2:$N$3601,"NO_API_RECORD") -> 12 | D10: =C10-B10 -> 0 | E10: =IF(ABS(D10)<=1,"PASS","REVIEW") -> PASS | F10: fct_partner_monthly
A11: 2025 four-code World value GBP | B11: 2554995126 | C11: =SUMIFS(fct_world_monthly!$J$2:$J$361,fct_world_monthly!$D$2:$D$361,2025) -> 2554995126 | D11: =C11-B11 -> 0 | E11: =IF(ABS(D11)<=1,"PASS","REVIEW") -> PASS | F11: fct_world_monthly
A14: Annual / YTD population view
A15: calendar_year | B15: period | C15: months | D15: world_value_gbp | E15: selected_10_value_gbp | F15: selected_10_share | G15: world_net_mass_kg | H15: world_unit_value_gbp_per_kg | I15: note
A16: 2019 | B16: Full calendar year | C16: 12 | D16: =SUMIFS(fct_world_monthly!$J$2:$J$361,fct_world_monthly!$D$2:$D$361,A16) -> 3134552398 | E16: =SUMIFS(fct_partner_monthly!$Q$2:$Q$3601,fct_partner_monthly!$D$2:$D$3601,A16) -> 1907011738 | F16: =IF(D16>0,E16/D16,"") -> 0.60838407 | G16: =SUMIFS(fct_world_monthly!$M$2:$M$361,fct_world_monthly!$D$2:$D$361,A16) -> 197418361 | H16: =IF(G16>0,D16/G16,"") -> 15.877715 | I16: Complete year
A17: 2020 | B17: Full calendar year | C17: 12 | D17: =SUMIFS(fct_world_monthly!$J$2:$J$361,fct_world_monthly!$D$2:$D$361,A17) -> 2412567099 | E17: =SUMIFS(fct_partner_monthly!$Q$2:$Q$3601,fct_partner_monthly!$D$2:$D$3601,A17) -> 1385434514 | F17: =IF(D17>0,E17/D17,"") -> 0.5742574 | G17: =SUMIFS(fct_world_monthly!$M$2:$M$361,fct_world_monthly!$D$2:$D$361,A17) -> 133376846 | H17: =IF(G17>0,D17/G17,"") -> 18.08835 | I17: Complete year
A18: 2021 | B18: Full calendar year | C18: 12 | D18: =SUMIFS(fct_world_monthly!$J$2:$J$361,fct_world_monthly!$D$2:$D$361,A18) -> 2239557158 | E18: =SUMIFS(fct_partner_monthly!$Q$2:$Q$3601,fct_partner_monthly!$D$2:$D$3601,A18) -> 1336243679 | F18: =IF(D18>0,E18/D18,"") -> 0.59665531 | G18: =SUMIFS(fct_world_monthly!$M$2:$M$361,fct_world_monthly!$D$2:$D$361,A18) -> 137160029 | H18: =IF(G18>0,D18/G18,"") -> 16.32806 | I18: Complete year
A19: 2022 | B19: Full calendar year | C19: 12 | D19: =SUMIFS(fct_world_monthly!$J$2:$J$361,fct_world_monthly!$D$2:$D$361,A19) -> 2966480577 | E19: =SUMIFS(fct_partner_monthly!$Q$2:$Q$3601,fct_partner_monthly!$D$2:$D$3601,A19) -> 1956339588 | F19: =IF(D19>0,E19/D19,"") -> 0.65948168 | G19: =SUMIFS(fct_world_monthly!$M$2:$M$361,fct_world_monthly!$D$2:$D$361,A19) -> 154030800 | H19: =IF(G19>0,D19/G19,"") -> 19.259009 | I19: Complete year
A20: 2023 | B20: Full calendar year | C20: 12 | D20: =SUMIFS(fct_world_monthly!$J$2:$J$361,fct_world_monthly!$D$2:$D$361,A20) -> 2524135335 | E20: =SUMIFS(fct_partner_monthly!$Q$2:$Q$3601,fct_partner_monthly!$D$2:$D$3601,A20) -> 1660379867 | F20: =IF(D20>0,E20/D20,"") -> 0.65780144 | G20: =SUMIFS(fct_world_monthly!$M$2:$M$361,fct_world_monthly!$D$2:$D$361,A20) -> 135912715 | H20: =IF(G20>0,D20/G20,"") -> 18.571738 | I20: Complete year
A21: 2024 | B21: Full calendar year | C21: 12 | D21: =SUMIFS(fct_world_monthly!$J$2:$J$361,fct_world_monthly!$D$2:$D$361,A21) -> 2397215956 | E21: =SUMIFS(fct_partner_monthly!$Q$2:$Q$3601,fct_partner_monthly!$D$2:$D$3601,A21) -> 1623330564 | F21: =IF(D21>0,E21/D21,"") -> 0.67717327 | G21: =SUMIFS(fct_world_monthly!$M$2:$M$361,fct_world_monthly!$D$2:$D$361,A21) -> 144281581 | H21: =IF(G21>0,D21/G21,"") -> 16.614844 | I21: Complete year
A22: 2025 | B22: Full calendar year | C22: 12 | D22: =SUMIFS(fct_world_monthly!$J$2:$J$361,fct_world_monthly!$D$2:$D$361,A22) -> 2554995126 | E22: =SUMIFS(fct_partner_monthly!$Q$2:$Q$3601,fct_partner_monthly!$D$2:$D$3601,A22) -> 1763901155 | F22: =IF(D22>0,E22/D22,"") -> 0.69037359 | G22: =SUMIFS(fct_world_monthly!$M$2:$M$361,fct_world_monthly!$D$2:$D$361,A22) -> 162682851 | H22: =IF(G22>0,D22/G22,"") -> 15.705375 | I22: Complete year
A23: 2026 | B23: H1 / YTD June | C23: 6 | D23: =SUMIFS(fct_world_monthly!$J$2:$J$361,fct_world_monthly!$D$2:$D$361,A23) -> 1153111572 | E23: =SUMIFS(fct_partner_monthly!$Q$2:$Q$3601,fct_partner_monthly!$D$2:$D$3601,A23) -> 766935890 | F23: =IF(D23>0,E23/D23,"") -> 0.6651012 | G23: =SUMIFS(fct_world_monthly!$M$2:$M$361,fct_world_monthly!$D$2:$D$361,A23) -> 68213683 | H23: =IF(G23>0,D23/G23,"") -> 16.904403 | I23: Compare only with H1 periods
A26: 2025 reconciliation to WP004 locked screen
A27: cn8_code | B27: description | C27: wp004_value_gbp | D27: wp005_monthly_value_gbp | E27: value_difference_gbp | F27: wp004_net_mass_kg | G27: wp005_monthly_net_mass_kg | H27: mass_difference_kg | I27: status | J27: note
A28: 61091000 | B28: T-shirts, singlets and other vests of cotton, knitted or crocheted | C28: 1223299784 | D28: =SUMIFS(fct_world_monthly!$J$2:$J$361,fct_world_monthly!$D$2:$D$361,2025,fct_world_monthly!$F$2:$F$361,A28) -> 1223299784 | E28: =D28-C28 -> 0 | F28: 90508362 | G28: =SUMIFS(fct_world_monthly!$M$2:$M$361,fct_world_monthly!$D$2:$D$361,2025,fct_world_monthly!$F$2:$F$361,A28) -> 90508362 | H28: =G28-F28 -> 0 | I28: =IF(AND(ABS(E28)<=1,ABS(H28)<=1),"PASS","REVIEW") -> PASS | J28: Monthly-to-annual tie-back
A29: 61103099 | B29: Women's/girls' jerseys, pullovers, cardigans and similar of man-made fibres, residual line | C29: 719371758 | D29: =SUMIFS(fct_world_monthly!$J$2:$J$361,fct_world_monthly!$D$2:$D$361,2025,fct_world_monthly!$F$2:$F$361,A29) -> 719371758 | E29: =D29-C29 -> 0 | F29: 51671885 | G29: =SUMIFS(fct_world_monthly!$M$2:$M$361,fct_world_monthly!$D$2:$D$361,2025,fct_world_monthly!$F$2:$F$361,A29) -> 51671885 | H29: =G29-F29 -> 0 | I29: =IF(AND(ABS(E29)<=1,ABS(H29)<=1),"PASS","REVIEW") -> PASS | J29: Monthly-to-annual tie-back
A30: 62044300 | B30: Women's/girls' dresses of synthetic fibres, not knitted or crocheted | C30: 349077816 | D30: =SUMIFS(fct_world_monthly!$J$2:$J$361,fct_world_monthly!$D$2:$D$361,2025,fct_world_monthly!$F$2:$F$361,A30) -> 349077816 | E30: =D30-C30 -> 0 | F30: 10212693 | G30: =SUMIFS(fct_world_monthly!$M$2:$M$361,fct_world_monthly!$D$2:$D$361,2025,fct_world_monthly!$F$2:$F$361,A30) -> 10212693 | H30: =G30-F30 -> 0 | I30: =IF(AND(ABS(E30)<=1,ABS(H30)<=1),"PASS","REVIEW") -> PASS | J30: Monthly-to-annual tie-back
A31: 62052000 | B31: Men's/boys' shirts of cotton, not knitted or crocheted | C31: 263245768 | D31: =SUMIFS(fct_world_monthly!$J$2:$J$361,fct_world_monthly!$D$2:$D$361,2025,fct_world_monthly!$F$2:$F$361,A31) -> 263245768 | E31: =D31-C31 -> 0 | F31: 10289911 | G31: =SUMIFS(fct_world_monthly!$M$2:$M$361,fct_world_monthly!$D$2:$D$361,2025,fct_world_monthly!$F$2:$F$361,A31) -> 10289911 | H31: =G31-F31 -> 0 | I31: =IF(AND(ABS(E31)<=1,ABS(H31)<=1),"PASS","REVIEW") -> PASS | J31: Monthly-to-annual tie-back
A34: No-API-record combinations retained in the dense partner panel
A35: month_id | B35: cn8_code | C35: partner_country_id | D35: partner_country_iso2 | E35: partner_country_name | F35: treatment
A36: 202004 | B36: 61103099 | C36: 204 | D36: MA | E36: Morocco | F36: Values set to zero with api_row_present_flag=0 and record_status=NO_API_RECORD
A37: 202004 | B37: 62052000 | C37: 204 | D37: MA | E37: Morocco | F37: Values set to zero with api_row_present_flag=0 and record_status=NO_API_RECORD
A38: 202005 | B38: 61103099 | C38: 204 | D38: MA | E38: Morocco | F38: Values set to zero with api_row_present_flag=0 and record_status=NO_API_RECORD
A39: 202011 | B39: 61091000 | C39: 676 | D39: MM | E39: Myanmar | F39: Values set to zero with api_row_present_flag=0 and record_status=NO_API_RECORD
A40: 202103 | B40: 62052000 | C40: 662 | D40: PK | E40: Pakistan | F40: Values set to zero with api_row_present_flag=0 and record_status=NO_API_RECORD
A41: 202109 | B41: 61103099 | C41: 204 | D41: MA | E41: Morocco | F41: Values set to zero with api_row_present_flag=0 and record_status=NO_API_RECORD
A42: 202109 | B42: 62052000 | C42: 676 | D42: MM | E42: Myanmar | F42: Values set to zero with api_row_present_flag=0 and record_status=NO_API_RECORD
A43: 202201 | B43: 61103099 | C43: 204 | D43: MA | E43: Morocco | F43: Values set to zero with api_row_present_flag=0 and record_status=NO_API_RECORD
A44: 202203 | B44: 62052000 | C44: 676 | D44: MM | E44: Myanmar | F44: Values set to zero with api_row_present_flag=0 and record_status=NO_API_RECORD
A45: 202210 | B45: 62052000 | C45: 676 | D45: MM | E45: Myanmar | F45: Values set to zero with api_row_present_flag=0 and record_status=NO_API_RECORD
A46: 202302 | B46: 62052000 | C46: 676 | D46: MM | E46: Myanmar | F46: Values set to zero with api_row_present_flag=0 and record_status=NO_API_RECORD
A47: 202306 | B47: 62052000 | C47: 676 | D47: MM | E47: Myanmar | F47: Values set to zero with api_row_present_flag=0 and record_status=NO_API_RECORD

Sheet Mass_Coverage_QC
A1: Mass Coverage QC
A2: Value-weighted coverage is tested by calendar year, CN8 and selected partner country; locked threshold = 99.5%.
A4: calendar_year | B4: cn8_code | C4: partner_country_iso2 | D4: partner_country_name | E4: total_value_gbp | F4: value_with_positive_mass_gbp | G4: mass_coverage_ratio | H4: threshold | I4: status | J4: months_with_reported_trade | K4: months_value_without_mass
A5: 2019 | B5: 61091000 | C5: TR | D5: Turkey | E5: =SUMIFS(fct_partner_monthly!$Q$2:$Q$3601,fct_partner_monthly!$D$2:$D$3601,A5,fct_partner_monthly!$F$2:$F$3601,B5,fct_partner_monthly!$I$2:$I$3601,C5) -> 175402444 | F5: =SUMIFS(fct_partner_monthly!$Q$2:$Q$3601,fct_partner_monthly!$D$2:$D$3601,A5,fct_partner_monthly!$F$2:$F$3601,B5,fct_partner_monthly!$I$2:$I$3601,C5,fct_partner_monthly!$T$2:$T$3601,"USABLE") -> 175402444 | G5: =IF(E5>0,F5/E5,"") -> 1 | H5: 0.995 | I5: =IF(E5=0,"N/A - no reported trade",IF(G5>=H5,"PASS","REVIEW")) -> PASS | J5: =COUNTIFS(fct_partner_monthly!$D$2:$D$3601,A5,fct_partner_monthly!$F$2:$F$3601,B5,fct_partner_monthly!$I$2:$I$3601,C5,fct_partner_monthly!$Q$2:$Q$3601,">0") -> 12 | K5: =COUNTIFS(fct_partner_monthly!$D$2:$D$3601,A5,fct_partner_monthly!$F$2:$F$3601,B5,fct_partner_monthly!$I$2:$I$3601,C5,fct_partner_monthly!$T$2:$T$3601,"VALUE_WITHOUT_MASS") -> 0
A6: 2019 | B6: 61091000 | C6: MA | D6: Morocco | E6: =SUMIFS(fct_partner_monthly!$Q$2:$Q$3601,fct_partner_monthly!$D$2:$D$3601,A6,fct_partner_monthly!$F$2:$F$3601,B6,fct_partner_monthly!$I$2:$I$3601,C6) -> 8526968 | F6: =SUMIFS(fct_partner_monthly!$Q$2:$Q$3601,fct_partner_monthly!$D$2:$D$3601,A6,fct_partner_monthly!$F$2:$F$3601,B6,fct_partner_monthly!$I$2:$I$3601,C6,fct_partner_monthly!$T$2:$T$3601,"USABLE") -> 8526968 | G6: =IF(E6>0,F6/E6,"") -> 1 | H6: 0.995 | I6: =IF(E6=0,"N/A - no reported trade",IF(G6>=H6,"PASS","REVIEW")) -> PASS | J6: =COUNTIFS(fct_partner_monthly!$D$2:$D$3601,A6,fct_partner_monthly!$F$2:$F$3601,B6,fct_partner_monthly!$I$2:$I$3601,C6,fct_partner_monthly!$Q$2:$Q$3601,">0") -> 12 | K6: =COUNTIFS(fct_partner_monthly!$D$2:$D$3601,A6,fct_partner_monthly!$F$2:$F$3601,B6,fct_partner_monthly!$I$2:$I$3601,C6,fct_partner_monthly!$T$2:$T$3601,"VALUE_WITHOUT_MASS") -> 0
A7: 2019 | B7: 61091000 | C7: PK | D7: Pakistan | E7: =SUMIFS(fct_partner_monthly!$Q$2:$Q$3601,fct_partner_monthly!$D$2:$D$3601,A7,fct_partner_monthly!$F$2:$F$3601,B7,fct_partner_monthly!$I$2:$I$3601,C7) -> 25996895 | F7: =SUMIFS(fct_partner_monthly!$Q$2:$Q$3601,fct_partner_monthly!$D$2:$D$3601,A7,fct_partner_monthly!$F$2:$F$3601,B7,fct_partner_monthly!$I$2:$I$3601,C7,fct_partner_monthly!$T$2:$T$3601,"USABLE") -> 25996895 | G7: =IF(E7>0,F7/E7,"") -> 1 | H7: 0.995 | I7: =IF(E7=0,"N/A - no reported trade",IF(G7>=H7,"PASS","REVIEW")) -> PASS | J7: =COUNTIFS(fct_partner_monthly!$D$2:$D$3601,A7,fct_partner_monthly!$F$2:$F$3601,B7,fct_partner_monthly!$I$2:$I$3601,C7,fct_partner_monthly!$Q$2:$Q$3601,">0") -> 12 | K7: =COUNTIFS(fct_partner_monthly!$D$2:$D$3601,A7,fct_partner_monthly!$F$2:$F$3601,B7,fct_partner_monthly!$I$2:$I$3601,C7,fct_partner_monthly!$T$2:$T$3601,"VALUE_WITHOUT_MASS") -> 0
A8: 2019 | B8: 61091000 | C8: IN | D8: India | E8: =SUMIFS(fct_partner_monthly!$Q$2:$Q$3601,fct_partner_monthly!$D$2:$D$3601,A8,fct_partner_monthly!$F$2:$F$3601,B8,fct_partner_monthly!$I$2:$I$3601,C8) -> 127247225 | F8: =SUMIFS(fct_partner_monthly!$Q$2:$Q$3601,fct_partner_monthly!$D$2:$D$3601,A8,fct_partner_monthly!$F$2:$F$3601,B8,fct_partner_monthly!$I$2:$I$3601,C8,fct_partner_monthly!$T$2:$T$3601,"USABLE") -> 127247225 | G8: =IF(E8>0,F8/E8,"") -> 1 | H8: 0.995 | I8: =IF(E8=0,"N/A - no reported trade",IF(G8>=H8,"PASS","REVIEW")) -> PASS | J8: =COUNTIFS(fct_partner_monthly!$D$2:$D$3601,A8,fct_partner_monthly!$F$2:$F$3601,B8,fct_partner_monthly!$I$2:$I$3601,C8,fct_partner_monthly!$Q$2:$Q$3601,">0") -> 12 | K8: =COUNTIFS(fct_partner_monthly!$D$2:$D$3601,A8,fct_partner_monthly!$F$2:$F$3601,B8,fct_partner_monthly!$I$2:$I$3601,C8,fct_partner_monthly!$T$2:$T$3601,"VALUE_WITHOUT_MASS") -> 0
A9: 2019 | B9: 61091000 | C9: BD | D9: Bangladesh | E9: =SUMIFS(fct_partner_monthly!$Q$2:$Q$3601,fct_partner_monthly!$D$2:$D$3601,A9,fct_partner_monthly!$F$2:$F$3601,B9,fct_partner_monthly!$I$2:$I$3601,C9) -> 408449059 | F9: =SUMIFS(fct_partner_monthly!$Q$2:$Q$3601,fct_partner_monthly!$D$2:$D$3601,A9,fct_partner_monthly!$F$2:$F$3601,B9,fct_partner_monthly!$I$2:$I$3601,C9,fct_partner_monthly!$T$2:$T$3601,"USABLE") -> 408449059 | G9: =IF(E9>0,F9/E9,"") -> 1 | H9: 0.995 | I9: =IF(E9=0,"N/A - no reported trade",IF(G9>=H9,"PASS","REVIEW")) -> PASS | J9: =COUNTIFS(fct_partner_monthly!$D$2:$D$3601,A9,fct_partner_monthly!$F$2:$F$3601,B9,fct_partner_monthly!$I$2:$I$3601,C9,fct_partner_monthly!$Q$2:$Q$3601,">0") -> 12 | K9: =COUNTIFS(fct_partner_monthly!$D$2:$D$3601,A9,fct_partner_monthly!$F$2:$F$3601,B9,fct_partner_monthly!$I$2:$I$3601,C9,fct_partner_monthly!$T$2:$T$3601,"VALUE_WITHOUT_MASS") -> 0
A10: 2019 | B10: 61091000 | C10: LK | D10: Sri Lanka | E10: =SUMIFS(fct_partner_monthly!$Q$2:$Q$3601,fct_partner_monthly!$D$2:$D$3601,A10,fct_partner_monthly!$F$2:$F$3601,B10,fct_partner_monthly!$I$2:$I$3601,C10) -> 29355675 | F10: =SUMIFS(fct_partner_monthly!$Q$2:$Q$3601,fct_partner_monthly!$D$2:$D$3601,A10,fct_partner_monthly!$F$2:$F$3601,B10,fct_partner_monthly!$I$2:$I$3601,C10,fct_partner_monthly!$T$2:$T$3601,"USABLE") -> 29355675 | G10: =IF(E10>0,F10/E10,"") -> 1 | H10: 0.995 | I10: =IF(E10=0,"N/A - no reported trade",IF(G10>=H10,"PASS","REVIEW")) -> PASS | J10: =COUNTIFS(fct_partner_monthly!$D$2:$D$3601,A10,fct_partner_monthly!$F$2:$F$3601,B10,fct_partner_monthly!$I$2:$I$3601,C10,fct_partner_monthly!$Q$2:$Q$3601,">0") -> 12 | K10: =COUNTIFS(fct_partner_monthly!$D$2:$D$3601,A10,fct_partner_monthly!$F$2:$F$3601,B10,fct_partner_monthly!$I$2:$I$3601,C10,fct_partner_monthly!$T$2:$T$3601,"VALUE_WITHOUT_MASS") -> 0
A11: 2019 | B11: 61091000 | C11: MM | D11: Myanmar | E11: =SUMIFS(fct_partner_monthly!$Q$2:$Q$3601,fct_partner_monthly!$D$2:$D$3601,A11,fct_partner_monthly!$F$2:$F$3601,B11,fct_partner_monthly!$I$2:$I$3601,C11) -> 1189572 | F11: =SUMIFS(fct_partner_monthly!$Q$2:$Q$3601,fct_partner_monthly!$D$2:$D$3601,A11,fct_partner_monthly!$F$2:$F$3601,B11,fct_partner_monthly!$I$2:$I$3601,C11,fct_partner_monthly!$T$2:$T$3601,"USABLE") -> 1189572 | G11: =IF(E11>0,F11/E11,"") -> 1 | H11: 0.995 | I11: =IF(E11=0,"N/A - no reported trade",IF(G11>=H11,"PASS","REVIEW")) -> PASS | J11: =COUNTIFS(fct_partner_monthly!$D$2:$D$3601,A11,fct_partner_monthly!$F$2:$F$3601,B11,fct_partner_monthly!$I$2:$I$3601,C11,fct_partner_monthly!$Q$2:$Q$3601,">0") -> 12 | K11: =COUNTIFS(fct_partner_monthly!$D$2:$D$3601,A11,fct_partner_monthly!$F$2:$F$3601,B11,fct_partner_monthly!$I$2:$I$3601,C11,fct_partner_monthly!$T$2:$T$3601,"VALUE_WITHOUT_MASS") -> 0
A12: 2019 | B12: 61091000 | C12: VN | D12: Vietnam | E12: =SUMIFS(fct_partner_monthly!$Q$2:$Q$3601,fct_partner_monthly!$D$2:$D$3601,A12,fct_partner_monthly!$F$2:$F$3601,B12,fct_partner_monthly!$I$2:$I$3601,C12) -> 18196606 | F12: =SUMIFS(fct_partner_monthly!$Q$2:$Q$3601,fct_partner_monthly!$D$2:$D$3601,A12,fct_partner_monthly!$F$2:$F$3601,B12,fct_partner_monthly!$I$2:$I$3601,C12,fct_partner_monthly!$T$2:$T$3601,"USABLE") -> 18196606 | G12: =IF(E12>0,F12/E12,"") -> 1 | H12: 0.995 | I12: =IF(E12=0,"N/A - no reported trade",IF(G12>=H12,"PASS","REVIEW")) -> PASS | J12: =COUNTIFS(fct_partner_monthly!$D$2:$D$3601,A12,fct_partner_monthly!$F$2:$F$3601,B12,fct_partner_monthly!$I$2:$I$3601,C12,fct_partner_monthly!$Q$2:$Q$3601,">0") -> 12 | K12: =COUNTIFS(fct_partner_monthly!$D$2:$D$3601,A12,fct_partner_monthly!$F$2:$F$3601,B12,fct_partner_monthly!$I$2:$I$3601,C12,fct_partner_monthly!$T$2:$T$3601,"VALUE_WITHOUT_MASS") -> 0
A13: 2019 | B13: 61091000 | C13: KH | D13: Cambodia | E13: =SUMIFS(fct_partner_monthly!$Q$2:$Q$3601,fct_partner_monthly!$D$2:$D$3601,A13,fct_partner_monthly!$F$2:$F$3601,B13,fct_partner_monthly!$I$2:$I$3601,C13) -> 18620703 | F13: =SUMIFS(fct_partner_monthly!$Q$2:$Q$3601,fct_partner_monthly!$D$2:$D$3601,A13,fct_partner_monthly!$F$2:$F$3601,B13,fct_partner_monthly!$I$2:$I$3601,C13,fct_partner_monthly!$T$2:$T$3601,"USABLE") -> 18620703 | G13: =IF(E13>0,F13/E13,"") -> 1 | H13: 0.995 | I13: =IF(E13=0,"N/A - no reported trade",IF(G13>=H13,"PASS","REVIEW")) -> PASS | J13: =COUNTIFS(fct_partner_monthly!$D$2:$D$3601,A13,fct_partner_monthly!$F$2:$F$3601,B13,fct_partner_monthly!$I$2:$I$3601,C13,fct_partner_monthly!$Q$2:$Q$3601,">0") -> 12 | K13: =COUNTIFS(fct_partner_monthly!$D$2:$D$3601,A13,fct_partner_monthly!$F$2:$F$3601,B13,fct_partner_monthly!$I$2:$I$3601,C13,fct_partner_monthly!$T$2:$T$3601,"VALUE_WITHOUT_MASS") -> 0
A14: 2019 | B14: 61091000 | C14: CN | D14: China | E14: =SUMIFS(fct_partner_monthly!$Q$2:$Q$3601,fct_partner_monthly!$D$2:$D$3601,A14,fct_partner_monthly!$F$2:$F$3601,B14,fct_partner_monthly!$I$2:$I$3601,C14) -> 51416220 | F14: =SUMIFS(fct_partner_monthly!$Q$2:$Q$3601,fct_partner_monthly!$D$2:$D$3601,A14,fct_partner_monthly!$F$2:$F$3601,B14,fct_partner_monthly!$I$2:$I$3601,C14,fct_partner_monthly!$T$2:$T$3601,"USABLE") -> 51416220 | G14: =IF(E14>0,F14/E14,"") -> 1 | H14: 0.995 | I14: =IF(E14=0,"N/A - no reported trade",IF(G14>=H14,"PASS","REVIEW")) -> PASS | J14: =COUNTIFS(fct_partner_monthly!$D$2:$D$3601,A14,fct_partner_monthly!$F$2:$F$3601,B14,fct_partner_monthly!$I$2:$I$3601,C14,fct_partner_monthly!$Q$2:$Q$3601,">0") -> 12 | K14: =COUNTIFS(fct_partner_monthly!$D$2:$D$3601,A14,fct_partner_monthly!$F$2:$F$3601,B14,fct_partner_monthly!$I$2:$I$3601,C14,fct_partner_monthly!$T$2:$T$3601,"VALUE_WITHOUT_MASS") -> 0
A15: 2019 | B15: 61103099 | C15: TR | D15: Turkey | E15: =SUMIFS(fct_partner_monthly!$Q$2:$Q$3601,fct_partner_monthly!$D$2:$D$3601,A15,fct_partner_monthly!$F$2:$F$3601,B15,fct_partner_monthly!$I$2:$I$3601,C15) -> 78697475 | F15: =SUMIFS(fct_partner_monthly!$Q$2:$Q$3601,fct_partner_monthly!$D$2:$D$3601,A15,fct_partner_monthly!$F$2:$F$3601,B15,fct_partner_monthly!$I$2:$I$3601,C15,fct_partner_monthly!$T$2:$T$3601,"USABLE") -> 78697475 | G15: =IF(E15>0,F15/E15,"") -> 1 | H15: 0.995 | I15: =IF(E15=0,"N/A - no reported trade",IF(G15>=H15,"PASS","REVIEW")) -> PASS | J15: =COUNTIFS(fct_partner_monthly!$D$2:$D$3601,A15,fct_partner_monthly!$F$2:$F$3601,B15,fct_partner_monthly!$I$2:$I$3601,C15,fct_partner_monthly!$Q$2:$Q$3601,">0") -> 12 | K15: =COUNTIFS(fct_partner_monthly!$D$2:$D$3601,A15,fct_partner_monthly!$F$2:$F$3601,B15,fct_partner_monthly!$I$2:$I$3601,C15,fct_partner_monthly!$T$2:$T$3601,"VALUE_WITHOUT_MASS") -> 0
A16: 2019 | B16: 61103099 | C16: MA | D16: Morocco | E16: =SUMIFS(fct_partner_monthly!$Q$2:$Q$3601,fct_partner_monthly!$D$2:$D$3601,A16,fct_partner_monthly!$F$2:$F$3601,B16,fct_partner_monthly!$I$2:$I$3601,C16) -> 1008796 | F16: =SUMIFS(fct_partner_monthly!$Q$2:$Q$3601,fct_partner_monthly!$D$2:$D$3601,A16,fct_partner_monthly!$F$2:$F$3601,B16,fct_partner_monthly!$I$2:$I$3601,C16,fct_partner_monthly!$T$2:$T$3601,"USABLE") -> 1008796 | G16: =IF(E16>0,F16/E16,"") -> 1 | H16: 0.995 | I16: =IF(E16=0,"N/A - no reported trade",IF(G16>=H16,"PASS","REVIEW")) -> PASS | J16: =COUNTIFS(fct_partner_monthly!$D$2:$D$3601,A16,fct_partner_monthly!$F$2:$F$3601,B16,fct_partner_monthly!$I$2:$I$3601,C16,fct_partner_monthly!$Q$2:$Q$3601,">0") -> 12 | K16: =COUNTIFS(fct_partner_monthly!$D$2:$D$3601,A16,fct_partner_monthly!$F$2:$F$3601,B16,fct_partner_monthly!$I$2:$I$3601,C16,fct_partner_monthly!$T$2:$T$3601,"VALUE_WITHOUT_MASS") -> 0
... A324: 2026 | B324: 62052000 | C324: CN | D324: China | E324: =SUMIFS(fct_partner_monthly!$Q$2:$Q$3601,fct_partner_monthly!$D$2:$D$3601,A324,fct_partner_monthly!$F$2:$F$3601,B324,fct_partner_monthly!$I$2:$I$3601,C324) -> 5317772 | F324: =SUMIFS(fct_partner_monthly!$Q$2:$Q$3601,fct_partner_monthly!$D$2:$D$3601,A324,fct_partner_monthly!$F$2:$F$3601,B324,fct_partner_monthly!$I$2:$I$3601,C324,fct_partner_monthly!$T$2:$T$3601,"USABLE") -> 5317772 | G324: =IF(E324>0,F324/E324,"") -> 1 | H324: 0.995 | I324: =IF(E324=0,"N/A - no reported trade",IF(G324>=H324,"PASS","REVIEW")) -> PASS | J324: =COUNTIFS(fct_partner_monthly!$D$2:$D$3601,A324,fct_partner_monthly!$F$2:$F$3601,B324,fct_partner_monthly!$I$2:$I$3601,C324,fct_partner_monthly!$Q$2:$Q$3601,">0") -> 6 | K324: =COUNTIFS(fct_partner_monthly!$D$2:$D$3601,A324,fct_partner_monthly!$F$2:$F$3601,B324,fct_partner_monthly!$I$2:$I$3601,C324,fct_partner_monthly!$T$2:$T$3601,"VALUE_WITHOUT_MASS") -> 0

Sheet QC_Checks
A1: WP005 Final QC Checks
A2: Formal completion evidence generated from the raw responses, transformed facts and the WP004 reconciliation controls.
A4: Check_ID | B4: Area | C4: Check | D4: Expected rule | E4: Actual | F4: Status | G4: Evidence | H4: Notes
A5: QC001 | B5: Raw evidence | C5: Both source files parse as JSON with a value array | D5: 2 valid responses | E5: 2 valid responses | F5: PASS | G5: W5Q01; W5Q02 | H5: Raw files retained unchanged
A6: QC002 | B6: Pagination | C6: No unresolved @odata.nextLink | D6: 0 | E6: 0 | F6: PASS | G6: Query_Manifest | H6: Both queries below the 40,000-item response limit
A7: QC003 | B7: Scope | C7: W5Q01 contains only four locked codes, ten selected countries, months 201901-202606 and FlowTypeId 3 | D7: No out-of-scope rows | E7: No out-of-scope rows | F7: PASS | G7: raw_partner_monthly | H7: Partner-country data uses HMRC country-of-dispatch basis
A8: QC004 | B8: Scope | C8: W5Q02 contains only four locked codes, months 201901-202606 and import flows 1/3 | D8: No out-of-scope rows | E8: No out-of-scope rows | F8: PASS | G8: raw_world_monthly | H8: World denominator has no country filter
A9: QC005 | B9: Duplicates | C9: Grouped raw keys are unique | D9: 0 duplicates | E9: 0 | F9: PASS | G9: raw_partner_monthly; raw_world_monthly | H9: Checked at each raw query grain
A10: QC006 | B10: Panel | C10: Partner fact has 4 x 10 x 90 rows | D10: 3600 | E10: 3600 | F10: PASS | G10: fct_partner_monthly | H10: Dense panel preserves no-API-record combinations
A11: QC007 | B11: Panel | C11: World fact has 4 x 90 rows | D11: 360 | E11: 360 | F11: PASS | G11: fct_world_monthly | H11: EU and non-EU flows combined
A12: QC008 | B12: Time | C12: Date dimension contains 90 months and 2026 stops at June | D12: 90 months | E12: 90 | F12: PASS | G12: dim_month | H12: 2019-2025 full years; 2026 H1
A13: QC009 | B13: Missing records | C13: Every absent API combination is retained and flagged | D13: 12 | E13: 12 | F13: PASS | G13: Reconciliation | H13: No-API-record is distinguishable from reported zero/suppressed data
A14: QC010 | B14: Suppression | C14: SuppressionIndex retained; no unhandled suppression rows | D14: Index 0 only | E14: Partner 0; World 0 | F14: PASS | G14: raw_*; fct_* | H14: Any future non-zero index must remain visible
A15: QC011 | B15: Mass | C15: No positive value without positive net mass | D15: 0 | E15: 0 | F15: PASS | G15: Mass_Coverage_QC | H15: Completeness test only; economic plausibility is handled separately by QC021.
A16: QC012 | B16: Mass | C16: All reported-value groups meet the 99.5% mass gate | D16: 0 | E16: 0 | F16: PASS | G16: Mass_Coverage_QC | H16: The 99.5% gate tests presence/coverage, not whether a reported mass is credible.
A17: QC013 | B17: Values | C17: No negative import value or net mass | D17: 0 | E17: 0 | F17: PASS | G17: fct_partner_monthly; fct_world_monthly | H17: Zero values are allowed only with explicit status
A18: QC014 | B18: Denominator | C18: Selected-ten value does not exceed World value by code-month | D18: 0 | E18: 0 | F18: PASS | G18: Reconciliation | H18: Rest-of-World balance is non-negative
A19: QC015 | B19: Reconciliation | C19: 2025 selected-country code totals equal WP004 | D19: 0 | E19: 0 | F19: PASS | G19: Reconciliation | H19: Value and net mass both tested
A20: QC016 | B20: Reconciliation | C20: 2025 World code totals equal WP004 | D20: 0 | E20: 0 | F20: PASS | G20: Reconciliation | H20: All four codes reconcile exactly
A21: QC017 | B21: Terminology | C21: Partner-country / country-of-dispatch wording used | D21: No origin-country claim | E21: Applied | F21: PASS | G21: README; Scope_Contract; Data_Dictionary | H21: Protects against misinterpreting HMRC OTS geography
A22: QC018 | B22: SQL readiness | C22: Stable headers, typed dates/numbers, unique keys and null/zero flags | D22: Ready | E22: Ready | F22: PASS | G22: fct_*; SQL_Load_Map | H22: CSV exports contain values, not Excel formulas
A23: QC019 | B23: Governance | C23: Final evidence snapshot released after WP005 quality checks | D23: QC before release | E23: Sequence respected | F23: PASS | G23: Publication sequence | H23: Release followed completed checks of the revised monthly-trade workbook.
A24: QC020 | B24: Workbook | C24: No Excel formula errors after build | D24: 0 | E24: Verified in final workbook scan | F24: PASS | G24: All formula sheets | H24: Rechecked after export
A25: QC021 | B25: Unit value | C25: Continuous median ratios retained; primary 2.5x review screen executed and alternative threshold counts disclosed | D25: No source values changed; REVIEW used only for labelled sensitivity | E25: ="Partner "&Unit_Value_Review_QC!C5&"; World "&Unit_Value_Review_QC!C6 -> Partner 37; World 2 | F25: PASS | G25: fct_partner_monthly; fct_world_monthly; Unit_Value_Review_QC | H25: Review heuristic, not proof of error. WP006/WP008 must carry the reported-data base case and exclusion sensitivity.

Sheet Data_Dictionary
A1: WP005 Data Dictionary
A2: Field definitions follow the workbook and SQL-ready outputs; identifiers remain text where leading zeros matter.
A4: Table / sheet | B4: Field | C4: Logical type | D4: Definition | E4: Source | F4: Derivation / rule | G4: Nullable | H4: Key / role
A5: Query_Manifest | B5: query_id | C5: text | D5: Stable query identifier within WP005 | E5: Project convention | F5: Assigned W5Q01/W5Q02 | G5: No | H5: Primary key
A6: Query_Manifest | B6: canonical_replay_url | C6: text | D6: Complete encoded API request used to reproduce the extract | E6: HMRC API | F6: Recorded at retrieval | G6: No | H6: Lineage
A7: Query_Manifest | B7: sha256 | C7: text | D7: SHA-256 digest of the immutable JSON response | E7: Local evidence file | F7: Cryptographic hash | G7: No | H7: Integrity
A8: dim_commodity | B8: cn8_code | C8: text | D8: Eight-digit Combined Nomenclature code | E8: WP004 lock / HMRC Commodity | F8: Preserve as text | G8: No | H8: Primary key
A9: dim_commodity | B9: basket_role | C9: text | D9: Strategic role assigned to the code in the paired basket | E9: WP004 | F9: Copied from locked scope | G9: No | H9: Attribute
A10: dim_partner_country | B10: partner_country_id | C10: integer | D10: HMRC CountryId | E10: HMRC Country lookup | F10: Direct mapping | G10: No | H10: Primary key
A11: dim_partner_country | B11: partner_country_iso2 | C11: text | D11: Two-character partner-country code | E11: HMRC Country lookup | F11: Direct mapping | G11: No | H11: Natural key
A12: dim_partner_country | B12: geographical_basis | C12: text | D12: Basis of HMRC partner geography | E12: HMRC methodology | F12: Country of dispatch / partner basis | G12: No | H12: Control attribute
A13: dim_month | B13: month_id | C13: integer | D13: HMRC month identifier in YYYYMM form | E13: HMRC Date convention | F13: Direct mapping | G13: No | H13: Primary key
A14: dim_month | B14: month_date | C14: date | D14: First day of the reporting month | E14: Derived | F14: DATE(year, month, 1) | G14: No | H14: Date key
A15: dim_month | B15: complete_calendar_year_flag | C15: smallint | D15: 1 for 2019-2025; 0 for partial 2026 | E15: Scope contract | F15: Year <= 2025 | G15: No | H15: Control attribute
A16: raw_partner_monthly | B16: source_query_id | C16: text | D16: Query identifier | E16: W5Q01 | F16: Direct unless stated | G16: No
A17: raw_partner_monthly | B17: source_record_no | C17: integer | D17: Sequential row number in the local representation | E17: Generated | F17: Direct unless stated | G17: No | H17: Row identifier
A18: raw_partner_monthly | B18: month_id | C18: integer | D18: HMRC month identifier | E18: MonthId | F18: Direct unless stated | G18: No
A19: raw_partner_monthly | B19: commodity_id | C19: text | D19: HMRC CN8 commodity identifier | E19: CommodityId | F19: Direct unless stated | G19: No
A20: raw_partner_monthly | B20: country_id | C20: integer | D20: HMRC partner-country identifier | E20: CountryId | F20: Direct unless stated | G20: No
A21: raw_partner_monthly | B21: flow_type_id | C21: integer | D21: HMRC flow identifier; 3 is non-EU imports | E21: FlowTypeId | F21: Direct unless stated | G21: No
A22: raw_partner_monthly | B22: suppression_index | C22: integer | D22: HMRC confidentiality/suppression category | E22: SuppressionIndex | F22: Direct unless stated | G22: No
A23: raw_partner_monthly | B23: supp_unit | C23: numeric | D23: Supplementary quantity where applicable | E23: SuppUnit | F23: Direct unless stated | G23: No
A24: raw_partner_monthly | B24: net_mass | C24: numeric | D24: Net mass in kilograms | E24: NetMass | F24: Direct unless stated | G24: No
A25: raw_partner_monthly | B25: value_gbp | C25: numeric | D25: HMRC import statistical value in GBP | E25: Value | F25: Direct unless stated | G25: No
A26: raw_partner_monthly | B26: source_file | C26: text | D26: Immutable evidence filename | E26: Manifest | F26: Direct unless stated | G26: No
A27: raw_world_monthly | B27: source_query_id | C27: text | D27: Query identifier | E27: W5Q02 | F27: Direct unless stated | G27: No
A28: raw_world_monthly | B28: source_record_no | C28: integer | D28: Sequential row number in the local representation | E28: Generated | F28: Direct unless stated | G28: No | H28: Row identifier
A29: raw_world_monthly | B29: month_id | C29: integer | D29: HMRC month identifier | E29: MonthId | F29: Direct unless stated | G29: No
A30: raw_world_monthly | B30: commodity_id | C30: text | D30: HMRC CN8 commodity identifier | E30: CommodityId | F30: Direct unless stated | G30: No
A31: raw_world_monthly | B31: flow_type_id | C31: integer | D31: HMRC flow identifier; 1 is EU imports and 3 is non-EU imports | E31: FlowTypeId | F31: Direct unless stated | G31: No
A32: raw_world_monthly | B32: suppression_index | C32: integer | D32: HMRC confidentiality/suppression category | E32: SuppressionIndex | F32: Direct unless stated | G32: No
A33: raw_world_monthly | B33: supp_unit | C33: numeric | D33: Supplementary quantity where applicable | E33: SuppUnit | F33: Direct unless stated | G33: No
A34: raw_world_monthly | B34: net_mass | C34: numeric | D34: Net mass in kilograms | E34: NetMass | F34: Direct unless stated | G34: No
A35: raw_world_monthly | B35: value_gbp | C35: numeric | D35: HMRC import statistical value in GBP | E35: Value | F35: Direct unless stated | G35: No
A36: raw_world_monthly | B36: source_file | C36: text | D36: Immutable evidence filename | E36: Manifest | F36: Direct unless stated | G36: No
A37: fct_partner_monthly | B37: monthly_import_key | C37: text | D37: Deterministic code-country-month-flow key | E37: Derived / lookup | F37: Concatenation | G37: No | H37: Primary key
A38: fct_partner_monthly | B38: month_date | C38: date | D38: First day of month | E38: Derived / lookup | F38: month_id | G38: No | H38: Foreign key
A39: fct_partner_monthly | B39: month_id | C39: integer | D39: HMRC month identifier | E39: HMRC OTS | F39: Raw | G39: No | H39: Foreign key
A40: fct_partner_monthly | B40: calendar_year | C40: integer | D40: Calendar year | E40: Derived / lookup | F40: month_id | G40: No | H40: Attribute
A41: fct_partner_monthly | B41: calendar_month | C41: integer | D41: Month number 1-12 | E41: Derived / lookup | F41: month_id | G41: No | H41: Attribute
A42: fct_partner_monthly | B42: cn8_code | C42: text | D42: Locked CN8 code | E42: Derived / lookup | F42: CommodityId | G42: No | H42: Foreign key
A43: fct_partner_monthly | B43: hs4_code | C43: text | D43: Four-digit HS heading | E43: Derived / lookup | F43: dim_commodity | G43: No | H43: Attribute
A44: fct_partner_monthly | B44: partner_country_id | C44: integer | D44: HMRC CountryId | E44: Derived / lookup | F44: CountryId | G44: No | H44: Foreign key
A45: fct_partner_monthly | B45: partner_country_iso2 | C45: text | D45: Partner ISO2 code | E45: Derived / lookup | F45: dim_partner_country | G45: No | H45: Natural key
A46: fct_partner_monthly | B46: partner_country_name | C46: text | D46: Partner-country label | E46: Derived / lookup | F46: dim_partner_country | G46: No | H46: Attribute
A47: fct_partner_monthly | B47: flow | C47: text | D47: Normalised trade flow | E47: Derived / lookup | F47: Constant IMPORT | G47: No | H47: Key component
A48: fct_partner_monthly | B48: flow_type_id | C48: integer | D48: HMRC non-EU import flow | E48: HMRC OTS | F48: Raw | G48: No | H48: Attribute
... A89: fct_world_monthly | B89: unit_value_review_flag_2_5x | C89: text | D89: WITHIN_BAND, REVIEW or NOT_APPLICABLE under the primary 2.5x review parameter | E89: Derived | F89: REVIEW below reciprocal 0.40x or above 2.50x; retain base value | G89: No | H89: Control

Sheet SQL_Load_Map
A1: SQL Load Map
A2: The workbook facts are formula-auditable; the companion CSVs are the fixed PostgreSQL load inputs.
A4: Load order | B4: Workbook source | C4: PostgreSQL target | D4: Load file / source | E4: Primary key | F4: Purpose
A5: 1 | B5: dim_commodity | C5: dim_commodity | D5: NEXT_WP005_dim_commodity.csv | E5: cn8_code | F5: One row per core/reserve code
A6: 2 | B6: dim_partner_country | C6: dim_partner_country | D6: NEXT_WP005_dim_partner_country.csv | E6: partner_country_id | F6: Ten selected partner countries
A7: 3 | B7: dim_month | C7: dim_month | D7: NEXT_WP005_dim_month.csv | E7: month_id | F7: Ninety monthly periods
A8: 4 | B8: raw_partner_monthly | C8: stg_hmrc_imports_core4 | D8: W5Q01 JSON / raw_partner_monthly | E8: source_query_id + source_record_no | F8: Immutable grouped-source staging
A9: 5 | B9: raw_world_monthly | C9: stg_hmrc_world_core4 | D9: W5Q02 JSON / raw_world_monthly | E9: source_query_id + source_record_no | F9: World-flow staging
A10: 6 | B10: fct_partner_monthly | C10: fct_hmrc_import_monthly | D10: NEXT_WP005_HMRC_Monthly_Trade_Core4_10Partners_2019-01_to_2026-06.csv | E10: monthly_import_key | F10: Dense partner-country monthly fact
A11: 7 | B11: fct_world_monthly | C11: fct_hmrc_world_monthly | D11: NEXT_WP005_HMRC_Monthly_Trade_Core4_World_2019-01_to_2026-06.csv | E11: world_monthly_key | F11: Inclusive World monthly denominator
A13: Field-level PostgreSQL typing
A14: PostgreSQL table | B14: column_name | C14: data_type | D14: nullable | E14: key / role | F14: workbook source | G14: transform rule | H14: definition | I14: source lineage
A15: dim_commodity | B15: cn8_code | C15: text | D15: NO | E15: Primary key | F15: dim_commodity | G15: Preserve as text | H15: Eight-digit Combined Nomenclature code | I15: WP004 lock / HMRC Commodity
A16: dim_commodity | B16: basket_role | C16: text | D16: NO | E16: Attribute | F16: dim_commodity | G16: Copied from locked scope | H16: Strategic role assigned to the code in the paired basket | I16: WP004
A17: dim_partner_country | B17: partner_country_id | C17: integer | D17: NO | E17: Primary key | F17: dim_partner_country | G17: Direct mapping | H17: HMRC CountryId | I17: HMRC Country lookup
A18: dim_partner_country | B18: partner_country_iso2 | C18: text | D18: NO | E18: Natural key | F18: dim_partner_country | G18: Direct mapping | H18: Two-character partner-country code | I18: HMRC Country lookup
A19: dim_partner_country | B19: geographical_basis | C19: text | D19: NO | E19: Control attribute | F19: dim_partner_country | G19: Country of dispatch / partner basis | H19: Basis of HMRC partner geography | I19: HMRC methodology
A20: dim_month | B20: month_id | C20: integer | D20: NO | E20: Primary key | F20: dim_month | G20: Direct mapping | H20: HMRC month identifier in YYYYMM form | I20: HMRC Date convention
A21: dim_month | B21: month_date | C21: date | D21: NO | E21: Date key | F21: dim_month | G21: DATE(year, month, 1) | H21: First day of the reporting month | I21: Derived
A22: dim_month | B22: complete_calendar_year_flag | C22: smallint | D22: NO | E22: Control attribute | F22: dim_month | G22: Year <= 2025 | H22: 1 for 2019-2025; 0 for partial 2026 | I22: Scope contract
A23: stg_hmrc_imports_core4 | B23: source_query_id | C23: text | D23: NO | F23: raw_partner_monthly | G23: Direct unless stated | H23: Query identifier | I23: W5Q01
A24: stg_hmrc_imports_core4 | B24: source_record_no | C24: integer | D24: NO | E24: Row identifier | F24: raw_partner_monthly | G24: Direct unless stated | H24: Sequential row number in the local representation | I24: Generated
A25: stg_hmrc_imports_core4 | B25: month_id | C25: integer | D25: NO | F25: raw_partner_monthly | G25: Direct unless stated | H25: HMRC month identifier | I25: MonthId
A26: stg_hmrc_imports_core4 | B26: commodity_id | C26: text | D26: NO | F26: raw_partner_monthly | G26: Direct unless stated | H26: HMRC CN8 commodity identifier | I26: CommodityId
A27: stg_hmrc_imports_core4 | B27: country_id | C27: integer | D27: NO | F27: raw_partner_monthly | G27: Direct unless stated | H27: HMRC partner-country identifier | I27: CountryId
A28: stg_hmrc_imports_core4 | B28: flow_type_id | C28: integer | D28: NO | F28: raw_partner_monthly | G28: Direct unless stated | H28: HMRC flow identifier; 3 is non-EU imports | I28: FlowTypeId
A29: stg_hmrc_imports_core4 | B29: suppression_index | C29: integer | D29: NO | F29: raw_partner_monthly | G29: Direct unless stated | H29: HMRC confidentiality/suppression category | I29: SuppressionIndex
A30: stg_hmrc_imports_core4 | B30: supp_unit | C30: numeric(20,6) | D30: NO | F30: raw_partner_monthly | G30: Direct unless stated | H30: Supplementary quantity where applicable | I30: SuppUnit
A31: stg_hmrc_imports_core4 | B31: net_mass | C31: numeric(20,6) | D31: NO | F31: raw_partner_monthly | G31: Direct unless stated | H31: Net mass in kilograms | I31: NetMass
A32: stg_hmrc_imports_core4 | B32: value_gbp | C32: numeric(20,6) | D32: NO | F32: raw_partner_monthly | G32: Direct unless stated | H32: HMRC import statistical value in GBP | I32: Value
A33: stg_hmrc_imports_core4 | B33: source_file | C33: text | D33: NO | F33: raw_partner_monthly | G33: Direct unless stated | H33: Immutable evidence filename | I33: Manifest
A34: stg_hmrc_world_core4 | B34: source_query_id | C34: text | D34: NO | F34: raw_world_monthly | G34: Direct unless stated | H34: Query identifier | I34: W5Q02
A35: stg_hmrc_world_core4 | B35: source_record_no | C35: integer | D35: NO | E35: Row identifier | F35: raw_world_monthly | G35: Direct unless stated | H35: Sequential row number in the local representation | I35: Generated
A36: stg_hmrc_world_core4 | B36: month_id | C36: integer | D36: NO | F36: raw_world_monthly | G36: Direct unless stated | H36: HMRC month identifier | I36: MonthId
A37: stg_hmrc_world_core4 | B37: commodity_id | C37: text | D37: NO | F37: raw_world_monthly | G37: Direct unless stated | H37: HMRC CN8 commodity identifier | I37: CommodityId
A38: stg_hmrc_world_core4 | B38: flow_type_id | C38: integer | D38: NO | F38: raw_world_monthly | G38: Direct unless stated | H38: HMRC flow identifier; 1 is EU imports and 3 is non-EU imports | I38: FlowTypeId
A39: stg_hmrc_world_core4 | B39: suppression_index | C39: integer | D39: NO | F39: raw_world_monthly | G39: Direct unless stated | H39: HMRC confidentiality/suppression category | I39: SuppressionIndex
A40: stg_hmrc_world_core4 | B40: supp_unit | C40: numeric(20,6) | D40: NO | F40: raw_world_monthly | G40: Direct unless stated | H40: Supplementary quantity where applicable | I40: SuppUnit
A41: stg_hmrc_world_core4 | B41: net_mass | C41: numeric(20,6) | D41: NO | F41: raw_world_monthly | G41: Direct unless stated | H41: Net mass in kilograms | I41: NetMass
A42: stg_hmrc_world_core4 | B42: value_gbp | C42: numeric(20,6) | D42: NO | F42: raw_world_monthly | G42: Direct unless stated | H42: HMRC import statistical value in GBP | I42: Value
A43: stg_hmrc_world_core4 | B43: source_file | C43: text | D43: NO | F43: raw_world_monthly | G43: Direct unless stated | H43: Immutable evidence filename | I43: Manifest
A44: fct_hmrc_import_monthly | B44: monthly_import_key | C44: text | D44: NO | E44: Primary key | F44: fct_partner_monthly | G44: Concatenation | H44: Deterministic code-country-month-flow key | I44: Derived / lookup
A45: fct_hmrc_import_monthly | B45: month_date | C45: date | D45: NO | E45: Foreign key | F45: fct_partner_monthly | G45: month_id | H45: First day of month | I45: Derived / lookup
A46: fct_hmrc_import_monthly | B46: month_id | C46: integer | D46: NO | E46: Foreign key | F46: fct_partner_monthly | G46: Raw | H46: HMRC month identifier | I46: HMRC OTS
A47: fct_hmrc_import_monthly | B47: calendar_year | C47: integer | D47: NO | E47: Attribute | F47: fct_partner_monthly | G47: month_id | H47: Calendar year | I47: Derived / lookup
A48: fct_hmrc_import_monthly | B48: calendar_month | C48: integer | D48: NO | E48: Attribute | F48: fct_partner_monthly | G48: month_id | H48: Month number 1-12 | I48: Derived / lookup
A49: fct_hmrc_import_monthly | B49: cn8_code | C49: text | D49: NO | E49: Foreign key | F49: fct_partner_monthly | G49: CommodityId | H49: Locked CN8 code | I49: Derived / lookup
A50: fct_hmrc_import_monthly | B50: hs4_code | C50: text | D50: NO | E50: Attribute | F50: fct_partner_monthly | G50: dim_commodity | H50: Four-digit HS heading | I50: Derived / lookup
A51: fct_hmrc_import_monthly | B51: partner_country_id | C51: integer | D51: NO | E51: Foreign key | F51: fct_partner_monthly | G51: CountryId | H51: HMRC CountryId | I51: Derived / lookup
A52: fct_hmrc_import_monthly | B52: partner_country_iso2 | C52: text | D52: NO | E52: Natural key | F52: fct_partner_monthly | G52: dim_partner_country | H52: Partner ISO2 code | I52: Derived / lookup
A53: fct_hmrc_import_monthly | B53: partner_country_name | C53: text | D53: NO | E53: Attribute | F53: fct_partner_monthly | G53: dim_partner_country | H53: Partner-country label | I53: Derived / lookup
A54: fct_hmrc_import_monthly | B54: flow | C54: text | D54: NO | E54: Key component | F54: fct_partner_monthly | G54: Constant IMPORT | H54: Normalised trade flow | I54: Derived / lookup
A55: fct_hmrc_import_monthly | B55: flow_type_id | C55: integer | D55: NO | E55: Attribute | F55: fct_partner_monthly | G55: Raw | H55: HMRC non-EU import flow | I55: HMRC OTS
... A96: fct_hmrc_world_monthly | B96: unit_value_review_flag_2_5x | C96: text | D96: NO | E96: Control | F96: fct_world_monthly | G96: Primary 2.5x review parameter | H96: Review state; base retained | I96: W5Q02 / derived

Sheet Unit_Value_Review_QC
A1: WP005 Unit-Value Review
A2: Diagnostic only. REVIEW rows remain in the official-data base case; the exclusion view is a labelled sensitivity, not a correction.
A4: Scope | B4: Eligible rows | C4: Review rows | D4: Review rate | E4: Review value GBP | F4: Review value share | H4: Parameter | I4: Value | J4: Interpretation
A5: Partner | B5: =COUNTIF(tbl_fct_partner_monthly[unit_value_review_flag_2_5x],"<>NOT_APPLICABLE") -> 3588 | C5: =COUNTIF(tbl_fct_partner_monthly[unit_value_review_flag_2_5x],"REVIEW") -> 37 | D5: =C5/B5 -> 0.010312152 | E5: =SUMIFS(tbl_fct_partner_monthly[import_value_gbp],tbl_fct_partner_monthly[unit_value_review_flag_2_5x],"REVIEW") -> 64711011 | F5: =E5/SUM(tbl_fct_partner_monthly[import_value_gbp]) -> 0.005218808 | H5: Primary review multiplier | I5: 2.5 | J5: Provisional exception-screening parameter
A6: World | B6: =COUNTIF(tbl_fct_world_monthly[unit_value_review_flag_2_5x],"<>NOT_APPLICABLE") -> 360 | C6: =COUNTIF(tbl_fct_world_monthly[unit_value_review_flag_2_5x],"REVIEW") -> 2 | D6: =C6/B6 -> 0.0055555556 | E6: =SUMIFS(tbl_fct_world_monthly[world_import_value_gbp],tbl_fct_world_monthly[unit_value_review_flag_2_5x],"REVIEW") -> 71188732 | F6: =E6/SUM(tbl_fct_world_monthly[world_import_value_gbp]) -> 0.0036728136 | H6: Reciprocal lower bound | I6: =1/I5 -> 0.4 | J6: Symmetric multiplicative lower boundary
H7: Treatment | I7: Flag and retain | J7: Official values remain in the base case
A9: Partner | B9: cn8_code | C9: Period | D9: Reported GBP/kg | E9: Excluding REVIEW GBP/kg | F9: Change | G9: Review months | I9: scope_key | J9: reference_group | K9: reference_median_unit_value_gbp_per_kg
A10: Pakistan | B10: 61091000 | C10: 2025 | D10: =SUMIFS(fct_partner_monthly!$Q$2:$Q$3601,fct_partner_monthly!$I$2:$I$3601,"PK",fct_partner_monthly!$F$2:$F$3601,B10,fct_partner_monthly!$D$2:$D$3601,C10)/SUMIFS(fct_partner_monthly!$R$2:$R$3601,fct_partner_monthly!$I$2:$I$3601,"PK",fct_partner_monthly!$F$2:$F$3601,B10,fct_partner_monthly!$D$2:$D$3601,C10) -> 4.6620388 | E10: =SUMIFS(fct_partner_monthly!$Q$2:$Q$3601,fct_partner_monthly!$I$2:$I$3601,"PK",fct_partner_monthly!$F$2:$F$3601,B10,fct_partner_monthly!$D$2:$D$3601,C10,fct_partner_monthly!$AB$2:$AB$3601,"WITHIN_BAND")/SUMIFS(fct_partner_monthly!$R$2:$R$3601,fct_partner_monthly!$I$2:$I$3601,"PK",fct_partner_monthly!$F$2:$F$3601,B10,fct_partner_monthly!$D$2:$D$3601,C10,fct_partner_monthly!$AB$2:$AB$3601,"WITHIN_BAND") -> 10.90064 | F10: =E10/D10-1 -> 1.3381703 | G10: =COUNTIFS(fct_partner_monthly!$I$2:$I$3601,"PK",fct_partner_monthly!$F$2:$F$3601,B10,fct_partner_monthly!$D$2:$D$3601,C10,fct_partner_monthly!$AB$2:$AB$3601,"REVIEW") -> 4 | I10: PARTNER|61091000|TR | J10: 61091000 x Turkey | K10: =MEDIAN(_xlfn._xlws.FILTER(fct_partner_monthly!$U$2:$U$3601,(fct_partner_monthly!$F$2:$F$3601=MID(I10,9,8))*(fct_partner_monthly!$I$2:$I$3601=RIGHT(I10,2))*(fct_partner_monthly!$N$2:$N$3601="REPORTED")*(fct_partner_monthly!$U$2:$U$3601>0))) -> 20.461445
A11: Turkey | B11: 61103099 | C11: 2025 | D11: =SUMIFS(fct_partner_monthly!$Q$2:$Q$3601,fct_partner_monthly!$I$2:$I$3601,"TR",fct_partner_monthly!$F$2:$F$3601,B11,fct_partner_monthly!$D$2:$D$3601,C11)/SUMIFS(fct_partner_monthly!$R$2:$R$3601,fct_partner_monthly!$I$2:$I$3601,"TR",fct_partner_monthly!$F$2:$F$3601,B11,fct_partner_monthly!$D$2:$D$3601,C11) -> 8.0187619 | E11: =SUMIFS(fct_partner_monthly!$Q$2:$Q$3601,fct_partner_monthly!$I$2:$I$3601,"TR",fct_partner_monthly!$F$2:$F$3601,B11,fct_partner_monthly!$D$2:$D$3601,C11,fct_partner_monthly!$AB$2:$AB$3601,"WITHIN_BAND")/SUMIFS(fct_partner_monthly!$R$2:$R$3601,fct_partner_monthly!$I$2:$I$3601,"TR",fct_partner_monthly!$F$2:$F$3601,B11,fct_partner_monthly!$D$2:$D$3601,C11,fct_partner_monthly!$AB$2:$AB$3601,"WITHIN_BAND") -> 17.61604 | F11: =E11/D11-1 -> 1.1968529 | G11: =COUNTIFS(fct_partner_monthly!$I$2:$I$3601,"TR",fct_partner_monthly!$F$2:$F$3601,B11,fct_partner_monthly!$D$2:$D$3601,C11,fct_partner_monthly!$AB$2:$AB$3601,"REVIEW") -> 2 | I11: PARTNER|61091000|MA | J11: 61091000 x Morocco | K11: =MEDIAN(_xlfn._xlws.FILTER(fct_partner_monthly!$U$2:$U$3601,(fct_partner_monthly!$F$2:$F$3601=MID(I11,9,8))*(fct_partner_monthly!$I$2:$I$3601=RIGHT(I11,2))*(fct_partner_monthly!$N$2:$N$3601="REPORTED")*(fct_partner_monthly!$U$2:$U$3601>0))) -> 7.8392981
I12: PARTNER|61091000|PK | J12: 61091000 x Pakistan | K12: =MEDIAN(_xlfn._xlws.FILTER(fct_partner_monthly!$U$2:$U$3601,(fct_partner_monthly!$F$2:$F$3601=MID(I12,9,8))*(fct_partner_monthly!$I$2:$I$3601=RIGHT(I12,2))*(fct_partner_monthly!$N$2:$N$3601="REPORTED")*(fct_partner_monthly!$U$2:$U$3601>0))) -> 10.235891
I13: PARTNER|61091000|IN | J13: 61091000 x India | K13: =MEDIAN(_xlfn._xlws.FILTER(fct_partner_monthly!$U$2:$U$3601,(fct_partner_monthly!$F$2:$F$3601=MID(I13,9,8))*(fct_partner_monthly!$I$2:$I$3601=RIGHT(I13,2))*(fct_partner_monthly!$N$2:$N$3601="REPORTED")*(fct_partner_monthly!$U$2:$U$3601>0))) -> 13.59406
A14: Review multiplier | B14: Lower bound | C14: Partner review rows | D14: World review rows | E14: Use | I14: PARTNER|61091000|BD | J14: 61091000 x Bangladesh | K14: =MEDIAN(_xlfn._xlws.FILTER(fct_partner_monthly!$U$2:$U$3601,(fct_partner_monthly!$F$2:$F$3601=MID(I14,9,8))*(fct_partner_monthly!$I$2:$I$3601=RIGHT(I14,2))*(fct_partner_monthly!$N$2:$N$3601="REPORTED")*(fct_partner_monthly!$U$2:$U$3601>0))) -> 10.323148
A15: 2 | B15: =1/A15 -> 0.5 | C15: =COUNTIFS(fct_partner_monthly!$N$2:$N$3601,"REPORTED",fct_partner_monthly!$AA$2:$AA$3601,"<"&B15)+COUNTIFS(fct_partner_monthly!$N$2:$N$3601,"REPORTED",fct_partner_monthly!$AA$2:$AA$3601,">"&A15) -> 82 | D15: =COUNTIF(fct_world_monthly!$X$2:$X$361,"<"&B15)+COUNTIF(fct_world_monthly!$X$2:$X$361,">"&A15) -> 3 | E15: Sensitivity | I15: PARTNER|61091000|LK | J15: 61091000 x Sri Lanka | K15: =MEDIAN(_xlfn._xlws.FILTER(fct_partner_monthly!$U$2:$U$3601,(fct_partner_monthly!$F$2:$F$3601=MID(I15,9,8))*(fct_partner_monthly!$I$2:$I$3601=RIGHT(I15,2))*(fct_partner_monthly!$N$2:$N$3601="REPORTED")*(fct_partner_monthly!$U$2:$U$3601>0))) -> 13.552232
A16: 2.5 | B16: =1/A16 -> 0.4 | C16: =COUNTIFS(fct_partner_monthly!$N$2:$N$3601,"REPORTED",fct_partner_monthly!$AA$2:$AA$3601,"<"&B16)+COUNTIFS(fct_partner_monthly!$N$2:$N$3601,"REPORTED",fct_partner_monthly!$AA$2:$AA$3601,">"&A16) -> 37 | D16: =COUNTIF(fct_world_monthly!$X$2:$X$361,"<"&B16)+COUNTIF(fct_world_monthly!$X$2:$X$361,">"&A16) -> 2 | E16: Primary diagnostic parameter | I16: PARTNER|61091000|MM | J16: 61091000 x Myanmar | K16: =MEDIAN(_xlfn._xlws.FILTER(fct_partner_monthly!$U$2:$U$3601,(fct_partner_monthly!$F$2:$F$3601=MID(I16,9,8))*(fct_partner_monthly!$I$2:$I$3601=RIGHT(I16,2))*(fct_partner_monthly!$N$2:$N$3601="REPORTED")*(fct_partner_monthly!$U$2:$U$3601>0))) -> 16.294942
A17: 3 | B17: =1/A17 -> 0.33333333 | C17: =COUNTIFS(fct_partner_monthly!$N$2:$N$3601,"REPORTED",fct_partner_monthly!$AA$2:$AA$3601,"<"&B17)+COUNTIFS(fct_partner_monthly!$N$2:$N$3601,"REPORTED",fct_partner_monthly!$AA$2:$AA$3601,">"&A17) -> 21 | D17: =COUNTIF(fct_world_monthly!$X$2:$X$361,"<"&B17)+COUNTIF(fct_world_monthly!$X$2:$X$361,">"&A17) -> 1 | E17: Sensitivity | I17: PARTNER|61091000|VN | J17: 61091000 x Vietnam | K17: =MEDIAN(_xlfn._xlws.FILTER(fct_partner_monthly!$U$2:$U$3601,(fct_partner_monthly!$F$2:$F$3601=MID(I17,9,8))*(fct_partner_monthly!$I$2:$I$3601=RIGHT(I17,2))*(fct_partner_monthly!$N$2:$N$3601="REPORTED")*(fct_partner_monthly!$U$2:$U$3601>0))) -> 21.029827
A18: 4 | B18: =1/A18 -> 0.25 | C18: =COUNTIFS(fct_partner_monthly!$N$2:$N$3601,"REPORTED",fct_partner_monthly!$AA$2:$AA$3601,"<"&B18)+COUNTIFS(fct_partner_monthly!$N$2:$N$3601,"REPORTED",fct_partner_monthly!$AA$2:$AA$3601,">"&A18) -> 11 | D18: =COUNTIF(fct_world_monthly!$X$2:$X$361,"<"&B18)+COUNTIF(fct_world_monthly!$X$2:$X$361,">"&A18) -> 1 | E18: Sensitivity | I18: PARTNER|61091000|KH | J18: 61091000 x Cambodia | K18: =MEDIAN(_xlfn._xlws.FILTER(fct_partner_monthly!$U$2:$U$3601,(fct_partner_monthly!$F$2:$F$3601=MID(I18,9,8))*(fct_partner_monthly!$I$2:$I$3601=RIGHT(I18,2))*(fct_partner_monthly!$N$2:$N$3601="REPORTED")*(fct_partner_monthly!$U$2:$U$3601>0))) -> 18.091181
I19: PARTNER|61091000|CN | J19: 61091000 x China | K19: =MEDIAN(_xlfn._xlws.FILTER(fct_partner_monthly!$U$2:$U$3601,(fct_partner_monthly!$F$2:$F$3601=MID(I19,9,8))*(fct_partner_monthly!$I$2:$I$3601=RIGHT(I19,2))*(fct_partner_monthly!$N$2:$N$3601="REPORTED")*(fct_partner_monthly!$U$2:$U$3601>0))) -> 18.213915
I20: PARTNER|61103099|TR | J20: 61103099 x Turkey | K20: =MEDIAN(_xlfn._xlws.FILTER(fct_partner_monthly!$U$2:$U$3601,(fct_partner_monthly!$F$2:$F$3601=MID(I20,9,8))*(fct_partner_monthly!$I$2:$I$3601=RIGHT(I20,2))*(fct_partner_monthly!$N$2:$N$3601="REPORTED")*(fct_partner_monthly!$U$2:$U$3601>0))) -> 19.213268
A21: The primary 2.5x multiplier is a review heuristic, not a statistical truth. A REVIEW label does not prove that the HMRC observation is erroneous. | I21: PARTNER|61103099|MA | J21: 61103099 x Morocco | K21: =MEDIAN(_xlfn._xlws.FILTER(fct_partner_monthly!$U$2:$U$3601,(fct_partner_monthly!$F$2:$F$3601=MID(I21,9,8))*(fct_partner_monthly!$I$2:$I$3601=RIGHT(I21,2))*(fct_partner_monthly!$N$2:$N$3601="REPORTED")*(fct_partner_monthly!$U$2:$U$3601>0))) -> 16.024819
A22: All published values and mass remain unchanged in the base case. Only the explicitly labelled sensitivity excludes REVIEW months; no winsorisation or replacement is applied. | I22: PARTNER|61103099|PK | J22: 61103099 x Pakistan | K22: =MEDIAN(_xlfn._xlws.FILTER(fct_partner_monthly!$U$2:$U$3601,(fct_partner_monthly!$F$2:$F$3601=MID(I22,9,8))*(fct_partner_monthly!$I$2:$I$3601=RIGHT(I22,2))*(fct_partner_monthly!$N$2:$N$3601="REPORTED")*(fct_partner_monthly!$U$2:$U$3601>0))) -> 13.240688
A23: HMRC notes that some net mass can be estimated, but the aggregate extract does not establish the cause of these specific observations; product mix, declarations, classification and reporting effects remain possible. | I23: PARTNER|61103099|IN | J23: 61103099 x India | K23: =MEDIAN(_xlfn._xlws.FILTER(fct_partner_monthly!$U$2:$U$3601,(fct_partner_monthly!$F$2:$F$3601=MID(I23,9,8))*(fct_partner_monthly!$I$2:$I$3601=RIGHT(I23,2))*(fct_partner_monthly!$N$2:$N$3601="REPORTED")*(fct_partner_monthly!$U$2:$U$3601>0))) -> 13.033767
A24: Filter unit_value_review_flag_2_5x = REVIEW in either fact table for the complete row-level review population. Source context: EXT_HMRC_SPEC. | I24: PARTNER|61103099|BD | J24: 61103099 x Bangladesh | K24: =MEDIAN(_xlfn._xlws.FILTER(fct_partner_monthly!$U$2:$U$3601,(fct_partner_monthly!$F$2:$F$3601=MID(I24,9,8))*(fct_partner_monthly!$I$2:$I$3601=RIGHT(I24,2))*(fct_partner_monthly!$N$2:$N$3601="REPORTED")*(fct_partner_monthly!$U$2:$U$3601>0))) -> 12.503788
A25: Residual partner scan: the remaining 31 REVIEW rows affect 24 origin-code-period aggregates; the largest exclusion sensitivity is Vietnam 61091000 in 2023, where aggregate unit value rises from GBP 12.43/kg to GBP 21.62/kg (+73.9%). Overall REVIEW value share of 0.52% therefore does not imply immaterial group-level impact. | I25: PARTNER|61103099|LK | J25: 61103099 x Sri Lanka | K25: =MEDIAN(_xlfn._xlws.FILTER(fct_partner_monthly!$U$2:$U$3601,(fct_partner_monthly!$F$2:$F$3601=MID(I25,9,8))*(fct_partner_monthly!$I$2:$I$3601=RIGHT(I25,2))*(fct_partner_monthly!$N$2:$N$3601="REPORTED")*(fct_partner_monthly!$U$2:$U$3601>0))) -> 16.584044
A26: China-probe check: excluding the March 2021 India 62044300 REVIEW month raises the 2021 aggregate from GBP 23.17/kg to GBP 27.42/kg (+18.3%); excluding the September 2021 China month raises it from GBP 22.81/kg to GBP 26.28/kg (+15.2%). Use reported and exclusion-sensitivity series in any 2019-2026 trend analysis. | I26: PARTNER|61103099|MM | J26: 61103099 x Myanmar | K26: =MEDIAN(_xlfn._xlws.FILTER(fct_partner_monthly!$U$2:$U$3601,(fct_partner_monthly!$F$2:$F$3601=MID(I26,9,8))*(fct_partner_monthly!$I$2:$I$3601=RIGHT(I26,2))*(fct_partner_monthly!$N$2:$N$3601="REPORTED")*(fct_partner_monthly!$U$2:$U$3601>0))) -> 12.70545
A27: cn8_code | B27: month_date | C27: Reported GBP/kg | D27: Reference median GBP/kg | E27: Ratio | F27: Review state | I27: PARTNER|61103099|VN | J27: 61103099 x Vietnam | K27: =MEDIAN(_xlfn._xlws.FILTER(fct_partner_monthly!$U$2:$U$3601,(fct_partner_monthly!$F$2:$F$3601=MID(I27,9,8))*(fct_partner_monthly!$I$2:$I$3601=RIGHT(I27,2))*(fct_partner_monthly!$N$2:$N$3601="REPORTED")*(fct_partner_monthly!$U$2:$U$3601>0))) -> 23.234222
A28: 62052000 | B28: 43525 | C28: =SUMIFS(fct_world_monthly!$Q$2:$Q$361,fct_world_monthly!$F$2:$F$361,A28,fct_world_monthly!$B$2:$B$361,B28) -> 4.2652936 | D28: =SUMIFS(fct_world_monthly!$W$2:$W$361,fct_world_monthly!$F$2:$F$361,A28,fct_world_monthly!$B$2:$B$361,B28) -> 25.220887 | E28: =SUMIFS(fct_world_monthly!$X$2:$X$361,fct_world_monthly!$F$2:$F$361,A28,fct_world_monthly!$B$2:$B$361,B28) -> 0.16911751 | F28: =IF(E28<Unit_Value_Review_QC!$I$6,"REVIEW",IF(E28>Unit_Value_Review_QC!$I$5,"REVIEW","WITHIN_BAND")) -> REVIEW | I28: PARTNER|61103099|KH | J28: 61103099 x Cambodia | K28: =MEDIAN(_xlfn._xlws.FILTER(fct_partner_monthly!$U$2:$U$3601,(fct_partner_monthly!$F$2:$F$3601=MID(I28,9,8))*(fct_partner_monthly!$I$2:$I$3601=RIGHT(I28,2))*(fct_partner_monthly!$N$2:$N$3601="REPORTED")*(fct_partner_monthly!$U$2:$U$3601>0))) -> 12.33939
A29: 62052000 | B29: 43556 | C29: =SUMIFS(fct_world_monthly!$Q$2:$Q$361,fct_world_monthly!$F$2:$F$361,A29,fct_world_monthly!$B$2:$B$361,B29) -> 9.1636215 | D29: =SUMIFS(fct_world_monthly!$W$2:$W$361,fct_world_monthly!$F$2:$F$361,A29,fct_world_monthly!$B$2:$B$361,B29) -> 25.220887 | E29: =SUMIFS(fct_world_monthly!$X$2:$X$361,fct_world_monthly!$F$2:$F$361,A29,fct_world_monthly!$B$2:$B$361,B29) -> 0.36333462 | F29: =IF(E29<Unit_Value_Review_QC!$I$6,"REVIEW",IF(E29>Unit_Value_Review_QC!$I$5,"REVIEW","WITHIN_BAND")) -> REVIEW | I29: PARTNER|61103099|CN | J29: 61103099 x China | K29: =MEDIAN(_xlfn._xlws.FILTER(fct_partner_monthly!$U$2:$U$3601,(fct_partner_monthly!$F$2:$F$3601=MID(I29,9,8))*(fct_partner_monthly!$I$2:$I$3601=RIGHT(I29,2))*(fct_partner_monthly!$N$2:$N$3601="REPORTED")*(fct_partner_monthly!$U$2:$U$3601>0))) -> 15.158853
I30: PARTNER|62044300|TR | J30: 62044300 x Turkey | K30: =MEDIAN(_xlfn._xlws.FILTER(fct_partner_monthly!$U$2:$U$3601,(fct_partner_monthly!$F$2:$F$3601=MID(I30,9,8))*(fct_partner_monthly!$I$2:$I$3601=RIGHT(I30,2))*(fct_partner_monthly!$N$2:$N$3601="REPORTED")*(fct_partner_monthly!$U$2:$U$3601>0))) -> 31.867133
I31: PARTNER|62044300|MA | J31: 62044300 x Morocco | K31: =MEDIAN(_xlfn._xlws.FILTER(fct_partner_monthly!$U$2:$U$3601,(fct_partner_monthly!$F$2:$F$3601=MID(I31,9,8))*(fct_partner_monthly!$I$2:$I$3601=RIGHT(I31,2))*(fct_partner_monthly!$N$2:$N$3601="REPORTED")*(fct_partner_monthly!$U$2:$U$3601>0))) -> 19.682232
I32: PARTNER|62044300|PK | J32: 62044300 x Pakistan | K32: =MEDIAN(_xlfn._xlws.FILTER(fct_partner_monthly!$U$2:$U$3601,(fct_partner_monthly!$F$2:$F$3601=MID(I32,9,8))*(fct_partner_monthly!$I$2:$I$3601=RIGHT(I32,2))*(fct_partner_monthly!$N$2:$N$3601="REPORTED")*(fct_partner_monthly!$U$2:$U$3601>0))) -> 19.366411
I33: PARTNER|62044300|IN | J33: 62044300 x India | K33: =MEDIAN(_xlfn._xlws.FILTER(fct_partner_monthly!$U$2:$U$3601,(fct_partner_monthly!$F$2:$F$3601=MID(I33,9,8))*(fct_partner_monthly!$I$2:$I$3601=RIGHT(I33,2))*(fct_partner_monthly!$N$2:$N$3601="REPORTED")*(fct_partner_monthly!$U$2:$U$3601>0))) -> 29.827361
I34: PARTNER|62044300|BD | J34: 62044300 x Bangladesh | K34: =MEDIAN(_xlfn._xlws.FILTER(fct_partner_monthly!$U$2:$U$3601,(fct_partner_monthly!$F$2:$F$3601=MID(I34,9,8))*(fct_partner_monthly!$I$2:$I$3601=RIGHT(I34,2))*(fct_partner_monthly!$N$2:$N$3601="REPORTED")*(fct_partner_monthly!$U$2:$U$3601>0))) -> 14.861069
I35: PARTNER|62044300|LK | J35: 62044300 x Sri Lanka | K35: =MEDIAN(_xlfn._xlws.FILTER(fct_partner_monthly!$U$2:$U$3601,(fct_partner_monthly!$F$2:$F$3601=MID(I35,9,8))*(fct_partner_monthly!$I$2:$I$3601=RIGHT(I35,2))*(fct_partner_monthly!$N$2:$N$3601="REPORTED")*(fct_partner_monthly!$U$2:$U$3601>0))) -> 17.070169
I36: PARTNER|62044300|MM | J36: 62044300 x Myanmar | K36: =MEDIAN(_xlfn._xlws.FILTER(fct_partner_monthly!$U$2:$U$3601,(fct_partner_monthly!$F$2:$F$3601=MID(I36,9,8))*(fct_partner_monthly!$I$2:$I$3601=RIGHT(I36,2))*(fct_partner_monthly!$N$2:$N$3601="REPORTED")*(fct_partner_monthly!$U$2:$U$3601>0))) -> 29.259592
I37: PARTNER|62044300|VN | J37: 62044300 x Vietnam | K37: =MEDIAN(_xlfn._xlws.FILTER(fct_partner_monthly!$U$2:$U$3601,(fct_partner_monthly!$F$2:$F$3601=MID(I37,9,8))*(fct_partner_monthly!$I$2:$I$3601=RIGHT(I37,2))*(fct_partner_monthly!$N$2:$N$3601="REPORTED")*(fct_partner_monthly!$U$2:$U$3601>0))) -> 24.149636
I38: PARTNER|62044300|KH | J38: 62044300 x Cambodia | K38: =MEDIAN(_xlfn._xlws.FILTER(fct_partner_monthly!$U$2:$U$3601,(fct_partner_monthly!$F$2:$F$3601=MID(I38,9,8))*(fct_partner_monthly!$I$2:$I$3601=RIGHT(I38,2))*(fct_partner_monthly!$N$2:$N$3601="REPORTED")*(fct_partner_monthly!$U$2:$U$3601>0))) -> 19.130986
I39: PARTNER|62044300|CN | J39: 62044300 x China | K39: =MEDIAN(_xlfn._xlws.FILTER(fct_partner_monthly!$U$2:$U$3601,(fct_partner_monthly!$F$2:$F$3601=MID(I39,9,8))*(fct_partner_monthly!$I$2:$I$3601=RIGHT(I39,2))*(fct_partner_monthly!$N$2:$N$3601="REPORTED")*(fct_partner_monthly!$U$2:$U$3601>0))) -> 27.635683
I40: PARTNER|62052000|TR | J40: 62052000 x Turkey | K40: =MEDIAN(_xlfn._xlws.FILTER(fct_partner_monthly!$U$2:$U$3601,(fct_partner_monthly!$F$2:$F$3601=MID(I40,9,8))*(fct_partner_monthly!$I$2:$I$3601=RIGHT(I40,2))*(fct_partner_monthly!$N$2:$N$3601="REPORTED")*(fct_partner_monthly!$U$2:$U$3601>0))) -> 35.036767
I41: PARTNER|62052000|MA | J41: 62052000 x Morocco | K41: =MEDIAN(_xlfn._xlws.FILTER(fct_partner_monthly!$U$2:$U$3601,(fct_partner_monthly!$F$2:$F$3601=MID(I41,9,8))*(fct_partner_monthly!$I$2:$I$3601=RIGHT(I41,2))*(fct_partner_monthly!$N$2:$N$3601="REPORTED")*(fct_partner_monthly!$U$2:$U$3601>0))) -> 33.195881
... I49: PARTNER|62052000|CN | J49: 62052000 x China | K49: =MEDIAN(_xlfn._xlws.FILTER(fct_partner_monthly!$U$2:$U$3601,(fct_partner_monthly!$F$2:$F$3601=MID(I49,9,8))*(fct_partner_monthly!$I$2:$I$3601=RIGHT(I49,2))*(fct_partner_monthly!$N$2:$N$3601="REPORTED")*(fct_partner_monthly!$U$2:$U$3601>0))) -> 23.211498
I50: WORLD|61091000 | J50: 61091000 x World | K50: =MEDIAN(_xlfn._xlws.FILTER(fct_world_monthly!$Q$2:$Q$361,fct_world_monthly!$F$2:$F$361=RIGHT(I50,8))) -> 15.322317
I51: WORLD|61103099 | J51: 61103099 x World | K51: =MEDIAN(_xlfn._xlws.FILTER(fct_world_monthly!$Q$2:$Q$361,fct_world_monthly!$F$2:$F$361=RIGHT(I51,8))) -> 15.61112
I52: WORLD|62044300 | J52: 62044300 x World | K52: =MEDIAN(_xlfn._xlws.FILTER(fct_world_monthly!$Q$2:$Q$361,fct_world_monthly!$F$2:$F$361=RIGHT(I52,8))) -> 31.446186
I53: WORLD|62052000 | J53: 62052000 x World | K53: =MEDIAN(_xlfn._xlws.FILTER(fct_world_monthly!$Q$2:$Q$361,fct_world_monthly!$F$2:$F$361=RIGHT(I53,8))) -> 25.220887
